Workbook

Sheet Нач.инв.
A1: Помещение
A2: Статья расходов | B2: Стоимость, руб.
A3: Проект вентиляции и ее могнтаж | B3: 100000
A4: Проект электропроводки и его выполнение | B4: 50000
A5: Пожарное оснащение | B5: 50000
A6: Ремонт | B6: 300000
A7: Видеонаблюдение | B7: 100000
A8: ИТОГО | B8: =SUM(B3:B7) -> 600000
A11: Игровое место стандарт
A12: Комлектующие | B12: Наименование | C12: Стоимость, руб. | F12: Амортизация стандартного ПК (5лет)
A13: Клавиатура | B13: RAZER BLACKWIDOW | C13: 7000 | F13: Стоимость, руб. | G13: =SUM(C13:C20) -> 87000
A14: Мышь | B14: THUNDER X3TM30 | C14: 1500 | F14: Ежегодная амортизация, руб. | G14: =G13/5 -> 17400
A15: Коврик | B15: THUNDER X3TMP40 | C15: 500 | F15: Ежемесячная амортизация, руб. | G15: =G14/30 -> 580
A16: Наушники | B16: RAZER KRAKEN | C16: 3000
A17: Процессор | B17: INTEL CORE i-5 9600k | C17: 17500
A18: Видеокарта | B18: NVIDIA RTX 2070 | C18: 36000
A19: Оперативная память | B19: 16 Gb DDR4 | C19: 7500
A20: Монитор | B20: ACER Nitro VG240Ybmipx 23.8" | C20: 14000
A21: ПО | B21: Windows 10 Pro | C21: 22000
A22: Игровое кресло | B22: DXRacer | C22: 30000
A23: Стол компьютерный | B23: Стол для ПК | C23: 5000
B24: ИТОГО | C24: =SUM(C13:C23) -> 144000
A27: Игровое место VIP
A28: Комлектующие | B28: Наименование | C28: Стоимость, руб. | F28: Амортизация VIP ПК (5лет)
A29: Клавиатура | B29: ASUS ROG CLAYMORE | C29: 9000 | F29: Стоимость, руб. | G29: =SUM(C29:C36) -> 165100
A30: Мышь | B30: ASUS ROG GLADIUS 2 | C30: 4000 | F30: Ежегодная амортизация, руб. | G30: =G29/5 -> 33020
A31: Коврик | B31: ASUS ROG SCABBARD | C31: 2600 | F31: Ежемесячная амортизация, руб. | G31: =G30/30 -> 1100.6667
A32: Наушники | B32: ASUS ROG DELTA | C32: 10000
A33: Процессор | B33: INTEL CORE i-9 9700k | C33: 35000
A34: Видеокарта | B34: MSI RTX 2080 | C34: 60000
A35: Оперативная память | B35: 16 Gb DDR4 | C35: 7500
A36: Монитор | B36: ASUS ROG Strix XG248Q 240 ГЦ, 24 “ | C36: 37000
A37: ПО | B37: Windows 10 Pro | C37: 22000
A38: Игровое кресло | B38: DXRacer | C38: 30000
A39: Стол компьютерный | B39: Стол для ПК | C39: 5000
B40: ИТОГО | C40: =SUM(C29:C39) -> 222100
A43: PS4+VR
A44: Комлектующие | B44: Наименование | C44: Цена, руб. | D44: Кол-во | E44: Стоимость, руб. | G44: Амортизация ТВ (5лет)
A45: PS4 | B45: - | C45: 26000 | D45: 2 | E45: =C45*D45 -> 52000 | G45: Стоимость, руб. | H45: =E47 -> 150000
A46: Sony PlayStation VR (CUH-ZVR2) + PlayStation Camera | B46: - | C46: 34000 | D46: 1 | E46: =C46*D46 -> 34000 | G46: Ежегодная амортизация, руб. | H46: =H45/5 -> 30000
A47: Телевизоры | B47: SAMSUNG UE49RU8000UXRU Ultra HD 4K (2160p) | C47: 50000 | D47: 3 | E47: =C47*D47 -> 150000 | G47: Ежемесячная амортизация, руб. | H47: =H46/30 -> 1000
D48: ИТОГО | E48: =SUM(E45:E47) -> 236000
A51: Зона кафе и администратора
A52: Статья расхода | B52: Наименование | C52: Цена, руб. | D52: Кол-во | E52: Стоимость, руб.
A53: Компьютер администратора | B53: - | C53: 50000 | D53: 1 | E53: =C53*D53 -> 50000
A54: Кресло администратора | B54: Кресло рабочее Arachno | C54: 4600 | D54: 1 | E54: =C54*D54 -> 4600 | G54: Амортизация ПК администратора (5лет)
A55: Стойка администратора | B55: - | C55: 30000 | D55: 1 | E55: =C55*D55 -> 30000 | G55: Стоимость, руб. | H55: =C53 -> 50000
A56: Принтер | B56: Xerox Phaser 3020BI | C56: 5600 | D56: 1 | E56: =C56*D56 -> 5600 | G56: Ежегодная амортизация, руб. | H56: =H55/5 -> 10000
A57: Онлайн касса | B57: - | C57: 20000 | D57: 1 | E57: =C57*D57 -> 20000 | G57: Ежемесячная амортизация, руб. | H57: =H56/30 -> 333.33333
A58: Стол кафе | B58: Стендмебель раскладной | C58: 1500 | D58: 6 | E58: =C58*D58 -> 9000
A59: Минидиваны | B59: СВЭНСТА | C59: 5000 | D59: 8 | E59: =C59*D59 -> 40000
A60: Оборудование кафе | B60: - | C60: 35000 | D60: 1 | E60: =C60*D60 -> 35000
A61: Диваны | B61: Милан 120 | C61: 6800 | D61: 2 | E61: =C61*D61 -> 13600
A62: Кальяны | B62: Khalil Mamoon Trimetal Triple | C62: 4000 | D62: 7 | E62: =C62*D62 -> 28000
D63: ИТОГО | E63: =SUM(E53:E62) -> 235800
E66: =B8+C24*10+C40*5+E48+E63 -> 3622300

Sheet Операц.изд. в мес.
A1: Заработная плата
A2: Должность | B2: Оклад, руб. | C2: Кол-во | D2: З/П, руб | E2: Отчисления ЕСН | F2: Стоимость, руб.
A3: Управляющий | B3: 35000 | C3: 1 | D3: =C3*B3 -> 35000 | E3: =D3*$I$4 -> 10500 | F3: =D3+E3 -> 45500
A4: Администратор | B4: 26000 | C4: 3 | D4: =C4*B4 -> 78000 | E4: =D4*$I$4 -> 23400 | F4: =D4+E4 -> 101400 | H4: ЕСН | I4: 0.3
A5: ИТ-специалист | B5: 40000 | C5: 1 | D5: =C5*B5 -> 40000 | E5: =D5*$I$4 -> 12000 | F5: =D5+E5 -> 52000
A6: Кальянщик | B6: 25000 | C6: 1 | D6: =C6*B6 -> 25000 | E6: =D6*$I$4 -> 7500 | F6: =D6+E6 -> 32500
A7: Уборщица | B7: 15000 | C7: 1 | D7: =C7*B7 -> 15000 | E7: =D7*$I$4 -> 4500 | F7: =D7+E7 -> 19500
D8: =SUM(D3:D7) -> 193000
E10: Аутсорсинг
E11: Бухгалтерия | F11: 1500
E12: ИТОГО | F12: =SUM(F3:F7)+F11 -> 252400
A17: Операционные затраты
A18: Статья расхода | B18: Сумма, руб.
A19: З/п | B19: =F12 -> 252400
A20: Аренда | B20: 150000
A21: Электричество и интернет | B21: 50000
A22: Покупка еды и напитков | B22: 10000
A23: Непредвиденное | B23: 15000
A24: ИТОГО | B24: =SUM(B19:B23) -> 477400

Sheet Инв.расчет
C1: CAPEX (ИНВЕСТИЦИИ)
D2: ед. изм. | E2: Кол-во | F2: Цена за ед., руб. | G2: Стоимость
C3: ПОМЕЩЕНИЕ | G3: =SUM(G4:G8) -> 600000
C4: Проект вентиляции и ее могнтаж | D4: работ | E4: 1 | F4: =Нач.инв.!B3 -> 100000 | G4: =E4*F4 -> 100000
C5: Проект электропроводки и его выполнение | D5: работ | E5: 1 | F5: =Нач.инв.!B4 -> 50000 | G5: =E5*F5 -> 50000
C6: Пожарное оснащение | D6: работ | E6: 1 | F6: =Нач.инв.!B5 -> 50000 | G6: =E6*F6 -> 50000
C7: Ремонт | D7: работ | E7: 1 | F7: =Нач.инв.!B6 -> 300000 | G7: =E7*F7 -> 300000
C8: Видеонаблюдение | D8: работ | E8: 1 | F8: =Нач.инв.!B7 -> 100000 | G8: =E8*F8 -> 100000
C10: Оборудование игровых мест | G10: =SUM(G11:G15) -> 2803100
C11: ПК стандарт+мебель | D11: 1 место | E11: ='Вход и предположения'!E4 -> 10 | F11: =Нач.инв.!C24 -> 144000 | G11: =E11*F11 -> 1440000
C12: ПК VIP+мебель | D12: 1 место | E12: ='Вход и предположения'!E5 -> 5 | F12: =Нач.инв.!C40 -> 222100 | G12: =E12*F12 -> 1110500
C13: PS4+мебель | D13: 1 место | E13: ='Вход и предположения'!E6 -> 2 | F13: =Нач.инв.!C45+Нач.инв.!C47+Нач.инв.!C61+Нач.инв.!C58 -> 84300 | G13: =E13*F13 -> 168600
C14: VR | D14: 1 место | E14: 1 | F14: =Нач.инв.!C46 -> 34000 | G14: =E14*F14 -> 34000
C15: ТВ | D15: 1 место | E15: 1 | F15: =Нач.инв.!C47 -> 50000 | G15: =E15*F15 -> 50000
C17: Зона кафе и администратора | G17: =SUM(G18:G26) -> 219200
C18: Компьютер администратора | D18: шт. | E18: 1 | F18: 50000 | G18: =E18*F18 -> 50000
C19: Кресло администратора | D19: шт. | E19: 1 | F19: 4600 | G19: =E19*F19 -> 4600
C20: Стойка администратора | D20: шт. | E20: 1 | F20: 30000 | G20: =E20*F20 -> 30000
C21: Принтер | D21: шт. | E21: 1 | F21: 5600 | G21: =E21*F21 -> 5600
C22: Онлайн касса | D22: шт. | E22: 1 | F22: 20000 | G22: =E22*F22 -> 20000
C23: Стол кафе | D23: шт. | E23: 4 | F23: 1500 | G23: =E23*F23 -> 6000
C24: Минидиваны | D24: шт. | E24: 8 | F24: 5000 | G24: =E24*F24 -> 40000
C25: Оборудование кафе | D25: шт. | E25: 1 | F25: 35000 | G25: =E25*F25 -> 35000
C26: Кальяны | D26: шт. | E26: 7 | F26: 4000 | G26: =E26*F26 -> 28000
C28: ИНВЕСТИЦИИ ВСЕГО | G28: =SUM(G3,G10,G17) -> 3622300

Sheet Вход и предположения
C1: ВВОДНЫЕ ДАННЫЕ / ASSUMPTIONS
C3: UNIT | D3: Ед. изм. | E3: Значение
C4: Количество стандартных PC | D4: шт. | E4: 10
C5: Количество PC Boot Camp (VIP) | D5: шт. | E5: 5
C6: Количество Sony PS + TV | D6: шт. | E6: 2
C7: Площадь помещения | D7: м2 | E7: 200
C9: REVENUE
E10: 1 год | F10: 2 год | G10: 3 год | H10: 4 год | I10: 5 год | L10: tax rate | M10: =E28 -> 0.15
C11: % загрузки PC | D11: % | E11: 0.4 | F11: 0.5 | G11: 0.5 | H11: 0.5 | I11: 0.5 | L11: rf | M11: ='re и wacc'!H24 -> 0.06245
C12: % загрузки PC VIP | D12: % | E12: 0.4 | F12: 0.5 | G12: 0.5 | H12: 0.5 | I12: 0.5 | L12: rd | M12: 0.075
C13: % загрузки Sony PS + TV Led | D13: % | E13: 0.4 | F13: 0.5 | G13: 0.5 | H13: 0.5 | I13: 0.5 | L13: re | M13: ='re и wacc'!C22 -> 0.16245
L14: wacc | M14: ='re и wacc'!C40 -> 0.13520212
C15: Средняя стоимость часа игры PC | D15: руб./час. | E15: 100
C16: Средняя стоимость часа игры PC VIP | D16: руб./час. | E16: 110 | L16: g | M16: 0.065 | N16: Исследование PwC
C17: Средняя стоимость часа игры Sony PS | D17: руб./час. | E17: 200
C18: Рублей выручки бара на 1 час игрового времени | D18: руб./час. | E18: 70
C19: Прочие доходы | D19: руб./мес. | E19: 15000
C21: OPEX (операционные расходы)
C22: Ставка аренды помещения (фикс ставка/постоянная часть) | D22: руб./м2 год | E22: 9000
C24: % роста годовой арендной ставки помещения | D24: % в год | E24: 0.05
C25: Доля прочих затрат (мелкие затраты) | D25: % от затрат | E25: 0.03
C26: Отношение оборотного капитала к выручке | D26: % | E26: 0.1
C27: Комаунальные платежи (вода) | D27: руб. | E27: 2500
C28: Ставка УСН (доходы-расходы) | D28: % | E28: 0.15
C29: Сумма официальной з/п в мес. | D29: руб./мес. | E29: ='Операц.изд. в мес.'!D8 -> 193000
C30: % затрат на рекламу от выручки | D30: % от выручки | E30: 0.02
C31: Маржинальность бара / % наценки | D31: % | E31: 1.1
C32: Затраты на интернет и электричество в мес. | D32: тыс.руб/мес. | E32: ='Операц.изд. в мес.'!B21 -> 50000
C34: Доля карточных платежей от выручки | D34: % | E34: 0.4
C35: Комиссия за эквайринг | D35: % | E35: 0.02
C37: Бухгалтерское обсулживание | D37: руб./мес. | E37: ='Операц.изд. в мес.'!F11 -> 1500
C39: Отношение кап затрат к выручке | E39: 0.02
E42: 1 год | F42: 2 год | G42: 3 год | H42: 4 год | I42: 5 год
C43: Инфляция | E43: 0 | F43: 0.04 | G43: 0.04 | H43: 0.04 | I43: 0.04
C50: Кредит на сумму 1млн.руб под 7,5% годовых | D50: 1000000
C52: По месяцам
C53: Период | D53: 0 | E53: 1 | F53: 2 | G53: 3 | H53: 4 | I53: 5 | J53: 6 | K53: 7 | L53: 8 | M53: 9 | N53: 10 | O53: 11 | P53: 12 | Q53: 13 | R53: 14 | S53: 15 | T53: 16 | U53: 17 | V53: 18 | W53: 19 | X53: 20 | Y53: 21 | Z53: 22 | AA53: 23 | AB53: 24 | AC53: 25 | AD53: 26 | AE53: 27 | AF53: 28 | AG53: 29 | AH53: 30 | AI53: 31 | AJ53: 32 | AK53: 33 | AL53: 34 | AM53: 35 | AN53: 36
C54: Платеж | D54: =D55+D56 -> 0 | E54: =E55+E56 -> 34027.778 | F54: =F55+F56 -> 33854.167 | G54: =G55+G56 -> 33680.556 | H54: =H55+H56 -> 33506.944 | I54: =I55+I56 -> 33333.333 | J54: =J55+J56 -> 33159.722 | K54: =K55+K56 -> 32986.111 | ... AN54: =AN55+AN56 -> 27951.389
C55: Процент | D55: 0 | E55: =D57*$M$12/12 -> 6250 | F55: =E57*$M$12/12 -> 6076.3889 | G55: =F57*$M$12/12 -> 5902.7778 | H55: =G57*$M$12/12 -> 5729.1667 | I55: =H57*$M$12/12 -> 5555.5556 | J55: =I57*$M$12/12 -> 5381.9444 | K55: =J57*$M$12/12 -> 5208.3333 | L55: =K57*$M$12/12 -> 5034.7222 | ... AN55: =AM57*$M$12/12 -> 173.61111
C56: Тело | D56: 0 | E56: =$D$50/36 -> 27777.778 | F56: =$D$50/36 -> 27777.778 | G56: =$D$50/36 -> 27777.778 | H56: =$D$50/36 -> 27777.778 | I56: =$D$50/36 -> 27777.778 | J56: =$D$50/36 -> 27777.778 | K56: =$D$50/36 -> 27777.778 | L56: =$D$50/36 -> 27777.778 | ... AN56: =$D$50/36 -> 27777.778
C57: Остаток | D57: =D50 -> 1000000 | E57: =D57-E56 -> 972222.22 | F57: =E57-F56 -> 944444.44 | G57: =F57-G56 -> 916666.67 | H57: =G57-H56 -> 888888.89 | I57: =H57-I56 -> 861111.11 | J57: =I57-J56 -> 833333.33 | K57: =J57-K56 -> 805555.56 | L57: =K57-L56 -> 777777.78 | ... AN57: =AM57-AN56 -> 6.4756023e-10

Sheet Модель
C1: МОДЕЛЬ
E3: 1 | F3: 1 | G3: 1 | H3: 1 | I3: 1 | J3: 1 | K3: 1 | L3: 1 | M3: 1 | N3: 1 | O3: 1 | P3: 1 | Q3: 1 | R3: 1 | S3: 1 | T3: 1 | U3: 1 | V3: 1 | W3: 1 | X3: 1 | Y3: 1 | Z3: 1 | AA3: 1 | AB3: 1 | AC3: 1 | AD3: 1 | AE3: 1 | AF3: 1 | AG3: 1 | AH3: 1 | AI3: 1 | AJ3: 1 | AK3: 1 | AL3: 1 | AM3: 1 | AN3: 1 | AO3: 1 | AP3: 1 | AQ3: 1 | AR3: 1 | AS3: 1 | AT3: 1 | AU3: 1 | AV3: 1 | AW3: 1 | AX3: 1 | AY3: 1 | AZ3: 1 | BA3: 1 | BB3: 1 | BC3: 1 | BD3: 1 | BE3: 1 | BF3: 1 | BG3: 1 | BH3: 1 | BI3: 1 | BJ3: 1 | BK3: 1 | BL3: 1 | BM3: 1
C4: Годовая инфляция | D4: % | F4: ='Вход и предположения'!$E$43 -> 0 | G4: ='Вход и предположения'!$E$43 -> 0 | H4: ='Вход и предположения'!$E$43 -> 0 | I4: ='Вход и предположения'!$E$43 -> 0 | J4: ='Вход и предположения'!$E$43 -> 0 | K4: ='Вход и предположения'!$E$43 -> 0 | L4: ='Вход и предположения'!$E$43 -> 0 | M4: ='Вход и предположения'!$E$43 -> 0 | ... Q4: ='Вход и предположения'!$E$43 -> 0 | R4: ='Вход и предположения'!$F$43 -> 0.04 | S4: ='Вход и предположения'!$F$43 -> 0.04 | T4: ='Вход и предположения'!$F$43 -> 0.04 | U4: ='Вход и предположения'!$F$43 -> 0.04 | V4: ='Вход и предположения'!$F$43 -> 0.04 | W4: ='Вход и предположения'!$F$43 -> 0.04 | X4: ='Вход и предположения'!$F$43 -> 0.04 | Y4: ='Вход и предположения'!$F$43 -> 0.04 | ... AC4: ='Вход и предположения'!$F$43 -> 0.04 | AD4: ='Вход и предположения'!$G$43 -> 0.04 | AE4: ='Вход и предположения'!$G$43 -> 0.04 | AF4: ='Вход и предположения'!$G$43 -> 0.04 | AG4: ='Вход и предположения'!$G$43 -> 0.04 | AH4: ='Вход и предположения'!$G$43 -> 0.04 | AI4: ='Вход и предположения'!$G$43 -> 0.04 | AJ4: ='Вход и предположения'!$G$43 -> 0.04 | AK4: ='Вход и предположения'!$G$43 -> 0.04 | ... AO4: ='Вход и предположения'!$G$43 -> 0.04 | AP4: ='Вход и предположения'!$H$43 -> 0.04 | AQ4: ='Вход и предположения'!$H$43 -> 0.04 | AR4: ='Вход и предположения'!$H$43 -> 0.04 | AS4: ='Вход и предположения'!$H$43 -> 0.04 | AT4: ='Вход и предположения'!$H$43 -> 0.04 | AU4: ='Вход и предположения'!$H$43 -> 0.04 | AV4: ='Вход и предположения'!$H$43 -> 0.04 | AW4: ='Вход и предположения'!$H$43 -> 0.04 | ... BA4: ='Вход и предположения'!$H$43 -> 0.04 | BB4: ='Вход и предположения'!$I$43 -> 0.04 | BC4: ='Вход и предположения'!$I$43 -> 0.04 | BD4: ='Вход и предположения'!$I$43 -> 0.04 | BE4: ='Вход и предположения'!$I$43 -> 0.04 | BF4: ='Вход и предположения'!$I$43 -> 0.04 | BG4: ='Вход и предположения'!$I$43 -> 0.04 | BH4: ='Вход и предположения'!$I$43 -> 0.04 | BI4: ='Вход и предположения'!$I$43 -> 0.04 | ... BM4: ='Вход и предположения'!$I$43 -> 0.04
C5: Инфляция периода | D5: % | F5: =F4/12 -> 0 | G5: =G4/12 -> 0 | H5: =H4/12 -> 0 | I5: =I4/12 -> 0 | J5: =J4/12 -> 0 | K5: =K4/12 -> 0 | L5: =L4/12 -> 0 | M5: =M4/12 -> 0 | ... BM5: =BM4/12 -> 0.0033333333
C6: Накопленная инфляция | D6: % | E6: 1 | F6: =E6*(1+F5) -> 1 | G6: =F6*(1+G5) -> 1 | H6: =G6*(1+H5) -> 1 | I6: =H6*(1+I5) -> 1 | J6: =I6*(1+J5) -> 1 | K6: =J6*(1+K5) -> 1 | L6: =K6*(1+L5) -> 1 | M6: =L6*(1+M5) -> 1 | ... BM6: =BL6*(1+BM5) -> 1.1731987
C7: Среднее количество часов в месяце всего 1PC | D7: часов/1PC | F7: =24*30 -> 720 | G7: =24*30 -> 720 | H7: =24*30 -> 720 | I7: =24*30 -> 720 | J7: =24*30 -> 720 | K7: =24*30 -> 720 | L7: =24*30 -> 720 | M7: =24*30 -> 720 | ... BM7: =24*30 -> 720
C8: Период | E8: 0 | F8: 1 | G8: 2 | H8: 3 | I8: 4 | J8: 5 | K8: 6 | L8: 7 | M8: 8 | N8: 9 | O8: 10 | P8: 11 | Q8: 12 | R8: 13 | S8: 14 | T8: 15 | U8: 16 | V8: 17 | W8: 18 | X8: 19 | Y8: 20 | Z8: 21 | AA8: 22 | AB8: 23 | AC8: 24 | AD8: 25 | AE8: 26 | AF8: 27 | AG8: 28 | AH8: 29 | AI8: 30 | AJ8: 31 | AK8: 32 | AL8: 33 | AM8: 34 | AN8: 35 | AO8: 36 | AP8: 37 | AQ8: 38 | AR8: 39 | AS8: 40 | AT8: 41 | AU8: 42 | AV8: 43 | AW8: 44 | AX8: 45 | AY8: 46 | AZ8: 47 | BA8: 48 | BB8: 49 | BC8: 50 | BD8: 51 | BE8: 52 | BF8: 53 | BG8: 54 | BH8: 55 | BI8: 56 | BJ8: 57 | BK8: 58 | BL8: 59 | BM8: 60
C9: REVENUE | D9: Ед. изм. | BP9: 1 год | BQ9: 2 год | BR9: 3 год | BS9: 4 год | BT9: 5 год | BU9: Всего
C10: Выручка от аренды стандартных PC | F10: =F11*F14*F15 -> 144000 | G10: =G11*G14*G15 -> 216000 | H10: =H11*H14*H15 -> 252000 | I10: =I11*I14*I15 -> 288000 | J10: =J11*J14*J15 -> 288000 | K10: =K11*K14*K15 -> 288000 | L10: =L11*L14*L15 -> 288000 | M10: =M11*M14*M15 -> 288000 | ... BM10: =BM11*BM14*BM15 -> 422351.52 | BO10: =SUM(F10:BM10) -> 21971808 | BP10: =SUM(F10:Q10) -> 3204000 | BQ10: =SUM(R10:AC10) -> 4414753.6 | BR10: =SUM(AD10:AO10) -> 4594617.5 | BS10: =SUM(AP10:BA10) -> 4781809.3 | BT10: =SUM(BB10:BM10) -> 4976627.6 | BU10: =SUM(BP10:BT10) -> 21971808
C11: Количество компьютеров PC | D11: шт. | F11: ='Вход и предположения'!$E$4 -> 10 | G11: ='Вход и предположения'!$E$4 -> 10 | H11: ='Вход и предположения'!$E$4 -> 10 | I11: ='Вход и предположения'!$E$4 -> 10 | J11: ='Вход и предположения'!$E$4 -> 10 | K11: ='Вход и предположения'!$E$4 -> 10 | L11: ='Вход и предположения'!$E$4 -> 10 | M11: ='Вход и предположения'!$E$4 -> 10 | ... BM11: ='Вход и предположения'!$E$4 -> 10
C12: % загрузки PC | D12: % | F12: 0.2 | G12: 0.3 | H12: 0.35 | I12: ='Вход и предположения'!$E$11 -> 0.4 | J12: ='Вход и предположения'!$E$11 -> 0.4 | K12: ='Вход и предположения'!$E$11 -> 0.4 | L12: ='Вход и предположения'!$E$11 -> 0.4 | M12: ='Вход и предположения'!$E$11 -> 0.4 | N12: ='Вход и предположения'!$E$11 -> 0.4 | O12: ='Вход и предположения'!$E$11 -> 0.4 | P12: ='Вход и предположения'!$E$11 -> 0.4 | Q12: ='Вход и предположения'!$E$11 -> 0.4 | R12: ='Вход и предположения'!$F$11 -> 0.5 | S12: ='Вход и предположения'!$F$11 -> 0.5 | T12: ='Вход и предположения'!$F$11 -> 0.5 | U12: ='Вход и предположения'!$F$11 -> 0.5 | V12: ='Вход и предположения'!$F$11 -> 0.5 | W12: ='Вход и предположения'!$F$11 -> 0.5 | X12: ='Вход и предположения'!$F$11 -> 0.5 | Y12: ='Вход и предположения'!$F$11 -> 0.5 | ... AC12: ='Вход и предположения'!$F$11 -> 0.5 | AD12: ='Вход и предположения'!$G$11 -> 0.5 | AE12: ='Вход и предположения'!$G$11 -> 0.5 | AF12: ='Вход и предположения'!$G$11 -> 0.5 | AG12: ='Вход и предположения'!$G$11 -> 0.5 | AH12: ='Вход и предположения'!$G$11 -> 0.5 | AI12: ='Вход и предположения'!$G$11 -> 0.5 | AJ12: ='Вход и предположения'!$G$11 -> 0.5 | AK12: ='Вход и предположения'!$G$11 -> 0.5 | ... AO12: ='Вход и предположения'!$G$11 -> 0.5 | AP12: ='Вход и предположения'!$H$11 -> 0.5 | AQ12: ='Вход и предположения'!$H$11 -> 0.5 | AR12: ='Вход и предположения'!$H$11 -> 0.5 | AS12: ='Вход и предположения'!$H$11 -> 0.5 | AT12: ='Вход и предположения'!$H$11 -> 0.5 | AU12: ='Вход и предположения'!$H$11 -> 0.5 | AV12: ='Вход и предположения'!$H$11 -> 0.5 | AW12: ='Вход и предположения'!$H$11 -> 0.5 | ... BA12: ='Вход и предположения'!$H$11 -> 0.5 | BB12: ='Вход и предположения'!$I$11 -> 0.5 | BC12: ='Вход и предположения'!$I$11 -> 0.5 | BD12: ='Вход и предположения'!$I$11 -> 0.5 | BE12: ='Вход и предположения'!$I$11 -> 0.5 | BF12: ='Вход и предположения'!$I$11 -> 0.5 | BG12: ='Вход и предположения'!$I$11 -> 0.5 | BH12: ='Вход и предположения'!$I$11 -> 0.5 | BI12: ='Вход и предположения'!$I$11 -> 0.5 | ... BM12: ='Вход и предположения'!$I$11 -> 0.5
C13: Средняя стоимость часа игры PC | D13: руб/час | F13: ='Вход и предположения'!$E$15 -> 100 | G13: ='Вход и предположения'!$E$15 -> 100 | H13: ='Вход и предположения'!$E$15 -> 100 | I13: ='Вход и предположения'!$E$15 -> 100 | J13: ='Вход и предположения'!$E$15 -> 100 | K13: ='Вход и предположения'!$E$15 -> 100 | L13: ='Вход и предположения'!$E$15 -> 100 | M13: ='Вход и предположения'!$E$15 -> 100 | ... BM13: ='Вход и предположения'!$E$15 -> 100
C14: Средняя стоимость часа игры PC с инфляцией | D14: руб/час | F14: =F13*F6 -> 100 | G14: =G13*G6 -> 100 | H14: =H13*H6 -> 100 | I14: =I13*I6 -> 100 | J14: =J13*J6 -> 100 | K14: =K13*K6 -> 100 | L14: =L13*L6 -> 100 | M14: =M13*M6 -> 100 | ... BM14: =BM13*BM6 -> 117.31987
C15: Количество часов игрового времени 1 PC | D15: часов /1 PC | F15: =F7*F12 -> 144 | G15: =G7*G12 -> 216 | H15: =H7*H12 -> 252 | I15: =I7*I12 -> 288 | J15: =J7*J12 -> 288 | K15: =K7*K12 -> 288 | L15: =L7*L12 -> 288 | M15: =M7*M12 -> 288 | ... BM15: =BM7*BM12 -> 360
C17: Выручка от PC VIP | F17: =F18*F21*F22 -> 79200 | G17: =G18*G21*G22 -> 118800 | H17: =H18*H21*H22 -> 138600 | I17: =I18*I21*I22 -> 158400 | J17: =J18*J21*J22 -> 158400 | K17: =K18*K21*K22 -> 158400 | L17: =L18*L21*L22 -> 158400 | M17: =M18*M21*M22 -> 158400 | ... BM17: =BM18*BM21*BM22 -> 232293.34 | BO17: =SUM(F17:BM17) -> 12084494 | BP17: =SUM(F17:Q17) -> 1762200 | BQ17: =SUM(R17:AC17) -> 2428114.5 | BR17: =SUM(AD17:AO17) -> 2527039.6 | BS17: =SUM(AP17:BA17) -> 2629995.1 | BT17: =SUM(BB17:BM17) -> 2737145.2 | BU17: =SUM(BP17:BT17) -> 12084494
C18: Количество компьютеров PC | D18: шт. | F18: ='Вход и предположения'!$E$5 -> 5 | G18: ='Вход и предположения'!$E$5 -> 5 | H18: ='Вход и предположения'!$E$5 -> 5 | I18: ='Вход и предположения'!$E$5 -> 5 | J18: ='Вход и предположения'!$E$5 -> 5 | K18: ='Вход и предположения'!$E$5 -> 5 | L18: ='Вход и предположения'!$E$5 -> 5 | M18: ='Вход и предположения'!$E$5 -> 5 | ... BM18: ='Вход и предположения'!$E$5 -> 5
C19: % загрузки PC | D19: % | F19: 0.2 | G19: 0.3 | H19: 0.35 | I19: ='Вход и предположения'!$E$12 -> 0.4 | J19: ='Вход и предположения'!$E$12 -> 0.4 | K19: ='Вход и предположения'!$E$12 -> 0.4 | L19: ='Вход и предположения'!$E$12 -> 0.4 | M19: ='Вход и предположения'!$E$12 -> 0.4 | N19: ='Вход и предположения'!$E$12 -> 0.4 | O19: ='Вход и предположения'!$E$12 -> 0.4 | P19: ='Вход и предположения'!$E$12 -> 0.4 | Q19: ='Вход и предположения'!$E$12 -> 0.4 | R19: ='Вход и предположения'!$F$12 -> 0.5 | S19: ='Вход и предположения'!$F$12 -> 0.5 | T19: ='Вход и предположения'!$F$12 -> 0.5 | U19: ='Вход и предположения'!$F$12 -> 0.5 | V19: ='Вход и предположения'!$F$12 -> 0.5 | W19: ='Вход и предположения'!$F$12 -> 0.5 | X19: ='Вход и предположения'!$F$12 -> 0.5 | Y19: ='Вход и предположения'!$F$12 -> 0.5 | ... AC19: ='Вход и предположения'!$F$12 -> 0.5 | AD19: ='Вход и предположения'!$G$12 -> 0.5 | AE19: ='Вход и предположения'!$G$12 -> 0.5 | AF19: ='Вход и предположения'!$G$12 -> 0.5 | AG19: ='Вход и предположения'!$G$12 -> 0.5 | AH19: ='Вход и предположения'!$G$12 -> 0.5 | AI19: ='Вход и предположения'!$G$12 -> 0.5 | AJ19: ='Вход и предположения'!$G$12 -> 0.5 | AK19: ='Вход и предположения'!$G$12 -> 0.5 | ... AO19: ='Вход и предположения'!$G$12 -> 0.5 | AP19: ='Вход и предположения'!$H$12 -> 0.5 | AQ19: ='Вход и предположения'!$H$12 -> 0.5 | AR19: ='Вход и предположения'!$H$12 -> 0.5 | AS19: ='Вход и предположения'!$H$12 -> 0.5 | AT19: ='Вход и предположения'!$H$12 -> 0.5 | AU19: ='Вход и предположения'!$H$12 -> 0.5 | AV19: ='Вход и предположения'!$H$12 -> 0.5 | AW19: ='Вход и предположения'!$H$12 -> 0.5 | ... BA19: ='Вход и предположения'!$H$12 -> 0.5 | BB19: ='Вход и предположения'!$I$12 -> 0.5 | BC19: ='Вход и предположения'!$I$12 -> 0.5 | BD19: ='Вход и предположения'!$I$12 -> 0.5 | BE19: ='Вход и предположения'!$I$12 -> 0.5 | BF19: ='Вход и предположения'!$I$12 -> 0.5 | BG19: ='Вход и предположения'!$I$12 -> 0.5 | BH19: ='Вход и предположения'!$I$12 -> 0.5 | BI19: ='Вход и предположения'!$I$12 -> 0.5 | ... BM19: ='Вход и предположения'!$I$12 -> 0.5
C20: Средняя стоимость часа игры PC | D20: руб/час | F20: ='Вход и предположения'!$E$16 -> 110 | G20: ='Вход и предположения'!$E$16 -> 110 | H20: ='Вход и предположения'!$E$16 -> 110 | I20: ='Вход и предположения'!$E$16 -> 110 | J20: ='Вход и предположения'!$E$16 -> 110 | K20: ='Вход и предположения'!$E$16 -> 110 | L20: ='Вход и предположения'!$E$16 -> 110 | M20: ='Вход и предположения'!$E$16 -> 110 | ... BM20: ='Вход и предположения'!$E$16 -> 110
C21: Средняя стоимость часа игры PC с инфляцией | D21: руб/час | F21: =F20*F6 -> 110 | G21: =G20*G6 -> 110 | H21: =H20*H6 -> 110 | I21: =I20*I6 -> 110 | J21: =J20*J6 -> 110 | K21: =K20*K6 -> 110 | L21: =L20*L6 -> 110 | M21: =M20*M6 -> 110 | ... BM21: =BM20*BM6 -> 129.05185
C22: Количество часов игрового времени 1 PC | D22: часов /1 PC | F22: =F7*F19 -> 144 | G22: =G7*G19 -> 216 | H22: =H7*H19 -> 252 | I22: =I7*I19 -> 288 | J22: =J7*J19 -> 288 | K22: =K7*K19 -> 288 | L22: =L7*L19 -> 288 | M22: =M7*M19 -> 288 | ... BM22: =BM7*BM19 -> 360
C24: Выручка от аренды Sony PS | F24: =F25*F28*F29 -> 57600 | G24: =G25*G28*G29 -> 86400 | H24: =H25*H28*H29 -> 100800 | I24: =I25*I28*I29 -> 115200 | J24: =J25*J28*J29 -> 115200 | K24: =K25*K28*K29 -> 115200 | L24: =L25*L28*L29 -> 115200 | M24: =M25*M28*M29 -> 115200 | ... BM24: =BM25*BM28*BM29 -> 168940.61 | BO24: =SUM(F24:BM24) -> 8788723.2 | BP24: =SUM(F24:Q24) -> 1281600 | BQ24: =SUM(R24:AC24) -> 1765901.4 | BR24: =SUM(AD24:AO24) -> 1837847 | BS24: =SUM(AP24:BA24) -> 1912723.7 | BT24: =SUM(BB24:BM24) -> 1990651 | BU24: =SUM(BP24:BT24) -> 8788723.2
C25: Количество компьютеров PS | D25: шт. | F25: ='Вход и предположения'!$E$6 -> 2 | G25: ='Вход и предположения'!$E$6 -> 2 | H25: ='Вход и предположения'!$E$6 -> 2 | I25: ='Вход и предположения'!$E$6 -> 2 | J25: ='Вход и предположения'!$E$6 -> 2 | K25: ='Вход и предположения'!$E$6 -> 2 | L25: ='Вход и предположения'!$E$6 -> 2 | M25: ='Вход и предположения'!$E$6 -> 2 | ... BM25: ='Вход и предположения'!$E$6 -> 2
C26: % загрузки PS | D26: % | F26: 0.2 | G26: 0.3 | H26: 0.35 | I26: ='Вход и предположения'!$E$13 -> 0.4 | J26: ='Вход и предположения'!$E$13 -> 0.4 | K26: ='Вход и предположения'!$E$13 -> 0.4 | L26: ='Вход и предположения'!$E$13 -> 0.4 | M26: ='Вход и предположения'!$E$13 -> 0.4 | N26: ='Вход и предположения'!$E$13 -> 0.4 | O26: ='Вход и предположения'!$E$13 -> 0.4 | P26: ='Вход и предположения'!$E$13 -> 0.4 | Q26: ='Вход и предположения'!$E$13 -> 0.4 | R26: ='Вход и предположения'!$F$13 -> 0.5 | S26: ='Вход и предположения'!$F$13 -> 0.5 | T26: ='Вход и предположения'!$F$13 -> 0.5 | U26: ='Вход и предположения'!$F$13 -> 0.5 | V26: ='Вход и предположения'!$F$13 -> 0.5 | W26: ='Вход и предположения'!$F$13 -> 0.5 | X26: ='Вход и предположения'!$F$13 -> 0.5 | Y26: ='Вход и предположения'!$F$13 -> 0.5 | ... AC26: ='Вход и предположения'!$F$13 -> 0.5 | AD26: ='Вход и предположения'!$G$13 -> 0.5 | AE26: ='Вход и предположения'!$G$13 -> 0.5 | AF26: ='Вход и предположения'!$G$13 -> 0.5 | AG26: ='Вход и предположения'!$G$13 -> 0.5 | AH26: ='Вход и предположения'!$G$13 -> 0.5 | AI26: ='Вход и предположения'!$G$13 -> 0.5 | AJ26: ='Вход и предположения'!$G$13 -> 0.5 | AK26: ='Вход и предположения'!$G$13 -> 0.5 | ... AO26: ='Вход и предположения'!$G$13 -> 0.5 | AP26: ='Вход и предположения'!$H$13 -> 0.5 | AQ26: ='Вход и предположения'!$H$13 -> 0.5 | AR26: ='Вход и предположения'!$H$13 -> 0.5 | AS26: ='Вход и предположения'!$H$13 -> 0.5 | AT26: ='Вход и предположения'!$H$13 -> 0.5 | AU26: ='Вход и предположения'!$H$13 -> 0.5 | AV26: ='Вход и предположения'!$H$13 -> 0.5 | AW26: ='Вход и предположения'!$H$13 -> 0.5 | ... BA26: ='Вход и предположения'!$H$13 -> 0.5 | BB26: ='Вход и предположения'!$I$13 -> 0.5 | BC26: ='Вход и предположения'!$I$13 -> 0.5 | BD26: ='Вход и предположения'!$I$13 -> 0.5 | BE26: ='Вход и предположения'!$I$13 -> 0.5 | BF26: ='Вход и предположения'!$I$13 -> 0.5 | BG26: ='Вход и предположения'!$I$13 -> 0.5 | BH26: ='Вход и предположения'!$I$13 -> 0.5 | BI26: ='Вход и предположения'!$I$13 -> 0.5 | ... BM26: ='Вход и предположения'!$I$13 -> 0.5
C27: Средняя стоимость часа игры PS | D27: руб/час | F27: ='Вход и предположения'!$E$17 -> 200 | G27: ='Вход и предположения'!$E$17 -> 200 | H27: ='Вход и предположения'!$E$17 -> 200 | I27: ='Вход и предположения'!$E$17 -> 200 | J27: ='Вход и предположения'!$E$17 -> 200 | K27: ='Вход и предположения'!$E$17 -> 200 | L27: ='Вход и предположения'!$E$17 -> 200 | M27: ='Вход и предположения'!$E$17 -> 200 | ... BM27: ='Вход и предположения'!$E$17 -> 200
C28: Средняя стоимость часа игры PS с инфляцией | D28: руб/час | F28: =F27*F6 -> 200 | G28: =G27*G6 -> 200 | H28: =H27*H6 -> 200 | I28: =I27*I6 -> 200 | J28: =J27*J6 -> 200 | K28: =K27*K6 -> 200 | L28: =L27*L6 -> 200 | M28: =M27*M6 -> 200 | ... BM28: =BM27*BM6 -> 234.63973
C29: Количество часов игрового времени 1 PS | D29: часов /1 PS | F29: =F7*F26 -> 144 | G29: =G7*G26 -> 216 | H29: =H7*H26 -> 252 | I29: =I7*I26 -> 288 | J29: =J7*J26 -> 288 | K29: =K7*K26 -> 288 | L29: =L7*L26 -> 288 | M29: =M7*M26 -> 288 | ... BM29: =BM7*BM26 -> 360
C31: Всего часов игрового времени всех PC / PS | F31: =F11*F15+F18*F22+F25*F29 -> 2448 | G31: =G11*G15+G18*G22+G25*G29 -> 3672 | H31: =H11*H15+H18*H22+H25*H29 -> 4284 | I31: =I11*I15+I18*I22+I25*I29 -> 4896 | J31: =J11*J15+J18*J22+J25*J29 -> 4896 | K31: =K11*K15+K18*K22+K25*K29 -> 4896 | L31: =L11*L15+L18*L22+L25*L29 -> 4896 | M31: =M11*M15+M18*M22+M25*M29 -> 4896 | ... BM31: =BM11*BM15+BM18*BM22+BM25*BM29 -> 6120
C33: Выручка кафе | F33: =F34*F36 -> 171360 | G33: =G34*G36 -> 257040 | H33: =H34*H36 -> 299880 | I33: =I34*I36 -> 342720 | J33: =J34*J36 -> 342720 | K33: =K34*K36 -> 342720 | L33: =L34*L36 -> 342720 | M33: =M34*M36 -> 342720 | ... BM33: =BM34*BM36 -> 502598.31 | BO33: =SUM(F33:BM33) -> 26146451 | BP33: =SUM(F33:Q33) -> 3812760 | BQ33: =SUM(R33:AC33) -> 5253556.8 | BR33: =SUM(AD33:AO33) -> 5467594.8 | BS33: =SUM(AP33:BA33) -> 5690353 | BT33: =SUM(BB33:BM33) -> 5922186.8 | BU33: =SUM(BP33:BT33) -> 26146451
C34: Всего часов игрового времени | D34: часов | F34: =F31 -> 2448 | G34: =G31 -> 3672 | H34: =H31 -> 4284 | I34: =I31 -> 4896 | J34: =J31 -> 4896 | K34: =K31 -> 4896 | L34: =L31 -> 4896 | M34: =M31 -> 4896 | ... BM34: =BM31 -> 6120
C35: Рублей выручки бара на 1 час игрового времени | D35: руб./час. | F35: ='Вход и предположения'!$E$18 -> 70 | G35: ='Вход и предположения'!$E$18 -> 70 | H35: ='Вход и предположения'!$E$18 -> 70 | I35: ='Вход и предположения'!$E$18 -> 70 | J35: ='Вход и предположения'!$E$18 -> 70 | K35: ='Вход и предположения'!$E$18 -> 70 | L35: ='Вход и предположения'!$E$18 -> 70 | M35: ='Вход и предположения'!$E$18 -> 70 | ... BM35: ='Вход и предположения'!$E$18 -> 70
C36: Рублей выручки бара на 1 час игрового времени с инфляцией | D36: руб./час. | F36: =F35*F6 -> 70 | G36: =G35*G6 -> 70 | H36: =H35*H6 -> 70 | I36: =I35*I6 -> 70 | J36: =J35*J6 -> 70 | K36: =K35*K6 -> 70 | L36: =L35*L6 -> 70 | M36: =M35*M6 -> 70 | ... BM36: =BM35*BM6 -> 82.123907
C38: Прочие доходы | D38: руб./мес. | F38: =F40 -> 15000 | G38: =G40 -> 15000 | H38: =H40 -> 15000 | I38: =I40 -> 15000 | J38: =J40 -> 15000 | K38: =K40 -> 15000 | L38: =L40 -> 15000 | M38: =M40 -> 15000 | ... BM38: =BM40 -> 17597.98 | BO38: =SUM(F38:BM38) -> 961991.99 | BP38: =SUM(F38:Q38) -> 180000 | BQ38: =SUM(R38:AC38) -> 183948.07 | BR38: =SUM(AD38:AO38) -> 191442.39 | BS38: =SUM(AP38:BA38) -> 199242.05 | BT38: =SUM(BB38:BM38) -> 207359.48 | BU38: =SUM(BP38:BT38) -> 961991.99
C39: Прочие доходы без инфляции | F39: ='Вход и предположения'!$E$19 -> 15000 | G39: ='Вход и предположения'!$E$19 -> 15000 | H39: ='Вход и предположения'!$E$19 -> 15000 | I39: ='Вход и предположения'!$E$19 -> 15000 | J39: ='Вход и предположения'!$E$19 -> 15000 | K39: ='Вход и предположения'!$E$19 -> 15000 | L39: ='Вход и предположения'!$E$19 -> 15000 | M39: ='Вход и предположения'!$E$19 -> 15000 | ... BM39: ='Вход и предположения'!$E$19 -> 15000
C40: Прочие доходы с инфляцией | F40: =F39*F6 -> 15000 | G40: =G39*G6 -> 15000 | H40: =H39*H6 -> 15000 | I40: =I39*I6 -> 15000 | J40: =J39*J6 -> 15000 | K40: =K39*K6 -> 15000 | L40: =L39*L6 -> 15000 | M40: =M39*M6 -> 15000 | ... BM40: =BM39*BM6 -> 17597.98
C42: TOTAL REVENUE | F42: =F10+F17+F24+F33+F38 -> 467160 | G42: =G10+G17+G24+G33+G38 -> 693240 | H42: =H10+H17+H24+H33+H38 -> 806280 | I42: =I10+I17+I24+I33+I38 -> 919320 | J42: =J10+J17+J24+J33+J38 -> 919320 | K42: =K10+K17+K24+K33+K38 -> 919320 | L42: =L10+L17+L24+L33+L38 -> 919320 | M42: =M10+M17+M24+M33+M38 -> 919320 | ... BM42: =BM10+BM17+BM24+BM33+BM38 -> 1343781.8 | BO42: =SUM(F42:BM42) -> 69953469 | BP42: =SUM(F42:Q42) -> 10240560 | BQ42: =SUM(R42:AC42) -> 14046274 | BR42: =SUM(AD42:AO42) -> 14618541 | BS42: =SUM(AP42:BA42) -> 15214123 | BT42: =SUM(BB42:BM42) -> 15833970 | BU42: =SUM(BP42:BT42) -> 69953469
C44: OPEX
C45: Площадь помещения | D45: м2 | F45: ='Вход и предположения'!$E$7 -> 200 | G45: ='Вход и предположения'!$E$7 -> 200 | H45: ='Вход и предположения'!$E$7 -> 200 | I45: ='Вход и предположения'!$E$7 -> 200 | J45: ='Вход и предположения'!$E$7 -> 200 | K45: ='Вход и предположения'!$E$7 -> 200 | L45: ='Вход и предположения'!$E$7 -> 200 | M45: ='Вход и предположения'!$E$7 -> 200 | ... BM45: ='Вход и предположения'!$E$7 -> 200
C46: Среднее количество рабочих дней | D46: дней | F46: =30 -> 30 | G46: =30 -> 30 | H46: =30 -> 30 | I46: =30 -> 30 | J46: =30 -> 30 | K46: =30 -> 30 | L46: =30 -> 30 | M46: =30 -> 30 | ... BM46: =30 -> 30
C48: Аренда помещения (фиксированная ставка) | F48: =F49*F50*F52/12 -> 150625 | G48: =G49*G50*G52/12 -> 151252.6 | H48: =H49*H50*H52/12 -> 151882.82 | I48: =I49*I50*I52/12 -> 152515.67 | J48: =J49*J50*J52/12 -> 153151.15 | K48: =K49*K50*K52/12 -> 153789.28 | L48: =L49*L50*L52/12 -> 154430.07 | M48: =M49*M50*M52/12 -> 155073.53 | ... BM48: =BM49*BM50*BM52/12 -> 192503.8 | BO48: =SUM(F48:BM48) -> 10243416 | BP48: =SUM(F48:Q48) -> 1849502.6 | BQ48: =SUM(R48:AC48) -> 1944126.7 | BR48: =SUM(AD48:AO48) -> 2043591.9 | BS48: =SUM(AP48:BA48) -> 2148145.9 | BT48: =SUM(BB48:BM48) -> 2258049.1 | BU48: =SUM(BP48:BT48) -> 10243416
C49: Площадь | D49: м2 | F49: =F45 -> 200 | G49: =G45 -> 200 | H49: =H45 -> 200 | I49: =I45 -> 200 | J49: =J45 -> 200 | K49: =K45 -> 200 | L49: =L45 -> 200 | M49: =M45 -> 200 | ... BM49: =BM45 -> 200
C50: Ставка аренды | D50: руб./м2 в год | F50: ='Вход и предположения'!$E$22 -> 9000 | G50: ='Вход и предположения'!$E$22 -> 9000 | H50: ='Вход и предположения'!$E$22 -> 9000 | I50: ='Вход и предположения'!$E$22 -> 9000 | J50: ='Вход и предположения'!$E$22 -> 9000 | K50: ='Вход и предположения'!$E$22 -> 9000 | L50: ='Вход и предположения'!$E$22 -> 9000 | M50: ='Вход и предположения'!$E$22 -> 9000 | ... BM50: ='Вход и предположения'!$E$22 -> 9000
C51: % роста годовой арендной ставки помещения | D51: % в год | F51: ='Вход и предположения'!$E$24 -> 0.05 | G51: ='Вход и предположения'!$E$24 -> 0.05 | H51: ='Вход и предположения'!$E$24 -> 0.05 | I51: ='Вход и предположения'!$E$24 -> 0.05 | J51: ='Вход и предположения'!$E$24 -> 0.05 | K51: ='Вход и предположения'!$E$24 -> 0.05 | L51: ='Вход и предположения'!$E$24 -> 0.05 | M51: ='Вход и предположения'!$E$24 -> 0.05 | ... BM51: ='Вход и предположения'!$E$24 -> 0.05
C52: Накопленный % роста | E52: 1 | F52: =E52*(1+F51/12) -> 1.0041667 | G52: =F52*(1+G51/12) -> 1.0083507 | H52: =G52*(1+H51/12) -> 1.0125522 | I52: =H52*(1+I51/12) -> 1.0167711 | J52: =I52*(1+J51/12) -> 1.0210077 | K52: =J52*(1+K51/12) -> 1.0252619 | L52: =K52*(1+L51/12) -> 1.0295338 | M52: =L52*(1+M51/12) -> 1.0338235 | ... BM52: =BL52*(1+BM51/12) -> 1.2833587
C54: Коммунальные платежи | F54: =F55*F6 -> 2500 | G54: =G55*G6 -> 2500 | H54: =H55*H6 -> 2500 | I54: =I55*I6 -> 2500 | J54: =J55*J6 -> 2500 | K54: =K55*K6 -> 2500 | L54: =L55*L6 -> 2500 | M54: =M55*M6 -> 2500 | ... BM54: =BM55*BM6 -> 2932.9967 | BO54: =SUM(F54:BM54) -> 160332 | BP54: =SUM(F54:Q54) -> 30000 | BQ54: =SUM(R54:AC54) -> 30658.011 | BR54: =SUM(AD54:AO54) -> 31907.066 | BS54: =SUM(AP54:BA54) -> 33207.009 | BT54: =SUM(BB54:BM54) -> 34559.914 | BU54: =SUM(BP54:BT54) -> 160332
C55: Коммунальные платежи в мес. на 1 м2 | D55: руб. | F55: ='Вход и предположения'!$E$27 -> 2500 | G55: ='Вход и предположения'!$E$27 -> 2500 | H55: ='Вход и предположения'!$E$27 -> 2500 | I55: ='Вход и предположения'!$E$27 -> 2500 | J55: ='Вход и предположения'!$E$27 -> 2500 | K55: ='Вход и предположения'!$E$27 -> 2500 | L55: ='Вход и предположения'!$E$27 -> 2500 | M55: ='Вход и предположения'!$E$27 -> 2500 | ... BM55: ='Вход и предположения'!$E$27 -> 2500
C57: Заработная плата | F57: =F58*F6 -> 252400 | G57: =G58*G6 -> 250900 | H57: =H58*H6 -> 250900 | I57: =I58*I6 -> 250900 | J57: =J58*J6 -> 250900 | K57: =K58*K6 -> 250900 | L57: =L58*L6 -> 250900 | M57: =M58*M6 -> 250900 | ... BM57: =BM58*BM6 -> 294355.55 | BO57: =SUM(F57:BM57) -> 16092419 | BP57: =SUM(F57:Q57) -> 3012300 | BQ57: =SUM(R57:AC57) -> 3076838 | BR57: =SUM(AD57:AO57) -> 3202193.1 | BS57: =SUM(AP57:BA57) -> 3332655.4 | BT57: =SUM(BB57:BM57) -> 3468432.9 | BU57: =SUM(BP57:BT57) -> 16092419
C58: Фонд оплаты труда | D58: руб. | F58: =F61+F62+'Операц.изд. в мес.'!F11 -> 252400 | G58: =G61+G62+'Операц.изд. в мес.'!G11 -> 250900 | H58: =H61+H62+'Операц.изд. в мес.'!H11 -> 250900 | I58: =I61+I62+'Операц.изд. в мес.'!I11 -> 250900 | J58: =J61+J62+'Операц.изд. в мес.'!J11 -> 250900 | K58: =K61+K62+'Операц.изд. в мес.'!K11 -> 250900 | L58: =L61+L62+'Операц.изд. в мес.'!L11 -> 250900 | M58: =M61+M62+'Операц.изд. в мес.'!M11 -> 250900 | ... BM58: =BM61+BM62+'Операц.изд. в мес.'!BM11 -> 250900
C60: ставка ЕСН | D60: % | F60: ='Операц.изд. в мес.'!$I$4 -> 0.3
C61: Сумма официальной з/п в мес. | D61: руб./мес. | F61: ='Вход и предположения'!$E$29 -> 193000 | G61: ='Вход и предположения'!$E$29 -> 193000 | H61: ='Вход и предположения'!$E$29 -> 193000 | I61: ='Вход и предположения'!$E$29 -> 193000 | J61: ='Вход и предположения'!$E$29 -> 193000 | K61: ='Вход и предположения'!$E$29 -> 193000 | L61: ='Вход и предположения'!$E$29 -> 193000 | M61: ='Вход и предположения'!$E$29 -> 193000 | ... BM61: ='Вход и предположения'!$E$29 -> 193000
C62: Сумма отчислений ЕСН | D62: руб./мес. | F62: =F61*$F$60 -> 57900 | G62: =G61*$F$60 -> 57900 | H62: =H61*$F$60 -> 57900 | I62: =I61*$F$60 -> 57900 | J62: =J61*$F$60 -> 57900 | K62: =K61*$F$60 -> 57900 | L62: =L61*$F$60 -> 57900 | M62: =M61*$F$60 -> 57900 | ... BM62: =BM61*$F$60 -> 57900
C64: Реклама | F64: =F42*F65*(1+F66) -> 72176.22 | G64: =G42*G65*(1+G66) -> 14003.448 | H64: =H42*H65*(1+H66) -> 16286.856 | I64: =I42*I65*(1+I66) -> 18570.264 | J64: =J42*J65*(1+J66) -> 18570.264 | K64: =K42*K65*(1+K66) -> 18570.264 | L64: =L42*L65*(1+L66) -> 18570.264 | M64: =M42*M65*(1+M66) -> 18570.264 | ... BM64: =BM42*BM65*(1+BM66) -> 27144.391 | BO64: =SUM(F64:BM64) -> 1480575.2 | BP64: =SUM(F64:Q64) -> 270150.49 | BQ64: =SUM(R64:AC64) -> 284907.19 | BR64: =SUM(AD64:AO64) -> 296518.83 | BS64: =SUM(AP64:BA64) -> 307827.36 | BT64: =SUM(BB64:BM64) -> 321171.37 | BU64: =SUM(BP64:BT64) -> 1480575.2
C65: % затрат на рекламу от выручки | D65: % от выручки | F65: =15% -> 0.15 | G65: ='Вход и предположения'!$E$30 -> 0.02 | H65: ='Вход и предположения'!$E$30 -> 0.02 | I65: ='Вход и предположения'!$E$30 -> 0.02 | J65: ='Вход и предположения'!$E$30 -> 0.02 | K65: ='Вход и предположения'!$E$30 -> 0.02 | L65: ='Вход и предположения'!$E$30 -> 0.02 | M65: ='Вход и предположения'!$E$30 -> 0.02 | N65: ='Вход и предположения'!$E$30 -> 0.02 | ... BM65: ='Вход и предположения'!$E$30 -> 0.02
C66: % корректировки суммы затрат на рекламу | F66: 0.03 | G66: 0.01 | H66: 0.01 | I66: 0.01 | J66: 0.01 | K66: 0.01 | L66: 0.01 | M66: 0.01 | N66: 0.02 | O66: 0.01 | P66: 0.02 | Q66: 0.02 | R66: 0.01 | S66: 0.01 | T66: 0.02 | U66: 0.01 | V66: 0.02 | W66: 0.01 | X66: 0.02 | Y66: 0.01 | Z66: 0.02 | AA66: 0.01 | AB66: 0.02 | AC66: 0.01 | AD66: 0.01 | AE66: 0.01 | AF66: 0.02 | AG66: 0.01 | AH66: 0.01 | AI66: 0.01 | AJ66: 0.03 | AK66: 0.01 | AL66: 0.01 | AM66: 0.01 | AN66: 0.02 | AO66: 0.02 | AP66: 0.01 | AQ66: 0.02 | AR66: 0.01 | AS66: 0.01 | AT66: 0.02 | AU66: 0.01 | AV66: 0.01 | AW66: 0.01 | AX66: 0.01 | AY66: 0.01 | AZ66: 0.01 | BA66: 0.01 | BB66: 0.01 | BC66: 0.01 | BD66: 0.01 | BE66: 0.02 | BF66: 0.01 | BG66: 0.02 | BH66: 0.01 | BI66: 0.01 | BJ66: 0.03 | BK66: 0.01 | BL66: 0.02 | BM66: 0.01
C68: Интернет | F68: =F69*F6 -> 50000 | G68: =G69*G6 -> 50000 | H68: =H69*H6 -> 50000 | I68: =I69*I6 -> 50000 | J68: =J69*J6 -> 50000 | K68: =K69*K6 -> 50000 | L68: =L69*L6 -> 50000 | M68: =M69*M6 -> 50000 | ... BM68: =BM69*BM6 -> 58659.933 | BO68: =SUM(F68:BM68) -> 3206640 | BP68: =SUM(F68:Q68) -> 600000 | BQ68: =SUM(R68:AC68) -> 613160.22 | BR68: =SUM(AD68:AO68) -> 638141.31 | BS68: =SUM(AP68:BA68) -> 664140.18 | BT68: =SUM(BB68:BM68) -> 691198.27 | BU68: =SUM(BP68:BT68) -> 3206640
C69: Затраты на интернет и электричество в мес. | D69: тыс.руб/мес. | F69: ='Вход и предположения'!$E$32 -> 50000 | G69: ='Вход и предположения'!$E$32 -> 50000 | H69: ='Вход и предположения'!$E$32 -> 50000 | I69: ='Вход и предположения'!$E$32 -> 50000 | J69: ='Вход и предположения'!$E$32 -> 50000 | K69: ='Вход и предположения'!$E$32 -> 50000 | L69: ='Вход и предположения'!$E$32 -> 50000 | M69: ='Вход и предположения'!$E$32 -> 50000 | ... BM69: ='Вход и предположения'!$E$32 -> 50000
C71: Закупки Бар | F71: =F33/$F$73 -> 81600 | G71: =G33/$F$73 -> 122400 | H71: =H33/$F$73 -> 142800 | I71: =I33/$F$73 -> 163200 | J71: =J33/$F$73 -> 163200 | K71: =K33/$F$73 -> 163200 | L71: =L33/$F$73 -> 163200 | M71: =M33/$F$73 -> 163200 | ... BM71: =BM33/$F$73 -> 239332.53 | BO71: =SUM(F71:BM71) -> 12450691 | BP71: =SUM(F71:Q71) -> 1815600 | BQ71: =SUM(R71:AC71) -> 2501693.7 | BR71: =SUM(AD71:AO71) -> 2603616.6 | BS71: =SUM(AP71:BA71) -> 2709691.9 | BT71: =SUM(BB71:BM71) -> 2820088.9 | BU71: =SUM(BP71:BT71) -> 12450691
C72: Маржинальность бара ( % наценки) | D72: % | F72: 1.1
F73: 2.1
C75: Прочие затраты | F75: =(F48+F54+F57+F62+F64+F68+F71)*'Вход и предположения'!$E$25 -> 20016.037 | G75: =(G48+G54+G57+G62+G64+G68+G71)*'Вход и предположения'!$E$25 -> 19468.682 | H75: =(H48+H54+H57+H62+H64+H68+H71)*'Вход и предположения'!$E$25 -> 20168.09 | I75: =(I48+I54+I57+I62+I64+I68+I71)*'Вход и предположения'!$E$25 -> 20867.578 | J75: =(J48+J54+J57+J62+J64+J68+J71)*'Вход и предположения'!$E$25 -> 20886.642 | K75: =(K48+K54+K57+K62+K64+K68+K71)*'Вход и предположения'!$E$25 -> 20905.786 | L75: =(L48+L54+L57+L62+L64+L68+L71)*'Вход и предположения'!$E$25 -> 20925.01 | M75: =(M48+M54+M57+M62+M64+M68+M71)*'Вход и предположения'!$E$25 -> 20944.314 | ... BM75: =(BM48+BM54+BM57+BM62+BM64+BM68+BM71)*'Вход и предположения'!$E$25 -> 26184.876 | BO75: =SUM(F75:BM75) -> 1413242.2 | BP75: =SUM(F75:Q75) -> 248170.59 | BQ75: =SUM(R75:AC75) -> 274385.51 | BR75: =SUM(AD75:AO75) -> 285323.06 | BS75: =SUM(AP75:BA75) -> 296714.03 | BT75: =SUM(BB75:BM75) -> 308649.02 | BU75: =SUM(BP75:BT75) -> 1413242.2
C77: Эквайринг | F77: =$F$78*$F$79*F42 -> 3737.28 | G77: =$F$78*$F$79*G42 -> 5545.92 | H77: =$F$78*$F$79*H42 -> 6450.24 | I77: =$F$78*$F$79*I42 -> 7354.56 | J77: =$F$78*$F$79*J42 -> 7354.56 | K77: =$F$78*$F$79*K42 -> 7354.56 | L77: =$F$78*$F$79*L42 -> 7354.56 | M77: =$F$78*$F$79*M42 -> 7354.56 | ... BM77: =$F$78*$F$79*BM42 -> 10750.254 | BO77: =SUM(F77:BM77) -> 559627.75 | BP77: =SUM(F77:Q77) -> 81924.48 | BQ77: =SUM(R77:AC77) -> 112370.19 | BR77: =SUM(AD77:AO77) -> 116948.33 | BS77: =SUM(AP77:BA77) -> 121712.99 | BT77: =SUM(BB77:BM77) -> 126671.76 | BU77: =SUM(BP77:BT77) -> 559627.75
C78: Доля карточных платежей от выручки | D78: % | F78: ='Вход и предположения'!E34 -> 0.4
C79: Комиссия за эквайринг | D79: % | F79: ='Вход и предположения'!E35 -> 0.02
C81: Бухгалтреское обслуживание | F81: =F6*'Вход и предположения'!$E$37 -> 1500 | G81: =G6*'Вход и предположения'!$E$37 -> 1500 | H81: =H6*'Вход и предположения'!$E$37 -> 1500 | I81: =I6*'Вход и предположения'!$E$37 -> 1500 | J81: =J6*'Вход и предположения'!$E$37 -> 1500 | K81: =K6*'Вход и предположения'!$E$37 -> 1500 | L81: =L6*'Вход и предположения'!$E$37 -> 1500 | M81: =M6*'Вход и предположения'!$E$37 -> 1500 | ... BM81: =BM6*'Вход и предположения'!$E$37 -> 1759.798 | BO81: =SUM(F81:BM81) -> 96199.199 | BP81: =SUM(F81:Q81) -> 18000 | BQ81: =SUM(R81:AC81) -> 18394.807 | BR81: =SUM(AD81:AO81) -> 19144.239 | BS81: =SUM(AP81:BA81) -> 19924.205 | BT81: =SUM(BB81:BM81) -> 20735.948 | BU81: =SUM(BP81:BT81) -> 96199.199
C83: Амортизация | D83: руб. | F83: =Нач.инв.!$G$15+Нач.инв.!$G$31+Нач.инв.!$H$47+Нач.инв.!$H$57 -> 3014 | G83: =Нач.инв.!$G$15+Нач.инв.!$G$31+Нач.инв.!$H$47+Нач.инв.!$H$57 -> 3014 | H83: =Нач.инв.!$G$15+Нач.инв.!$G$31+Нач.инв.!$H$47+Нач.инв.!$H$57 -> 3014 | I83: =Нач.инв.!$G$15+Нач.инв.!$G$31+Нач.инв.!$H$47+Нач.инв.!$H$57 -> 3014 | J83: =Нач.инв.!$G$15+Нач.инв.!$G$31+Нач.инв.!$H$47+Нач.инв.!$H$57 -> 3014 | K83: =Нач.инв.!$G$15+Нач.инв.!$G$31+Нач.инв.!$H$47+Нач.инв.!$H$57 -> 3014 | L83: =Нач.инв.!$G$15+Нач.инв.!$G$31+Нач.инв.!$H$47+Нач.инв.!$H$57 -> 3014 | M83: =Нач.инв.!$G$15+Нач.инв.!$G$31+Нач.инв.!$H$47+Нач.инв.!$H$57 -> 3014 | ... BM83: =Нач.инв.!$G$15+Нач.инв.!$G$31+Нач.инв.!$H$47+Нач.инв.!$H$57 -> 3014 | BO83: =SUM(F83:BM83) -> 180840 | BP83: =SUM(F83:Q83) -> 36168 | BQ83: =SUM(R83:AC83) -> 36168 | BR83: =SUM(AD83:AO83) -> 36168 | BS83: =SUM(AP83:BA83) -> 36168 | BT83: =SUM(BB83:BM83) -> 36168 | BU83: =SUM(BP83:BT83) -> 180840
C85: Процентные платежи | D85: руб. | F85: ='Вход и предположения'!E55 -> 6250 | G85: ='Вход и предположения'!F55 -> 6076.3889 | H85: ='Вход и предположения'!G55 -> 5902.7778 | I85: ='Вход и предположения'!H55 -> 5729.1667 | J85: ='Вход и предположения'!I55 -> 5555.5556 | K85: ='Вход и предположения'!J55 -> 5381.9444 | L85: ='Вход и предположения'!K55 -> 5208.3333 | M85: ='Вход и предположения'!L55 -> 5034.7222 | ... AO85: ='Вход и предположения'!AN55 -> 173.61111 | AP85: 0 | AQ85: 0 | AR85: 0 | AS85: 0 | AT85: 0 | AU85: 0 | AV85: 0 | AW85: 0 | AX85: 0 | AY85: 0 | AZ85: 0 | BA85: 0 | BB85: 0 | BC85: 0 | BD85: 0 | BE85: 0 | BF85: 0 | BG85: 0 | BH85: 0 | BI85: 0 | BJ85: 0 | BK85: 0 | BL85: 0 | BM85: 0 | BO85: =SUM(F85:BM85) -> 115625 | BP85: =SUM(F85:Q85) -> 63541.667 | BQ85: =SUM(R85:AC85) -> 38541.667 | BR85: =SUM(AD85:AO85) -> 13541.667 | BS85: =SUM(AP85:BA85) -> 0 | BT85: =SUM(BB85:BM85) -> 0 | BU85: =SUM(BP85:BT85) -> 115625
C87: Налоги (УСН 15%) | F87: =IF(F42>(F48+F54+F57+F64+F68+F71+F75+F77+F81+F83+F85),(F42-F48-F54-F57-F64-F68-F71-F75-F77-F81-F83-F85)*F88,F42*0.01) -> 4671.6 | G87: =IF(G42>(G48+G54+G57+G64+G68+G71+G75+G77+G81+G83+G85),(G42-G48-G54-G57-G64-G68-G71-G75-G77-G81-G83-G85)*G88,G42*0.01) -> 9986.8436 | H87: =IF(H42>(H48+H54+H57+H64+H68+H71+H75+H77+H81+H83+H85),(H42-H48-H54-H57-H64-H68-H71-H75-H77-H81-H83-H85)*H88,H42*0.01) -> 23231.282 | I87: =IF(I42>(I48+I54+I57+I64+I68+I71+I75+I77+I81+I83+I85),(I42-I48-I54-I57-I64-I68-I71-I75-I77-I81-I83-I85)*I88,I42*0.01) -> 36475.314 | J87: =IF(J42>(J48+J54+J57+J64+J68+J71+J75+J77+J81+J83+J85),(J42-J48-J54-J57-J64-J68-J71-J75-J77-J81-J83-J85)*J88,J42*0.01) -> 36403.174 | K87: =IF(K42>(K48+K54+K57+K64+K68+K71+K75+K77+K81+K83+K85),(K42-K48-K54-K57-K64-K68-K71-K75-K77-K81-K83-K85)*K88,K42*0.01) -> 36330.625 | L87: =IF(L42>(L48+L54+L57+L64+L68+L71+L75+L77+L81+L83+L85),(L42-L48-L54-L57-L64-L68-L71-L75-L77-L81-L83-L85)*L88,L42*0.01) -> 36257.665 | M87: =IF(M42>(M48+M54+M57+M64+M68+M71+M75+M77+M81+M83+M85),(M42-M48-M54-M57-M64-M68-M71-M75-M77-M81-M83-M85)*M88,M42*0.01) -> 36184.292 | ... BM87: =IF(BM42>(BM48+BM54+BM57+BM64+BM68+BM71+BM75+BM77+BM81+BM83+BM85),(BM42-BM48-BM54-BM57-BM64-BM68-BM71-BM75-BM77-BM81-BM83-BM85)*BM88,BM42*0.01) -> 73071.545 | BO87: =SUM(F87:BM87) -> 3624249.5 | BP87: =SUM(F87:Q87) -> 363450.7 | BQ87: =SUM(R87:AC87) -> 767254.56 | BR87: =SUM(AD87:AO87) -> 799717.07 | BS87: =SUM(AP87:BA87) -> 831590.42 | BT87: =SUM(BB87:BM87) -> 862236.71 | BU87: =SUM(BP87:BT87) -> 3624249.5
C88: Ставка УСН | D88: % | F88: =1% -> 0.01 | G88: ='Вход и предположения'!$E$28 -> 0.15 | H88: ='Вход и предположения'!$E$28 -> 0.15 | I88: ='Вход и предположения'!$E$28 -> 0.15 | J88: ='Вход и предположения'!$E$28 -> 0.15 | K88: ='Вход и предположения'!$E$28 -> 0.15 | L88: ='Вход и предположения'!$E$28 -> 0.15 | M88: ='Вход и предположения'!$E$28 -> 0.15 | N88: ='Вход и предположения'!$E$28 -> 0.15 | ... BM88: ='Вход и предположения'!$E$28 -> 0.15
C90: TOTAL OPEX | F90: =F48+F54+F57+F64+F68+F71+F75+F77+F81+F87+F83+F85 -> 648490.14 | G90: =G48+G54+G57+G64+G68+G71+G75+G77+G81+G87+G83+G85 -> 636647.89 | H90: =H48+H54+H57+H64+H68+H71+H75+H77+H81+H87+H83+H85 -> 674636.07 | I90: =I48+I54+I57+I64+I68+I71+I75+I77+I81+I87+I83+I85 -> 712626.55 | J90: =J48+J54+J57+J64+J68+J71+J75+J77+J81+J87+J83+J85 -> 713035.35 | K90: =K48+K54+K57+K64+K68+K71+K75+K77+K81+K87+K83+K85 -> 713446.46 | L90: =L48+L54+L57+L64+L68+L71+L75+L77+L81+L87+L83+L85 -> 713859.9 | M90: =M48+M54+M57+M64+M68+M71+M75+M77+M81+M87+M83+M85 -> 714275.68 | ... BM90: =BM48+BM54+BM57+BM64+BM68+BM71+BM75+BM77+BM81+BM87+BM83+BM85 -> 929709.67 | BO90: =SUM(F90:BM90) -> 49623858 | BP90: =SUM(F90:Q90) -> 8388808.5 | BQ90: =SUM(R90:AC90) -> 9698498.5 | BR90: =SUM(AD90:AO90) -> 10086811 | BS90: =SUM(AP90:BA90) -> 10501777 | BT90: =SUM(BB90:BM90) -> 10947962 | BU90: =SUM(BP90:BT90) -> 49623858
C93: Margin(Прибыль) | F93: =F42-F90 -> -181330.14 | G93: =G42-G90 -> 56592.114 | H93: =H42-H90 -> 131643.93 | I93: =I42-I90 -> 206693.45 | J93: =J42-J90 -> 206284.65 | K93: =K42-K90 -> 205873.54 | L93: =L42-L90 -> 205460.1 | M93: =M42-M90 -> 205044.32 | ... BM93: =BM42-BM90 -> 414072.09 | BO93: =SUM(F93:BM93) -> 20329611 | BP93: =SUM(F93:Q93) -> 1851751.5 | BQ93: =SUM(R93:AC93) -> 4347775.8 | BR93: =SUM(AD93:AO93) -> 4531730.1 | BS93: =SUM(AP93:BA93) -> 4712345.7 | BT93: =SUM(BB93:BM93) -> 4886008 | BU93: =SUM(BP93:BT93) -> 20329611
C94: Margin % | F94: =F93/F42 -> -0.38815424 | G94: =G93/G42 -> 0.08163423 | H94: =H93/H42 -> 0.16327322 | I94: =I93/I42 -> 0.22483297 | J94: =J93/J42 -> 0.2243883 | K94: =K93/K42 -> 0.22394111 | L94: =L93/L42 -> 0.22349138 | M94: =M93/M42 -> 0.22303912 | ... BM94: =BM93/BM42 -> 0.30813939
C97: CAPEX
C98: Инвестиции | D98: =Инв.расчет!G28 -> 3622300
C100: Total investments | D100: =D98 -> 3622300 | BO100: =D100 -> 3622300 | BP100: =SUM(F100:Q100) -> 0 | BQ100: =SUM(R100:AC100) -> 0 | BR100: =SUM(AD100:AO100) -> 0 | BS100: =SUM(AP100:BA100) -> 0 | BT100: =SUM(BB100:BM100) -> 0 | BU100: =BO100 -> 3622300
C103: Оборотные средства
C104: Отношение оборотного капитала к выручке | D104: % | E104: ='Вход и предположения'!E26 -> 0.1
C105: Требующиеся оборотные средства | D105: тыс. руб. | F105: =$E$104*F42 -> 46716 | G105: =$E$104*G42 -> 69324 | H105: =$E$104*H42 -> 80628 | I105: =$E$104*I42 -> 91932 | J105: =$E$104*J42 -> 91932 | K105: =$E$104*K42 -> 91932 | L105: =$E$104*L42 -> 91932 | M105: =$E$104*M42 -> 91932 | ... BM105: =$E$104*BM42 -> 134378.18
C106: Изменение оборотных средств | D106: тыс. руб. | F106: - | G106: =G105-F105 -> 22608 | H106: =H105-G105 -> 11304 | I106: =I105-H105 -> 11304 | J106: =J105-I105 -> 0 | K106: =K105-J105 -> 0 | L106: =L105-K105 -> 0 | M106: =M105-L105 -> 0 | N106: =N105-M105 -> 0 | ... BM106: =BM105-BL105 -> 446.43912
E108: 0 | F108: 1 | G108: 2 | H108: 3 | I108: 4 | J108: 5 | K108: 6 | L108: 7 | M108: 8 | N108: 9 | O108: 10 | P108: 11 | Q108: 12 | R108: 13 | S108: 14 | T108: 15 | U108: 16 | V108: 17 | W108: 18 | X108: 19 | Y108: 20 | Z108: 21 | AA108: 22 | AB108: 23 | AC108: 24 | AD108: 25 | AE108: 26 | AF108: 27 | AG108: 28 | AH108: 29 | AI108: 30 | AJ108: 31 | AK108: 32 | AL108: 33 | AM108: 34 | AN108: 35 | AO108: 36 | AP108: 37 | AQ108: 38 | AR108: 39 | AS108: 40 | AT108: 41 | AU108: 42 | AV108: 43 | AW108: 44 | AX108: 45 | AY108: 46 | AZ108: 47 | BA108: 48 | BB108: 49 | BC108: 50 | BD108: 51 | BE108: 52 | BF108: 53 | BG108: 54 | BH108: 55 | BI108: 56 | BJ108: 57 | BK108: 58 | BL108: 59 | BM108: 60
C109: Free Cash Flow | E109: =-D98 -> -3622300 | F109: =F42-F90 -> -181330.14 | G109: =G42-G90+G106 -> 79200.114 | H109: =H42-H90+H106 -> 142947.93 | I109: =I42-I90+I106 -> 217997.45 | J109: =J42-J90+J106 -> 206284.65 | K109: =K42-K90+K106 -> 205873.54 | L109: =L42-L90+L106 -> 205460.1 | M109: =M42-M90+M106 -> 205044.32 | N109: =N42-N90+N106 -> 204465.22 | ... BM109: =BM42-BM90+BM106 -> 414518.52 | BP109: =SUM(F109:Q109) -> 1896967.5 | BQ109: =SUM(R109:AC109) -> 4375050.4 | BR109: =SUM(AD109:AO109) -> 4536586.7 | BS109: =SUM(AP109:BA109) -> 4717400.2 | BT109: =SUM(BB109:BM109) -> 4891268.5 | BU109: =SUM(BP109:BT109) -> 20417273
C110: Cumulative cash flow | E110: =E109 -> -3622300 | F110: =F109+E110 -> -3803630.1 | G110: =G109+F110 -> -3724430 | H110: =H109+G110 -> -3581482.1 | I110: =I109+H110 -> -3363484.6 | J110: =J109+I110 -> -3157200 | K110: =K109+J110 -> -2951326.4 | L110: =L109+K110 -> -2745866.4 | M110: =M109+L110 -> -2540822 | ... BM110: =BM109+BL110 -> 16794973
E111: =IF(E110<0,E3,0) -> 1 | F111: =IF(F110<0,F3,0) -> 1 | G111: =IF(G110<0,G3,0) -> 1 | H111: =IF(H110<0,H3,0) -> 1 | I111: =IF(I110<0,I3,0) -> 1 | J111: =IF(J110<0,J3,0) -> 1 | K111: =IF(K110<0,K3,0) -> 1 | L111: =IF(L110<0,L3,0) -> 1 | ... BM111: =IF(BM110<0,BM3,0) -> 0
B113: =SUM(E111:BM111) -> 17 | C113: =B113/12 -> 1.4166667
C116: Discounted cash flow
C117: Ставка дисконтирования | D117: =C125/12 -> 0.011266843
C118: Discounted cash flow | E118: =E109/(1+$D$117)^E8 -> -3622300 | F118: =F109/(1+$D$117)^F8 -> -179309.88 | G118: =G109/(1+$D$117)^G8 -> 77445.158 | H118: =H109/(1+$D$117)^H8 -> 138223.08 | I118: =I109/(1+$D$117)^I8 -> 208443.49 | J118: =J109/(1+$D$117)^J8 -> 195046.46 | K118: =K109/(1+$D$117)^K8 -> 192489 | L118: =L109/(1+$D$117)^L8 -> 189962.17 | ... BM118: =BM109/(1+$D$117)^BM8 -> 211640.05
C119: Cumulative Discounted cash flow | E119: =E118 -> -3622300 | F119: =F118+E119 -> -3801609.9 | G119: =G118+F119 -> -3724164.7 | H119: =H118+G119 -> -3585941.6 | I119: =I118+H119 -> -3377498.2 | J119: =J118+I119 -> -3182451.7 | K119: =K118+J119 -> -2989962.7 | L119: =L118+K119 -> -2800000.5 | M119: =M118+L119 -> -2612534.9 | ... BM119: =BM118+BL119 -> 10483401
E120: =IF(E119<0,E3,0) -> 1 | F120: =IF(F119<0,F3,0) -> 1 | G120: =IF(G119<0,G3,0) -> 1 | H120: =IF(H119<0,H3,0) -> 1 | I120: =IF(I119<0,I3,0) -> 1 | J120: =IF(J119<0,J3,0) -> 1 | K120: =IF(K119<0,K3,0) -> 1 | L120: =IF(L119<0,L3,0) -> 1 | ... BM120: =IF(BM119<0,BM3,0) -> 0
B122: =SUM(E120:BM120) -> 19 | C122: =B122/12 -> 1.5833333
B125: Ставка дисконтирования | C125: ='Вход и предположения'!M14 -> 0.13520212

Sheet Отчетность
A1: Прогнозируемый отчет о прибылях и убытках
B2: 2021 | C2: 2022 | D2: 2023 | E2: 2024 | F2: 2025
A3: Выручка от реализации услуг | B3: =Модель!BP10+Модель!BP17+Модель!BP24 -> 6247800 | C3: =Модель!BQ10+Модель!BQ17+Модель!BQ24 -> 8608769.5 | D3: =Модель!BR10+Модель!BR17+Модель!BR24 -> 8959504.1 | E3: =Модель!BS10+Модель!BS17+Модель!BS24 -> 9324528.1 | F3: =Модель!BT10+Модель!BT17+Модель!BT24 -> 9704423.7
A4: Выручка от реализации товаров | B4: =Модель!BP33 -> 3812760 | C4: =Модель!BQ33 -> 5253556.8 | D4: =Модель!BR33 -> 5467594.8 | E4: =Модель!BS33 -> 5690353 | F4: =Модель!BT33 -> 5922186.8
A5: Выручка | B5: =B3+B4 -> 10060560 | C5: =C3+C4 -> 13862326 | D5: =D3+D4 -> 14427099 | E5: =E3+E4 -> 15014881 | F5: =F3+F4 -> 15626611
A6: Себестоимость оказанных услуг (коммуналка+интернет+аренда) | B6: =Модель!BP48+Модель!BP54+Модель!BP68 -> 2479502.6 | C6: =Модель!BQ48+Модель!BQ54+Модель!BQ68 -> 2587944.9 | D6: =Модель!BR48+Модель!BR54+Модель!BR68 -> 2713640.3 | E6: =Модель!BS48+Модель!BS54+Модель!BS68 -> 2845493.1 | F6: =Модель!BT48+Модель!BT54+Модель!BT68 -> 2983807.3
A7: Себестоимость реализованных товаров | B7: =Модель!BP71 -> 1815600 | C7: =Модель!BQ71 -> 2501693.7 | D7: =Модель!BR71 -> 2603616.6 | E7: =Модель!BS71 -> 2709691.9 | F7: =Модель!BT71 -> 2820088.9
A8: Коммерческие/управленческие расходы | B8: =Модель!BP57+Модель!BP64+Модель!BP81+Модель!BP77 -> 3382375 | C8: =Модель!BQ57+Модель!BQ64+Модель!BQ81+Модель!BQ77 -> 3492510.2 | D8: =Модель!BR57+Модель!BR64+Модель!BR81+Модель!BR77 -> 3634804.5 | E8: =Модель!BS57+Модель!BS64+Модель!BS81+Модель!BS77 -> 3782120 | F8: =Модель!BT57+Модель!BT64+Модель!BT81+Модель!BT77 -> 3937012
A9: Прибыль до процентов, налогов и амортизации (EBITDA) | B9: =B5-B6-B7-B8 -> 2383082.4 | C9: =C5-C6-C7-C8 -> 5280177.5 | D9: =D5-D6-D7-D8 -> 5475037.5 | E9: =E5-E6-E7-E8 -> 5677576.1 | F9: =F5-F6-F7-F8 -> 5885702.2
A10: Амортизация | B10: =Нач.инв.!$G$14+Нач.инв.!$G$30+Нач.инв.!$H$46+Нач.инв.!$H$56 -> 90420 | C10: =Нач.инв.!$G$14+Нач.инв.!$G$30+Нач.инв.!$H$46+Нач.инв.!$H$56 -> 90420 | D10: =Нач.инв.!$G$14+Нач.инв.!$G$30+Нач.инв.!$H$46+Нач.инв.!$H$56 -> 90420 | E10: =Нач.инв.!$G$14+Нач.инв.!$G$30+Нач.инв.!$H$46+Нач.инв.!$H$56 -> 90420 | F10: =Нач.инв.!$G$14+Нач.инв.!$G$30+Нач.инв.!$H$46+Нач.инв.!$H$56 -> 90420
A11: Прибыль до процентов и налогов (EBIT) | B11: =B9-B10 -> 2292662.4 | C11: =C9-C10 -> 5189757.5 | D11: =D9-D10 -> 5384617.5 | E11: =E9-E10 -> 5587156.1 | F11: =F9-F10 -> 5795282.2
A12: Процентные расходы | B12: =Модель!BP85 -> 63541.667 | C12: =Модель!BQ85 -> 38541.667 | D12: =Модель!BR85 -> 13541.667 | E12: =Модель!BS85 -> 0 | F12: =Модель!BT85 -> 0
A13: Прочие доходы | B13: =Модель!BP38 -> 180000 | C13: =Модель!BQ38 -> 183948.07 | D13: =Модель!BR38 -> 191442.39 | E13: =Модель!BS38 -> 199242.05 | F13: =Модель!BT38 -> 207359.48
A14: Прибыль до налогообложения (EBT) | B14: =B11-B12+B13 -> 2409120.8 | C14: =C11-C12+C13 -> 5335163.9 | D14: =D11-D12+D13 -> 5562518.2 | E14: =E11-E12+E13 -> 5786398.2 | F14: =F11-F12+F13 -> 6002641.7
A15: Налог на прибыль | B15: =Модель!BP87 -> 363450.7 | C15: =Модель!BQ87 -> 767254.56 | D15: =Модель!BR87 -> 799717.07 | E15: =Модель!BS87 -> 831590.42 | F15: =Модель!BT87 -> 862236.71
A16: Чистая прибыль | B16: =B14-B15 -> 2045670 | C16: =C14-C15 -> 4567909.3 | D16: =D14-D15 -> 4762801.1 | E16: =E14-E15 -> 4954807.8 | F16: =F14-F15 -> 5140405
A20: Прогнозируемый баланс (некоторые статьи)
B21: 2021 | C21: 2022 | D21: 2023 | E21: 2024 | F21: 2025
A22: Основные средства | B22: =Инв.расчет!$G$3+Инв.расчет!$G$10+Инв.расчет!$G$17 -> 3622300 | C22: =Инв.расчет!$G$3+Инв.расчет!$G$10+Инв.расчет!$G$17 -> 3622300 | D22: =Инв.расчет!$G$3+Инв.расчет!$G$10+Инв.расчет!$G$17 -> 3622300 | E22: =Инв.расчет!$G$3+Инв.расчет!$G$10+Инв.расчет!$G$17 -> 3622300 | F22: =Инв.расчет!$G$3+Инв.расчет!$G$10+Инв.расчет!$G$17 -> 3622300
A23: Оборотные средства | B23: =Модель!$E$104*Модель!BP42 -> 1024056 | C23: =Модель!$E$104*Модель!BQ42 -> 1404627.4 | D23: =Модель!$E$104*Модель!BR42 -> 1461854.1 | E23: =Модель!$E$104*Модель!BS42 -> 1521412.3 | F23: =Модель!$E$104*Модель!BT42 -> 1583397
A29: Промежуточные операционные денежные потоки
A30: Operating Results | B30: 2021 | C30: 2022 | D30: 2023 | E30: 2024 | F30: 2025
A31: Выручка от реализации услуг | B31: =B3 -> 6247800 | C31: =C3 -> 8608769.5 | D31: =D3 -> 8959504.1 | E31: =E3 -> 9324528.1 | F31: =F3 -> 9704423.7
A32: Выручка от реализации товаров | B32: =B4 -> 3812760 | C32: =C4 -> 5253556.8 | D32: =D4 -> 5467594.8 | E32: =E4 -> 5690353 | F32: =F4 -> 5922186.8
A33: Выручка | B33: =B5 -> 10060560 | C33: =C5 -> 13862326 | D33: =D5 -> 14427099 | E33: =E5 -> 15014881 | F33: =F5 -> 15626611
A34: Себестоимость оказанных услуг (коммуналка+интернет+аренда) | B34: =B6 -> 2479502.6 | C34: =C6 -> 2587944.9 | D34: =D6 -> 2713640.3 | E34: =E6 -> 2845493.1 | F34: =F6 -> 2983807.3
A35: Себестоимость реализованных товаров | B35: =B7 -> 1815600 | C35: =C7 -> 2501693.7 | D35: =D7 -> 2603616.6 | E35: =E7 -> 2709691.9 | F35: =F7 -> 2820088.9
A36: Коммерческие/управленческие расходы | B36: =B8 -> 3382375 | C36: =C8 -> 3492510.2 | D36: =D8 -> 3634804.5 | E36: =E8 -> 3782120 | F36: =F8 -> 3937012
A37: Прибыль до процентов, налогов и амортизации (EBITDA) | B37: =B9 -> 2383082.4 | C37: =C9 -> 5280177.5 | D37: =D9 -> 5475037.5 | E37: =E9 -> 5677576.1 | F37: =F9 -> 5885702.2
A38: Амортизация | B38: =B10 -> 90420 | C38: =C10 -> 90420 | D38: =D10 -> 90420 | E38: =E10 -> 90420 | F38: =F10 -> 90420
A39: Прибыль до процентов и налогов (EBIT) | B39: =B11 -> 2292662.4 | C39: =C11 -> 5189757.5 | D39: =D11 -> 5384617.5 | E39: =E11 -> 5587156.1 | F39: =F11 -> 5795282.2
A40: Свободный денежный поток без учета долгового бремени:
A41: Чистая операционная прибыль после вычета налога (NOPAT) | B41: =B39-B15 -> 1929211.7 | C41: =C39-C15 -> 4422502.9 | D41: =D39-D15 -> 4584900.4 | E41: =E39-E15 -> 4755565.7 | F41: =F39-F15 -> 4933045.5
A42: Амортизация | B42: =B10 -> 90420 | C42: =C10 -> 90420 | D42: =D10 -> 90420 | E42: =E10 -> 90420 | F42: =F10 -> 90420
A43: Изменение оборотного капитала | B43: 0 | C43: =C23-B23 -> 380571.43 | D43: =D23-C23 -> 57226.689 | E43: =E23-D23 -> 59558.192 | F43: =F23-E23 -> 61984.685
A44: Капитальные расходы | B44: =Модель!D98 -> 3622300 | C44: ='Вход и предположения'!$E$39*Модель!BP42 -> 204811.2 | D44: ='Вход и предположения'!$E$39*Модель!BQ42 -> 280925.49 | E44: ='Вход и предположения'!$E$39*Модель!BR42 -> 292370.82 | F44: ='Вход и предположения'!$E$39*Модель!BS42 -> 304282.46
A45: Свободный денежный поток без использования заемных средств (unlevered FCF) | B45: =B41+B42-B43-B44 -> -1602668.3 | C45: =C41+C42-C43-C44 -> 3927540.3 | D45: =D41+D42-D43-D44 -> 4337168.2 | E45: =E41+E42-E43-E44 -> 4494056.7 | F45: =F41+F42-F43-F44 -> 4657198.4

Sheet re и wacc
A1: Расчет re
A2: Для расчета ставки дисконтирования по кумулятивному методу необходимо рассчитать безрисковую процентную ставку,
A3: премию за риск (степень влияния различных рисков) и провести корректировку на инфляцию. | F3: Бескупонная доходность государственных облигаций (ЦБРФ)
A7: где:
A8: r – ставка дисконтирования;
A9: rf – безрисковая процентная ставка (оценка доходности на основе доходности государственных ценных бумаг (ГКО, ОФЗ));
A10: rp – премия за риски компании;
A11: rс – премия за страновой риск (используется для оценки и сравнения международных компаний);
A12: I – процент инфляции (корректировка на рост потребительских цен). | H12: 0.0569
H13: 0.0602
H14: 0.0622
H15: 0.0645
A16: Вид риска | B16: Интервал оценки | C16: Оценка | D16: Пояснение | H16: 0.0659
A17: Безоисковая ставка (rf) | B17: - | C17: =H24 -> 0.06245 | D17: доходности государственных ценных бумаг (ГКО, ОФЗ) | H17: 0.0676
A18: Размер фирмы | B18: 0-5 | C18: 0.03 | D18: Малый размер компании, незначительная конкуренция | H18: 0.0691
A19: Финансовая структура | B19: 0-5 | C19: 0.03 | D19: Часть капитала заемная, рентабельность в 1-ый год ниже, чем в последующие | H19: 0.0698
A20: Диверсификация | B20: 0-5 | C20: 0.03 | D20: Низкая | H20: 0.0702
A21: Менеджмент | B21: 0-5 | C21: 0.01 | D21: Простая организационная структура | H21: 0.0529
A22: re | B22: - | C22: =SUM(C17:C21) -> 0.16245 | H22: 0.0544
H23: 0.0557
H24: =AVERAGE(H12:H23) -> 0.06245
A27: Расчет WACC
B32: E | C32: =Инв.расчет!G28-'Вход и предположения'!D50 -> 2622300
B33: D | C33: ='Вход и предположения'!D50 -> 1000000
B34: V | C34: =C32+C33 -> 3622300
B35: E/V | C35: =C32/C34 -> 0.72393231
B36: D/V | C36: =C33/C34 -> 0.27606769
B37: re | C37: ='Вход и предположения'!M13 -> 0.16245
B38: rd | C38: ='Вход и предположения'!M12 -> 0.075
B39: tax rate | C39: ='Вход и предположения'!M10 -> 0.15
B40: WACC | C40: =C35*C37+C36*C38*(1-C39) -> 0.13520212

Sheet Стоимость компании
A1: Текущая стоимость промежуточных денежных потоков
A7: Период | B7: 1 | C7: 2 | D7: 3 | E7: 4 | F7: 5
A8: Свободный денежный поток без использования заемных средств (unlevered FCF) | B8: =Отчетность!B45 -> -1602668.3 | C8: =Отчетность!C45 -> 3927540.3 | D8: =Отчетность!D45 -> 4337168.2 | E8: =Отчетность!E45 -> 4494056.7 | F8: =Отчетность!F45 -> 4657198.4
A9: WACC(D/V=0) | B9: =$I$9 -> 0.1176028 | C9: =$I$9 -> 0.1176028 | D9: =$I$9 -> 0.1176028 | E9: =$I$9 -> 0.1176028 | F9: =$I$9 -> 0.1176028 | H9: WACC(D/V=0) | I9: ='re и wacc'!C35*'re и wacc'!C37 -> 0.1176028
A10: Discounted un-FCF | B10: =B8/(1+B9)^B7 -> -1434023.1 | C10: =C8/(1+C9)^C7 -> 3144457.2 | D10: =D8/(1+D9)^D7 -> 3107018.4 | E10: =E8/(1+E9)^E7 -> 2880637.5 | F10: =F8/(1+F9)^F7 -> 2671082.6
C13: PV un-FCF | D13: =SUM(B10:F10) -> 10369173
A17: Промежуточный налоговый щит
A23: Период | B23: 1 | C23: 2 | D23: 3
A24: Оплата процентов | B24: =SUM('Вход и предположения'!E55:P55) -> 63541.667 | C24: =SUM('Вход и предположения'!Q55:AB55) -> 38541.667 | D24: =SUM('Вход и предположения'!AC55:AN55) -> 13541.667
A25: Ставка налога на прибыль | B25: ='Вход и предположения'!$M$10 -> 0.15 | C25: ='Вход и предположения'!$M$10 -> 0.15 | D25: ='Вход и предположения'!$M$10 -> 0.15
A26: Налоговый щит | B26: =B24*B25 -> 9531.25 | C26: =C24*C25 -> 5781.25 | D26: =D24*D25 -> 2031.25
A27: Ставка дисконтирования | B27: ='Вход и предположения'!$M$12 -> 0.075 | C27: ='Вход и предположения'!$M$12 -> 0.075 | D27: ='Вход и предположения'!$M$12 -> 0.075
A28: Текущая стоимость налогового щита | B28: =B26/(1+B27)^B23 -> 8866.2791 | C28: =C26/(1+C27)^C23 -> 5002.7042 | D28: =D26/(1+D27)^D23 -> 1635.0762
C31: PV tax sheild | D31: =SUM(B28:D28) -> 15504.059
A34: Итого Стоимость в прогнозный период
A35: Total Intermediate Term Value=PV of FCF+PV of Interest Tax Shields
B37: Total Intermediate Term Value | D37: =D13+D31 -> 10384677
A47: Un-FCF 2025 | B47: =Отчетность!F45 -> 4657198.4
A48: g | B48: ='Вход и предположения'!M16 -> 0.065
A49: WACC | B49: ='Вход и предположения'!M14 -> 0.13520212
C52: TV | D52: =B47*(1+B48)/(B49-B48) -> 70651946
C54: PV of TV | D54: =D52/(1+B49)^5 -> 37476425
A58: Стоимость операционных активов
A59: Value of Operating Assets=Total Intermediate Term Value+PV of Terminal Value
B61: Value of Operating Asset | D61: =D37+D54 -> 47861102

Sheet Фин.эффективность
A1: Денежные потоки
B2: 1 | C2: 2 | D2: 3 | E2: 4 | F2: 5
A3: FCF | B3: =Модель!BP109 -> 1896967.5 | C3: =Модель!BQ109 -> 4375050.4 | D3: =Модель!BR109 -> 4536586.7 | E3: =Модель!BS109 -> 4717400.2 | F3: =Модель!BT109 -> 4891268.5 | H3: wacc | I3: ='Вход и предположения'!M14 -> 0.13520212
A4: Disc.FCF | B4: =B3/(1+$I$3)^B2 -> 1671039.4 | C4: =C3/(1+$I$3)^C2 -> 3394975.7 | D4: =D3/(1+$I$3)^D2 -> 3101056.2 | E4: =E3/(1+$I$3)^E2 -> 2840599.2 | F4: =F3/(1+$I$3)^F2 -> 2594511.1
A6: SUM DFCF | B6: =SUM(B4:F4) -> 13602182
A9: 1. NPV (чистая приведенная стоимость)
A14: С учетом терминальной стоимости
A15: Инвестиции | B15: =Инв.расчет!G28 -> 3622300
A16: Сумма дисконтированных ден.потоков | B16: =B6 -> 13602182
A17: Дисконтированная терминальная стоимость | B17: ='Стоимость компании'!D54 -> 37476425
A18: NPV | B18: =B16+B17-B15 -> 47456307
A21: Без учета терминальной стоимости
A22: Инвестиции | B22: =Инв.расчет!G28 -> 3622300
A23: Сумма дисконтированных ден.потоков | B23: =B6 -> 13602182
A24: NPV | B24: =B23-B22 -> 9979881.6
A27: 2. IRR (внутренняя норма доходности)
B32: 1 | C32: 2 | D32: 3 | E32: 4 | F32: 5 | G32: TV | H32: Io
A33: FCF | B33: =B3 -> 1896967.5 | C33: =C3 -> 4375050.4 | D33: =D3 -> 4536586.7 | E33: =E3 -> 4717400.2 | F33: =F3 -> 4891268.5 | G33: ='Стоимость компании'!D52 -> 70651946 | H33: =Инв.расчет!G28 -> 3622300
A34: Discounted | B34: =B33/(1+$B$37)^B32 -> 844817.03 | C34: =C33/(1+$B$37)^C32 -> 867738 | D34: =D33/(1+$B$37)^D32 -> 400716.81 | E34: =E33/(1+$B$37)^E32 -> 185572.6 | F34: =F33/(1+$B$37)^F32 -> 85691.038 | G34: =G33/(1+B37)^5 -> 1237764.5 | H34: =-H33 -> -3622300 | I34: =SUM(B34:H34) -> -3.9394945e-07
A36: С учетом TV
A37: IRR | B37: 1.2454181
B40: 1 | C40: 2 | D40: 3 | E40: 4 | F40: 5 | G40: Io
A41: FCF | B41: =B3 -> 1896967.5 | C41: =C3 -> 4375050.4 | D41: =D3 -> 4536586.7 | E41: =E3 -> 4717400.2 | F41: =F3 -> 4891268.5 | G41: =Инв.расчет!G28 -> 3622300
A42: Discounted | B42: =B41/(1+$B$45)^B40 -> 1022188.4 | C42: =C41/(1+$B$45)^C40 -> 1270355.4 | D42: =D41/(1+$B$45)^D40 -> 709810.58 | E42: =E41/(1+$B$45)^E40 -> 397728.82 | F42: =F41/(1+$B$45)^F40 -> 222216.81 | G42: =-G41 -> -3622300 | H42: =SUM(A42:G42) -> -8.0093741e-08
A44: Без учета TV
A45: IRR | B45: 0.85579037
A48: 3. РР (период окупаемости) и DPP
A49: РР | B49: =Модель!B113 -> 17 | C49: мес.
A50: DPP | B50: =Модель!B122 -> 19 | C50: мес.
A53: 4. РI (индекс прибыльности)
A54: PI с учетом TV | B54: =B18/B15 -> 13.101153
A55: PI без учета TV | B55: =B24/B22 -> 2.7551229
A57: 5. IRR-WACC (запас финансовой прочности)
A58: IRR-WACC с учетом TV | B58: =B37-I3 -> 1.110216
A59: IRR-WACC без учета TV | B59: =B45-I3 -> 0.72058825

Sheet Чувств. NPV
A1: Изменяемый фактор | B1: Значение NPV (без учета терминальной стоимости) при изменении фактора на %
B2: -0.3 | C2: -0.2 | D2: -0.1 | E2: 0 | F2: 0.1 | G2: 0.2 | H2: 0.3
A3: Загрузка оборудования | B3: 912564.79 | C3: 3935003.7 | D3: 6957442.6 | E3: =Фин.эффективность!$B$24 -> 9979881.6 | F3: 13002321 | G3: 16024759 | H3: 19047198
A4: Стоимость 1 часа игры | B4: 2755643.8 | C4: 5164620 | D4: 7575939.6 | E4: =Фин.эффективность!$B$24 -> 9979881.6 | F4: 12383824 | G4: 14787766 | H4: 17191707
A5: Выручка бара на 1 час времени | B5: 7800995.2 | C5: 8527290.7 | D5: 9253586.1 | E5: =Фин.эффективность!$B$24 -> 9979881.6 | F5: 10706177 | G5: 11432472 | H5: 12158768
A6: Сумма официальной заработной платы | B6: 12917572 | C6: 11938342 | D6: 10959112 | E6: =Фин.эффективность!$B$24 -> 9979881.6 | F6: 9000651.3 | G6: 8021421 | H6: 7034568.3
A7: Затраты на электричество и интернет | B7: 10561620 | C7: 10367707 | D7: 10173794 | E7: =Фин.эффективность!$B$24 -> 9979881.6 | F7: 9785968.9 | G7: 9592056.1 | H7: 9398143.4
A8: Налоговая ставка | B8: 9945394.1 | C8: 9956875.3 | D8: 9968371.1 | E8: =Фин.эффективность!$B$24 -> 9979881.6 | F8: 9991406.7 | G8: 10002946 | H8: 10014501
A9: Стоимость собственного капитала (re) | B9: 11388888 | C9: 10895913 | D9: 10426727 | E9: =Фин.эффективность!$B$24 -> 9979881.6 | F9: 9554033.1 | G9: 9147934.2 | H9: 8760425.5
A10: Стоимость заемного капитала (rd) | B10: 10202499 | C10: 10127777 | D10: 10053573 | E10: =Фин.эффективность!$B$24 -> 9979881.6 | F10: 9906698.3 | G10: 9834018.6 | H10: 9761837.9
A11: Ставка роста (g) | B11: 38772430 | C11: 41214782 | D11: 44071080 | E11: =Фин.эффективность!B18 -> 47456307 | F11: 51532373 | G11: 56534784 | H11: 62819810 | I11: NPV с учетом TV
A14: Изменяемый фактор | B14: Изменение NPV (без учета терминальной стоимости) при изменении фактора на %
B15: -0.3 | C15: -0.2 | D15: -0.1 | E15: 0 | F15: 0.1 | G15: 0.2 | H15: 0.3
A16: Загрузка оборудования | B16: =B3-$E$3 -> -9067316.8 | C16: =C3-$E$3 -> -6044877.9 | D16: =D3-$E$3 -> -3022438.9 | E16: =E3-$E$3 -> 0 | F16: =F3-$E$3 -> 3022438.9 | G16: =G3-$E$3 -> 6044877.9 | H16: =H3-$E$3 -> 9067316.8
A17: Стоимость 1 часа игры | B17: =B4-$E$3 -> -7224237.8 | C17: =C4-$E$3 -> -4815261.6 | D17: =D4-$E$3 -> -2403942 | E17: =E4-$E$3 -> 0 | F17: =F4-$E$3 -> 2403942 | G17: =G4-$E$3 -> 4807883.9 | H17: =H4-$E$3 -> 7211825.9
A18: Выручка бара на 1 час времени | B18: =B5-$E$3 -> -2178886.3 | C18: =C5-$E$3 -> -1452590.9 | D18: =D5-$E$3 -> -726295.44 | E18: =E5-$E$3 -> 0 | F18: =F5-$E$3 -> 726295.44 | G18: =G5-$E$3 -> 1452590.9 | H18: =H5-$E$3 -> 2178886.3
A19: Сумма официальной заработной платы | B19: =B6-$E$3 -> 2937690.9 | C19: =C6-$E$3 -> 1958460.6 | D19: =D6-$E$3 -> 979230.29 | E19: =E6-$E$3 -> 0 | F19: =F6-$E$3 -> -979230.29 | G19: =G6-$E$3 -> -1958460.6 | H19: =H6-$E$3 -> -2945313.2
A20: Затраты на электричество и интернет | B20: =B7-$E$3 -> 581738.15 | C20: =C7-$E$3 -> 387825.43 | D20: =D7-$E$3 -> 193912.72 | E20: =E7-$E$3 -> 0 | F20: =F7-$E$3 -> -193912.72 | G20: =G7-$E$3 -> -387825.43 | H20: =H7-$E$3 -> -581738.15
A21: Налоговая ставка | B21: =B8-$E$3 -> -34487.5 | C21: =C8-$E$3 -> -23006.265 | D21: =D8-$E$3 -> -11510.44 | E21: =E8-$E$3 -> 0 | F21: =F8-$E$3 -> 11525.078 | G21: =G8-$E$3 -> 23064.819 | H21: =H8-$E$3 -> 34619.246
A22: Стоимость собственного капитала (re) | B22: =B9-$E$3 -> 1409006.3 | C22: =C9-$E$3 -> 916031.82 | D22: =D9-$E$3 -> 446845.67 | E22: =E9-$E$3 -> 0 | F22: =F9-$E$3 -> -425848.51 | G22: =G9-$E$3 -> -831947.36 | H22: =H9-$E$3 -> -1219456.1
A23: Стоимость заемного капитала (rd) | B23: =B10-$E$3 -> 222617.32 | C23: =C10-$E$3 -> 147895.68 | D23: =D10-$E$3 -> 73691.458 | E23: =E10-$E$3 -> 0 | F23: =F10-$E$3 -> -73183.304 | G23: =G10-$E$3 -> -145863.01 | H23: =H10-$E$3 -> -218043.63
A24: Ставка роста (g) | B24: =B11-$E$11 -> -8683876.9 | C24: =C11-$E$11 -> -6241525 | D24: =D11-$E$11 -> -3385226.6 | E24: =E11-$E$11 -> 0 | F24: =F11-$E$11 -> 4076066.2 | G24: =G11-$E$11 -> 9078476.7 | H24: =H11-$E$11 -> 15363503 | I24: NPV с учетом TV
A27: Изменяемый фактор | B27: Изменение NPV (без учета терминальной стоимости) при изменении фактора на %
B28: -0.3 | C28: -0.2 | D28: -0.1 | E28: 0 | F28: 0.1 | G28: 0.2 | H28: 0.3
A29: Загрузка оборудования | B29: =B3/$E$3-1 -> -0.90855956 | C29: =C3/$E$3-1 -> -0.60570637 | D29: =D3/$E$3-1 -> -0.30285319 | E29: =E3/$E$3-1 -> 0 | F29: =F3/$E$3-1 -> 0.30285319 | G29: =G3/$E$3-1 -> 0.60570637 | H29: =H3/$E$3-1 -> 0.90855956
A30: Стоимость 1 часа игры | B30: =B4/$E$3-1 -> -0.72388011 | C30: =C4/$E$3-1 -> -0.48249687 | D30: =D4/$E$3-1 -> -0.24087881 | E30: =E4/$E$3-1 -> 0 | F30: =F4/$E$3-1 -> 0.24087881 | G30: =G4/$E$3-1 -> 0.48175761 | H30: =H4/$E$3-1 -> 0.72263642
A31: Выручка бара на 1 час времени | B31: =B5/$E$3-1 -> -0.21832787 | C31: =C5/$E$3-1 -> -0.14555192 | D31: =D5/$E$3-1 -> -0.072775958 | E31: =E5/$E$3-1 -> 0 | F31: =F5/$E$3-1 -> 0.072775958 | G31: =G5/$E$3-1 -> 0.14555192 | H31: =H5/$E$3-1 -> 0.21832787
A32: Сумма официальной заработной платы | B32: =B6/$E$3-1 -> 0.2943613 | C32: =C6/$E$3-1 -> 0.19624086 | D32: =D6/$E$3-1 -> 0.098120432 | E32: =E6/$E$3-1 -> 0 | F32: =F6/$E$3-1 -> -0.098120432 | G32: =G6/$E$3-1 -> -0.19624086 | H32: =H6/$E$3-1 -> -0.29512507
A33: Затраты на электричество и интернет | B33: =B7/$E$3-1 -> 0.058291087 | C33: =C7/$E$3-1 -> 0.038860725 | D33: =D7/$E$3-1 -> 0.019430362 | E33: =E7/$E$3-1 -> 0 | F33: =F7/$E$3-1 -> -0.019430362 | G33: =G7/$E$3-1 -> -0.038860725 | H33: =H7/$E$3-1 -> -0.058291087
A34: Налоговая ставка | B34: =B8/$E$3-1 -> -0.0034557023 | C34: =C8/$E$3-1 -> -0.0023052643 | D34: =D8/$E$3-1 -> -0.0011533644 | E34: =E8/$E$3-1 -> 0 | F34: =F8/$E$3-1 -> 0.0011548312 | G34: =G8/$E$3-1 -> 0.0023111316 | H34: =H8/$E$3-1 -> 0.0034689035
A35: Стоимость собственного капитала (re) | B35: =B9/$E$3-1 -> 0.14118467 | C35: =C9/$E$3-1 -> 0.091787845 | D35: =D9/$E$3-1 -> 0.044774646 | E35: =E9/$E$3-1 -> 0 | F35: =F9/$E$3-1 -> -0.042670698 | G35: =G9/$E$3-1 -> -0.083362448 | H35: =H9/$E$3-1 -> -0.12219144
A36: Стоимость заемного капитала (rd) | B36: =B10/$E$3-1 -> 0.022306609 | C36: =C10/$E$3-1 -> 0.014819382 | D36: =D10/$E$3-1 -> 0.0073840013 | E36: =E10/$E$3-1 -> 0 | F36: =F10/$E$3-1 -> -0.0073330834 | G36: =G10/$E$3-1 -> -0.014615706 | H36: =H10/$E$3-1 -> -0.021848318
A37: Ставка роста (g) | B37: =B11/$E$11-1 -> -0.18298678 | C37: =C11/$E$11-1 -> -0.13152151 | D37: =D11/$E$11-1 -> -0.071333544 | E37: =E11/$E$11-1 -> 0 | F37: =F11/$E$11-1 -> 0.085890926 | G37: =G11/$E$11-1 -> 0.19130179 | H37: =H11/$E$11-1 -> 0.32373996 | I37: NPV с учетом TV

Sheet Сценарии
A1: Сценарий | B1: Пессимистичный | C1: Наиболее вероятный | D1: Оптимистичный
A2: Вероятность реализации | B2: 0.2 | C2: 0.6 | D2: 0.2
A4: Фактор | B4: Доля от планового показателя при реализации сценария
A5: Загрузка оборудования | B5: 0.9 | C5: 1 | D5: 1.1
A6: Стоимость 1 часа игры | B6: 0.9 | C6: 1 | D6: 1.1
A7: Выручка бара на 1 час времени | B7: 0.9 | C7: 1 | D7: 1.1
A8: Сумма официальной з/п | B8: 1.1 | C8: 1 | D8: 0.9
A9: Ставка роста (g) | B9: 0.9 | C9: 1 | D9: 1.1
A11: Показатели финансовой эффективности
A12: Сценарий | B12: Пессимистичный | C12: Наиболее вероятный | D12: Оптимистичный
A13: NPV (с учетом TV) | B13: 20955627 | C13: 47456307 | D13: 80621347
A14: NPV (без учета TV) | B14: 3143031.4 | C14: 9979881.6 | D14: 17414032
A15: IRR (с учетом TV) | B15: 0.78941184 | C15: 1.2454181 | D15: 1.67752
A16: IRR (без учета TV) | B16: 0.38874834 | C16: 0.85579037 | D16: 1.3176681
A17: PP | B17: 29 | C17: 17 | D17: 13
A18: DPP | B18: 34 | C18: 19 | D18: 13
A19: PI с учетом TV | B19: 5.7852 | C19: 13.1012 | D19: 22.2569
A20: PI без учета TV | B20: 0.8677 | C20: 2.7551 | D20: 4.8075
A25: Ожидаемые:
A26: NPV (с учетом TV) | B26: =0.2*B13+0.6*C13+0.2*D13 -> 48789179
A27: NPV (без учета TV) | B27: =0.2*B14+0.6*C14+0.2*D14 -> 10099342
A28: Sigma (с учетом TV) | B28: =STDEV(B13:D13) -> 29894827
A29: Sigma (без учета TV) | B29: =STDEV(B14:D14) -> 7137583.4
