Workbook
Name T: SNGS!$E$23
Name X: SNGS!$H$21
Name X_2: SNGS!$J$21
Name XY: SNGS!$K$21
Name Y: SNGS!$E$21
Name Y_2: SNGS!$I$21

Sheet SNGS
A1: Апостериорная характеристическая линия для акции Сургутнефтегаз об
A2: 251 дата | D2: 250 доходностей | F2: 0.01
A3: Дата | B3: Безрисковая доходность MosPrime Rate (дневная), % | C3: Цена акции SNGS | D3: Доходность акции SNGS, % | E3: Избыточная дох-ть акции SNGS, % (Y) | F3: Значение бенчмарка IMOEX | G3: Доходность бенчмарка IMOEX,% | H3: Избыточная дох-ть бенчмарка IMOEX,% (X) | I3: Y^2 | J3: X^2 | K3: Y*X | N3: Rt | P3: Расчет VAR и ES (все приросты) | V3: Rt | X3: Расчет VAR и ES (отрицательные приросты) | AG3: Rt | AI3: Расчет VAR и ES (все приросты без учета знака)
A4: 43621 | B4: =Расчеты!G17/360 -> 0.021888889 | C4: 25.205 | F4: 2701.84 | N4: 0.01 | AG4: 0.01
A5: 43622 | B5: =Расчеты!G18/360 -> 0.021972222 | C5: 25.26 | D5: =(C5/C4-1)*100 -> 0.21821067 | E5: =D5-B5 -> 0.19623845 | F5: 2728.25 | G5: =(F5/F4-1)*100 -> 0.97748201 | H5: =G5-B5 -> 0.95550979 | I5: =E5^2 -> 0.038509529 | J5: =H5^2 -> 0.91299896 | K5: =E5*H5 -> 0.18750776 | M5: -13.579036 | N5: =M5*$N$4 -> -0.13579036 | P5: Количество наблюдений | Q5: 250 | V5: -0.13579036 | X5: Количество наблюдений | Y5: =COUNT(V5:V125) -> 121 | AD5: -13.579036 | AE5: =IF(AD5<0,AD5,AD5*(-1)) -> -13.579036 | AF5: -15.166261 | AG5: =AF5*$AG$4 -> -0.15166261 | AI5: Количество наблюдений | AJ5: 250
A6: 43623 | B6: =Расчеты!G19/360 -> 0.022027778 | C6: 25.2 | D6: =(C6/C5-1)*100 -> -0.23752969 | E6: =D6-B6 -> -0.25955747 | F6: 2729.61 | G6: =(F6/F5-1)*100 -> 0.049848804 | H6: =G6-B6 -> 0.027821026 | I6: =E6^2 -> 0.06737008 | J6: =H6^2 -> 0.00077400951 | K6: =E6*H6 -> -0.0072211552 | M6: -10 | N6: =M6*$N$4 -> -0.1 | P6: Среднее | Q6: =AVERAGE(N5:N254) -> 0.0023176308 | V6: -0.1 | X6: Среднее | Y6: =AVERAGE(V5:V125) -> -0.01826273 | AD6: -10 | AE6: =IF(AD6<0,AD6,AD6*(-1)) -> -10 | AF6: -13.579036 | AG6: =AF6*$AG$4 -> -0.13579036 | AI6: Среднее | AJ6: =AVERAGE(AG5:AG254) -> -0.019995954
A7: 43626 | B7: =Расчеты!G20/360 -> 0.022055556 | C7: 25.08 | D7: =(C7/C6-1)*100 -> -0.47619048 | E7: =D7-B7 -> -0.49824603 | F7: 2742.59 | G7: =(F7/F6-1)*100 -> 0.47552581 | H7: =G7-B7 -> 0.45347025 | I7: =E7^2 -> 0.24824911 | J7: =H7^2 -> 0.20563527 | K7: =E7*H7 -> -0.22593975 | M7: -6.462585 | N7: =M7*$N$4 -> -0.06462585 | P7: Станд.отклонение | Q7: =_xlfn.STDEV.S(N5:N254) -> 0.030946648 | R7: =Q7*C254 -> 1.237247 | S7: руб. | V7: -0.06462585 | X7: Станд.отклонение | Y7: =_xlfn.STDEV.S(V5:V125) -> 0.019836539 | Z7: =Y7*C254 -> 0.79306484 | AA7: руб. | AD7: -6.462585 | AE7: =IF(AD7<0,AD7,AD7*(-1)) -> -6.462585 | AF7: -12.295082 | AG7: =AF7*$AG$4 -> -0.12295082 | AI7: Станд.отклонение | AJ7: =_xlfn.STDEV.S(AG5:AG254) -> 0.023699031 | AK7: =AJ7*C254 -> 0.94748727 | AL7: руб.
A8: 43627 | B8: =Расчеты!G21/360 -> 0.021833333 | C8: 25.39 | D8: =(C8/C7-1)*100 -> 1.2360447 | E8: =D8-B8 -> 1.2142113 | F8: 2751.75 | G8: =(F8/F7-1)*100 -> 0.33399086 | H8: =G8-B8 -> 0.31215753 | I8: =E8^2 -> 1.4743091 | J8: =H8^2 -> 0.097442323 | K8: =E8*H8 -> 0.37902521 | M8: -5.9049448 | N8: =M8*$N$4 -> -0.059049448 | V8: -0.059049448 | AD8: -5.9049448 | AE8: =IF(AD8<0,AD8,AD8*(-1)) -> -5.9049448 | AF8: -10 | AG8: =AF8*$AG$4 -> -0.1
A9: 43629 | B9: =Расчеты!G22/360 -> 0.021722222 | C9: 25.08 | D9: =(C9/C8-1)*100 -> -1.2209531 | E9: =D9-B9 -> -1.2426754 | F9: 2758.36 | G9: =(F9/F8-1)*100 -> 0.24021077 | H9: =G9-B9 -> 0.21848855 | I9: =E9^2 -> 1.544242 | J9: =H9^2 -> 0.047737248 | K9: =E9*H9 -> -0.27151034 | M9: -5.6779339 | N9: =M9*$N$4 -> -0.056779339 | P9: Квантиль распределения | Q9: 0.05 | V9: -0.056779339 | X9: Квантиль распределения | Y9: 0.05 | AD9: -5.6779339 | AE9: =IF(AD9<0,AD9,AD9*(-1)) -> -5.6779339 | AF9: -9.380531 | AG9: =AF9*$AG$4 -> -0.09380531 | AI9: Квантиль распределения | AJ9: 0.05
A10: 43630 | B10: =Расчеты!G23/360 -> 0.021694444 | C10: 25.175 | D10: =(C10/C9-1)*100 -> 0.37878788 | E10: =D10-B10 -> 0.35709343 | F10: 2739.28 | G10: =(F10/F9-1)*100 -> -0.69171537 | H10: =G10-B10 -> -0.71340981 | I10: =E10^2 -> 0.12751572 | J10: =H10^2 -> 0.50895356 | K10: =E10*H10 -> -0.25475396 | M10: -5.5084746 | N10: =M10*$N$4 -> -0.055084746 | P10: VAR (1, 95%) | Q10: =_xlfn.NORM.INV(Q9,Q6,Q7) -> -0.048585076 | R10: =Q10*C254 -> -1.9424313 | S10: руб. | V10: -0.055084746 | X10: VAR (1, 95%) | Y10: =_xlfn.NORM.INV(Y9,Y6,Y7) -> -0.050890934 | Z10: =Y10*C254 -> -2.0346195 | AA10: руб. | AD10: -5.5084746 | AE10: =IF(AD10<0,AD10,AD10*(-1)) -> -5.5084746 | AF10: -8.7175357 | AG10: =AF10*$AG$4 -> -0.087175357 | AI10: VAR (1, 95%) | AJ10: =_xlfn.NORM.INV(AJ9,AJ6,AJ7) -> -0.058977391 | AK10: =AJ10*C254 -> -2.3579161 | AL10: руб.
A11: 43633 | B11: =Расчеты!G24/360 -> 0.021388889 | C11: 25.15 | D11: =(C11/C10-1)*100 -> -0.099304866 | E11: =D11-B11 -> -0.12069375 | F11: 2734.31 | G11: =(F11/F10-1)*100 -> -0.18143454 | H11: =G11-B11 -> -0.20282343 | I11: =E11^2 -> 0.014566982 | J11: =H11^2 -> 0.041137342 | K11: =E11*H11 -> 0.024479521 | M11: -5.3295933 | N11: =M11*$N$4 -> -0.053295933 | P11: C вероятность 95% убыток не превысит 1,94 руб. | V11: -0.053295933 | X11: C вероятность 95% убыток не превысит 2,03 руб. | AD11: -5.3295933 | AE11: =IF(AD11<0,AD11,AD11*(-1)) -> -5.3295933 | AF11: -8.7139727 | AG11: =AF11*$AG$4 -> -0.087139727 | AI11: C вероятность 95% убыток или прибыль не превысит 2,36 руб.
A12: 43634 | B12: =Расчеты!G25/360 -> 0.021388889 | C12: 25.28 | D12: =(C12/C11-1)*100 -> 0.51689861 | E12: =D12-B12 -> 0.49550972 | F12: 2761.69 | G12: =(F12/F11-1)*100 -> 1.0013495 | H12: =G12-B12 -> 0.97996063 | I12: =E12^2 -> 0.24552988 | J12: =H12^2 -> 0.96032283 | K12: =E12*H12 -> 0.48558002 | M12: -5.2909091 | N12: =M12*$N$4 -> -0.052909091 | P12: Ист.наблюдение (мин.) № | Q12: =_xlfn.FLOOR.MATH(Q5*Q9) -> 12 | V12: -0.052909091 | X12: Ист.наблюдение (мин.) № | Y12: =_xlfn.FLOOR.MATH(Y5*Y9) -> 6 | AD12: -5.2909091 | AE12: =IF(AD12<0,AD12,AD12*(-1)) -> -5.2909091 | AF12: -8.4142395 | AG12: =AF12*$AG$4 -> -0.084142395 | AI12: Ист.наблюдение (мин.) № | AJ12: =_xlfn.FLOOR.MATH(AJ5*AJ9) -> 12
A13: 43635 | B13: =Расчеты!G26/360 -> 0.021277778 | C13: 25.41 | D13: =(C13/C12-1)*100 -> 0.51424051 | E13: =D13-B13 -> 0.49296273 | F13: 2759.12 | G13: =(F13/F12-1)*100 -> -0.09305896 | H13: =G13-B13 -> -0.11433674 | I13: =E13^2 -> 0.24301225 | J13: =H13^2 -> 0.01307289 | K13: =E13*H13 -> -0.05636375 | M13: -4.9300749 | N13: =M13*$N$4 -> -0.049300749 | P13: Ист.наблюдение (макс.) № | Q13: =_xlfn.CEILING.MATH(Q5*Q9) -> 13 | V13: -0.049300749 | X13: Ист.наблюдение (макс.) № | Y13: =_xlfn.CEILING.MATH(Y5*Y9) -> 7 | AD13: -4.9300749 | AE13: =IF(AD13<0,AD13,AD13*(-1)) -> -4.9300749 | AF13: -8.258287 | AG13: =AF13*$AG$4 -> -0.08258287 | AI13: Ист.наблюдение (макс.) № | AJ13: =_xlfn.CEILING.MATH(AJ5*AJ9) -> 13
A14: 43636 | B14: =Расчеты!G27/360 -> 0.021305556 | C14: 25.94 | D14: =(C14/C13-1)*100 -> 2.085793 | E14: =D14-B14 -> 2.0644874 | F14: 2780.2 | G14: =(F14/F13-1)*100 -> 0.76401171 | H14: =G14-B14 -> 0.74270616 | I14: =E14^2 -> 4.2621084 | J14: =H14^2 -> 0.55161244 | K14: =E14*H14 -> 1.5333075 | M14: -4.8808609 | N14: =M14*$N$4 -> -0.048808609 | P14: Ист.наблюдение (точное) № | Q14: =Q5*Q9 -> 12.5 | V14: -0.048808609 | X14: Ист.наблюдение (точное) № | Y14: =Y5*Y9 -> 6.05 | AD14: -4.8808609 | AE14: =IF(AD14<0,AD14,AD14*(-1)) -> -4.8808609 | AF14: -7.7788448 | AG14: =AF14*$AG$4 -> -0.077788448 | AI14: Ист.наблюдение (точное) № | AJ14: =AJ5*AJ9 -> 12.5
A15: 43637 | B15: =Расчеты!G28/360 -> 0.021305556 | C15: 25.825 | D15: =(C15/C14-1)*100 -> -0.44333076 | E15: =D15-B15 -> -0.46463632 | F15: 2761.23 | G15: =(F15/F14-1)*100 -> -0.68232501 | H15: =G15-B15 -> -0.70363057 | I15: =E15^2 -> 0.21588691 | J15: =H15^2 -> 0.49509598 | K15: =E15*H15 -> 0.32693232 | M15: -4.400049 | N15: =M15*$N$4 -> -0.04400049 | P15: Ист.наблюдение (мин.) | Q15: =SMALL(N5:N254,Q12) -> -0.042507514 | R15: =C254*Q15 -> -1.6994504 | S15: руб. | V15: -0.04400049 | X15: Ист.наблюдение (мин.) | Y15: =SMALL(V5:V125,Y12) -> -0.055084746 | Z15: =Y15*C254 -> -2.2022881 | AA15: руб. | AD15: -4.400049 | AE15: =IF(AD15<0,AD15,AD15*(-1)) -> -4.400049 | AF15: -7.5697674 | AG15: =AF15*$AG$4 -> -0.075697674 | AI15: Ист.наблюдение (мин.) | AJ15: =SMALL(AG5:AG254,AJ12) -> -0.07357373 | AK15: =AJ15*C254 -> -2.9414777 | AL15: руб.
A16: 43640 | B16: =Расчеты!G29/360 -> 0.021277778 | C16: 26 | D16: =(C16/C15-1)*100 -> 0.67763795 | E16: =D16-B16 -> 0.65636017 | F16: 2762.65 | G16: =(F16/F15-1)*100 -> 0.051426357 | H16: =G16-B16 -> 0.030148579 | I16: =E16^2 -> 0.43080867 | J16: =H16^2 -> 0.00090893683 | K16: =E16*H16 -> 0.019788327 | M16: -4.2507514 | N16: =M16*$N$4 -> -0.042507514 | P16: Ист.наблюдение (макс.) | Q16: =SMALL(N5:N254,Q13) -> -0.041706769 | R16: =C254*Q16 -> -1.6674366 | S16: руб. | V16: -0.042507514 | X16: Ист.наблюдение (макс.) | Y16: =SMALL(V5:V125,Y13) -> -0.053295933 | Z16: =C254*Y16 -> -2.1307714 | AA16: руб. | AD16: -4.2507514 | AE16: =IF(AD16<0,AD16,AD16*(-1)) -> -4.2507514 | AF16: -7.357373 | AG16: =AF16*$AG$4 -> -0.07357373 | AI16: Ист.наблюдение (макс.) | AJ16: =SMALL(AG5:AG254,AJ13) -> -0.071747544 | AK16: =C254*AJ16 -> -2.8684668 | AL16: руб.
A17: 43641 | B17: =Расчеты!G30/360 -> 0.021472222 | C17: 25.92 | D17: =(C17/C16-1)*100 -> -0.30769231 | E17: =D17-B17 -> -0.32916453 | F17: 2753.96 | G17: =(F17/F16-1)*100 -> -0.31455306 | H17: =G17-B17 -> -0.33602528 | I17: =E17^2 -> 0.10834929 | J17: =H17^2 -> 0.11291299 | K17: =E17*H17 -> 0.1106076 | M17: -4.1706769 | N17: =M17*$N$4 -> -0.041706769 | P17: Исторический VAR (1, 95%) | Q17: =(Q16-Q15)*(Q14-Q12)/(Q13-Q12)+Q15 -> -0.042107142 | R17: =C254*Q17 -> -1.6834435 | S17: руб. | V17: -0.041706769 | X17: Исторический VAR (1, 95%) | Y17: =(Y16-Y15)*(Y14-Y12)/(Y13-Y12)+Y15 -> -0.054995305 | Z17: =C254*Y17 -> -2.1987123 | AA17: руб. | AD17: -4.1706769 | AE17: =IF(AD17<0,AD17,AD17*(-1)) -> -4.1706769 | AF17: -7.1747544 | AG17: =AF17*$AG$4 -> -0.071747544 | AI17: Исторический VAR (1, 95%) | AJ17: =(AJ16-AJ15)*(AJ14-AJ12)/(AJ13-AJ12)+AJ15 -> -0.072660637 | AK17: =C254*AJ17 -> -2.9049723 | AL17: руб.
A18: 43642 | B18: =Расчеты!G31/360 -> 0.021472222 | C18: 26.285 | D18: =(C18/C17-1)*100 -> 1.408179 | E18: =D18-B18 -> 1.3867068 | F18: 2775.14 | G18: =(F18/F17-1)*100 -> 0.76907435 | H18: =G18-B18 -> 0.74760213 | I18: =E18^2 -> 1.9229557 | J18: =H18^2 -> 0.55890894 | K18: =E18*H18 -> 1.0367049 | M18: -4.1085271 | N18: =M18*$N$4 -> -0.041085271 | P18: C вероятность 95% убыток не превысит 1,94 руб. | V18: -0.041085271 | X18: C вероятность 95% убыток не превысит 2,20 руб. | AD18: -4.1085271 | AE18: =IF(AD18<0,AD18,AD18*(-1)) -> -4.1085271 | AF18: -7.0278672 | AG18: =AF18*$AG$4 -> -0.070278672 | AI18: C вероятность 95% убыток или прибыль не превысит 2,90 руб.
A19: 43643 | B19: =Расчеты!G32/360 -> 0.021416667 | C19: 26.32 | D19: =(C19/C18-1)*100 -> 0.13315579 | E19: =D19-B19 -> 0.11173913 | F19: 2779.66 | G19: =(F19/F18-1)*100 -> 0.16287467 | H19: =G19-B19 -> 0.141458 | I19: =E19^2 -> 0.012485632 | J19: =H19^2 -> 0.020010366 | K19: =E19*H19 -> 0.015806393 | M19: -3.9691517 | N19: =M19*$N$4 -> -0.039691517 | P19: Expected Shortfall | Q19: =AVERAGE(N5:N16) -> -0.063512677 | R19: =Q19*C254 -> -2.5392368 | S19: руб. | V19: -0.039691517 | X19: Expected Shortfall | Y19: =AVERAGE(V5:V10) -> -0.078554957 | Z19: =Y19*C254 -> -3.1406272 | AA19: руб. | AD19: -3.9691517 | AE19: =IF(AD19<0,AD19,AD19*(-1)) -> -3.9691517 | AF19: -6.9575201 | AG19: =AF19*$AG$4 -> -0.069575201 | AI19: Expected Shortfall | AJ19: =AVERAGE(AG5:AG16) -> -0.097692442 | AK19: =AJ19*C254 -> -3.9057438 | AL19: руб.
A20: 43644 | B20: =Расчеты!G33/360 -> 0.021444444 | C20: 26.34 | D20: =(C20/C19-1)*100 -> 0.075987842 | E20: =D20-B20 -> 0.054543398 | F20: 2765.85 | G20: =(F20/F19-1)*100 -> -0.49682335 | H20: =G20-B20 -> -0.5182678 | I20: =E20^2 -> 0.0029749822 | J20: =H20^2 -> 0.26860151 | K20: =E20*H20 -> -0.028268086 | M20: -3.9320657 | N20: =M20*$N$4 -> -0.039320657 | P20: Потенциальный размер убытка, если он превысит VaR, составит 2,54 руб. | V20: -0.039320657 | X20: Потенциальный размер убытка, если он превысит VaR, составит 3,14 руб. | AD20: -3.9320657 | AE20: =IF(AD20<0,AD20,AD20*(-1)) -> -3.9320657 | AF20: -6.9400631 | AG20: =AF20*$AG$4 -> -0.069400631 | AI20: Потенциальный размер убытка или прибыли, если он превысит VaR, составит 2,90 руб.
A21: 43647 | B21: =Расчеты!G34/360 -> 0.021333333 | C21: 26.37 | D21: =(C21/C20-1)*100 -> 0.11389522 | E21: =D21-B21 -> 0.092561883 | F21: 2801.47 | G21: =(F21/F20-1)*100 -> 1.28785 | H21: =G21-B21 -> 1.2665167 | I21: =E21^2 -> 0.0085677022 | J21: =H21^2 -> 1.6040645 | K21: =E21*H21 -> 0.11723117 | M21: -3.8726514 | N21: =M21*$N$4 -> -0.038726514 | V21: -0.038726514 | AD21: -3.8726514 | AE21: =IF(AD21<0,AD21,AD21*(-1)) -> -3.8726514 | AF21: -6.462585 | AG21: =AF21*$AG$4 -> -0.06462585
A22: 43648 | B22: =Расчеты!G35/360 -> 0.021222222 | C22: 26.735 | D22: =(C22/C21-1)*100 -> 1.3841487 | E22: =D22-B22 -> 1.3629264 | F22: 2809.81 | G22: =(F22/F21-1)*100 -> 0.29770085 | H22: =G22-B22 -> 0.27647863 | I22: =E22^2 -> 1.8575685 | J22: =H22^2 -> 0.076440432 | K22: =E22*H22 -> 0.37682003 | M22: -3.4531437 | N22: =M22*$N$4 -> -0.034531437 | V22: -0.034531437 | AD22: -3.4531437 | AE22: =IF(AD22<0,AD22,AD22*(-1)) -> -3.4531437 | AF22: -6.318927 | AG22: =AF22*$AG$4 -> -0.06318927
A23: 43649 | B23: =Расчеты!G36/360 -> 0.021111111 | C23: 26.8 | D23: =(C23/C22-1)*100 -> 0.24312699 | E23: =D23-B23 -> 0.22201588 | F23: 2823.95 | G23: =(F23/F22-1)*100 -> 0.50323687 | H23: =G23-B23 -> 0.48212576 | I23: =E23^2 -> 0.049291049 | J23: =H23^2 -> 0.23244525 | K23: =E23*H23 -> 0.10703957 | M23: -3.4343434 | N23: =M23*$N$4 -> -0.034343434 | V23: -0.034343434 | AD23: -3.4343434 | AE23: =IF(AD23<0,AD23,AD23*(-1)) -> -3.4343434 | AF23: -5.9049448 | AG23: =AF23*$AG$4 -> -0.059049448
A24: 43650 | B24: =Расчеты!G37/360 -> 0.021 | C24: 26.85 | D24: =(C24/C23-1)*100 -> 0.18656716 | E24: =D24-B24 -> 0.16556716 | F24: 2842.78 | G24: =(F24/F23-1)*100 -> 0.66679651 | H24: =G24-B24 -> 0.64579651 | I24: =E24^2 -> 0.027412486 | J24: =H24^2 -> 0.41705313 | K24: =E24*H24 -> 0.1069227 | M24: -3.3023873 | N24: =M24*$N$4 -> -0.033023873 | V24: -0.033023873 | AD24: -3.3023873 | AE24: =IF(AD24<0,AD24,AD24*(-1)) -> -3.3023873 | AF24: -5.6779339 | AG24: =AF24*$AG$4 -> -0.056779339
A25: 43651 | B25: =Расчеты!G38/360 -> 0.021 | C25: 26.8 | D25: =(C25/C24-1)*100 -> -0.18621974 | E25: =D25-B25 -> -0.20721974 | F25: 2835.35 | G25: =(F25/F24-1)*100 -> -0.26136388 | H25: =G25-B25 -> -0.28236388 | I25: =E25^2 -> 0.04294002 | J25: =H25^2 -> 0.079729359 | K25: =E25*H25 -> 0.058511369 | M25: -3.2861897 | N25: =M25*$N$4 -> -0.032861897 | V25: -0.032861897 | AD25: -3.2861897 | AE25: =IF(AD25<0,AD25,AD25*(-1)) -> -3.2861897 | AF25: -5.5084746 | AG25: =AF25*$AG$4 -> -0.055084746
A26: 43654 | B26: =Расчеты!G39/360 -> 0.021055556 | C26: 26.92 | D26: =(C26/C25-1)*100 -> 0.44776119 | E26: =D26-B26 -> 0.42670564 | F26: 2822.55 | G26: =(F26/F25-1)*100 -> -0.45144338 | H26: =G26-B26 -> -0.47249894 | I26: =E26^2 -> 0.1820777 | J26: =H26^2 -> 0.22325525 | K26: =E26*H26 -> -0.20161796 | M26: -3.0533315 | N26: =M26*$N$4 -> -0.030533315 | V26: -0.030533315 | AD26: -3.0533315 | AE26: =IF(AD26<0,AD26,AD26*(-1)) -> -3.0533315 | AF26: -5.3295933 | AG26: =AF26*$AG$4 -> -0.053295933
A27: 43655 | B27: =Расчеты!G40/360 -> 0.021138889 | C27: 27.2 | D27: =(C27/C26-1)*100 -> 1.0401189 | E27: =D27-B27 -> 1.01898 | F27: 2822.66 | G27: =(F27/F26-1)*100 -> 0.0038971852 | H27: =G27-B27 -> -0.017241704 | I27: =E27^2 -> 1.0383202 | J27: =H27^2 -> 0.00029727635 | K27: =E27*H27 -> -0.017568951 | M27: -2.9419192 | N27: =M27*$N$4 -> -0.029419192 | V27: -0.029419192 | AD27: -2.9419192 | AE27: =IF(AD27<0,AD27,AD27*(-1)) -> -2.9419192 | AF27: -5.2909091 | AG27: =AF27*$AG$4 -> -0.052909091
A28: 43656 | B28: =Расчеты!G41/360 -> 0.021166667 | C28: 27.145 | D28: =(C28/C27-1)*100 -> -0.20220588 | E28: =D28-B28 -> -0.22337255 | F28: 2822.75 | G28: =(F28/F27-1)*100 -> 0.0031884818 | H28: =G28-B28 -> -0.017978185 | I28: =E28^2 -> 0.049895296 | J28: =H28^2 -> 0.00032321513 | K28: =E28*H28 -> 0.004015833 | M28: -2.8856526 | N28: =M28*$N$4 -> -0.028856526 | V28: -0.028856526 | AD28: -2.8856526 | AE28: =IF(AD28<0,AD28,AD28*(-1)) -> -2.8856526 | AF28: -5.1428571 | AG28: =AF28*$AG$4 -> -0.051428571
A29: 43657 | B29: =Расчеты!G42/360 -> 0.021027778 | C29: 26.705 | D29: =(C29/C28-1)*100 -> -1.6209247 | E29: =D29-B29 -> -1.6419524 | F29: 2789.66 | G29: =(F29/F28-1)*100 -> -1.1722611 | H29: =G29-B29 -> -1.1932889 | I29: =E29^2 -> 2.6960078 | J29: =H29^2 -> 1.4239383 | K29: =E29*H29 -> 1.9593236 | M29: -2.8481013 | N29: =M29*$N$4 -> -0.028481013 | V29: -0.028481013 | AD29: -2.8481013 | AE29: =IF(AD29<0,AD29,AD29*(-1)) -> -2.8481013 | AF29: -5.0879397 | AG29: =AF29*$AG$4 -> -0.050879397
A30: 43658 | B30: =Расчеты!G43/360 -> 0.021 | C30: 26.79 | D30: =(C30/C29-1)*100 -> 0.31829245 | E30: =D30-B30 -> 0.29729245 | F30: 2777.58 | G30: =(F30/F29-1)*100 -> -0.43302768 | H30: =G30-B30 -> -0.45402768 | I30: =E30^2 -> 0.088382804 | J30: =H30^2 -> 0.20614113 | K30: =E30*H30 -> -0.134979 | M30: -2.6253646 | N30: =M30*$N$4 -> -0.026253646 | V30: -0.026253646 | AD30: -2.6253646 | AE30: =IF(AD30<0,AD30,AD30*(-1)) -> -2.6253646 | AF30: -5.0612979 | AG30: =AF30*$AG$4 -> -0.050612979
A31: 43661 | B31: =Расчеты!G44/360 -> 0.021 | C31: 26.57 | D31: =(C31/C30-1)*100 -> -0.82120194 | E31: =D31-B31 -> -0.84220194 | F31: 2756.44 | G31: =(F31/F30-1)*100 -> -0.76109419 | H31: =G31-B31 -> -0.78209419 | I31: =E31^2 -> 0.70930411 | J31: =H31^2 -> 0.61167132 | K31: =E31*H31 -> 0.65868124 | M31: -2.6059525 | N31: =M31*$N$4 -> -0.026059525 | V31: -0.026059525 | AD31: -2.6059525 | AE31: =IF(AD31<0,AD31,AD31*(-1)) -> -2.6059525 | AF31: -5.0088496 | AG31: =AF31*$AG$4 -> -0.050088496
A32: 43662 | B32: =Расчеты!G45/360 -> 0.021 | C32: 26.83 | D32: =(C32/C31-1)*100 -> 0.97854723 | E32: =D32-B32 -> 0.95754723 | F32: 2755.88 | G32: =(F32/F31-1)*100 -> -0.02031606 | H32: =G32-B32 -> -0.04131606 | I32: =E32^2 -> 0.9168967 | J32: =H32^2 -> 0.0017070168 | K32: =E32*H32 -> -0.039562079 | M32: -2.5813692 | N32: =M32*$N$4 -> -0.025813692 | V32: -0.025813692 | AD32: -2.5813692 | AE32: =IF(AD32<0,AD32,AD32*(-1)) -> -2.5813692 | AF32: -4.9300749 | AG32: =AF32*$AG$4 -> -0.049300749
... A125: 43794 | B125: =Расчеты!G138/360 -> 0.018388889 | C125: 46.185 | D125: =(C125/C124-1)*100 -> -1.1662743 | E125: =D125-B125 -> -1.1846632 | F125: 2955.32 | G125: =(F125/F124-1)*100 -> 0.25918689 | H125: =G125-B125 -> 0.240798 | I125: =E125^2 -> 1.403427 | J125: =H125^2 -> 0.057983675 | K125: =E125*H125 -> -0.28526453 | M125: -0.037671878 | N125: =M125*$N$4 -> -0.00037671878 | V125: -0.00037671878 | AD125: -0.037671878 | AE125: =IF(AD125<0,AD125,AD125*(-1)) -> -0.037671878 | AF125: -1.309016 | AG125: =AF125*$AG$4 -> -0.01309016
A126: 43795 | B126: =Расчеты!G139/360 -> 0.018416667 | C126: 45 | D126: =(C126/C125-1)*100 -> -2.5657681 | E126: =D126-B126 -> -2.5841848 | F126: 2930.62 | G126: =(F126/F125-1)*100 -> -0.8357809 | H126: =G126-B126 -> -0.85419756 | I126: =E126^2 -> 6.6780109 | J126: =H126^2 -> 0.72965348 | K126: =E126*H126 -> 2.2074043 | M126: 0 | N126: =M126*$N$4 -> 0 | AD126: 0 | AE126: =IF(AD126<0,AD126,AD126*(-1)) -> 0 | AF126: -1.2933969 | AG126: =AF126*$AG$4 -> -0.012933969
A127: 43796 | B127: =Расчеты!G140/360 -> 0.018416667 | C127: 44.51 | D127: =(C127/C126-1)*100 -> -1.0888889 | E127: =D127-B127 -> -1.1073056 | F127: 2929.05 | G127: =(F127/F126-1)*100 -> -0.053572282 | H127: =G127-B127 -> -0.071988948 | I127: =E127^2 -> 1.2261256 | J127: =H127^2 -> 0.0051824087 | K127: =E127*H127 -> 0.079713762 | M127: 0 | N127: =M127*$N$4 -> 0 | AD127: 0 | AE127: =IF(AD127<0,AD127,AD127*(-1)) -> 0 | AF127: -1.280396 | AG127: =AF127*$AG$4 -> -0.01280396
A128: 43797 | B128: =Расчеты!G141/360 -> 0.018416667 | C128: 43.645 | D128: =(C128/C127-1)*100 -> -1.9433835 | E128: =D128-B128 -> -1.9618002 | F128: 2927.57 | G128: =(F128/F127-1)*100 -> -0.050528328 | H128: =G128-B128 -> -0.068944995 | I128: =E128^2 -> 3.8486599 | J128: =H128^2 -> 0.0047534123 | K128: =E128*H128 -> 0.1352563 | M128: 0.020699648 | N128: =M128*$N$4 -> 0.00020699648 | AD128: 0.020699648 | AE128: =IF(AD128<0,AD128,AD128*(-1)) -> -0.020699648 | AF128: -1.2720714 | AG128: =AF128*$AG$4 -> -0.012720714
A129: 43798 | B129: =Расчеты!G142/360 -> 0.018444444 | C129: 44.1 | D129: =(C129/C128-1)*100 -> 1.042502 | E129: =D129-B129 -> 1.0240576 | F129: 2935.37 | G129: =(F129/F128-1)*100 -> 0.26643257 | H129: =G129-B129 -> 0.24798813 | I129: =E129^2 -> 1.0486939 | J129: =H129^2 -> 0.061498111 | K129: =E129*H129 -> 0.25395412 | M129: 0.07390983 | N129: =M129*$N$4 -> 0.0007390983 | AD129: 0.07390983 | AE129: =IF(AD129<0,AD129,AD129*(-1)) -> -0.07390983 | AF129: -1.2565661 | AG129: =AF129*$AG$4 -> -0.012565661
A130: 43801 | B130: =Расчеты!G143/360 -> 0.018444444 | C130: 43.27 | D130: =(C130/C129-1)*100 -> -1.8820862 | E130: =D130-B130 -> -1.9005306 | F130: 2921.18 | G130: =(F130/F129-1)*100 -> -0.48341436 | H130: =G130-B130 -> -0.5018588 | I130: =E130^2 -> 3.6120166 | J130: =H130^2 -> 0.25186226 | K130: =E130*H130 -> 0.95379801 | M130: 0.075987842 | N130: =M130*$N$4 -> 0.00075987842 | AD130: 0.075987842 | AE130: =IF(AD130<0,AD130,AD130*(-1)) -> -0.075987842 | AF130: -1.2360447 | AG130: =AF130*$AG$4 -> -0.012360447
A131: 43802 | B131: =Расчеты!G144/360 -> 0.0185 | C131: 42.54 | D131: =(C131/C130-1)*100 -> -1.6870811 | E131: =D131-B131 -> -1.7055811 | F131: 2883.48 | G131: =(F131/F130-1)*100 -> -1.2905744 | H131: =G131-B131 -> -1.3090744 | I131: =E131^2 -> 2.909007 | J131: =H131^2 -> 1.7136757 | K131: =E131*H131 -> 2.2327325 | M131: 0.11389522 | N131: =M131*$N$4 -> 0.0011389522 | AD131: 0.11389522 | AE131: =IF(AD131<0,AD131,AD131*(-1)) -> -0.11389522 | AF131: -1.2292283 | AG131: =AF131*$AG$4 -> -0.012292283
A132: 43803 | B132: =Расчеты!G145/360 -> 0.018416667 | C132: 43.7 | D132: =(C132/C131-1)*100 -> 2.7268453 | E132: =D132-B132 -> 2.7084287 | F132: 2900.66 | G132: =(F132/F131-1)*100 -> 0.59580784 | H132: =G132-B132 -> 0.57739118 | I132: =E132^2 -> 7.3355858 | J132: =H132^2 -> 0.33338057 | K132: =E132*H132 -> 1.5638228 | M132: 0.1150748 | N132: =M132*$N$4 -> 0.001150748 | AD132: 0.1150748 | AE132: =IF(AD132<0,AD132,AD132*(-1)) -> -0.1150748 | AF132: -1.2209531 | AG132: =AF132*$AG$4 -> -0.012209531
A133: 43804 | B133: =Расчеты!G146/360 -> 0.018416667 | C133: 43.2 | D133: =(C133/C132-1)*100 -> -1.1441648 | E133: =D133-B133 -> -1.1625814 | F133: 2899.29 | G133: =(F133/F132-1)*100 -> -0.04723063 | H133: =G133-B133 -> -0.065647297 | I133: =E133^2 -> 1.3515956 | J133: =H133^2 -> 0.0043095676 | K133: =E133*H133 -> 0.076320328 | M133: 0.13315579 | N133: =M133*$N$4 -> 0.0013315579 | AD133: 0.13315579 | AE133: =IF(AD133<0,AD133,AD133*(-1)) -> -0.13315579 | AF133: -1.1947267 | AG133: =AF133*$AG$4 -> -0.011947267
A134: 43805 | B134: =Расчеты!G147/360 -> 0.018277778 | C134: 43.345 | D134: =(C134/C133-1)*100 -> 0.33564815 | E134: =D134-B134 -> 0.31737037 | F134: 2928.76 | G134: =(F134/F133-1)*100 -> 1.0164558 | H134: =G134-B134 -> 0.99817798 | I134: =E134^2 -> 0.10072395 | J134: =H134^2 -> 0.99635927 | K134: =E134*H134 -> 0.31679211 | M134: 0.17656352 | N134: =M134*$N$4 -> 0.0017656352 | AD134: 0.17656352 | AE134: =IF(AD134<0,AD134,AD134*(-1)) -> -0.17656352 | AF134: -1.1727079 | AG134: =AF134*$AG$4 -> -0.011727079
A135: 43808 | B135: =Расчеты!G148/360 -> 0.018222222 | C135: 43.93 | D135: =(C135/C134-1)*100 -> 1.3496366 | E135: =D135-B135 -> 1.3314144 | F135: 2945.03 | G135: =(F135/F134-1)*100 -> 0.55552521 | H135: =G135-B135 -> 0.53730298 | I135: =E135^2 -> 1.7726643 | J135: =H135^2 -> 0.2886945 | K135: =E135*H135 -> 0.71537294 | M135: 0.18656716 | N135: =M135*$N$4 -> 0.0018656716 | AD135: 0.18656716 | AE135: =IF(AD135<0,AD135,AD135*(-1)) -> -0.18656716 | AF135: -1.1662743 | AG135: =AF135*$AG$4 -> -0.011662743
A136: 43809 | B136: =Расчеты!G149/360 -> 0.018222222 | C136: 43.39 | D136: =(C136/C135-1)*100 -> -1.2292283 | E136: =D136-B136 -> -1.2474505 | F136: 2932.4 | G136: =(F136/F135-1)*100 -> -0.42885811 | H136: =G136-B136 -> -0.44708033 | I136: =E136^2 -> 1.5561328 | J136: =H136^2 -> 0.19988082 | K136: =E136*H136 -> 0.5577106 | M136: 0.189532 | N136: =M136*$N$4 -> 0.00189532 | AD136: 0.189532 | AE136: =IF(AD136<0,AD136,AD136*(-1)) -> -0.189532 | AF136: -1.1659193 | AG136: =AF136*$AG$4 -> -0.011659193
A137: 43810 | B137: =Расчеты!G150/360 -> 0.018111111 | C137: 45.035 | D137: =(C137/C136-1)*100 -> 3.7911961 | E137: =D137-B137 -> 3.773085 | F137: 2954.4 | G137: =(F137/F136-1)*100 -> 0.75023871 | H137: =G137-B137 -> 0.7321276 | I137: =E137^2 -> 14.236171 | J137: =H137^2 -> 0.53601082 | K137: =E137*H137 -> 2.7623797 | M137: 0.192 | N137: =M137*$N$4 -> 0.00192 | AD137: 0.192 | AE137: =IF(AD137<0,AD137,AD137*(-1)) -> -0.192 | AF137: -1.1587983 | AG137: =AF137*$AG$4 -> -0.011587983
... A254: 43985 | B254: =Расчеты!G267/360 -> 0.015738095 | C254: 39.98 | D254: =(C254/C253-1)*100 -> -0.60907396 | E254: =D254-B254 -> -0.62481205 | F254: 2801.77 | G254: =(F254/F253-1)*100 -> 0.18809159 | H254: =G254-B254 -> 0.17235349 | I254: =E254^2 -> 0.3903901 | J254: =H254^2 -> 0.029705726 | K254: =E254*H254 -> -0.10768854 | M254: 15.166261 | N254: =M254*$N$4 -> 0.15166261 | AD254: 15.166261 | AE254: =IF(AD254<0,AD254,AD254*(-1)) -> -15.166261 | AF254: 0 | AG254: =AF254*$AG$4 -> 0
A255: Сумма | E255: =SUM(E5:E254) -> 53.302656 | H255: =SUM(H5:H254) -> 1.9905879 | I255: =SUM(I5:I254) -> 2395.8486 | J255: =SUM(J5:J254) -> 594.19371 | K255: =SUM(K5:K254) -> 742.58843
A259: Количество наблюдений | E259: 250
A260: Бета | E260: =((E259*K255)-(E255*H255))/(E259*J255-H255^2) -> 1.2490604 | F260: Актив изменяется быстрее, чем рынок (бенчмарк)
A261: Альфа | E261: =E255/E259-E260*H255/E259 -> 0.20326517 | F261: Положительна, хорошо, по данному активу фактическая доходность выше, чем ожидаемая
A262: Стандартное отклонение случайно погрешности | E262: =((I255-E261*E255-E260*K255)/(E259-2))^0.5 -> 2.424236 | F262: Высокая ошибка, с учетом низкой доходности акции
A263: Стандартная ошибка беты | E263: =E262/(J255-H255^2/E259)^0.5 -> 0.09945272
A264: Стандартная ошибка альфы | E264: =E262/(E259-(H255)^2/J255)^0.5 -> 0.15332419
A265: Коэффициент корреляции | E265: =CORREL(E5:E254,H5:H254) -> 0.6235115 | F265: Среднее значение, величина избыточной доходности акции Сургутнефтегаза зависит от избыточной доходности МосБиржи на 62%
A266: Коэффициент детерминации | E266: =E265^2 -> 0.38876659 | F266: Модель объясняет изменение прогнозируемой величины (избыточную доходность Сургутнефтегаза) на 39%
A267: Коэффициент непределенности | E267: =1-E266 -> 0.61123341 | F267: 61% осталось не объяснено
A270: Мат ожидание доходности акции | E270: =AVERAGE(D5:D254) -> 0.23176308
F280: ВЫВОД ИТОГОВ
F282: Регрессионная статистика
F283: Множественный R | G283: 0.6235115
F284: R-квадрат | G284: 0.38876659
F285: Нормированный R-квадрат | G285: 0.38630194
F286: Стандартная ошибка | G286: 2.424236
F287: Наблюдения | G287: 250
F289: Дисперсионный анализ
G290: df | H290: SS | I290: MS | J290: F | K290: Значимость F
F291: Регрессия | G291: 1 | H291: 927.00766 | I291: 927.00766 | J291: 157.73698 | K291: 2.491268e-28
F292: Остаток | G292: 248 | H292: 1457.4762 | I292: 5.8769202
F293: Итого | G293: 249 | H293: 2384.4839
G295: Коэффициенты | H295: Стандартная ошибка | I295: t-статистика | J295: P-Значение | K295: Нижние 95% | L295: Верхние 95% | M295: Нижние 95,0% | N295: Верхние 95,0%
F296: Y-пересечение | G296: 0.20326517 | H296: 0.15332419 | I296: 1.3257214 | J296: 0.18615183 | K296: -0.098718427 | L296: 0.50524876 | M296: -0.098718427 | N296: 0.50524876
F297: Переменная X 1 | G297: 1.2490604 | H297: 0.09945272 | I297: 12.559339 | J297: 2.491268e-28 | K297: 1.0531807 | L297: 1.44494 | M297: 1.0531807 | N297: 1.44494

Sheet FXGD ETF
A1: Апостериорная характеристическая линия для ETF на физическое золото
A2: 251 дата | D2: 250 доходностей | F2: 0.01
A3: Дата | B3: Безрисковая доходность MosPrime Rate, % | C3: Цена FXGD ETF | D3: Доходность FXGD ETF, % | E3: Избыточная дох-ть FXGD ETF, % (Y) | F3: Значение бенчмарка IMOEX | G3: Доходность бенчмарка IMOEX,% | H3: Избыточная дох-ть бенчмарка IMOEX, % (X) | I3: Y^2 | J3: X^2 | K3: Y*X | N3: Rt | P3: Расчет VAR и ES (все приросты) | V3: Rt | X3: Расчет VAR и ES (отрицательные приросты) | AG3: Rt | AI3: Расчет VAR и ES (все приросты без учета знака)
A4: 43621 | B4: =Расчеты!G17/360 -> 0.021888889 | C4: 601.4 | F4: 2701.84 | N4: 0.01 | AG4: 0.01
A5: 43622 | B5: =Расчеты!G18/360 -> 0.021972222 | C5: 604 | D5: =(C5/C4-1)*100 -> 0.43232458 | E5: =D5-B5 -> 0.41035235 | F5: 2728.25 | G5: =(F5/F4-1)*100 -> 0.97748201 | H5: =G5-B5 -> 0.95550979 | I5: =E5^2 -> 0.16838905 | J5: =H5^2 -> 0.91299896 | K5: =E5*H5 -> 0.39209569 | M5: -3.525212 | N5: =M5*$N$4 -> -0.03525212 | P5: Количество наблюдений | Q5: 250 | V5: -0.03525212 | X5: Количество наблюдений | Y5: =COUNT(V5:V119) -> 115 | AD5: -3.525212 | AE5: =IF(AD5<0,AD5,AD5*(-1)) -> -3.525212 | AF5: -15.166261 | AG5: =AF5*$AG$4 -> -0.15166261 | AI5: Количество наблюдений | AJ5: 250
A6: 43623 | B6: =Расчеты!G19/360 -> 0.022027778 | C6: 604.2 | D6: =(C6/C5-1)*100 -> 0.033112583 | E6: =D6-B6 -> 0.011084805 | F6: 2729.61 | G6: =(F6/F5-1)*100 -> 0.049848804 | H6: =G6-B6 -> 0.027821026 | I6: =E6^2 -> 0.0001228729 | J6: =H6^2 -> 0.00077400951 | K6: =E6*H6 -> 0.00030839065 | M6: -3.3398342 | N6: =M6*$N$4 -> -0.033398342 | P6: Среднее | Q6: =AVERAGE(N5:N254) -> 0.0012804093 | V6: -0.033398342 | X6: Среднее | Y6: =AVERAGE(V5:V119) -> -0.0080884869 | AD6: -3.3398342 | AE6: =IF(AD6<0,AD6,AD6*(-1)) -> -3.3398342 | AF6: -13.579036 | AG6: =AF6*$AG$4 -> -0.13579036 | AI6: Среднее | AJ6: =AVERAGE(AG5:AG254) -> -0.019995954
A7: 43626 | B7: =Расчеты!G20/360 -> 0.022055556 | C7: 595.2 | D7: =(C7/C6-1)*100 -> -1.489573 | E7: =D7-B7 -> -1.5116285 | F7: 2742.59 | G7: =(F7/F6-1)*100 -> 0.47552581 | H7: =G7-B7 -> 0.45347025 | I7: =E7^2 -> 2.2850209 | J7: =H7^2 -> 0.20563527 | K7: =E7*H7 -> -0.68547858 | M7: -2.8072034 | N7: =M7*$N$4 -> -0.028072034 | P7: Станд.отклонение | Q7: =_xlfn.STDEV.S(N5:N254) -> 0.012208739 | R7: =Q7*C254 -> 9.9257047 | S7: руб. | V7: -0.028072034 | X7: Станд.отклонение | Y7: =_xlfn.STDEV.S(V5:V125) -> 0.0072158282 | Z7: =Y7*C254 -> 5.8664683 | AA7: руб. | AD7: -2.8072034 | AE7: =IF(AD7<0,AD7,AD7*(-1)) -> -2.8072034 | AF7: -12.295082 | AG7: =AF7*$AG$4 -> -0.12295082 | AI7: Станд.отклонение | AJ7: =_xlfn.STDEV.S(AG5:AG254) -> 0.023699031 | AK7: =AJ7*C254 -> 19.267312 | AL7: руб.
A8: 43627 | B8: =Расчеты!G21/360 -> 0.021833333 | C8: 592.2 | D8: =(C8/C7-1)*100 -> -0.50403226 | E8: =D8-B8 -> -0.52586559 | F8: 2751.75 | G8: =(F8/F7-1)*100 -> 0.33399086 | H8: =G8-B8 -> 0.31215753 | I8: =E8^2 -> 0.27653462 | J8: =H8^2 -> 0.097442323 | K8: =E8*H8 -> -0.1641529 | M8: -2.4744898 | N8: =M8*$N$4 -> -0.024744898 | V8: -0.024744898 | AD8: -2.4744898 | AE8: =IF(AD8<0,AD8,AD8*(-1)) -> -2.4744898 | AF8: -10 | AG8: =AF8*$AG$4 -> -0.1
A9: 43629 | B9: =Расчеты!G22/360 -> 0.021722222 | C9: 599 | D9: =(C9/C8-1)*100 -> 1.1482607 | E9: =D9-B9 -> 1.1265385 | F9: 2758.36 | G9: =(F9/F8-1)*100 -> 0.24021077 | H9: =G9-B9 -> 0.21848855 | I9: =E9^2 -> 1.269089 | J9: =H9^2 -> 0.047737248 | K9: =E9*H9 -> 0.24613577 | M9: -2.268088 | N9: =M9*$N$4 -> -0.02268088 | P9: Квантиль распределения | Q9: 0.05 | V9: -0.02268088 | X9: Квантиль распределения | Y9: 0.05 | AD9: -2.268088 | AE9: =IF(AD9<0,AD9,AD9*(-1)) -> -2.268088 | AF9: -9.380531 | AG9: =AF9*$AG$4 -> -0.09380531 | AI9: Квантиль распределения | AJ9: 0.05
A10: 43630 | B10: =Расчеты!G23/360 -> 0.021694444 | C10: 603 | D10: =(C10/C9-1)*100 -> 0.66777963 | E10: =D10-B10 -> 0.64608519 | F10: 2739.28 | G10: =(F10/F9-1)*100 -> -0.69171537 | H10: =G10-B10 -> -0.71340981 | I10: =E10^2 -> 0.41742607 | J10: =H10^2 -> 0.50895356 | K10: =E10*H10 -> -0.46092351 | M10: -2.1732995 | N10: =M10*$N$4 -> -0.021732995 | P10: VAR (1, 95%) | Q10: =_xlfn.NORM.INV(Q9,Q6,Q7) -> -0.018801179 | R10: =Q10*C254 -> -15.285359 | S10: руб. | V10: -0.021732995 | X10: VAR (1, 95%) | Y10: =_xlfn.NORM.INV(Y9,Y6,Y7) -> -0.019957468 | Z10: =Y10*C254 -> -16.225422 | AA10: руб. | AD10: -2.1732995 | AE10: =IF(AD10<0,AD10,AD10*(-1)) -> -2.1732995 | AF10: -8.7175357 | AG10: =AF10*$AG$4 -> -0.087175357 | AI10: VAR (1, 95%) | AJ10: =_xlfn.NORM.INV(AJ9,AJ6,AJ7) -> -0.058977391 | AK10: =AJ10*C254 -> -47.948619 | AL10: руб.
A11: 43633 | B11: =Расчеты!G24/360 -> 0.021388889 | C11: 595.8 | D11: =(C11/C10-1)*100 -> -1.1940299 | E11: =D11-B11 -> -1.2154187 | F11: 2734.31 | G11: =(F11/F10-1)*100 -> -0.18143454 | H11: =G11-B11 -> -0.20282343 | I11: =E11^2 -> 1.4772427 | J11: =H11^2 -> 0.041137342 | K11: =E11*H11 -> 0.24651539 | M11: -2.1643007 | N11: =M11*$N$4 -> -0.021643007 | P11: C вероятность 95% убыток не превысит 15,29 руб. | V11: -0.021643007 | X11: C вероятность 95% убыток не превысит 16,23 руб. | AD11: -2.1643007 | AE11: =IF(AD11<0,AD11,AD11*(-1)) -> -2.1643007 | AF11: -8.7139727 | AG11: =AF11*$AG$4 -> -0.087139727 | AI11: C вероятность 95% убыток или прибыль не превысит 47,95 руб.
A12: 43634 | B12: =Расчеты!G25/360 -> 0.021388889 | C12: 598.2 | D12: =(C12/C11-1)*100 -> 0.40281974 | E12: =D12-B12 -> 0.38143085 | F12: 2761.69 | G12: =(F12/F11-1)*100 -> 1.0013495 | H12: =G12-B12 -> 0.97996063 | I12: =E12^2 -> 0.14548949 | J12: =H12^2 -> 0.96032283 | K12: =E12*H12 -> 0.37378721 | M12: -2.1590909 | N12: =M12*$N$4 -> -0.021590909 | P12: Ист.наблюдение (мин.) № | Q12: =_xlfn.FLOOR.MATH(Q5*Q9) -> 12 | V12: -0.021590909 | X12: Ист.наблюдение (мин.) № | Y12: =_xlfn.FLOOR.MATH(Y5*Y9) -> 5 | AD12: -2.1590909 | AE12: =IF(AD12<0,AD12,AD12*(-1)) -> -2.1590909 | AF12: -8.4142395 | AG12: =AF12*$AG$4 -> -0.084142395 | AI12: Ист.наблюдение (мин.) № | AJ12: =_xlfn.FLOOR.MATH(AJ5*AJ9) -> 12
A13: 43635 | B13: =Расчеты!G26/360 -> 0.021277778 | C13: 595.2 | D13: =(C13/C12-1)*100 -> -0.50150451 | E13: =D13-B13 -> -0.52278229 | F13: 2759.12 | G13: =(F13/F12-1)*100 -> -0.09305896 | H13: =G13-B13 -> -0.11433674 | I13: =E13^2 -> 0.27330132 | J13: =H13^2 -> 0.01307289 | K13: =E13*H13 -> 0.059773222 | M13: -2.0053876 | N13: =M13*$N$4 -> -0.020053876 | P13: Ист.наблюдение (макс.) № | Q13: =_xlfn.CEILING.MATH(Q5*Q9) -> 13 | V13: -0.020053876 | X13: Ист.наблюдение (макс.) № | Y13: =_xlfn.CEILING.MATH(Y5*Y9) -> 6 | AD13: -2.0053876 | AE13: =IF(AD13<0,AD13,AD13*(-1)) -> -2.0053876 | AF13: -8.258287 | AG13: =AF13*$AG$4 -> -0.08258287 | AI13: Ист.наблюдение (макс.) № | AJ13: =_xlfn.CEILING.MATH(AJ5*AJ9) -> 13
A14: 43636 | B14: =Расчеты!G27/360 -> 0.021305556 | C14: 605 | D14: =(C14/C13-1)*100 -> 1.6465054 | E14: =D14-B14 -> 1.6251998 | F14: 2780.2 | G14: =(F14/F13-1)*100 -> 0.76401171 | H14: =G14-B14 -> 0.74270616 | I14: =E14^2 -> 2.6412745 | J14: =H14^2 -> 0.55161244 | K14: =E14*H14 -> 1.2070459 | M14: -1.853842 | N14: =M14*$N$4 -> -0.01853842 | P14: Ист.наблюдение (точное) № | Q14: =Q5*Q9 -> 12.5 | V14: -0.01853842 | X14: Ист.наблюдение (точное) № | Y14: =Y5*Y9 -> 5.75 | AD14: -1.853842 | AE14: =IF(AD14<0,AD14,AD14*(-1)) -> -1.853842 | AF14: -7.7788448 | AG14: =AF14*$AG$4 -> -0.077788448 | AI14: Ист.наблюдение (точное) № | AJ14: =AJ5*AJ9 -> 12.5
A15: 43637 | B15: =Расчеты!G28/360 -> 0.021305556 | C15: 612.8 | D15: =(C15/C14-1)*100 -> 1.2892562 | E15: =D15-B15 -> 1.2679506 | F15: 2761.23 | G15: =(F15/F14-1)*100 -> -0.68232501 | H15: =G15-B15 -> -0.70363057 | I15: =E15^2 -> 1.6076988 | J15: =H15^2 -> 0.49509598 | K15: =E15*H15 -> -0.89216883 | M15: -1.8464529 | N15: =M15*$N$4 -> -0.018464529 | P15: Ист.наблюдение (мин.) | Q15: =SMALL(N5:N254,Q12) -> -0.018352941 | R15: =C254*Q15 -> -14.920941 | S15: руб. | V15: -0.018464529 | X15: Ист.наблюдение (мин.) | Y15: =SMALL(V5:V125,Y12) -> -0.02268088 | Z15: =Y15*C254 -> -18.439555 | AA15: руб. | AD15: -1.8464529 | AE15: =IF(AD15<0,AD15,AD15*(-1)) -> -1.8464529 | AF15: -7.5697674 | AG15: =AF15*$AG$4 -> -0.075697674 | AI15: Ист.наблюдение (мин.) | AJ15: =SMALL(AG5:AG254,AJ12) -> -0.07357373 | AK15: =AJ15*C254 -> -59.815442 | AL15: руб.
A16: 43640 | B16: =Расчеты!G29/360 -> 0.021277778 | C16: 616 | D16: =(C16/C15-1)*100 -> 0.52219321 | E16: =D16-B16 -> 0.50091543 | F16: 2762.65 | G16: =(F16/F15-1)*100 -> 0.051426357 | H16: =G16-B16 -> 0.030148579 | I16: =E16^2 -> 0.25091627 | J16: =H16^2 -> 0.00090893683 | K16: =E16*H16 -> 0.015101889 | M16: -1.8352941 | N16: =M16*$N$4 -> -0.018352941 | P16: Ист.наблюдение (макс.) | Q16: =SMALL(N5:N254,Q13) -> -0.018244014 | R16: =C254*Q16 -> -14.832383 | S16: руб. | V16: -0.018352941 | X16: Ист.наблюдение (макс.) | Y16: =SMALL(V5:V125,Y13) -> -0.021732995 | Z16: =C254*Y16 -> -17.668925 | AA16: руб. | AD16: -1.8352941 | AE16: =IF(AD16<0,AD16,AD16*(-1)) -> -1.8352941 | AF16: -7.357373 | AG16: =AF16*$AG$4 -> -0.07357373 | AI16: Ист.наблюдение (макс.) | AJ16: =SMALL(AG5:AG254,AJ13) -> -0.071747544 | AK16: =C254*AJ16 -> -58.330753 | AL16: руб.
A17: 43641 | B17: =Расчеты!G30/360 -> 0.021472222 | C17: 621.6 | D17: =(C17/C16-1)*100 -> 0.90909091 | E17: =D17-B17 -> 0.88761869 | F17: 2753.96 | G17: =(F17/F16-1)*100 -> -0.31455306 | H17: =G17-B17 -> -0.33602528 | I17: =E17^2 -> 0.78786693 | J17: =H17^2 -> 0.11291299 | K17: =E17*H17 -> -0.29826232 | M17: -1.8244014 | N17: =M17*$N$4 -> -0.018244014 | P17: Исторический VAR (1, 95%) | Q17: =(Q16-Q15)*(Q14-Q12)/(Q13-Q12)+Q15 -> -0.018298477 | R17: =C254*Q17 -> -14.876662 | S17: руб. | V17: -0.018244014 | X17: Исторический VAR (1, 95%) | Y17: =(Y16-Y15)*(Y14-Y12)/(Y13-Y12)+Y15 -> -0.021969966 | Z17: =C254*Y17 -> -17.861582 | AA17: руб. | AD17: -1.8244014 | AE17: =IF(AD17<0,AD17,AD17*(-1)) -> -1.8244014 | AF17: -7.1747544 | AG17: =AF17*$AG$4 -> -0.071747544 | AI17: Исторический VAR (1, 95%) | AJ17: =(AJ16-AJ15)*(AJ14-AJ12)/(AJ13-AJ12)+AJ15 -> -0.072660637 | AK17: =C254*AJ17 -> -59.073098 | AL17: руб.
A18: 43642 | B18: =Расчеты!G31/360 -> 0.021472222 | C18: 616 | D18: =(C18/C17-1)*100 -> -0.9009009 | E18: =D18-B18 -> -0.92237312 | F18: 2775.14 | G18: =(F18/F17-1)*100 -> 0.76907435 | H18: =G18-B18 -> 0.74760213 | I18: =E18^2 -> 0.85077218 | J18: =H18^2 -> 0.55890894 | K18: =E18*H18 -> -0.68956811 | M18: -1.7056953 | N18: =M18*$N$4 -> -0.017056953 | P18: C вероятность 95% убыток не превысит 14,88 руб. | V18: -0.017056953 | X18: C вероятность 95% убыток не превысит 17,86 руб. | AD18: -1.7056953 | AE18: =IF(AD18<0,AD18,AD18*(-1)) -> -1.7056953 | AF18: -7.0278672 | AG18: =AF18*$AG$4 -> -0.070278672 | AI18: C вероятность 95% убыток или прибыль не превысит 59,07 руб.
A19: 43643 | B19: =Расчеты!G32/360 -> 0.021416667 | C19: 613.2 | D19: =(C19/C18-1)*100 -> -0.45454545 | E19: =D19-B19 -> -0.47596212 | F19: 2779.66 | G19: =(F19/F18-1)*100 -> 0.16287467 | H19: =G19-B19 -> 0.141458 | I19: =E19^2 -> 0.22653994 | J19: =H19^2 -> 0.020010366 | K19: =E19*H19 -> -0.067328649 | M19: -1.6714697 | N19: =M19*$N$4 -> -0.016714697 | P19: Expected Shortfall | Q19: =AVERAGE(N5:N16) -> -0.023710413 | R19: =Q19*C254 -> -19.276565 | S19: руб. | V19: -0.016714697 | X19: Expected Shortfall | Y19: =AVERAGE(V5:V9) -> -0.028829655 | Z19: =Y19*C254 -> -23.438509 | AA19: руб. | AD19: -1.6714697 | AE19: =IF(AD19<0,AD19,AD19*(-1)) -> -1.6714697 | AF19: -6.9575201 | AG19: =AF19*$AG$4 -> -0.069575201 | AI19: Expected Shortfall | AJ19: =AVERAGE(AG5:AG16) -> -0.097692442 | AK19: =AJ19*C254 -> -79.423955 | AL19: руб.
A20: 43644 | B20: =Расчеты!G33/360 -> 0.021444444 | C20: 617.4 | D20: =(C20/C19-1)*100 -> 0.68493151 | E20: =D20-B20 -> 0.66348706 | F20: 2765.85 | G20: =(F20/F19-1)*100 -> -0.49682335 | H20: =G20-B20 -> -0.5182678 | I20: =E20^2 -> 0.44021508 | J20: =H20^2 -> 0.26860151 | K20: =E20*H20 -> -0.34386398 | M20: -1.6301126 | N20: =M20*$N$4 -> -0.016301126 | P20: Потенциальный размер убытка, если он превысит VaR, составит 19,28 руб. | V20: -0.016301126 | X20: Потенциальный размер убытка, если он превысит VaR, составит 23,44 руб. | AD20: -1.6301126 | AE20: =IF(AD20<0,AD20,AD20*(-1)) -> -1.6301126 | AF20: -6.9400631 | AG20: =AF20*$AG$4 -> -0.069400631 | AI20: Потенциальный размер убытка или прибыли, если он превысит VaR, составит 79,42 руб.
A21: 43647 | B21: =Расчеты!G34/360 -> 0.021333333 | C21: 606 | D21: =(C21/C20-1)*100 -> -1.8464529 | E21: =D21-B21 -> -1.8677862 | F21: 2801.47 | G21: =(F21/F20-1)*100 -> 1.28785 | H21: =G21-B21 -> 1.2665167 | I21: =E21^2 -> 3.4886253 | J21: =H21^2 -> 1.6040645 | K21: =E21*H21 -> -2.3655824 | M21: -1.5079834 | N21: =M21*$N$4 -> -0.015079834 | V21: -0.015079834 | AD21: -1.5079834 | AE21: =IF(AD21<0,AD21,AD21*(-1)) -> -1.5079834 | AF21: -6.462585 | AG21: =AF21*$AG$4 -> -0.06462585
A22: 43648 | B22: =Расчеты!G35/360 -> 0.021222222 | C22: 614.8 | D22: =(C22/C21-1)*100 -> 1.4521452 | E22: =D22-B22 -> 1.430923 | F22: 2809.81 | G22: =(F22/F21-1)*100 -> 0.29770085 | H22: =G22-B22 -> 0.27647863 | I22: =E22^2 -> 2.0475406 | J22: =H22^2 -> 0.076440432 | K22: =E22*H22 -> 0.39561963 | M22: -1.5010507 | N22: =M22*$N$4 -> -0.015010507 | V22: -0.015010507 | AD22: -1.5010507 | AE22: =IF(AD22<0,AD22,AD22*(-1)) -> -1.5010507 | AF22: -6.318927 | AG22: =AF22*$AG$4 -> -0.06318927
A23: 43649 | B23: =Расчеты!G36/360 -> 0.021111111 | C23: 621.6 | D23: =(C23/C22-1)*100 -> 1.1060507 | E23: =D23-B23 -> 1.0849396 | F23: 2823.95 | G23: =(F23/F22-1)*100 -> 0.50323687 | H23: =G23-B23 -> 0.48212576 | I23: =E23^2 -> 1.177094 | J23: =H23^2 -> 0.23244525 | K23: =E23*H23 -> 0.52307735 | M23: -1.489573 | N23: =M23*$N$4 -> -0.01489573 | V23: -0.01489573 | AD23: -1.489573 | AE23: =IF(AD23<0,AD23,AD23*(-1)) -> -1.489573 | AF23: -5.9049448 | AG23: =AF23*$AG$4 -> -0.059049448
A24: 43650 | B24: =Расчеты!G37/360 -> 0.021 | C24: 622.8 | D24: =(C24/C23-1)*100 -> 0.19305019 | E24: =D24-B24 -> 0.17205019 | F24: 2842.78 | G24: =(F24/F23-1)*100 -> 0.66679651 | H24: =G24-B24 -> 0.64579651 | I24: =E24^2 -> 0.029601269 | J24: =H24^2 -> 0.41705313 | K24: =E24*H24 -> 0.11110941 | M24: -1.4869888 | N24: =M24*$N$4 -> -0.014869888 | V24: -0.014869888 | AD24: -1.4869888 | AE24: =IF(AD24<0,AD24,AD24*(-1)) -> -1.4869888 | AF24: -5.6779339 | AG24: =AF24*$AG$4 -> -0.056779339
A25: 43651 | B25: =Расчеты!G38/360 -> 0.021 | C25: 619.4 | D25: =(C25/C24-1)*100 -> -0.54592164 | E25: =D25-B25 -> -0.56692164 | F25: 2835.35 | G25: =(F25/F24-1)*100 -> -0.26136388 | H25: =G25-B25 -> -0.28236388 | I25: =E25^2 -> 0.32140015 | J25: =H25^2 -> 0.079729359 | K25: =E25*H25 -> 0.16007819 | M25: -1.426271 | N25: =M25*$N$4 -> -0.01426271 | V25: -0.01426271 | AD25: -1.426271 | AE25: =IF(AD25<0,AD25,AD25*(-1)) -> -1.426271 | AF25: -5.5084746 | AG25: =AF25*$AG$4 -> -0.055084746
A26: 43654 | B26: =Расчеты!G39/360 -> 0.021055556 | C26: 616 | D26: =(C26/C25-1)*100 -> -0.54891831 | E26: =D26-B26 -> -0.56997386 | F26: 2822.55 | G26: =(F26/F25-1)*100 -> -0.45144338 | H26: =G26-B26 -> -0.47249894 | I26: =E26^2 -> 0.32487021 | J26: =H26^2 -> 0.22325525 | K26: =E26*H26 -> 0.26931205 | M26: -1.4063873 | N26: =M26*$N$4 -> -0.014063873 | V26: -0.014063873 | AD26: -1.4063873 | AE26: =IF(AD26<0,AD26,AD26*(-1)) -> -1.4063873 | AF26: -5.3295933 | AG26: =AF26*$AG$4 -> -0.053295933
A27: 43655 | B27: =Расчеты!G40/360 -> 0.021138889 | C27: 618.2 | D27: =(C27/C26-1)*100 -> 0.35714286 | E27: =D27-B27 -> 0.33600397 | F27: 2822.66 | G27: =(F27/F26-1)*100 -> 0.0038971852 | H27: =G27-B27 -> -0.017241704 | I27: =E27^2 -> 0.11289867 | J27: =H27^2 -> 0.00029727635 | K27: =E27*H27 -> -0.0057932809 | M27: -1.3820904 | N27: =M27*$N$4 -> -0.013820904 | V27: -0.013820904 | AD27: -1.3820904 | AE27: =IF(AD27<0,AD27,AD27*(-1)) -> -1.3820904 | AF27: -5.2909091 | AG27: =AF27*$AG$4 -> -0.052909091
A28: 43656 | B28: =Расчеты!G41/360 -> 0.021166667 | C28: 616.4 | D28: =(C28/C27-1)*100 -> -0.29116791 | E28: =D28-B28 -> -0.31233457 | F28: 2822.75 | G28: =(F28/F27-1)*100 -> 0.0031884818 | H28: =G28-B28 -> -0.017978185 | I28: =E28^2 -> 0.097552886 | J28: =H28^2 -> 0.00032321513 | K28: =E28*H28 -> 0.0056152087 | M28: -1.3722628 | N28: =M28*$N$4 -> -0.013722628 | V28: -0.013722628 | AD28: -1.3722628 | AE28: =IF(AD28<0,AD28,AD28*(-1)) -> -1.3722628 | AF28: -5.1428571 | AG28: =AF28*$AG$4 -> -0.051428571
A29: 43657 | B29: =Расчеты!G42/360 -> 0.021027778 | C29: 614.2 | D29: =(C29/C28-1)*100 -> -0.3569111 | E29: =D29-B29 -> -0.37793887 | F29: 2789.66 | G29: =(F29/F28-1)*100 -> -1.1722611 | H29: =G29-B29 -> -1.1932889 | I29: =E29^2 -> 0.14283779 | J29: =H29^2 -> 1.4239383 | K29: =E29*H29 -> 0.45099025 | M29: -1.3091922 | N29: =M29*$N$4 -> -0.013091922 | V29: -0.013091922 | AD29: -1.3091922 | AE29: =IF(AD29<0,AD29,AD29*(-1)) -> -1.3091922 | AF29: -5.0879397 | AG29: =AF29*$AG$4 -> -0.050879397
A30: 43658 | B30: =Расчеты!G43/360 -> 0.021 | C30: 615 | D30: =(C30/C29-1)*100 -> 0.13025073 | E30: =D30-B30 -> 0.10925073 | F30: 2777.58 | G30: =(F30/F29-1)*100 -> -0.43302768 | H30: =G30-B30 -> -0.45402768 | I30: =E30^2 -> 0.011935723 | J30: =H30^2 -> 0.20614113 | K30: =E30*H30 -> -0.049602857 | M30: -1.2975256 | N30: =M30*$N$4 -> -0.012975256 | V30: -0.012975256 | AD30: -1.2975256 | AE30: =IF(AD30<0,AD30,AD30*(-1)) -> -1.2975256 | AF30: -5.0612979 | AG30: =AF30*$AG$4 -> -0.050612979
A31: 43661 | B31: =Расчеты!G44/360 -> 0.021 | C31: 614 | D31: =(C31/C30-1)*100 -> -0.16260163 | E31: =D31-B31 -> -0.18360163 | F31: 2756.44 | G31: =(F31/F30-1)*100 -> -0.76109419 | H31: =G31-B31 -> -0.78209419 | I31: =E31^2 -> 0.033709557 | J31: =H31^2 -> 0.61167132 | K31: =E31*H31 -> 0.14359376 | M31: -1.2812872 | N31: =M31*$N$4 -> -0.012812872 | V31: -0.012812872 | AD31: -1.2812872 | AE31: =IF(AD31<0,AD31,AD31*(-1)) -> -1.2812872 | AF31: -5.0088496 | AG31: =AF31*$AG$4 -> -0.050088496
A32: 43662 | B32: =Расчеты!G45/360 -> 0.021 | C32: 615 | D32: =(C32/C31-1)*100 -> 0.16286645 | E32: =D32-B32 -> 0.14186645 | F32: 2755.88 | G32: =(F32/F31-1)*100 -> -0.02031606 | H32: =G32-B32 -> -0.04131606 | I32: =E32^2 -> 0.020126089 | J32: =H32^2 -> 0.0017070168 | K32: =E32*H32 -> -0.0058613627 | M32: -1.2492737 | N32: =M32*$N$4 -> -0.012492737 | V32: -0.012492737 | AD32: -1.2492737 | AE32: =IF(AD32<0,AD32,AD32*(-1)) -> -1.2492737 | AF32: -4.9300749 | AG32: =AF32*$AG$4 -> -0.049300749
... A119: 43784 | B119: =Расчеты!G132/360 -> 0.018416667 | C119: 646.8 | D119: =(C119/C118-1)*100 -> -0.33898305 | E119: =D119-B119 -> -0.35739972 | F119: 2934.82 | G119: =(F119/F118-1)*100 -> 0.42327499 | H119: =G119-B119 -> 0.40485833 | I119: =E119^2 -> 0.12773456 | J119: =H119^2 -> 0.16391026 | K119: =E119*H119 -> -0.14469625 | M119: -0.03113325 | N119: =M119*$N$4 -> -0.0003113325 | V119: -0.0003113325 | AD119: -0.03113325 | AE119: =IF(AD119<0,AD119,AD119*(-1)) -> -0.03113325 | AF119: -1.3793103 | AG119: =AF119*$AG$4 -> -0.013793103
A120: 43787 | B120: =Расчеты!G133/360 -> 0.018416667 | C120: 647.8 | D120: =(C120/C119-1)*100 -> 0.1546073 | E120: =D120-B120 -> 0.13619063 | F120: 2924.48 | G120: =(F120/F119-1)*100 -> -0.35232144 | H120: =G120-B120 -> -0.3707381 | I120: =E120^2 -> 0.018547888 | J120: =H120^2 -> 0.13744674 | K120: =E120*H120 -> -0.050491056 | M120: 0 | N120: =M120*$N$4 -> 0 | AD120: 0 | AE120: =IF(AD120<0,AD120,AD120*(-1)) -> 0 | AF120: -1.3496366 | AG120: =AF120*$AG$4 -> -0.013496366
A121: 43788 | B121: =Расчеты!G134/360 -> 0.018472222 | C121: 647.8 | D121: =(C121/C120-1)*100 -> 0 | E121: =D121-B121 -> -0.018472222 | F121: 2941.69 | G121: =(F121/F120-1)*100 -> 0.58848069 | H121: =G121-B121 -> 0.57000846 | I121: =E121^2 -> 0.00034122299 | J121: =H121^2 -> 0.32490965 | K121: =E121*H121 -> -0.010529323 | M121: 0 | N121: =M121*$N$4 -> 0 | AD121: 0 | AE121: =IF(AD121<0,AD121,AD121*(-1)) -> 0 | AF121: -1.3427786 | AG121: =AF121*$AG$4 -> -0.013427786
A122: 43789 | B122: =Расчеты!G135/360 -> 0.018472222 | C122: 648.2 | D122: =(C122/C121-1)*100 -> 0.061747453 | E122: =D122-B122 -> 0.043275231 | F122: 2936.47 | G122: =(F122/F121-1)*100 -> -0.17744902 | H122: =G122-B122 -> -0.19592124 | I122: =E122^2 -> 0.0018727456 | J122: =H122^2 -> 0.038385132 | K122: =E122*H122 -> -0.0084785368 | M122: 0 | N122: =M122*$N$4 -> 0 | AD122: 0 | AE122: =IF(AD122<0,AD122,AD122*(-1)) -> 0 | AF122: -1.3399451 | AG122: =AF122*$AG$4 -> -0.013399451
A123: 43790 | B123: =Расчеты!G136/360 -> 0.018444444 | C123: 646.2 | D123: =(C123/C122-1)*100 -> -0.30854674 | E123: =D123-B123 -> -0.32699119 | F123: 2942.6 | G123: =(F123/F122-1)*100 -> 0.20875405 | H123: =G123-B123 -> 0.1903096 | I123: =E123^2 -> 0.10692324 | J123: =H123^2 -> 0.036217745 | K123: =E123*H123 -> -0.062229564 | M123: 0 | N123: =M123*$N$4 -> 0 | AD123: 0 | AE123: =IF(AD123<0,AD123,AD123*(-1)) -> 0 | AF123: -1.3296579 | AG123: =AF123*$AG$4 -> -0.013296579
A124: 43791 | B124: =Расчеты!G137/360 -> 0.018388889 | C124: 644.4 | D124: =(C124/C123-1)*100 -> -0.27855153 | E124: =D124-B124 -> -0.29694042 | F124: 2947.68 | G124: =(F124/F123-1)*100 -> 0.17263644 | H124: =G124-B124 -> 0.15424756 | I124: =E124^2 -> 0.088173614 | J124: =H124^2 -> 0.023792308 | K124: =E124*H124 -> -0.045802334 | M124: 0 | N124: =M124*$N$4 -> 0 | AD124: 0 | AE124: =IF(AD124<0,AD124,AD124*(-1)) -> 0 | AF124: -1.3284341 | AG124: =AF124*$AG$4 -> -0.013284341
A125: 43794 | B125: =Расчеты!G138/360 -> 0.018388889 | C125: 644.4 | D125: =(C125/C124-1)*100 -> 0 | E125: =D125-B125 -> -0.018388889 | F125: 2955.32 | G125: =(F125/F124-1)*100 -> 0.25918689 | H125: =G125-B125 -> 0.240798 | I125: =E125^2 -> 0.00033815123 | J125: =H125^2 -> 0.057983675 | K125: =E125*H125 -> -0.0044280076 | M125: 0 | N125: =M125*$N$4 -> 0 | AD125: 0 | AE125: =IF(AD125<0,AD125,AD125*(-1)) -> 0 | AF125: -1.309016 | AG125: =AF125*$AG$4 -> -0.01309016
A126: 43795 | B126: =Расчеты!G139/360 -> 0.018416667 | C126: 645 | D126: =(C126/C125-1)*100 -> 0.09310987 | E126: =D126-B126 -> 0.074693203 | F126: 2930.62 | G126: =(F126/F125-1)*100 -> -0.8357809 | H126: =G126-B126 -> -0.85419756 | I126: =E126^2 -> 0.0055790746 | J126: =H126^2 -> 0.72965348 | K126: =E126*H126 -> -0.063802752 | M126: 0 | N126: =M126*$N$4 -> 0 | AD126: 0 | AE126: =IF(AD126<0,AD126,AD126*(-1)) -> 0 | AF126: -1.2933969 | AG126: =AF126*$AG$4 -> -0.012933969
A127: 43796 | B127: =Расчеты!G140/360 -> 0.018416667 | C127: 644 | D127: =(C127/C126-1)*100 -> -0.15503876 | E127: =D127-B127 -> -0.17345543 | F127: 2929.05 | G127: =(F127/F126-1)*100 -> -0.053572282 | H127: =G127-B127 -> -0.071988948 | I127: =E127^2 -> 0.030086785 | J127: =H127^2 -> 0.0051824087 | K127: =E127*H127 -> 0.012486874 | M127: 0 | N127: =M127*$N$4 -> 0 | AD127: 0 | AE127: =IF(AD127<0,AD127,AD127*(-1)) -> 0 | AF127: -1.280396 | AG127: =AF127*$AG$4 -> -0.01280396
A128: 43797 | B128: =Расчеты!G141/360 -> 0.018416667 | C128: 644 | D128: =(C128/C127-1)*100 -> 0 | E128: =D128-B128 -> -0.018416667 | F128: 2927.57 | G128: =(F128/F127-1)*100 -> -0.050528328 | H128: =G128-B128 -> -0.068944995 | I128: =E128^2 -> 0.00033917361 | J128: =H128^2 -> 0.0047534123 | K128: =E128*H128 -> 0.001269737 | M128: 0.02824061 | N128: =M128*$N$4 -> 0.0002824061 | AD128: 0.02824061 | AE128: =IF(AD128<0,AD128,AD128*(-1)) -> -0.02824061 | AF128: -1.2720714 | AG128: =AF128*$AG$4 -> -0.012720714
A129: 43798 | B129: =Расчеты!G142/360 -> 0.018444444 | C129: 649 | D129: =(C129/C128-1)*100 -> 0.77639752 | E129: =D129-B129 -> 0.75795307 | F129: 2935.37 | G129: =(F129/F128-1)*100 -> 0.26643257 | H129: =G129-B129 -> 0.24798813 | I129: =E129^2 -> 0.57449286 | J129: =H129^2 -> 0.061498111 | K129: =E129*H129 -> 0.18796336 | M129: 0.029664788 | N129: =M129*$N$4 -> 0.00029664788 | AD129: 0.029664788 | AE129: =IF(AD129<0,AD129,AD129*(-1)) -> -0.029664788 | AF129: -1.2565661 | AG129: =AF129*$AG$4 -> -0.012565661
A130: 43801 | B130: =Расчеты!G143/360 -> 0.018444444 | C130: 648 | D130: =(C130/C129-1)*100 -> -0.1540832 | E130: =D130-B130 -> -0.17252765 | F130: 2921.18 | G130: =(F130/F129-1)*100 -> -0.48341436 | H130: =G130-B130 -> -0.5018588 | I130: =E130^2 -> 0.02976579 | J130: =H130^2 -> 0.25186226 | K130: =E130*H130 -> 0.086584519 | M130: 0.030111412 | N130: =M130*$N$4 -> 0.00030111412 | AD130: 0.030111412 | AE130: =IF(AD130<0,AD130,AD130*(-1)) -> -0.030111412 | AF130: -1.2360447 | AG130: =AF130*$AG$4 -> -0.012360447
A131: 43802 | B131: =Расчеты!G144/360 -> 0.0185 | C131: 655.2 | D131: =(C131/C130-1)*100 -> 1.1111111 | E131: =D131-B131 -> 1.0926111 | F131: 2883.48 | G131: =(F131/F130-1)*100 -> -1.2905744 | H131: =G131-B131 -> -1.3090744 | I131: =E131^2 -> 1.193799 | J131: =H131^2 -> 1.7136757 | K131: =E131*H131 -> -1.4303092 | M131: 0.033112583 | N131: =M131*$N$4 -> 0.00033112583 | AD131: 0.033112583 | AE131: =IF(AD131<0,AD131,AD131*(-1)) -> -0.033112583 | AF131: -1.2292283 | AG131: =AF131*$AG$4 -> -0.012292283
... A254: 43985 | B254: =Расчеты!G267/360 -> 0.015738095 | C254: 813 | D254: =(C254/C253-1)*100 -> -0.97442144 | E254: =D254-B254 -> -0.99015953 | F254: 2801.77 | G254: =(F254/F253-1)*100 -> 0.18809159 | H254: =G254-B254 -> 0.17235349 | I254: =E254^2 -> 0.9804159 | J254: =H254^2 -> 0.029705726 | K254: =E254*H254 -> -0.17065745 | M254: 5.4451613 | N254: =M254*$N$4 -> 0.054451613 | AD254: 5.4451613 | AE254: =IF(AD254<0,AD254,AD254*(-1)) -> -5.4451613 | AF254: 0 | AG254: =AF254*$AG$4 -> 0
A255: Сумма | E255: =SUM(E5:E254) -> 27.37212 | H255: =SUM(H5:H254) -> 1.9905879 | I255: =SUM(I5:I254) -> 374.12904 | J255: =SUM(J5:J254) -> 594.19371 | K255: =SUM(K5:K254) -> -143.94791
A259: Количество наблюдений | E259: 250
A260: Бета | E260: =((E259*K255)-(E255*H255))/(E259*J255-H255^2) -> -0.24263081 | F260: Когда изменения рынка положительны, изменения цены актива склонны быть отрицательными
A261: Альфа | E261: =E255/E259-E260*H255/E259 -> 0.11142039 | F261: Положительна, хорошо, по данному активу фактическая доходность больше, чем ожидаемая
A262: Стандартное отклонение случайно погрешности | E262: =((I255-E261*E255-E260*K255)/(E259-2))^0.5 -> 1.1642404 | F262: Высокая ошибка, с учетом низкой доходности акции
A263: Стандартная ошибка беты | E263: =E262/(J255-H255^2/E259)^0.5 -> 0.047762214
A264: Стандартная ошибка альфы | E264: =E262/(E259-(H255)^2/J255)^0.5 -> 0.073634012
A265: Коэффициент корреляции | E265: =CORREL(E5:E254,H5:H254) -> -0.30700109 | F265: Низкое отрицательное значение, величина избыточной доходности ETF физического золота слабо зависит от избыточной доходности МосБиржи
A266: Коэффициент детерминации | E266: =E265^2 -> 0.094249671 | F266: Модель объясняет изменение прогнозируемой величины (избыточную доходность FXGD ETF) плохо
A267: Коэффициент непределенности | E267: =1-E266 -> 0.90575033 | F267: 91% осталост не объяснено
A270: Мат ожидание доходности ETF | E270: =AVERAGE(D5:D254) -> 0.12804093
F280: ВЫВОД ИТОГОВ
F282: Регрессионная статистика
F283: Множественный R | G283: 0.30700109
F284: R-квадрат | G284: 0.094249671
F285: Нормированный R-квадрат | G285: 0.090597452
F286: Стандартная ошибка | G286: 1.1642404
F287: Наблюдения | G287: 250
F289: Дисперсионный анализ
G290: df | H290: SS | I290: MS | J290: F | K290: Значимость F
F291: Регрессия | G291: 1 | H291: 34.979079 | I291: 34.979079 | J291: 25.806138 | K291: 7.427607e-07
F292: Остаток | G292: 248 | H292: 336.15303 | I292: 1.3554558
F293: Итого | G293: 249 | H293: 371.13211
G295: Коэффициенты | H295: Стандартная ошибка | I295: t-статистика | J295: P-Значение | K295: Нижние 95% | L295: Верхние 95% | M295: Нижние 95,0% | N295: Верхние 95,0%
F296: Y-пересечение | G296: 0.11142039 | H296: 0.073634012 | I296: 1.5131647 | J296: 0.13151113 | K296: -0.033607367 | L296: 0.25644815 | M296: -0.033607367 | N296: 0.25644815
F297: Переменная X 1 | G297: -0.24263081 | H297: 0.047762214 | I297: -5.0799743 | J297: 7.427607e-07 | K297: -0.33670211 | L297: -0.14855952 | M297: -0.33670211 | N297: -0.14855952

Sheet Составление портфеля
A1: Акция SNGS | B1: FXGD ETF | C1: Доходносить портфеля | D1: Бета портфеля | E1: Риск портфеля Sx^2 (через cov) | F1: Риск портфеля Sx (через cov)
A2: 1 | B2: =1-A2 -> 0 | C2: =A2*$B$107+B2*$C$107 -> 0.2318 | D2: =A2*$B$108+B2*$C$108 -> 1.25 | E2: =Расчеты!L19*Расчеты!$M$19 -> 0.095386426 | F2: =SQRT(E2) -> 0.30884693
A3: 0.99 | B3: =1-A3 -> 0.01 | C3: =A3*$B$107+B3*$C$107 -> 0.230762 | D3: =A3*$B$108+B3*$C$108 -> 1.2351 | E3: =Расчеты!L20*Расчеты!$M$19 -> 0.093341882 | F3: =SQRT(E3) -> 0.30551904
A4: 0.98 | B4: =1-A4 -> 0.02 | C4: =A4*$B$107+B4*$C$107 -> 0.229724 | D4: =A4*$B$108+B4*$C$108 -> 1.2202 | E4: =Расчеты!L21*Расчеты!$M$19 -> 0.091322371 | F4: =SQRT(E4) -> 0.30219592 | H4: Для 2-ух данных активов риск (стд.откл.) находится в пределах [10,43%; 30,88%]
A5: 0.97 | B5: =1-A5 -> 0.03 | C5: =A5*$B$107+B5*$C$107 -> 0.228686 | D5: =A5*$B$108+B5*$C$108 -> 1.2053 | E5: =Расчеты!L22*Расчеты!$M$19 -> 0.089327894 | F5: =SQRT(E5) -> 0.29887772 | H5: Для нахождения эффективного портфеля зафиксируем величину риска на уровне 25% и найдем веса активов
A6: 0.96 | B6: =1-A6 -> 0.04 | C6: =A6*$B$107+B6*$C$107 -> 0.227648 | D6: =A6*$B$108+B6*$C$108 -> 1.1904 | E6: =Расчеты!L23*Расчеты!$M$19 -> 0.087358449 | F6: =SQRT(E6) -> 0.29556463 | H6: Эффективный портфель при риске 25%
A7: 0.95 | B7: =1-A7 -> 0.05 | C7: =A7*$B$107+B7*$C$107 -> 0.22661 | D7: =A7*$B$108+B7*$C$108 -> 1.1755 | E7: =Расчеты!L24*Расчеты!$M$19 -> 0.085414038 | F7: =SQRT(E7) -> 0.2922568 | H7: Акция SNGS | I7: FXGD ETF | J7: Доходносить портфеля | K7: Риск портфеля Sx (через cov) | L7: Бета портфеля
A8: 0.94 | B8: =1-A8 -> 0.06 | C8: =A8*$B$107+B8*$C$107 -> 0.225572 | D8: =A8*$B$108+B8*$C$108 -> 1.1606 | E8: =Расчеты!L25*Расчеты!$M$19 -> 0.08349466 | F8: =SQRT(E8) -> 0.28895442 | H8: 0.82053055 | I8: 0.17946945 | J8: =H8*B107+I8*C107 -> 0.21317107 | K8: =SQRT((H8^2)*(B114)+(I8^2)*(C115)+2*H8*I8*B115)*10 -> 24.999993 | L8: =H8*$B$108+I8*$C$108 -> 0.98259053
A9: 0.93 | B9: =1-A9 -> 0.07 | C9: =A9*$B$107+B9*$C$107 -> 0.224534 | D9: =A9*$B$108+B9*$C$108 -> 1.1457 | E9: =Расчеты!L26*Расчеты!$M$19 -> 0.081600314 | F9: =SQRT(E9) -> 0.28565769
A10: 0.92 | B10: =1-A10 -> 0.08 | C10: =A10*$B$107+B10*$C$107 -> 0.223496 | D10: =A10*$B$108+B10*$C$108 -> 1.1308 | E10: =Расчеты!L27*Расчеты!$M$19 -> 0.079731002 | F10: =SQRT(E10) -> 0.28236679 | H10: =H8+I8 -> 1 | J10: 0.2132 | K10: 0.25
A11: 0.91 | B11: =1-A11 -> 0.09 | C11: =A11*$B$107+B11*$C$107 -> 0.222458 | D11: =A11*$B$108+B11*$C$108 -> 1.1159 | E11: =Расчеты!L28*Расчеты!$M$19 -> 0.077886723 | F11: =SQRT(E11) -> 0.27908193
A12: 0.9 | B12: =1-A12 -> 0.1 | C12: =A12*$B$107+B12*$C$107 -> 0.22142 | D12: =A12*$B$108+B12*$C$108 -> 1.101 | E12: =Расчеты!L29*Расчеты!$M$19 -> 0.076067477 | F12: =SQRT(E12) -> 0.27580333
A13: 0.89 | B13: =1-A13 -> 0.11 | C13: =A13*$B$107+B13*$C$107 -> 0.220382 | D13: =A13*$B$108+B13*$C$108 -> 1.0861 | E13: =Расчеты!L30*Расчеты!$M$19 -> 0.074273263 | F13: =SQRT(E13) -> 0.27253122
A14: 0.88 | B14: =1-A14 -> 0.12 | C14: =A14*$B$107+B14*$C$107 -> 0.219344 | D14: =A14*$B$108+B14*$C$108 -> 1.0712 | E14: =Расчеты!L31*Расчеты!$M$19 -> 0.072504083 | F14: =SQRT(E14) -> 0.26926582
A15: 0.87 | B15: =1-A15 -> 0.13 | C15: =A15*$B$107+B15*$C$107 -> 0.218306 | D15: =A15*$B$108+B15*$C$108 -> 1.0563 | E15: =Расчеты!L32*Расчеты!$M$19 -> 0.070759936 | F15: =SQRT(E15) -> 0.2660074
A16: 0.86 | B16: =1-A16 -> 0.14 | C16: =A16*$B$107+B16*$C$107 -> 0.217268 | D16: =A16*$B$108+B16*$C$108 -> 1.0414 | E16: =Расчеты!L33*Расчеты!$M$19 -> 0.069040823 | F16: =SQRT(E16) -> 0.2627562
A17: 0.85 | B17: =1-A17 -> 0.15 | C17: =A17*$B$107+B17*$C$107 -> 0.21623 | D17: =A17*$B$108+B17*$C$108 -> 1.0265 | E17: =Расчеты!L34*Расчеты!$M$19 -> 0.067346742 | F17: =SQRT(E17) -> 0.25951251 | G17: =MIN(F2:F102) -> 0.10425276
A18: 0.84 | B18: =1-A18 -> 0.16 | C18: =A18*$B$107+B18*$C$107 -> 0.215192 | D18: =A18*$B$108+B18*$C$108 -> 1.0116 | E18: =Расчеты!L35*Расчеты!$M$19 -> 0.065677694 | F18: =SQRT(E18) -> 0.2562766 | G18: =MAX(F2:F102) -> 0.30884693
A19: 0.83 | B19: =1-A19 -> 0.17 | C19: =A19*$B$107+B19*$C$107 -> 0.214154 | D19: =A19*$B$108+B19*$C$108 -> 0.9967 | E19: =Расчеты!L36*Расчеты!$M$19 -> 0.064033679 | F19: =SQRT(E19) -> 0.25304877
A20: 0.82 | B20: =1-A20 -> 0.18 | C20: =A20*$B$107+B20*$C$107 -> 0.213116 | D20: =A20*$B$108+B20*$C$108 -> 0.9818 | E20: =Расчеты!L37*Расчеты!$M$19 -> 0.062414698 | F20: =SQRT(E20) -> 0.24982934
A21: 0.81 | B21: =1-A21 -> 0.19 | C21: =A21*$B$107+B21*$C$107 -> 0.212078 | D21: =A21*$B$108+B21*$C$108 -> 0.9669 | E21: =Расчеты!L38*Расчеты!$M$19 -> 0.060820749 | F21: =SQRT(E21) -> 0.24661863
A22: 0.8 | B22: =1-A22 -> 0.2 | C22: =A22*$B$107+B22*$C$107 -> 0.21104 | D22: =A22*$B$108+B22*$C$108 -> 0.952 | E22: =Расчеты!L39*Расчеты!$M$19 -> 0.059251833 | F22: =SQRT(E22) -> 0.24341699
A23: 0.79 | B23: =1-A23 -> 0.21 | C23: =A23*$B$107+B23*$C$107 -> 0.210002 | D23: =A23*$B$108+B23*$C$108 -> 0.9371 | E23: =Расчеты!L40*Расчеты!$M$19 -> 0.057707951 | F23: =SQRT(E23) -> 0.24022479
A24: 0.78 | B24: =1-A24 -> 0.22 | C24: =A24*$B$107+B24*$C$107 -> 0.208964 | D24: =A24*$B$108+B24*$C$108 -> 0.9222 | E24: =Расчеты!L41*Расчеты!$M$19 -> 0.056189102 | F24: =SQRT(E24) -> 0.2370424
A25: 0.77 | B25: =1-A25 -> 0.23 | C25: =A25*$B$107+B25*$C$107 -> 0.207926 | D25: =A25*$B$108+B25*$C$108 -> 0.9073 | E25: =Расчеты!L42*Расчеты!$M$19 -> 0.054695285 | F25: =SQRT(E25) -> 0.23387023
A26: 0.76 | B26: =1-A26 -> 0.24 | C26: =A26*$B$107+B26*$C$107 -> 0.206888 | D26: =A26*$B$108+B26*$C$108 -> 0.8924 | E26: =Расчеты!L43*Расчеты!$M$19 -> 0.053226502 | F26: =SQRT(E26) -> 0.23070869
A27: 0.75 | B27: =1-A27 -> 0.25 | C27: =A27*$B$107+B27*$C$107 -> 0.20585 | D27: =A27*$B$108+B27*$C$108 -> 0.8775 | E27: =Расчеты!L44*Расчеты!$M$19 -> 0.051782752 | F27: =SQRT(E27) -> 0.22755824
A28: 0.74 | B28: =1-A28 -> 0.26 | C28: =A28*$B$107+B28*$C$107 -> 0.204812 | D28: =A28*$B$108+B28*$C$108 -> 0.8626 | E28: =Расчеты!L45*Расчеты!$M$19 -> 0.050364035 | F28: =SQRT(E28) -> 0.22441933
A29: 0.73 | B29: =1-A29 -> 0.27 | C29: =A29*$B$107+B29*$C$107 -> 0.203774 | D29: =A29*$B$108+B29*$C$108 -> 0.8477 | E29: =Расчеты!L46*Расчеты!$M$19 -> 0.04897035 | F29: =SQRT(E29) -> 0.22129245
A30: 0.72 | B30: =1-A30 -> 0.28 | C30: =A30*$B$107+B30*$C$107 -> 0.202736 | D30: =A30*$B$108+B30*$C$108 -> 0.8328 | E30: =Расчеты!L47*Расчеты!$M$19 -> 0.047601699 | F30: =SQRT(E30) -> 0.21817814
... A38: 0.64 | B38: =1-A38 -> 0.36 | C38: =A38*$B$107+B38*$C$107 -> 0.194432 | D38: =A38*$B$108+B38*$C$108 -> 0.7136 | E38: =Расчеты!L55*Расчеты!$M$19 -> 0.037553681 | F38: =SQRT(E38) -> 0.19378772
A39: 0.63 | B39: =1-A39 -> 0.37 | C39: =A39*$B$107+B39*$C$107 -> 0.193394 | D39: =A39*$B$108+B39*$C$108 -> 0.6987 | E39: =Расчеты!L56*Расчеты!$M$19 -> 0.036410328 | F39: =SQRT(E39) -> 0.1908149 | I39: Предположим, что мы вложили в портфель 1 000 000 руб.
A40: 0.62 | B40: =1-A40 -> 0.38 | C40: =A40*$B$107+B40*$C$107 -> 0.192356 | D40: =A40*$B$108+B40*$C$108 -> 0.6838 | E40: =Расчеты!L57*Расчеты!$M$19 -> 0.035292007 | F40: =SQRT(E40) -> 0.18786167 | I40: Проведем бэктестинг
A41: 0.61 | B41: =1-A41 -> 0.39 | C41: =A41*$B$107+B41*$C$107 -> 0.191318 | D41: =A41*$B$108+B41*$C$108 -> 0.6689 | E41: =Расчеты!L58*Расчеты!$M$19 -> 0.03419872 | F41: =SQRT(E41) -> 0.18492896
A42: 0.6 | B42: =1-A42 -> 0.4 | C42: =A42*$B$107+B42*$C$107 -> 0.19028 | D42: =A42*$B$108+B42*$C$108 -> 0.654 | E42: =Расчеты!L59*Расчеты!$M$19 -> 0.033130466 | F42: =SQRT(E42) -> 0.18201776
A43: 0.59 | B43: =1-A43 -> 0.41 | C43: =A43*$B$107+B43*$C$107 -> 0.189242 | D43: =A43*$B$108+B43*$C$108 -> 0.6391 | E43: =Расчеты!L60*Расчеты!$M$19 -> 0.032087244 | F43: =SQRT(E43) -> 0.17912913
A44: 0.58 | B44: =1-A44 -> 0.42 | C44: =A44*$B$107+B44*$C$107 -> 0.188204 | D44: =A44*$B$108+B44*$C$108 -> 0.6242 | E44: =Расчеты!L61*Расчеты!$M$19 -> 0.031069056 | F44: =SQRT(E44) -> 0.17626417
A45: 0.57 | B45: =1-A45 -> 0.43 | C45: =A45*$B$107+B45*$C$107 -> 0.187166 | D45: =A45*$B$108+B45*$C$108 -> 0.6093 | E45: =Расчеты!L62*Расчеты!$M$19 -> 0.030075901 | F45: =SQRT(E45) -> 0.17342405
A46: 0.56 | B46: =1-A46 -> 0.44 | C46: =A46*$B$107+B46*$C$107 -> 0.186128 | D46: =A46*$B$108+B46*$C$108 -> 0.5944 | E46: =Расчеты!L63*Расчеты!$M$19 -> 0.029107779 | F46: =SQRT(E46) -> 0.17061002
A47: 0.55 | B47: =1-A47 -> 0.45 | C47: =A47*$B$107+B47*$C$107 -> 0.18509 | D47: =A47*$B$108+B47*$C$108 -> 0.5795 | E47: =Расчеты!L64*Расчеты!$M$19 -> 0.02816469 | F47: =SQRT(E47) -> 0.16782339
A48: 0.54 | B48: =1-A48 -> 0.46 | C48: =A48*$B$107+B48*$C$107 -> 0.184052 | D48: =A48*$B$108+B48*$C$108 -> 0.5646 | E48: =Расчеты!L65*Расчеты!$M$19 -> 0.027246634 | F48: =SQRT(E48) -> 0.16506554
A49: 0.53 | B49: =1-A49 -> 0.47 | C49: =A49*$B$107+B49*$C$107 -> 0.183014 | D49: =A49*$B$108+B49*$C$108 -> 0.5497 | E49: =Расчеты!L66*Расчеты!$M$19 -> 0.026353611 | F49: =SQRT(E49) -> 0.16233795
A50: 0.52 | B50: =1-A50 -> 0.48 | C50: =A50*$B$107+B50*$C$107 -> 0.181976 | D50: =A50*$B$108+B50*$C$108 -> 0.5348 | E50: =Расчеты!L67*Расчеты!$M$19 -> 0.025485621 | F50: =SQRT(E50) -> 0.15964217
A51: 0.51 | B51: =1-A51 -> 0.49 | C51: =A51*$B$107+B51*$C$107 -> 0.180938 | D51: =A51*$B$108+B51*$C$108 -> 0.5199 | E51: =Расчеты!L68*Расчеты!$M$19 -> 0.024642665 | F51: =SQRT(E51) -> 0.15697982
A52: 0.5 | B52: =1-A52 -> 0.5 | C52: =A52*$B$107+B52*$C$107 -> 0.1799 | D52: =A52*$B$108+B52*$C$108 -> 0.505 | E52: =Расчеты!L69*Расчеты!$M$19 -> 0.023824741 | F52: =SQRT(E52) -> 0.15435265
... A102: 0 | B102: =1-A102 -> 1 | C102: =A102*$B$107+B102*$C$107 -> 0.128 | D102: =A102*$B$108+B102*$C$108 -> -0.24 | E102: =Расчеты!L119*Расчеты!$M$19 -> 0.014845709 | F102: =SQRT(E102) -> 0.12184297
B106: SNGS | C106: FXGD ETF
A107: r | B107: 0.2318 | C107: 0.128
A108: b | B108: 1.25 | C108: -0.24
A113: Ковариация доходностей активов | B113: SNGS | C113: FXGD ETF
A114: SNGS | B114: =VARP(Расчеты!$B$6:$B$255) -> 9.5386426
A115: FXGD ETF | B115: -0.74665858 | C115: =VARP(Расчеты!$C$6:$C$255) -> 1.4845709

Sheet Бэктестинг
A1: Апостериорная характеристическая линия для портфеля
B3: Вложено | C3: 1000000
B5: SNGS | C5: FXGD
A6: Доля | B6: 0.8205 | C6: 0.1795 | D6: =SUM(B6:C6) -> 1
A7: Стоимость | B7: =C3*B6 -> 820500 | C7: =C3*C6 -> 179500 | D7: =SUM(B7:C7) -> 1000000
A8: Количество изначально | B8: =B7/C13 -> 32553.065 | C8: =C7/D13 -> 298.47024
A11: 251 дата | D11: 250 доходностей | H11: 0.01
A12: Дата | B12: Безрисковая доходность MosPrime Rate, % | C12: Цена акции SNGS | D12: Цена FXGD ETF | E12: Стоимость портфеля | F12: Доходность портфеля,% | G12: Избыточная дох-ть портфеля, % (Y) | H12: Значение бенчмарка IMOEX | I12: Доходность бенчмарка IMOEX,% | J12: Избыточная дох-ть бенчмарка IMOEX,% (X) | K12: Y^2 | L12: X^2 | M12: Y*X | P12: Rt | R12: Расчет VAR и ES (все приросты) | X12: Rt | Z12: Расчет VAR и ES (отрицательные приросты) | AI12: Rt | AK12: Расчет VAR и ES (все приросты без учета знака)
A13: 43621 | B13: =Расчеты!G17/360 -> 0.021888889 | C13: =SNGS!C4 -> 25.205 | D13: ='FXGD ETF'!C4 -> 601.4 | E13: 1000000 | H13: 2701.84 | P13: 0.01 | AI13: 0.01
A14: 43622 | B14: =Расчеты!G18/360 -> 0.021972222 | C14: =SNGS!C5 -> 25.26 | D14: ='FXGD ETF'!C5 -> 604 | E14: =$B$8*C14+$C$8*D14 -> 1002566.4 | F14: =(E14/E13-1)*100 -> 0.25664412 | G14: =F14-B14 -> 0.2346719 | H14: 2728.25 | I14: =(H14/H13-1)*100 -> 0.97748201 | J14: =I14-B14 -> 0.95550979 | K14: =G14^2 -> 0.055070899 | L14: =J14^2 -> 0.91299896 | M14: =G14*J14 -> 0.22423129 | O14: -10.419539 | P14: =O14*$P$13 -> -0.10419539 | R14: Количество наблюдений | S14: 250 | X14: -0.10419539 | Z14: Количество наблюдений | AA14: =COUNT(X14:X135) -> 122 | AF14: -10.419539 | AG14: =IF(AF14<0,AF14,AF14*(-1)) -> -10.419539 | AH14: -12.867974 | AI14: =AH14*$AI$13 -> -0.12867974 | AK14: Количество наблюдений | AL14: 250
A15: 43623 | B15: =Расчеты!G19/360 -> 0.022027778 | C15: =SNGS!C6 -> 25.2 | D15: ='FXGD ETF'!C6 -> 604.2 | E15: =$B$8*C15+$C$8*D15 -> 1000673 | F15: =(E15/E14-1)*100 -> -0.18886428 | G15: =F15-B15 -> -0.21089205 | H15: 2729.61 | I15: =(H15/H14-1)*100 -> 0.049848804 | J15: =I15-B15 -> 0.027821026 | K15: =G15^2 -> 0.044475458 | L15: =J15^2 -> 0.00077400951 | M15: =G15*J15 -> -0.0058672334 | O15: -8.2338432 | P15: =O15*$P$13 -> -0.082338432 | R15: Среднее | S15: =AVERAGE(P14:P263) -> 0.002061838 | X15: -0.082338432 | Z15: Среднее | AA15: =AVERAGE(X14:X135) -> -0.014903316 | AF15: -8.2338432 | AG15: =IF(AF15<0,AF15,AF15*(-1)) -> -8.2338432 | AH15: -10.419539 | AI15: =AH15*$AI$13 -> -0.10419539 | AK15: Среднее | AL15: =AVERAGE(AI14:AI263) -> -0.016607516
A16: 43626 | B16: =Расчеты!G20/360 -> 0.022055556 | C16: =SNGS!C7 -> 25.08 | D16: ='FXGD ETF'!C7 -> 595.2 | E16: =$B$8*C16+$C$8*D16 -> 994080.35 | F16: =(E16/E15-1)*100 -> -0.65881664 | G16: =F16-B16 -> -0.68087219 | H16: 2742.59 | I16: =(H16/H15-1)*100 -> 0.47552581 | J16: =I16-B16 -> 0.45347025 | K16: =G16^2 -> 0.46358695 | L16: =J16^2 -> 0.20563527 | M16: =G16*J16 -> -0.30875529 | O16: -5.4072325 | P16: =O16*$P$13 -> -0.054072325 | R16: Станд.отклонение | S16: =_xlfn.STDEV.S(P14:P263) -> 0.025616865 | T16: =S16*E263 -> 39555.714 | U16: руб. | X16: -0.054072325 | Z16: Станд.отклонение | AA16: =_xlfn.STDEV.S(X14:X134) -> 0.016155344 | AB16: =AA16*E263 -> 24945.917 | AC16: руб. | AF16: -5.4072325 | AG16: =IF(AF16<0,AF16,AF16*(-1)) -> -5.4072325 | AH16: -9.9348975 | AI16: =AH16*$AI$13 -> -0.099348975 | AK16: Станд.отклонение | AL16: =_xlfn.STDEV.S(AI14:AI263) -> 0.019585064 | AM16: =AL16*E263 -> 30241.843 | AN16: руб.
A17: 43627 | B17: =Расчеты!G21/360 -> 0.021833333 | C17: =SNGS!C8 -> 25.39 | D17: ='FXGD ETF'!C8 -> 592.2 | E17: =$B$8*C17+$C$8*D17 -> 1003276.4 | F17: =(E17/E16-1)*100 -> 0.92508009 | G17: =F17-B17 -> 0.90324676 | H17: 2751.75 | I17: =(H17/H16-1)*100 -> 0.33399086 | J17: =I17-B17 -> 0.31215753 | K17: =G17^2 -> 0.8158547 | L17: =J17^2 -> 0.097442323 | M17: =G17*J17 -> 0.28195528 | O17: -5.406259 | P17: =O17*$P$13 -> -0.05406259 | X17: -0.05406259 | AF17: -5.406259 | AG17: =IF(AF17<0,AF17,AF17*(-1)) -> -5.406259 | AH17: -8.2338432 | AI17: =AH17*$AI$13 -> -0.082338432
A18: 43629 | B18: =Расчеты!G22/360 -> 0.021722222 | C18: =SNGS!C9 -> 25.08 | D18: ='FXGD ETF'!C9 -> 599 | E18: =$B$8*C18+$C$8*D18 -> 995214.54 | F18: =(E18/E17-1)*100 -> -0.8035525 | G18: =F18-B18 -> -0.82527472 | H18: 2758.36 | I18: =(H18/H17-1)*100 -> 0.24021077 | J18: =I18-B18 -> 0.21848855 | K18: =G18^2 -> 0.68107836 | L18: =J18^2 -> 0.047737248 | M18: =G18*J18 -> -0.18031308 | O18: -4.7072763 | P18: =O18*$P$13 -> -0.047072763 | R18: Квантиль распределения | S18: 0.05 | X18: -0.047072763 | Z18: Квантиль распределения | AA18: 0.05 | AF18: -4.7072763 | AG18: =IF(AF18<0,AF18,AF18*(-1)) -> -4.7072763 | AH18: -8.206588 | AI18: =AH18*$AI$13 -> -0.08206588 | AK18: Квантиль распределения | AL18: 0.05
A19: 43630 | B19: =Расчеты!G23/360 -> 0.021694444 | C19: =SNGS!C10 -> 25.175 | D19: ='FXGD ETF'!C10 -> 603 | E19: =$B$8*C19+$C$8*D19 -> 999500.96 | F19: =(E19/E18-1)*100 -> 0.43070332 | G19: =F19-B19 -> 0.40900888 | H19: 2739.28 | I19: =(H19/H18-1)*100 -> -0.69171537 | J19: =I19-B19 -> -0.71340981 | K19: =G19^2 -> 0.16728826 | L19: =J19^2 -> 0.50895356 | M19: =G19*J19 -> -0.29179095 | O19: -4.5025307 | P19: =O19*$P$13 -> -0.045025307 | R19: VAR (1, 95%) | S19: =_xlfn.NORM.INV(S18,S15,S16) -> -0.040074155 | T19: =S19*E263 -> -61879.618 | U19: руб. | X19: -0.045025307 | Z19: VAR (1, 95%) | AA19: =_xlfn.NORM.INV(AA18,AA15,AA16) -> -0.041476493 | AB19: =AA19*E263 -> -64045.008 | AC19: руб. | AF19: -4.5025307 | AG19: =IF(AF19<0,AF19,AF19*(-1)) -> -4.5025307 | AH19: -7.3959498 | AI19: =AH19*$AI$13 -> -0.073959498 | AK19: VAR (1, 95%) | AL19: =_xlfn.NORM.INV(AL18,AL15,AL16) -> -0.04882208 | AM19: =AL19*E263 -> -75387.533 | AN19: руб.
A20: 43633 | B20: =Расчеты!G24/360 -> 0.021388889 | C20: =SNGS!C11 -> 25.15 | D20: ='FXGD ETF'!C11 -> 595.8 | E20: =$B$8*C20+$C$8*D20 -> 996538.15 | F20: =(E20/E19-1)*100 -> -0.29642916 | G20: =F20-B20 -> -0.31781805 | H20: 2734.31 | I20: =(H20/H19-1)*100 -> -0.18143454 | J20: =I20-B20 -> -0.20282343 | K20: =G20^2 -> 0.10100831 | L20: =J20^2 -> 0.041137342 | M20: =G20*J20 -> 0.064460946 | O20: -4.4211951 | P20: =O20*$P$13 -> -0.044211951 | R20: C вероятность 95% убыток не превысит 61879,62 руб. | X20: -0.044211951 | Z20: C вероятность 95% убыток не превысит 64045,01 руб. | AF20: -4.4211951 | AG20: =IF(AF20<0,AF20,AF20*(-1)) -> -4.4211951 | AH20: -6.9332561 | AI20: =AH20*$AI$13 -> -0.069332561 | AK20: C вероятность 95% убыток или прибыль не превысит 75387,53 руб.
A21: 43634 | B21: =Расчеты!G25/360 -> 0.021388889 | C21: =SNGS!C12 -> 25.28 | D21: ='FXGD ETF'!C12 -> 598.2 | E21: =$B$8*C21+$C$8*D21 -> 1001486.4 | F21: =(E21/E20-1)*100 -> 0.49654165 | G21: =F21-B21 -> 0.47515276 | H21: 2761.69 | I21: =(H21/H20-1)*100 -> 1.0013495 | J21: =I21-B21 -> 0.97996063 | K21: =G21^2 -> 0.22577015 | L21: =J21^2 -> 0.96032283 | M21: =G21*J21 -> 0.465631 | O21: -4.3703536 | P21: =O21*$P$13 -> -0.043703536 | R21: Ист.наблюдение (мин.) № | S21: =_xlfn.FLOOR.MATH(S14*S18) -> 12 | X21: -0.043703536 | Z21: Ист.наблюдение (мин.) № | AA21: =_xlfn.FLOOR.MATH(AA14*AA18) -> 6 | AF21: -4.3703536 | AG21: =IF(AF21<0,AF21,AF21*(-1)) -> -4.3703536 | AH21: -6.8865923 | AI21: =AH21*$AI$13 -> -0.068865923 | AK21: Ист.наблюдение (мин.) № | AL21: =_xlfn.FLOOR.MATH(AL14*AL18) -> 12
A22: 43635 | B22: =Расчеты!G26/360 -> 0.021277778 | C22: =SNGS!C13 -> 25.41 | D22: ='FXGD ETF'!C13 -> 595.2 | E22: =$B$8*C22+$C$8*D22 -> 1004822.9 | F22: =(E22/E21-1)*100 -> 0.33315358 | G22: =F22-B22 -> 0.3118758 | H22: 2759.12 | I22: =(H22/H21-1)*100 -> -0.09305896 | J22: =I22-B22 -> -0.11433674 | K22: =G22^2 -> 0.097266517 | L22: =J22^2 -> 0.01307289 | M22: =G22*J22 -> -0.035658862 | O22: -4.0693003 | P22: =O22*$P$13 -> -0.040693003 | R22: Ист.наблюдение (макс.) № | S22: =_xlfn.CEILING.MATH(S14*S18) -> 13 | X22: -0.040693003 | Z22: Ист.наблюдение (макс.) № | AA22: =_xlfn.CEILING.MATH(AA14*AA18) -> 7 | AF22: -4.0693003 | AG22: =IF(AF22<0,AF22,AF22*(-1)) -> -4.0693003 | AH22: -6.5969688 | AI22: =AH22*$AI$13 -> -0.065969688 | AK22: Ист.наблюдение (макс.) № | AL22: =_xlfn.CEILING.MATH(AL14*AL18) -> 13
A23: 43636 | B23: =Расчеты!G27/360 -> 0.021305556 | C23: =SNGS!C14 -> 25.94 | D23: ='FXGD ETF'!C14 -> 605 | E23: =$B$8*C23+$C$8*D23 -> 1025001 | F23: =(E23/E22-1)*100 -> 2.0081283 | G23: =F23-B23 -> 1.9868228 | H23: 2780.2 | I23: =(H23/H22-1)*100 -> 0.76401171 | J23: =I23-B23 -> 0.74270616 | K23: =G23^2 -> 3.9474648 | L23: =J23^2 -> 0.55161244 | M23: =G23*J23 -> 1.4756255 | O23: -4.0381187 | P23: =O23*$P$13 -> -0.040381187 | R23: Ист.наблюдение (точное) № | S23: =S14*S18 -> 12.5 | X23: -0.040381187 | Z23: Ист.наблюдение (точное) № | AA23: =AA14*AA18 -> 6.1 | AF23: -4.0381187 | AG23: =IF(AF23<0,AF23,AF23*(-1)) -> -4.0381187 | AH23: -6.5597786 | AI23: =AH23*$AI$13 -> -0.065597786 | AK23: Ист.наблюдение (точное) № | AL23: =AL14*AL18 -> 12.5
A24: 43637 | B24: =Расчеты!G28/360 -> 0.021305556 | C24: =SNGS!C15 -> 25.825 | D24: ='FXGD ETF'!C15 -> 612.8 | E24: =$B$8*C24+$C$8*D24 -> 1023585.5 | F24: =(E24/E23-1)*100 -> -0.1381008 | G24: =F24-B24 -> -0.15940636 | H24: 2761.23 | I24: =(H24/H23-1)*100 -> -0.68232501 | J24: =I24-B24 -> -0.70363057 | K24: =G24^2 -> 0.025410388 | L24: =J24^2 -> 0.49509598 | M24: =G24*J24 -> 0.11216319 | O24: -3.8043932 | P24: =O24*$P$13 -> -0.038043932 | R24: Ист.наблюдение (мин.) | S24: =SMALL(P14:P263,S21) -> -0.036373329 | T24: =E263*S24 -> -56165.07 | U24: руб. | X24: -0.038043932 | Z24: Ист.наблюдение (мин.) | AA24: =SMALL(X14:X134,AA21) -> -0.045025307 | AB24: =AA24*E263 -> -69524.83 | AC24: руб. | AF24: -3.8043932 | AG24: =IF(AF24<0,AF24,AF24*(-1)) -> -3.8043932 | AH24: -6.524963 | AI24: =AH24*$AI$13 -> -0.06524963 | AK24: Ист.наблюдение (мин.) | AL24: =SMALL(AI14:AI263,AL21) -> -0.065099605 | AM24: =AL24*E263 -> -100522.11 | AN24: руб.
A25: 43640 | B25: =Расчеты!G29/360 -> 0.021277778 | C25: =SNGS!C16 -> 26 | D25: ='FXGD ETF'!C16 -> 616 | E25: =$B$8*C25+$C$8*D25 -> 1030237.4 | F25: =(E25/E24-1)*100 -> 0.64986182 | G25: =F25-B25 -> 0.62858404 | H25: 2762.65 | I25: =(H25/H24-1)*100 -> 0.051426357 | J25: =I25-B25 -> 0.030148579 | K25: =G25^2 -> 0.3951179 | L25: =J25^2 -> 0.00090893683 | M25: =G25*J25 -> 0.018950916 | O25: -3.6373329 | P25: =O25*$P$13 -> -0.036373329 | R25: Ист.наблюдение (макс.) | S25: =SMALL(P14:P263,S22) -> -0.035294638 | T25: =E263*S25 -> -54499.433 | U25: руб. | X25: -0.036373329 | Z25: Ист.наблюдение (макс.) | AA25: =SMALL(X14:X134,AA22) -> -0.044211951 | AB25: =E263*AA25 -> -68268.905 | AC25: руб. | AF25: -3.6373329 | AG25: =IF(AF25<0,AF25,AF25*(-1)) -> -3.6373329 | AH25: -6.5099605 | AI25: =AH25*$AI$13 -> -0.065099605 | AK25: Ист.наблюдение (макс.) | AL25: =SMALL(AI14:AI263,AL22) -> -0.061076585 | AM25: =E263*AL25 -> -94310.055 | AN25: руб.
A26: 43641 | B26: =Расчеты!G30/360 -> 0.021472222 | C26: =SNGS!C17 -> 25.92 | D26: ='FXGD ETF'!C17 -> 621.6 | E26: =$B$8*C26+$C$8*D26 -> 1029304.5 | F26: =(E26/E25-1)*100 -> -0.090543394 | G26: =F26-B26 -> -0.11201562 | H26: 2753.96 | I26: =(H26/H25-1)*100 -> -0.31455306 | J26: =I26-B26 -> -0.33602528 | K26: =G26^2 -> 0.012547498 | L26: =J26^2 -> 0.11291299 | M26: =G26*J26 -> 0.037640079 | O26: -3.5294638 | P26: =O26*$P$13 -> -0.035294638 | R26: Исторический VAR (1, 95%) | S26: =(S25-S24)*(S23-S21)/(S22-S21)+S24 -> -0.035833984 | T26: =E263*S26 -> -55332.251 | U26: руб. | X26: -0.035294638 | Z26: Исторический VAR (1, 95%) | AA26: =(AA25-AA24)*(AA23-AA21)/(AA22-AA21)+AA24 -> -0.044943971 | AB26: =E263*AA26 -> -69399.237 | AC26: руб. | AF26: -3.5294638 | AG26: =IF(AF26<0,AF26,AF26*(-1)) -> -3.5294638 | AH26: -6.1076585 | AI26: =AH26*$AI$13 -> -0.061076585 | AK26: Исторический VAR (1, 95%) | AL26: =(AL25-AL24)*(AL23-AL21)/(AL22-AL21)+AL24 -> -0.063088095 | AM26: =E263*AL26 -> -97416.084 | AN26: руб.
A27: 43642 | B27: =Расчеты!G31/360 -> 0.021472222 | C27: =SNGS!C18 -> 26.285 | D27: ='FXGD ETF'!C18 -> 616 | E27: =$B$8*C27+$C$8*D27 -> 1039515 | F27: =(E27/E26-1)*100 -> 0.99197419 | G27: =F27-B27 -> 0.97050197 | H27: 2775.14 | I27: =(H27/H26-1)*100 -> 0.76907435 | J27: =I27-B27 -> 0.74760213 | K27: =G27^2 -> 0.94187407 | L27: =J27^2 -> 0.55890894 | M27: =G27*J27 -> 0.72554934 | O27: -3.3416781 | P27: =O27*$P$13 -> -0.033416781 | R27: C вероятность 95% убыток не превысит 55332,25 руб. | X27: -0.033416781 | Z27: C вероятность 95% убыток не превысит 69399,24 руб. | AF27: -3.3416781 | AG27: =IF(AF27<0,AF27,AF27*(-1)) -> -3.3416781 | AH27: -6.0424316 | AI27: =AH27*$AI$13 -> -0.060424316 | AK27: C вероятность 95% убыток или прибыль не превысит 97416,08 руб.
A28: 43643 | B28: =Расчеты!G32/360 -> 0.021416667 | C28: =SNGS!C19 -> 26.32 | D28: ='FXGD ETF'!C19 -> 613.2 | E28: =$B$8*C28+$C$8*D28 -> 1039818.6 | F28: =(E28/E27-1)*100 -> 0.029209835 | G28: =F28-B28 -> 0.0077931683 | H28: 2779.66 | I28: =(H28/H27-1)*100 -> 0.16287467 | J28: =I28-B28 -> 0.141458 | K28: =G28^2 -> 6.0733473e-05 | L28: =J28^2 -> 0.020010366 | M28: =G28*J28 -> 0.001102406 | O28: -3.3121922 | P28: =O28*$P$13 -> -0.033121922 | R28: Expected Shortfall | S28: =AVERAGE(P14:P25) -> -0.052514479 | T28: =S28*E263 -> -81089.069 | U28: руб. | X28: -0.033121922 | Z28: Expected Shortfall | AA28: =AVERAGE(X14:X19) -> -0.064461135 | AB28: =AA28*E263 -> -99536.233 | AC28: руб. | AF28: -3.3121922 | AG28: =IF(AF28<0,AF28,AF28*(-1)) -> -3.3121922 | AH28: -6.0387019 | AI28: =AH28*$AI$13 -> -0.060387019 | AK28: Expected Shortfall | AL28: =AVERAGE(AI14:AI25) -> -0.080891926 | AM28: =AL28*E263 -> -124907.47 | AN28: руб.
A29: 43644 | B29: =Расчеты!G33/360 -> 0.021444444 | C29: =SNGS!C20 -> 26.34 | D29: ='FXGD ETF'!C20 -> 617.4 | E29: =$B$8*C29+$C$8*D29 -> 1041723.3 | F29: =(E29/E28-1)*100 -> 0.18317005 | G29: =F29-B29 -> 0.16172561 | H29: 2765.85 | I29: =(H29/H28-1)*100 -> -0.49682335 | J29: =I29-B29 -> -0.5182678 | K29: =G29^2 -> 0.026155172 | L29: =J29^2 -> 0.26860151 | M29: =G29*J29 -> -0.083817174 | O29: -3.2764279 | P29: =O29*$P$13 -> -0.032764279 | R29: Потенциальный размер убытка, если он превысит VaR, составит 81089,07 руб. | X29: -0.032764279 | Z29: Потенциальный размер убытка, если он превысит VaR, составит 99536,23 руб. | AF29: -3.2764279 | AG29: =IF(AF29<0,AF29,AF29*(-1)) -> -3.2764279 | AH29: -5.4072325 | AI29: =AH29*$AI$13 -> -0.054072325 | AK29: Потенциальный размер убытка или прибыли, если он превысит VaR, составит 124907,47 руб.
A30: 43647 | B30: =Расчеты!G34/360 -> 0.021333333 | C30: =SNGS!C21 -> 26.37 | D30: ='FXGD ETF'!C21 -> 606 | E30: =$B$8*C30+$C$8*D30 -> 1039297.3 | F30: =(E30/E29-1)*100 -> -0.23288035 | G30: =F30-B30 -> -0.25421368 | H30: 2801.47 | I30: =(H30/H29-1)*100 -> 1.28785 | J30: =I30-B30 -> 1.2665167 | K30: =G30^2 -> 0.064624596 | L30: =J30^2 -> 1.6040645 | M30: =G30*J30 -> -0.32196587 | O30: -3.1652928 | P30: =O30*$P$13 -> -0.031652928 | X30: -0.031652928 | AF30: -3.1652928 | AG30: =IF(AF30<0,AF30,AF30*(-1)) -> -3.1652928 | AH30: -5.406259 | AI30: =AH30*$AI$13 -> -0.05406259
A31: 43648 | B31: =Расчеты!G35/360 -> 0.021222222 | C31: =SNGS!C22 -> 26.735 | D31: ='FXGD ETF'!C22 -> 614.8 | E31: =$B$8*C31+$C$8*D31 -> 1053805.7 | F31: =(E31/E30-1)*100 -> 1.3959824 | G31: =F31-B31 -> 1.3747601 | H31: 2809.81 | I31: =(H31/H30-1)*100 -> 0.29770085 | J31: =I31-B31 -> 0.27647863 | K31: =G31^2 -> 1.8899654 | L31: =J31^2 -> 0.076440432 | M31: =G31*J31 -> 0.3800918 | O31: -2.9795319 | P31: =O31*$P$13 -> -0.029795319 | X31: -0.029795319 | AF31: -2.9795319 | AG31: =IF(AF31<0,AF31,AF31*(-1)) -> -2.9795319 | AH31: -5.0712252 | AI31: =AH31*$AI$13 -> -0.050712252
A32: 43649 | B32: =Расчеты!G36/360 -> 0.021111111 | C32: =SNGS!C23 -> 26.8 | D32: ='FXGD ETF'!C23 -> 621.6 | E32: =$B$8*C32+$C$8*D32 -> 1057951.2 | F32: =(E32/E31-1)*100 -> 0.39338816 | G32: =F32-B32 -> 0.37227705 | H32: 2823.95 | I32: =(H32/H31-1)*100 -> 0.50323687 | J32: =I32-B32 -> 0.48212576 | K32: =G32^2 -> 0.1385902 | L32: =J32^2 -> 0.23244525 | M32: =G32*J32 -> 0.17948436 | O32: -2.9218694 | P32: =O32*$P$13 -> -0.029218694 | X32: -0.029218694 | AF32: -2.9218694 | AG32: =IF(AF32<0,AF32,AF32*(-1)) -> -2.9218694 | AH32: -4.7853789 | AI32: =AH32*$AI$13 -> -0.047853789
A33: 43650 | B33: =Расчеты!G37/360 -> 0.021 | C33: =SNGS!C24 -> 26.85 | D33: ='FXGD ETF'!C24 -> 622.8 | E33: =$B$8*C33+$C$8*D33 -> 1059937.1 | F33: =(E33/E32-1)*100 -> 0.18770407 | G33: =F33-B33 -> 0.16670407 | H33: 2842.78 | I33: =(H33/H32-1)*100 -> 0.66679651 | J33: =I33-B33 -> 0.64579651 | K33: =G33^2 -> 0.027790247 | L33: =J33^2 -> 0.41705313 | M33: =G33*J33 -> 0.10765691 | O33: -2.8620699 | P33: =O33*$P$13 -> -0.028620699 | X33: -0.028620699 | AF33: -2.8620699 | AG33: =IF(AF33<0,AF33,AF33*(-1)) -> -2.8620699 | AH33: -4.7072763 | AI33: =AH33*$AI$13 -> -0.047072763
A34: 43651 | B34: =Расчеты!G38/360 -> 0.021 | C34: =SNGS!C25 -> 26.8 | D34: ='FXGD ETF'!C25 -> 619.4 | E34: =$B$8*C34+$C$8*D34 -> 1057294.6 | F34: =(E34/E33-1)*100 -> -0.24930273 | G34: =F34-B34 -> -0.27030273 | H34: 2835.35 | I34: =(H34/H33-1)*100 -> -0.26136388 | J34: =I34-B34 -> -0.28236388 | K34: =G34^2 -> 0.073063567 | L34: =J34^2 -> 0.079729359 | M34: =G34*J34 -> 0.076323727 | O34: -2.7418171 | P34: =O34*$P$13 -> -0.027418171 | X34: -0.027418171 | AF34: -2.7418171 | AG34: =IF(AF34<0,AF34,AF34*(-1)) -> -2.7418171 | AH34: -4.5025307 | AI34: =AH34*$AI$13 -> -0.045025307
A35: 43654 | B35: =Расчеты!G39/360 -> 0.021055556 | C35: =SNGS!C26 -> 26.92 | D35: ='FXGD ETF'!C26 -> 616 | E35: =$B$8*C35+$C$8*D35 -> 1060186.2 | F35: =(E35/E34-1)*100 -> 0.27348754 | G35: =F35-B35 -> 0.25243198 | H35: 2822.55 | I35: =(H35/H34-1)*100 -> -0.45144338 | J35: =I35-B35 -> -0.47249894 | K35: =G35^2 -> 0.063721906 | L35: =J35^2 -> 0.22325525 | M35: =G35*J35 -> -0.11927384 | O35: -2.5994652 | P35: =O35*$P$13 -> -0.025994652 | X35: -0.025994652 | AF35: -2.5994652 | AG35: =IF(AF35<0,AF35,AF35*(-1)) -> -2.5994652 | AH35: -4.4211951 | AI35: =AH35*$AI$13 -> -0.044211951
A36: 43655 | B36: =Расчеты!G40/360 -> 0.021138889 | C36: =SNGS!C27 -> 27.2 | D36: ='FXGD ETF'!C27 -> 618.2 | E36: =$B$8*C36+$C$8*D36 -> 1069957.7 | F36: =(E36/E35-1)*100 -> 0.92167705 | G36: =F36-B36 -> 0.90053817 | H36: 2822.66 | I36: =(H36/H35-1)*100 -> 0.0038971852 | J36: =I36-B36 -> -0.017241704 | K36: =G36^2 -> 0.81096899 | L36: =J36^2 -> 0.00029727635 | M36: =G36*J36 -> -0.015526812 | O36: -2.4940754 | P36: =O36*$P$13 -> -0.024940754 | X36: -0.024940754 | AF36: -2.4940754 | AG36: =IF(AF36<0,AF36,AF36*(-1)) -> -2.4940754 | AH36: -4.3703536 | AI36: =AH36*$AI$13 -> -0.043703536
A37: 43656 | B37: =Расчеты!G41/360 -> 0.021166667 | C37: =SNGS!C28 -> 27.145 | D37: ='FXGD ETF'!C28 -> 616.4 | E37: =$B$8*C37+$C$8*D37 -> 1067630 | F37: =(E37/E36-1)*100 -> -0.21754739 | G37: =F37-B37 -> -0.23871406 | H37: 2822.75 | I37: =(H37/H36-1)*100 -> 0.0031884818 | J37: =I37-B37 -> -0.017978185 | K37: =G37^2 -> 0.056984402 | L37: =J37^2 -> 0.00032321513 | M37: =G37*J37 -> 0.0042916455 | O37: -2.2642031 | P37: =O37*$P$13 -> -0.022642031 | X37: -0.022642031 | AF37: -2.2642031 | AG37: =IF(AF37<0,AF37,AF37*(-1)) -> -2.2642031 | AH37: -4.3122121 | AI37: =AH37*$AI$13 -> -0.043122121
A38: 43657 | B38: =Расчеты!G42/360 -> 0.021027778 | C38: =SNGS!C29 -> 26.705 | D38: ='FXGD ETF'!C29 -> 614.2 | E38: =$B$8*C38+$C$8*D38 -> 1052650 | F38: =(E38/E37-1)*100 -> -1.4031062 | G38: =F38-B38 -> -1.424134 | H38: 2789.66 | I38: =(H38/H37-1)*100 -> -1.1722611 | J38: =I38-B38 -> -1.1932889 | K38: =G38^2 -> 2.0281577 | L38: =J38^2 -> 1.4239383 | M38: =G38*J38 -> 1.6994033 | O38: -2.2127395 | P38: =O38*$P$13 -> -0.022127395 | X38: -0.022127395 | AF38: -2.2127395 | AG38: =IF(AF38<0,AF38,AF38*(-1)) -> -2.2127395 | AH38: -4.210623 | AI38: =AH38*$AI$13 -> -0.04210623
A39: 43658 | B39: =Расчеты!G43/360 -> 0.021 | C39: =SNGS!C30 -> 26.79 | D39: ='FXGD ETF'!C30 -> 615 | E39: =$B$8*C39+$C$8*D39 -> 1055655.8 | F39: =(E39/E38-1)*100 -> 0.28554474 | G39: =F39-B39 -> 0.26454474 | H39: 2777.58 | I39: =(H39/H38-1)*100 -> -0.43302768 | J39: =I39-B39 -> -0.45402768 | K39: =G39^2 -> 0.069983917 | L39: =J39^2 -> 0.20614113 | M39: =G39*J39 -> -0.12011063 | O39: -2.203813 | P39: =O39*$P$13 -> -0.02203813 | X39: -0.02203813 | AF39: -2.203813 | AG39: =IF(AF39<0,AF39,AF39*(-1)) -> -2.203813 | AH39: -4.0693003 | AI39: =AH39*$AI$13 -> -0.040693003
A40: 43661 | B40: =Расчеты!G44/360 -> 0.021 | C40: =SNGS!C31 -> 26.57 | D40: ='FXGD ETF'!C31 -> 614 | E40: =$B$8*C40+$C$8*D40 -> 1048195.7 | F40: =(E40/E39-1)*100 -> -0.70668342 | G40: =F40-B40 -> -0.72768342 | H40: 2756.44 | I40: =(H40/H39-1)*100 -> -0.76109419 | J40: =I40-B40 -> -0.78209419 | K40: =G40^2 -> 0.52952316 | L40: =J40^2 -> 0.61167132 | M40: =G40*J40 -> 0.56911697 | O40: -2.1868811 | P40: =O40*$P$13 -> -0.021868811 | X40: -0.021868811 | AF40: -2.1868811 | AG40: =IF(AF40<0,AF40,AF40*(-1)) -> -2.1868811 | AH40: -4.0381187 | AI40: =AH40*$AI$13 -> -0.040381187
A41: 43662 | B41: =Расчеты!G45/360 -> 0.021 | C41: =SNGS!C32 -> 26.83 | D41: ='FXGD ETF'!C32 -> 615 | E41: =$B$8*C41+$C$8*D41 -> 1056957.9 | F41: =(E41/E40-1)*100 -> 0.83593812 | G41: =F41-B41 -> 0.81493812 | H41: 2755.88 | I41: =(H41/H40-1)*100 -> -0.02031606 | J41: =I41-B41 -> -0.04131606 | K41: =G41^2 -> 0.66412414 | L41: =J41^2 -> 0.0017070168 | M41: =G41*J41 -> -0.033670032 | O41: -2.0900444 | P41: =O41*$P$13 -> -0.020900444 | X41: -0.020900444 | AF41: -2.0900444 | AG41: =IF(AF41<0,AF41,AF41*(-1)) -> -2.0900444 | AH41: -3.9891507 | AI41: =AH41*$AI$13 -> -0.039891507
... A135: 43795 | B135: =Расчеты!G139/360 -> 0.018416667 | C135: =SNGS!C126 -> 45 | D135: ='FXGD ETF'!C126 -> 645 | E135: =$B$8*C135+$C$8*D135 -> 1657401.2 | F135: =(E135/E134-1)*100 -> -2.2642031 | G135: =F135-B135 -> -2.2826197 | H135: 2930.62 | I135: =(H135/H134-1)*100 -> -0.8357809 | J135: =I135-B135 -> -0.85419756 | K135: =G135^2 -> 5.2103529 | L135: =J135^2 -> 0.72965348 | M135: =G135*J135 -> 1.9498082 | O135: -0.022788697 | P135: =O135*$P$13 -> -0.00022788697 | X135: -0.00022788697 | AF135: -0.022788697 | AG135: =IF(AF135<0,AF135,AF135*(-1)) -> -0.022788697 | AH135: -1.0525194 | AI135: =AH135*$AI$13 -> -0.010525194
A136: 43796 | B136: =Расчеты!G140/360 -> 0.018416667 | C136: =SNGS!C127 -> 44.51 | D136: ='FXGD ETF'!C127 -> 644 | E136: =$B$8*C136+$C$8*D136 -> 1641151.7 | F136: =(E136/E135-1)*100 -> -0.98041873 | G136: =F136-B136 -> -0.9988354 | H136: 2929.05 | I136: =(H136/H135-1)*100 -> -0.053572282 | J136: =I136-B136 -> -0.071988948 | K136: =G136^2 -> 0.99767215 | L136: =J136^2 -> 0.0051824087 | M136: =G136*J136 -> 0.07190511 | O136: -0.00052156183 | P136: =O136*$P$13 -> -5.2156183e-06 | AF136: -0.00052156183 | AG136: =IF(AF136<0,AF136,AF136*(-1)) -> -0.00052156183 | AH136: -1.0505797 | AI136: =AH136*$AI$13 -> -0.010505797
A137: 43797 | B137: =Расчеты!G141/360 -> 0.018416667 | C137: =SNGS!C128 -> 43.645 | D137: ='FXGD ETF'!C128 -> 644 | E137: =$B$8*C137+$C$8*D137 -> 1612993.3 | F137: =(E137/E136-1)*100 -> -1.7157707 | G137: =F137-B137 -> -1.7341874 | H137: 2927.57 | I137: =(H137/H136-1)*100 -> -0.050528328 | J137: =I137-B137 -> -0.068944995 | K137: =G137^2 -> 3.0074059 | L137: =J137^2 -> 0.0047534123 | M137: =G137*J137 -> 0.11956354 | O137: 0.0033920963 | P137: =O137*$P$13 -> 3.3920963e-05 | AF137: 0.0033920963 | AG137: =IF(AF137<0,AF137,AF137*(-1)) -> -0.0033920963 | AH137: -1.0353672 | AI137: =AH137*$AI$13 -> -0.010353672
A138: 43798 | B138: =Расчеты!G142/360 -> 0.018444444 | C138: =SNGS!C129 -> 44.1 | D138: ='FXGD ETF'!C129 -> 649 | E138: =$B$8*C138+$C$8*D138 -> 1629297.3 | F138: =(E138/E137-1)*100 -> 1.0107913 | G138: =F138-B138 -> 0.99234681 | H138: 2935.37 | I138: =(H138/H137-1)*100 -> 0.26643257 | J138: =I138-B138 -> 0.24798813 | K138: =G138^2 -> 0.98475219 | L138: =J138^2 -> 0.061498111 | M138: =G138*J138 -> 0.24609023 | O138: 0.026922709 | P138: =O138*$P$13 -> 0.00026922709 | AF138: 0.026922709 | AG138: =IF(AF138<0,AF138,AF138*(-1)) -> -0.026922709 | AH138: -1.024724 | AI138: =AH138*$AI$13 -> -0.01024724
A139: 43801 | B139: =Расчеты!G143/360 -> 0.018444444 | C139: =SNGS!C130 -> 43.27 | D139: ='FXGD ETF'!C130 -> 648 | E139: =$B$8*C139+$C$8*D139 -> 1601979.8 | F139: =(E139/E138-1)*100 -> -1.6766439 | G139: =F139-B139 -> -1.6950883 | H139: 2921.18 | I139: =(H139/H138-1)*100 -> -0.48341436 | J139: =I139-B139 -> -0.5018588 | K139: =G139^2 -> 2.8733244 | L139: =J139^2 -> 0.25186226 | M139: =G139*J139 -> 0.85069499 | O139: 0.029209835 | P139: =O139*$P$13 -> 0.00029209835 | AF139: 0.029209835 | AG139: =IF(AF139<0,AF139,AF139*(-1)) -> -0.029209835 | AH139: -1.0107913 | AI139: =AH139*$AI$13 -> -0.010107913
A140: 43802 | B140: =Расчеты!G144/360 -> 0.0185 | C140: =SNGS!C131 -> 42.54 | D140: ='FXGD ETF'!C131 -> 655.2 | E140: =$B$8*C140+$C$8*D140 -> 1580365.1 | F140: =(E140/E139-1)*100 -> -1.3492524 | G140: =F140-B140 -> -1.3677524 | H140: 2883.48 | I140: =(H140/H139-1)*100 -> -1.2905744 | J140: =I140-B140 -> -1.3090744 | K140: =G140^2 -> 1.8707467 | L140: =J140^2 -> 1.7136757 | M140: =G140*J140 -> 1.7904896 | O140: 0.041791816 | P140: =O140*$P$13 -> 0.00041791816 | AF140: 0.041791816 | AG140: =IF(AF140<0,AF140,AF140*(-1)) -> -0.041791816 | AH140: -1.0096003 | AI140: =AH140*$AI$13 -> -0.010096003
A141: 43803 | B141: =Расчеты!G145/360 -> 0.018416667 | C141: =SNGS!C132 -> 43.7 | D141: ='FXGD ETF'!C132 -> 649.6 | E141: =$B$8*C141+$C$8*D141 -> 1616455.2 | F141: =(E141/E140-1)*100 -> 2.2836573 | G141: =F141-B141 -> 2.2652406 | H141: 2900.66 | I141: =(H141/H140-1)*100 -> 0.59580784 | J141: =I141-B141 -> 0.57739118 | K141: =G141^2 -> 5.131315 | L141: =J141^2 -> 0.33338057 | M141: =G141*J141 -> 1.3079299 | O141: 0.051879438 | P141: =O141*$P$13 -> 0.00051879438 | AF141: 0.051879438 | AG141: =IF(AF141<0,AF141,AF141*(-1)) -> -0.051879438 | AH141: -1.0011099 | AI141: =AH141*$AI$13 -> -0.010011099
A142: 43804 | B142: =Расчеты!G146/360 -> 0.018416667 | C142: =SNGS!C133 -> 43.2 | D142: ='FXGD ETF'!C133 -> 651.6 | E142: =$B$8*C142+$C$8*D142 -> 1600775.6 | F142: =(E142/E141-1)*100 -> -0.96999855 | G142: =F142-B142 -> -0.98841521 | H142: 2899.29 | I142: =(H142/H141-1)*100 -> -0.04723063 | J142: =I142-B142 -> -0.065647297 | K142: =G142^2 -> 0.97696464 | L142: =J142^2 -> 0.0043095676 | M142: =G142*J142 -> 0.064886787 | O142: 0.053840888 | P142: =O142*$P$13 -> 0.00053840888 | AF142: 0.053840888 | AG142: =IF(AF142<0,AF142,AF142*(-1)) -> -0.053840888 | AH142: -0.99197419 | AI142: =AH142*$AI$13 -> -0.0099197419
A143: 43805 | B143: =Расчеты!G147/360 -> 0.018277778 | C143: =SNGS!C134 -> 43.345 | D143: ='FXGD ETF'!C134 -> 645.6 | E143: =$B$8*C143+$C$8*D143 -> 1603705 | F143: =(E143/E142-1)*100 -> 0.1829971 | G143: =F143-B143 -> 0.16471933 | H143: 2928.76 | I143: =(H143/H142-1)*100 -> 1.0164558 | J143: =I143-B143 -> 0.99817798 | K143: =G143^2 -> 0.027132456 | L143: =J143^2 -> 0.99635927 | M143: =G143*J143 -> 0.1644192 | O143: 0.1080693 | P143: =O143*$P$13 -> 0.001080693 | AF143: 0.1080693 | AG143: =IF(AF143<0,AF143,AF143*(-1)) -> -0.1080693 | AH143: -0.9893309 | AI143: =AH143*$AI$13 -> -0.009893309
A144: 43808 | B144: =Расчеты!G148/360 -> 0.018222222 | C144: =SNGS!C135 -> 43.93 | D144: ='FXGD ETF'!C135 -> 642.4 | E144: =$B$8*C144+$C$8*D144 -> 1621793.4 | F144: =(E144/E143-1)*100 -> 1.1279156 | G144: =F144-B144 -> 1.1096933 | H144: 2945.03 | I144: =(H144/H143-1)*100 -> 0.55552521 | J144: =I144-B144 -> 0.53730298 | K144: =G144^2 -> 1.2314193 | L144: =J144^2 -> 0.2886945 | M144: =G144*J144 -> 0.59624155 | O144: 0.11896697 | P144: =O144*$P$13 -> 0.0011896697 | AF144: 0.11896697 | AG144: =IF(AF144<0,AF144,AF144*(-1)) -> -0.11896697 | AH144: -0.98041873 | AI144: =AH144*$AI$13 -> -0.0098041873
A145: 43809 | B145: =Расчеты!G149/360 -> 0.018222222 | C145: =SNGS!C136 -> 43.39 | D145: ='FXGD ETF'!C136 -> 642.2 | E145: =$B$8*C145+$C$8*D145 -> 1604155.1 | F145: =(E145/E144-1)*100 -> -1.087583 | G145: =F145-B145 -> -1.1058052 | H145: 2932.4 | I145: =(H145/H144-1)*100 -> -0.42885811 | J145: =I145-B145 -> -0.44708033 | K145: =G145^2 -> 1.2228051 | L145: =J145^2 -> 0.19988082 | M145: =G145*J145 -> 0.49438375 | O145: 0.154786 | P145: =O145*$P$13 -> 0.00154786 | AF145: 0.154786 | AG145: =IF(AF145<0,AF145,AF145*(-1)) -> -0.154786 | AH145: -0.97616402 | AI145: =AH145*$AI$13 -> -0.0097616402
A146: 43810 | B146: =Расчеты!G150/360 -> 0.018111111 | C146: =SNGS!C137 -> 45.035 | D146: ='FXGD ETF'!C137 -> 645.6 | E146: =$B$8*C146+$C$8*D146 -> 1658719.7 | F146: =(E146/E145-1)*100 -> 3.4014536 | G146: =F146-B146 -> 3.3833425 | H146: 2954.4 | I146: =(H146/H145-1)*100 -> 0.75023871 | J146: =I146-B146 -> 0.7321276 | K146: =G146^2 -> 11.447006 | L146: =J146^2 -> 0.53601082 | M146: =G146*J146 -> 2.4770384 | O146: 0.17608217 | P146: =O146*$P$13 -> 0.0017608217 | AF146: 0.17608217 | AG146: =IF(AF146<0,AF146,AF146*(-1)) -> -0.17608217 | AH146: -0.96999855 | AI146: =AH146*$AI$13 -> -0.0096999855
A147: 43811 | B147: =Расчеты!G151/360 -> 0.017916667 | C147: =SNGS!C138 -> 48.2 | D147: ='FXGD ETF'!C138 -> 636 | E147: =$B$8*C147+$C$8*D147 -> 1758884.8 | F147: =(E147/E146-1)*100 -> 6.0387019 | G147: =F147-B147 -> 6.0207853 | H147: 2982.86 | I147: =(H147/H146-1)*100 -> 0.96330896 | J147: =I147-B147 -> 0.9453923 | K147: =G147^2 -> 36.249855 | L147: =J147^2 -> 0.89376659 | M147: =G147*J147 -> 5.692004 | O147: 0.1829971 | P147: =O147*$P$13 -> 0.001829971 | AF147: 0.1829971 | AG147: =IF(AF147<0,AF147,AF147*(-1)) -> -0.1829971 | AH147: -0.96546085 | AI147: =AH147*$AI$13 -> -0.0096546085
... A263: 43985 | B263: =Расчеты!G267/360 -> 0.015738095 | C263: =SNGS!C254 -> 39.98 | D263: ='FXGD ETF'!C254 -> 813 | E263: =$B$8*C263+$C$8*D263 -> 1544127.8 | F263: =(E263/E262-1)*100 -> -0.66666595 | G263: =F263-B263 -> -0.68240404 | H263: 2801.77 | I263: =(H263/H262-1)*100 -> 0.18809159 | J263: =I263-B263 -> 0.17235349 | K263: =G263^2 -> 0.46567528 | L263: =J263^2 -> 0.029705726 | M263: =G263*J263 -> -0.11761472 | O263: 12.867974 | P263: =O263*$P$13 -> 0.12867974 | AF263: 12.867974 | AG263: =IF(AF263<0,AF263,AF263*(-1)) -> -12.867974 | AH263: -0.00052156183 | AI263: =AH263*$AI$13 -> -5.2156183e-06
A264: Сумма | G264: =SUM(G14:G263) -> 46.907836 | J264: =SUM(J14:J263) -> 1.9905879 | K264: =SUM(K14:K263) -> 1642.6424 | L264: =SUM(L14:L263) -> 594.19371 | M264: =SUM(M14:M263) -> 586.55493
A268: Количество наблюдений | E268: 250
A269: Бета | E269: =((E268*M264)-(G264*J264))/(E268*L264-J264^2) -> 0.98654203 | F269: Актив изменяется почти так же как и рынок (бенчмарк)
A270: Альфа | E270: =G264/E268-E269*J264/E268 -> 0.17977615 | F270: Положительна, хорошо, по данному портфелю фактическая доходность выше , чем ожидаемая
A271: Стандартное отклонение случайно погрешности | E271: =((K264-E270*G264-E269*M264)/(E268-2))^0.5 -> 2.0630666 | F271: Высокая ошибка, с учетом низкой доходности портфеля
A272: Стандартная ошибка беты | E272: =E271/(L264-J264^2/E268)^0.5 -> 0.084635977
A273: Стандартная ошибка альфы | E273: =E271/(E268-(J264)^2/L264)^0.5 -> 0.13048153
A274: Коэффициент корреляции | E274: =CORREL(G14:G263,J14:J263) -> 0.59493418 | F274: Среднее значение, величина избыточной доходности портфеля зависит от избыточной доходности МосБиржи на 59%
A275: Коэффициент детерминации | E275: =E274^2 -> 0.35394668 | F275: Модель объясняет изменение прогнозируемой величины (избыточная доходность портфеля) на 35%
A276: Коэффициент непределенности | E276: =1-E275 -> 0.64605332 | F276: 65% осталось не объяснено
A279: Мат ожидание доходности акции | E279: =AVERAGE(F14:F263) -> 0.2061838
A281: Коэффициент Шарпа | E281: =(21.32%-0.02%)/25% -> 0.852
A282: Коэффициент Тейнера | E282: =(21.32%-0.02%)/0.98 -> 0.21734694
A283: Return replacement
A284: годовое отношение/убытки
E288: ВЫВОД ИТОГОВ
E290: Регрессионная статистика
E291: Множественный R | F291: 0.59493418
E292: R-квадрат | F292: 0.35394668
E293: Нормированный R-квадрат | F293: 0.35134163
E294: Стандартная ошибка | F294: 2.0630666
E295: Наблюдения | F295: 250
E297: Дисперсионный анализ
F298: df | G298: SS | H298: MS | I298: F | J298: Значимость F
E299: Регрессия | F299: 1 | G299: 578.29262 | H299: 578.29262 | I299: 135.86924 | J299: 2.5117078e-25
E300: Остаток | F300: 248 | G300: 1055.5484 | H300: 4.2562437
E301: Итого | F301: 249 | G301: 1633.8411
F303: Коэффициенты | G303: Стандартная ошибка | H303: t-статистика | I303: P-Значение | J303: Нижние 95% | K303: Верхние 95% | L303: Нижние 95,0% | M303: Верхние 95,0%
E304: Y-пересечение | F304: 0.17977615 | G304: 0.13048153 | H304: 1.37779 | I304: 0.16951009 | J304: -0.077217091 | K304: 0.43676939 | L304: -0.077217091 | M304: 0.43676939
E305: Переменная X 1 | F305: 0.98654203 | G305: 0.084635977 | H305: 11.656296 | I305: 2.5117078e-25 | J305: 0.81984507 | K305: 1.153239 | L305: 0.81984507 | M305: 1.153239

Sheet Расчеты
B4: Прирост,%
A5: Дата | B5: SNGS | C5: FXGD ETF | E5: коррел
A6: 43622 | B6: 0.21821067 | C6: 0.43232458 | E6: {=CORREL(B6:B255,C6:C255)} -> -0.19841673
A7: 43623 | B7: -0.23752969 | C7: 0.033112583
A8: 43626 | B8: -0.47619048 | C8: -1.489573
A9: 43627 | B9: 1.2360447 | C9: -0.50403226
A10: 43629 | B10: -1.2209531 | C10: 1.1482607 | J10: Ковариация доходностей активов | K10: SNGS | L10: FXGD ETF
A11: 43630 | B11: 0.37878788 | C11: 0.66777963 | J11: SNGS | K11: =VARP(Расчеты!$B$6:$B$255) -> 9.5386426
A12: 43633 | B12: -0.099304866 | C12: -1.1940299 | J12: FXGD ETF | K12: -0.74665858 | L12: =VARP(Расчеты!$C$6:$C$255) -> 1.4845709
A13: 43634 | B13: 0.51689861 | C13: 0.40281974
A14: 43635 | B14: 0.51424051 | C14: -0.50150451
A15: 43636 | B15: 2.085793 | C15: 1.6465054
A16: 43637 | B16: -0.44333076 | C16: 1.2892562 | G16: Безрисковая годовая | H16: Безрисковая дневная
A17: 43640 | B17: 0.67763795 | C17: 0.52219321 | G17: 7.88 | H17: =G17/360 -> 0.021888889 | K17: Риск
A18: 43641 | B18: -0.30769231 | C18: 0.90909091 | G18: 7.91
A19: 43642 | B19: 1.408179 | C19: -0.9009009 | G19: 7.93 | J19: 1 | K19: 0 | L19: =(J19^2)*('Составление портфеля'!$B$114)+(K19^2)*('Составление портфеля'!$C$115)+2*J19*K19*'Составление портфеля'!$B$115 -> 9.5386426 | M19: 0.01
A20: 43643 | B20: 0.13315579 | C20: -0.45454545 | G20: 7.94 | J20: 0.99 | K20: =1-J20 -> 0.01 | L20: =(J20^2)*('Составление портфеля'!$B$114)+(K20^2)*('Составление портфеля'!$C$115)+2*J20*K20*'Составление портфеля'!$B$115 -> 9.3341882
A21: 43644 | B21: 0.075987842 | C21: 0.68493151 | G21: 7.86 | J21: 0.98 | K21: =1-J21 -> 0.02 | L21: =(J21^2)*('Составление портфеля'!$B$114)+(K21^2)*('Составление портфеля'!$C$115)+2*J21*K21*'Составление портфеля'!$B$115 -> 9.1322371
A22: 43647 | B22: 0.11389522 | C22: -1.8464529 | G22: 7.82 | J22: 0.97 | K22: =1-J22 -> 0.03 | L22: =(J22^2)*('Составление портфеля'!$B$114)+(K22^2)*('Составление портфеля'!$C$115)+2*J22*K22*'Составление портфеля'!$B$115 -> 8.9327894
A23: 43648 | B23: 1.3841487 | C23: 1.4521452 | G23: 7.81 | J23: 0.96 | K23: =1-J23 -> 0.04 | L23: =(J23^2)*('Составление портфеля'!$B$114)+(K23^2)*('Составление портфеля'!$C$115)+2*J23*K23*'Составление портфеля'!$B$115 -> 8.7358449
A24: 43649 | B24: 0.24312699 | C24: 1.1060507 | G24: 7.7 | J24: 0.95 | K24: =1-J24 -> 0.05 | L24: =(J24^2)*('Составление портфеля'!$B$114)+(K24^2)*('Составление портфеля'!$C$115)+2*J24*K24*'Составление портфеля'!$B$115 -> 8.5414038
A25: 43650 | B25: 0.18656716 | C25: 0.19305019 | G25: 7.7 | J25: 0.94 | K25: =1-J25 -> 0.06 | L25: =(J25^2)*('Составление портфеля'!$B$114)+(K25^2)*('Составление портфеля'!$C$115)+2*J25*K25*'Составление портфеля'!$B$115 -> 8.349466
A26: 43651 | B26: -0.18621974 | C26: -0.54592164 | G26: 7.66 | J26: 0.93 | K26: =1-J26 -> 0.07 | L26: =(J26^2)*('Составление портфеля'!$B$114)+(K26^2)*('Составление портфеля'!$C$115)+2*J26*K26*'Составление портфеля'!$B$115 -> 8.1600314
A27: 43654 | B27: 0.44776119 | C27: -0.54891831 | G27: 7.67 | J27: 0.92 | K27: =1-J27 -> 0.08 | L27: =(J27^2)*('Составление портфеля'!$B$114)+(K27^2)*('Составление портфеля'!$C$115)+2*J27*K27*'Составление портфеля'!$B$115 -> 7.9731002
A28: 43655 | B28: 1.0401189 | C28: 0.35714286 | G28: 7.67 | J28: 0.91 | K28: =1-J28 -> 0.09 | L28: =(J28^2)*('Составление портфеля'!$B$114)+(K28^2)*('Составление портфеля'!$C$115)+2*J28*K28*'Составление портфеля'!$B$115 -> 7.7886723
A29: 43656 | B29: -0.20220588 | C29: -0.29116791 | G29: 7.66 | J29: 0.9 | K29: =1-J29 -> 0.1 | L29: =(J29^2)*('Составление портфеля'!$B$114)+(K29^2)*('Составление портфеля'!$C$115)+2*J29*K29*'Составление портфеля'!$B$115 -> 7.6067477
A30: 43657 | B30: -1.6209247 | C30: -0.3569111 | G30: 7.73 | J30: 0.89 | K30: =1-J30 -> 0.11 | L30: =(J30^2)*('Составление портфеля'!$B$114)+(K30^2)*('Составление портфеля'!$C$115)+2*J30*K30*'Составление портфеля'!$B$115 -> 7.4273263
A31: 43658 | B31: 0.31829245 | C31: 0.13025073 | G31: 7.73 | J31: 0.88 | K31: =1-J31 -> 0.12 | L31: =(J31^2)*('Составление портфеля'!$B$114)+(K31^2)*('Составление портфеля'!$C$115)+2*J31*K31*'Составление портфеля'!$B$115 -> 7.2504083
... A119: 43783 | B119: -1.0253191 | C119: -0.061595319 | G119: 6.77 | J119: 0 | K119: =1-J119 -> 1 | L119: =(J119^2)*('Составление портфеля'!$B$114)+(K119^2)*('Составление портфеля'!$C$115)+2*J119*K119*'Составление портфеля'!$B$115 -> 1.4845709
A120: 43784 | B120: -1.7970402 | C120: -0.33898305 | G120: 6.78
A121: 43787 | B121: -0.2583423 | C121: 0.1546073 | G121: 6.78
A122: 43788 | B122: 1.0144615 | C122: 0 | G122: 6.74
A123: 43789 | B123: -0.70512821 | C123: 0.061747453 | G123: 6.7
A124: 43790 | B124: -1.280396 | C124: -0.30854674 | G124: 6.68
A125: 43791 | B125: 1.8637602 | C125: -0.27855153 | G125: 6.69
A126: 43794 | B126: -1.1662743 | C126: 0 | G126: 6.68
A127: 43795 | B127: -2.5657681 | C127: 0.09310987 | G127: 6.68
A128: 43796 | B128: -1.0888889 | C128: -0.15503876 | G128: 6.68
A129: 43797 | B129: -1.9433835 | C129: 0 | G129: 6.67
A130: 43798 | B130: 1.042502 | C130: 0.77639752 | G130: 6.63
A131: 43801 | B131: -1.8820862 | C131: -0.1540832 | G131: 6.63
... A255: 43985 | B255: -0.60907396 | C255: -0.97442144 | G255: 5.6
G256: 5.62
G257: 5.62
G258: 5.6
G259: 5.62
G260: 5.65
G261: 5.66
G262: 5.66
G263: 5.69
G264: 5.69
G265: 5.67
G266: 5.64
G267: 5.6657143

Sheet Лист1
A1: 600
A2: 0.08
A3: =A1/(1+A2)^7 -> 350.09424
A8: 1000
A9: =A8/(1+10%)^2 -> 826.44628 | B9: a
A11: 1200
A12: =A11/(1+12%)^3 -> 854.1363 | B12: b
A14: 750 | B14: v | D14: =350+75-30 -> 395 | F14: =150+30-40-70 -> 70
I17: 0.13
D18: =700*(1+12%)^4 -> 1101.4636 | I18: 13000
A19: 350 | I19: 1 | J19: 2 | K19: 3 | L19: 4 | M19: 5 | N19: 6 | O19: 7 | P19: 8
I20: =$I$18/(1+$I$17)^I19 -> 11504.425 | J20: =$I$18/(1+$I$17)^J19 -> 10180.907 | K20: =$I$18/(1+$I$17)^K19 -> 9009.6521 | L20: =$I$18/(1+$I$17)^L19 -> 7973.1435 | M20: =$I$18/(1+$I$17)^M19 -> 7055.8792 | N20: =$I$18/(1+$I$17)^N19 -> 6244.1409 | O20: =$I$18/(1+$I$17)^O19 -> 5525.7884 | P20: =$I$18/(1+$I$17)^P19 -> 4890.0782 | R20: =SUM(I20:P20) -> 62384.014
D21: 0.13
D22: 1 | E22: 2
D23: 540 | E23: 200
D24: =D23/(1+$D$21)^D22 -> 477.87611 | E24: =E23/(1+$D$21)^E22 -> 156.62934 | F24: =D24+E24 -> 634.50544
F26: =F24-430 -> 204.50544
