Workbook

Sheet Inputs
D2: Income Statement, MLN $
E3: Historical Results
C4: Revenue | E4: 2005 | F4: 2006 | G4: 2007 | J4: Tax rate | K4: 0.2
D5: Service revenue | E5: 2827 | F5: 3214.4 | G5: 3679.2
D6: Equipment sales | E6: 203.7 | F6: 258.7 | G6: 267 | J6: Cost of debt (rd) | K6: 0.055
D7: Total revenue | E7: 3030.8 | F7: 3473.2 | G7: 3946.3
J8: Risk free rate | K8: 0.0425
D9: System operating expenses | E9: 604.1 | F9: 639.7 | G9: 717.1
D10: Cost of equipment sold | E10: 511.9 | F10: 568.9 | G10: 640.2 | J10: Market risk premium | K10: 0.05
D11: Selling, general, administration costs | E11: 1217.7 | F11: 1399.6 | G11: 1555.6
D12: EBITDA | E12: =E7-E9-E10-E11 -> 697.1 | F12: =F7-F9-F10-F11 -> 865 | G12: =G7-G9-G10-G11 -> 1033.4 | J12: ba average | K12: =Сalculations!G75 -> 0.76828257
D14: Depreciation, amortization | E14: 490.1 | F14: 555.5 | G14: 582.3 | J14: Debt/Value average | K14: 0.281
D15: EBIT | E15: =E12-E14 -> 207 | F15: =F12-F14 -> 309.5 | G15: =G12-G14 -> 451.1
J16: re (D/E=0) WACC | K16: =Сalculations!E80 -> 0.080914128
D17: Interest expenses | E17: 84.9 | F17: 93.7 | G17: 84.7
D18: Equity in Earnings of Affiliates | E18: 66.7 | F18: 93.1 | G18: 90 | J18: WACC (D/V=average) | K18: =Сalculations!G81 -> 0.062780106
D19: Gain/Loss on investment | E19: 18.1 | F19: 50.8 | G19: 83.1
D20: Other Income | E20: 54.5 | F20: -46.6 | G20: 7
D21: EBT | E21: =E15-E17+E18+E19+E20 -> 261.4 | F21: =F15-F17+F18+F19+F20 -> 313.1 | G21: =G15-G17+G18+G19+G20 -> 546.5
D23: Tax | E23: =$K$4*E21 -> 52.28 | F23: =$K$4*F21 -> 62.62 | G23: =$K$4*G21 -> 109.3
D24: Net income | E24: =E21-E23 -> 209.12 | F24: =F21-F23 -> 250.48 | G24: =G21-G23 -> 437.2
D29: Balance Sheet, MLN$
E31: Historical Results
C32: Assets | E32: 2005 | F32: 2006 | G32: 2007
C33: Current Assets
D34: Cash | E34: 29 | F34: 32.9 | G34: 204.5
D35: Marketable securities | E35: 0 | F35: 249 | G35: 16.4
D36: Accounts receivable | E36: 362.4 | F36: 407.4 | G36: 435.5
D37: Inventory | E37: 92.7 | F37: 117.2 | G37: 101
D38: Prepaid expenses | E38: 32.1 | F38: 35 | G38: 41.6
D39: Deferred taxes | E39: 8.2 | F39: 0 | G39: 18.6
D40: Other current assets | E40: 15.5 | F40: 13.4 | G40: 16.2
D41: Total current assets | E41: =SUM(E34:E40) -> 539.9 | F41: =SUM(F34:F40) -> 854.9 | G41: =SUM(G34:G40) -> 833.8
C42: Fixed (Long-Term) Assets
D43: Property, plant, and equipment | E43: 2553 | F43: 2628.8 | G43: 2595.1
D44: Licenses | E44: 1362.3 | F44: 1494.3 | G44: 1482.4
D45: Customer lists | E45: 47.6 | F45: 26.2 | G45: 15.4
D46: Marketable equity securities | E46: 225.4 | F46: 4.9 | G46: 0
D47: Investment in affiliated entities | E47: 172.1 | F47: 150.3 | G47: 157.7
D48: Long-Term note receivable | E48: 4.7 | F48: 4.5 | G48: 4.4
D49: Goodwill | E49: 481.2 | F49: 485.5 | G49: 491.3
D50: Other Long-Term assets | E50: 30 | F50: 31.4 | G50: 31.8
D51: Total fixed assets | E51: =SUM(E43:E50) -> 4876.3 | F51: =SUM(F43:F50) -> 4825.9 | G51: =SUM(G43:G50) -> 4778.1
C53: Total Assets | E53: =E41+E51 -> 5416.2 | F53: =F41+F51 -> 5680.8 | G53: =G41+G51 -> 5611.9
B55: [42] | C55: Liabilities and Owner's Equity
C56: Current Liabilities
D57: Accounts payable | E57: 254.1 | F57: 254.9 | G57: 260.8
D58: Deffered revenue deposits | E58: 111.4 | F58: 123.3 | G58: 143.4
D59: Accrued liabilities | E59: 42.9 | F59: 47.8 | G59: 59.2
D60: Tax payble | E60: 36.7 | F60: 26.9 | G60: 43.1
D61: Deffered taxes | E61: 0 | F61: 26.3 | G61: 0
A62: [42] | D62: Note payables | E62: 135 | F62: 35 | G62: 0
D63: Forward contract | E63: 0 | F63: 159.9 | G63: 0
D64: Derivative liability | E64: 0 | F64: 88.8 | G64: 0
D65: Other current liabilities | E65: 82.6 | F65: 93.7 | G65: 97.7
D66: Total current liabilities | E66: =SUM(E57:E65) -> 662.7 | F66: =SUM(F57:F65) -> 856.6 | G66: =SUM(G57:G65) -> 604.2
C67: Long-Term Liabilities
D68: Long-term debt | E68: 1001.4 | F68: 1001.8 | G68: 1002.3
D69: Forward contracts | E69: 159.9 | F69: 0 | G69: 0
D70: Derivative liability | E70: 25.8 | F70: 0 | G70: 0
D71: Deferred income tax | E71: 647.1 | F71: 601.5 | G71: 554.4
D72: Assets retirement obligation | E72: 90.2 | F72: 127.6 | G72: 126.8
D73: Other deffered liabilities | E73: 46.2 | F73: 62.9 | G73: 84.5
D74: Minority interest | E74: 41.9 | F74: 36.7 | G74: 43.4
D75: Common,stocks, paid in capital | E75: 1375 | F75: 1378.9 | G75: 1404.1
D76: Retained earning | E76: 1366 | F76: 1614.4 | G76: 1792.1
D77: Total long-term liabilities | E77: =SUM(E68:E76) -> 4753.5 | F77: =SUM(F68:F76) -> 4823.8 | G77: =SUM(G68:G76) -> 5007.6
C79: Total Liabilities and Owner's Equity | E79: =E66+E77 -> 5416.2 | F79: =F66+F77 -> 5680.4 | G79: =G66+G77 -> 5611.8
D86: Operating Assumptions | E86: Forecast Period
C87: Service revenue increase | E87: 2008 | F87: 2009 | G87: 2010 | H87: 2011 | I87: 2012
E88: 0.14 | F88: 0.14 | G88: 0.125 | H88: 0.1 | I88: 0.07
D92: Сapital expenditures to revenue ratio | E92: Forecast Period
C93: Сapital expenditures to revenue ratio | E93: 2008 | F93: 2009 | G93: 2010 | H93: 2011 | I93: 2012
E94: 0.14 | F94: 0.14 | G94: 0.15 | H94: 0.153 | I94: 0.155
D97: Term Loan | E97: Forecast Period
E98: 2008 | F98: 2009 | G98: 2010 | H98: 2011 | I98: 2012
D99: Payment | E99: 492 | F99: 492 | G99: 492 | H99: 492 | I99: 2627
D100: Annual interest | E100: 199 | F100: 184 | G100: 165 | H100: 148 | I100: 127
D101: Principal | E101: 293 | F101: 308 | G101: 327 | H101: 344 | I101: 2500

Sheet Сalculations
A1: 0. | B1: Historical Results
B2: 2005 | C2: 2006 | D2: 2007
A3: CapEx | B3: - | C3: =Inputs!F43-Inputs!E43+Inputs!F14 -> 631.3 | D3: =Inputs!G43-Inputs!F43+Inputs!G14 -> 548.6 | F3: Capex=capital expenditures
A4: NWC | B4: =Inputs!E36+Inputs!E37+Inputs!E38-Inputs!E57-Inputs!E58-Inputs!E59 -> 78.8 | C4: =Inputs!F36+Inputs!F37+Inputs!F38-Inputs!F57-Inputs!F58-Inputs!F59 -> 133.6 | D4: =Inputs!G36+Inputs!G37+Inputs!G38-Inputs!G57-Inputs!G58-Inputs!G59 -> 114.7 | F4: chage NWC=change working capital
A5: Delta NWC | B5: - | C5: =C4-B4 -> 54.8 | D5: =D4-C4 -> -18.9 | F5: CapEx = PP&E (current period) – PP&E (prior period) + Depreciation (current period)
A6: EBITDA | B6: =Inputs!E12 -> 697.1 | C6: =Inputs!F12 -> 865 | D6: =Inputs!G12 -> 1033.4 | F6: NWC= (accunt recievable+inventory+prepaid expenses)-(accounts payable+deffered revenue deposits+accrued liabilities)
A7: EBIT | B7: =Inputs!E15 -> 207 | C7: =Inputs!F15 -> 309.5 | D7: =Inputs!G15 -> 451.1
A8: NOPAT | B8: =(1-Inputs!$K$4)*Сalculations!B7 -> 165.6 | C8: =(1-Inputs!$K$4)*Сalculations!C7 -> 247.6 | D8: =(1-Inputs!$K$4)*Сalculations!D7 -> 360.88 | F8: Delta NWC=WCt-WCt-1
A9: Unlevered FCF | B9: - | C9: =C8+Inputs!F14-C5-C3 -> 117 | D9: =D8+Inputs!G14-D5-D3 -> 413.48
F10: EBITDA=ser.rev+eq.rev.-sys.oper.exp-cost of eq.sold-selling,gen,adm exp
F11: EBIT=EBITDA-depr,amort
F12: NOPAT=(1-t)*EBIT
F13: UNLFCF=NOPAT+depr,amort-deltaNWC-CaPex
A16: 1. | B16: Operating Assumptions
B17: 2007
A18: Service revenue | B18: =Inputs!G5 -> 3679.2
A19: Equipment sales/Service revenue | B19: =Inputs!G6/Inputs!G5 -> 0.072570124
A20: System operating expenses/Service revenue | B20: =Inputs!G9/Inputs!G5 -> 0.1949065
A21: Equipment COGS (Cost of equipment sold/equipment sales) | B21: =Inputs!G10/Inputs!G6 -> 2.3977528
A22: SG&A/Total Revenue | B22: =Inputs!G11/Inputs!G7 -> 0.39419203
A23: Depreciation, amortization in CapEX | B23: =Inputs!G14/Сalculations!D3 -> 1.0614291
A24: Tax Rate | B24: =Inputs!K4 -> 0.2
A25: Working Capital Assumptions:
A26: Accounts Receivable (turnover) | B26: =Inputs!G36/((Inputs!$G$7)/360) -> 39.728353 | D26: turnover assets=Balance/(revenue/360)
A27: Days Sales Equip. Rev. (turnover) | B27: =Inputs!G37/((Inputs!$G$7)/360) -> 9.2136938 | D27: turnover liabilities=Balance/(cash operating expenditure/360)
A28: Prepaid Expenses (turnover) | B28: =Inputs!G38/((Inputs!$G$7)/360) -> 3.7949472 | D28: forcasted indicator= turnover*revenue or cost of sales/360
A29: Accounts Payable (turnover) | B29: =Inputs!G57/((Inputs!G9)/360) -> 130.92735
A30: Deferred Serv. Revenue (turnover) | B30: =Inputs!G58/((Inputs!G9)/360) -> 71.98996
A31: Accrued Liabilities (turnover) | B31: =Inputs!G59/((Inputs!G9)/360) -> 29.719704
A32: Cap-x/Total Revenue | B32: =D3/Inputs!G7 -> 0.13901629
A35: 2. | B35: Intermediate Operating Cash Flows
A36: Operating Results | B36: 2008 | C36: 2009 | D36: 2010 | E36: 2011 | F36: 2012
A37: Service Revenue | B37: =Inputs!G5*(1+Inputs!E88) -> 4194.288 | C37: =B37*(1+Inputs!F88) -> 4781.4883 | D37: =C37*(1+Inputs!G88) -> 5379.1744 | E37: =D37*(1+Inputs!H88) -> 5917.0918 | F37: =E37*(1+Inputs!I88) -> 6331.2882
A38: Plus: Equipment Sales | B38: =$B$19*B37 -> 304.38 | C38: =$B$19*C37 -> 346.9932 | D38: =$B$19*D37 -> 390.36735 | E38: =$B$19*E37 -> 429.40409 | F38: =$B$19*F37 -> 459.46237
A39: Total Revenue | B39: =B37+B38 -> 4498.668 | C39: =C37+C38 -> 5128.4815 | D39: =D37+D38 -> 5769.5417 | E39: =E37+E38 -> 6346.4959 | F39: =F37+F38 -> 6790.7506
A40: Less: System Operating Expenses | B40: =$B$20*B37 -> 817.494 | C40: =$B$20*C37 -> 931.94316 | D40: =$B$20*D37 -> 1048.4361 | E40: =$B$20*E37 -> 1153.2797 | F40: =$B$20*F37 -> 1234.0092
A41: Less: Cost of Equipment Sold | B41: =$B$21*B38 -> 729.828 | C41: =$B$21*C38 -> 832.00392 | D41: =$B$21*D38 -> 936.00441 | E41: =$B$21*E38 -> 1029.6049 | F41: =$B$21*F38 -> 1101.6772
A42: Less: Selling, General & Administrative | B42: =$B$22*B39 -> 1773.3391 | C42: =$B$22*C39 -> 2021.6065 | D42: =$B$22*D39 -> 2274.3073 | E42: =$B$22*E39 -> 2501.7381 | F42: =$B$22*F39 -> 2676.8597
A43: EBITDA | B43: =B39-B40-B41-B42 -> 1178.0069 | C43: =C39-C40-C41-C42 -> 1342.9279 | D43: =D39-D40-D41-D42 -> 1510.7939 | E43: =E39-E40-E41-E42 -> 1661.8733 | F43: =F39-F40-F41-F42 -> 1778.2044
A44: Less: Depreciation & Amortization | B44: =$B$23*B55 -> 668.50239 | C44: =$B$23*C55 -> 762.09273 | D44: =$B$23*D55 -> 918.59391 | E44: =$B$23*E55 -> 1030.6624 | F44: =$B$23*F55 -> 1117.2245
A45: EBIT | B45: =B43-B44 -> 509.50455 | C45: =C43-C44 -> 580.83518 | D45: =D43-D44 -> 592.19998 | E45: =E43-E44 -> 631.21092 | F45: =F43-F44 -> 660.97988
A46: Un-Levered Free Cash Flow:
A47: NOPAT | B47: =(1-Inputs!$K$4)*Сalculations!B45 -> 407.60364 | C47: =(1-Inputs!$K$4)*Сalculations!C45 -> 464.66815 | D47: =(1-Inputs!$K$4)*Сalculations!D45 -> 473.75999 | E47: =(1-Inputs!$K$4)*Сalculations!E45 -> 504.96873 | F47: =(1-Inputs!$K$4)*Сalculations!F45 -> 528.7839
A48: Plus: Depreciation & Amortization | B48: =$B$23*B55 -> 668.50239 | C48: =$B$23*C55 -> 762.09273 | D48: =$B$23*D55 -> 918.59391 | E48: =$B$23*E55 -> 1030.6624 | F48: =$B$23*F55 -> 1117.2245
A49: Less: Changes in Working Capital | B49: =B63 -> 16.0413 | C49: =C63 -> 18.303782 | D49: =D63 -> 18.630635 | E49: =E63 -> 16.767572 | F49: =F63 -> 12.91103
A50: Less: Capital Expenditures | B50: =B55 -> 629.81352 | C50: =C55 -> 717.98741 | D50: =D55 -> 865.43126 | E50: =E55 -> 971.01387 | F50: =F55 -> 1052.5663
A51: Un-Levered Free Cash Flow | B51: =B47+B48-B49-B50 -> 430.25121 | C51: =C47+C48-C49-C50 -> 490.46968 | D51: =D47+D48-D49-D50 -> 508.29201 | E51: =E47+E48-E49-E50 -> 547.84966 | F51: =F47+F48-F49-F50 -> 580.53107
B54: 2008 | C54: 2009 | D54: 2010 | E54: 2011 | F54: 2012
A55: CapEX | B55: =B39*Inputs!E94 -> 629.81352 | C55: =C39*Inputs!F94 -> 717.98741 | D55: =D39*Inputs!G94 -> 865.43126 | E55: =E39*Inputs!H94 -> 971.01387 | F55: =F39*Inputs!I94 -> 1052.5663
A56: Accounts receivable | B56: =$B$26*B39/360 -> 496.45742 | C56: =$B$26*C39/360 -> 565.96146 | D56: =$B$26*D39/360 -> 636.70664 | E56: =$B$26*E39/360 -> 700.3773 | F56: =$B$26*F39/360 -> 749.40372
A57: Inventory | B57: =$B$27*B39/360 -> 115.13708 | C57: =$B$27*C39/360 -> 131.25627 | D57: =$B$27*D39/360 -> 147.66331 | E57: =$B$27*E39/360 -> 162.42964 | F57: =$B$27*F39/360 -> 173.79971
A58: Prepaid expenses | B58: =$B$28*B39/360 -> 47.422798 | C58: =$B$28*C39/360 -> 54.06199 | D58: =$B$28*D39/360 -> 60.819739 | E58: =$B$28*E39/360 -> 66.901713 | F58: =$B$28*F39/360 -> 71.584833
A59: Accounts payable | B59: =$B$29*B40/360 -> 297.312 | C59: =$B$29*C40/360 -> 338.93568 | D59: =$B$29*D40/360 -> 381.30264 | E59: =$B$29*E40/360 -> 419.4329 | F59: =$B$29*F40/360 -> 448.79321
A60: Deffered revenue deposits | B60: =$B$30*B40/360 -> 163.476 | C60: =$B$30*C40/360 -> 186.36264 | D60: =$B$30*D40/360 -> 209.65797 | E60: =$B$30*E40/360 -> 230.62377 | F60: =$B$30*F40/360 -> 246.76743
A61: Accrued liabilities | B61: =$B$31*B40/360 -> 67.488 | C61: =$B$31*C40/360 -> 76.93632 | D61: =$B$31*D40/360 -> 86.55336 | E61: =$B$31*E40/360 -> 95.208696 | F61: =$B$31*F40/360 -> 101.8733
A62: NWC | B62: =B56+B57+B58-B59-B60-B61 -> 130.7413 | C62: =C56+C57+C58-C59-C60-C61 -> 149.04508 | D62: =D56+D57+D58-D59-D60-D61 -> 167.67572 | E62: =E56+E57+E58-E59-E60-E61 -> 184.44329 | F62: =F56+F57+F58-F59-F60-F61 -> 197.35432
A63: Delta NWC | B63: =B62-D4 -> 16.0413 | C63: =C62-B62 -> 18.303782 | D63: =D62-C62 -> 18.630635 | E63: =E62-D62 -> 16.767572 | F63: =F62-E62 -> 12.91103
A68: 3. | C68: Cost of capital
B69: Value | C69: Net debt | D69: D/V | E69: D/E | F69: bl=be | G69: ba
A70: Universal Mobile | B70: 118497 | C70: 69130 | D70: =C70/(B70+C70) -> 0.36844377 | E70: =C70/B70 -> 0.5833903 | F70: 0.86 | G70: =F70/(1+(1-Inputs!$K$4)*E70) -> 0.58634542
A71: Neuberger Wireless | B71: 189470 | C71: 79351 | D71: =C71/(B71+C71) -> 0.29518155 | E71: =C71/B71 -> 0.41880509 | F71: 0.89 | G71: =F71/(1+(1-Inputs!$K$4)*E71) -> 0.66664466
A72: Agile Connections | B72: 21079 | C72: 5080 | D72: =C72/(B72+C72) -> 0.19419703 | E72: =C72/B72 -> 0.24099815 | F72: 1.17 | G72: =F72/(1+(1-Inputs!$K$4)*E72) -> 0.98088653
A73: Big Country Communications | B73: 26285 | C73: 8335 | D73: =C73/(B73+C73) -> 0.24075679 | E73: =C73/B73 -> 0.31710101 | F73: 0.97 | G73: =F73/(1+(1-Inputs!$K$4)*E73) -> 0.77372166
A74: Rocky Mountain Wireless | B74: 7360 | C74: 3268 | D74: =C74/(B74+C74) -> 0.30748965 | E74: =C74/B74 -> 0.44402174 | F74: 1.13 | G74: =F74/(1+(1-Inputs!$K$4)*E74) -> 0.83381457
A75: Average | B75: =AVERAGE(B70:B74) -> 72538.2 | C75: =AVERAGE(C70:C74) -> 33032.8 | D75: =AVERAGE(D70:D74) -> 0.28121376 | E75: =AVERAGE(E70:E74) -> 0.40086326 | F75: =AVERAGE(F70:F74) -> 1.004 | G75: =AVERAGE(G70:G74) -> 0.76828257
A79: D/V | B79: D/E | C79: ba | D79: bl=be | E79: re | F79: rd | G79: wacc
A80: 0 | B80: =A80 -> 0 | C80: =G75 -> 0.76828257 | D80: =C80/(1-A80) -> 0.76828257 | E80: =Inputs!K8+Сalculations!D80*Inputs!K10 -> 0.080914128 | F80: =Inputs!K6 -> 0.055 | G80: =E80*(1-A80)+F80*A80*(1-Inputs!K4) -> 0.080914128
A81: 0.281 | B81: =A81/(1-A81) -> 0.39082058 | C81: =G75 -> 0.76828257 | D81: =C81/(1/(1-A81)) -> 0.55239517 | E81: =Inputs!K8+D81*Inputs!K10 -> 0.070119758 | F81: =Inputs!K6 -> 0.055 | G81: =E81*(1-A81)+F81*A81*(1-Inputs!K4) -> 0.062780106
A85: 4. | B85: PV Intermediate FCF
B90: 2008 | C90: 2009 | D90: 2010 | E90: 2011 | F90: 2012
A91: Un-Levered Free Cash Flow | B91: =B51 -> 430.25121 | C91: =C51 -> 490.46968 | D91: =D51 -> 508.29201 | E91: =E51 -> 547.84966 | F91: =F51 -> 580.53107
A92: WACC (D/V=0) | B92: =G80 -> 0.080914128 | C92: =G80 -> 0.080914128 | D92: =G80 -> 0.080914128 | E92: =G80 -> 0.080914128 | F92: =G80 -> 0.080914128
A93: Discounted un-FCF | B93: =B91/(1+B92)^1 -> 398.04384 | C93: =C91/(1+C92)^2 -> 419.78777 | D93: =D91/(1+D92)^3 -> 402.47573 | E93: =E91/(1+E92)^4 -> 401.32538 | F93: =F91/(1+F92)^5 -> 393.43184
B96: PV un-FCF | C96: =SUM(B93:F93) -> 2015.0646
A100: 5. | B100: Intermediate Tax Shields
B105: 2008 | C105: 2009 | D105: 2010 | E105: 2011 | F105: 2012
A106: Annual interest (inrest tax shield) | B106: 199 | C106: 184 | D106: 165 | E106: 148 | F106: 127
A107: Tax rate | B107: =Inputs!$K$4 -> 0.2 | C107: =Inputs!$K$4 -> 0.2 | D107: =Inputs!$K$4 -> 0.2 | E107: =Inputs!$K$4 -> 0.2 | F107: =Inputs!$K$4 -> 0.2
A108: Tax shield | B108: =(B106)*B107 -> 39.8 | C108: =(C106)*C107 -> 36.8 | D108: =(D106)*D107 -> 33 | E108: =(E106)*E107 -> 29.6 | F108: =(F106)*F107 -> 25.4
A109: Interest rate | B109: =Inputs!$K$6 -> 0.055 | C109: =Inputs!$K$6 -> 0.055 | D109: =Inputs!$K$6 -> 0.055 | E109: =Inputs!$K$6 -> 0.055 | F109: =Inputs!$K$6 -> 0.055
A110: Discounted tax savings | B110: =B108/(1+B109)^1 -> 37.725118 | C110: =C108/(1+C109)^2 -> 33.063049 | D110: =D108/(1+D109)^3 -> 28.103251 | E110: =E108/(1+E109)^4 -> 23.893616 | F110: =F108/(1+F109)^5 -> 19.434413
B114: PV tax sheild | C114: =SUM(B110:F110) -> 142.21945
A118: 6. | B118: Cash Reconciliation
B119: 2008 | C119: 2009 | D119: 2010 | E119: 2011 | F119: 2012
A120: Un-Levered Free Cash Flow | B120: =B51 -> 430.25121 | C120: =C51 -> 490.46968 | D120: =D51 -> 508.29201 | E120: =E51 -> 547.84966 | F120: =F51 -> 580.53107
A121: Less: After-Tax Interest Expenses | B121: =Inputs!E100*(1-Inputs!$K$4) -> 159.2 | C121: =Inputs!F100*(1-Inputs!$K$4) -> 147.2 | D121: =Inputs!G100*(1-Inputs!$K$4) -> 132 | E121: =Inputs!H100*(1-Inputs!$K$4) -> 118.4 | F121: =Inputs!I100*(1-Inputs!$K$4) -> 101.6
A122: Less: Scheduled Principal Payments | B122: =Inputs!E101 -> 293 | C122: =Inputs!F101 -> 308 | D122: =Inputs!G101 -> 327 | E122: =Inputs!H101 -> 344 | F122: =Inputs!I101 -> 2500
A123: Excess Cash | B123: =B120-B121-B122 -> -21.948791 | C123: =C120-C121-C122 -> 35.269678 | D123: =D120-D121-D122 -> 49.292009 | E123: =E120-E121-E122 -> 85.449663 | F123: =F120-F121-F122 -> -2021.0689
A124: Cash on Balance Sheet | B124: =Inputs!G34+Сalculations!B120-Сalculations!B121-Сalculations!B122 -> 182.55121 | C124: =B124+C120-C121-C122 -> 217.82089 | D124: =C124+D120-D121-D122 -> 267.1129 | E124: =D124+E120-E121-E122 -> 352.56256 | F124: =E124+F120-F121-F122 -> -1668.5064
A128: 7. | B128: Projected Income Statement
B129: 2007 | C129: 2008 | D129: 2009 | E129: 2010 | F129: 2011 | G129: 2012
A130: Service Revenue | B130: 3679.2 | C130: 4194.3 | D130: 4781.5 | E130: 5379.2 | F130: 5917.1 | G130: 6331.3
A131: Plus: Equipment Sales | B131: 267 | C131: 304.4 | D131: 347 | E131: 390.4 | F131: 429.4 | G131: 459.5
A132: Total Revenue | B132: 3946.3 | C132: 4498.7 | D132: 5128.5 | E132: 5769.5 | F132: 6346.5 | G132: 6790.8
A133: Less: System Operating Expenses | B133: 717.1 | C133: 817.5 | D133: 931.9 | E133: 1048.4 | F133: 1153.3 | G133: 1234
A134: Less: Cost of Equipment Sold | B134: 640.2 | C134: 729.8 | D134: 832 | E134: 936 | F134: 1029.6 | G134: 1101.7
A135: Less: Selling, General & Administrative | B135: 1555.6 | C135: 1773.3 | D135: 2021.6 | E135: 2274.3 | F135: 2501.7 | G135: 2676.9
A136: EBITDA | B136: 1033.4 | C136: 1178 | D136: 1342.9 | E136: 1510.8 | F136: 1661.9 | G136: 1778.2
A137: Less: Depreciation & Amortization | B137: 582.3 | C137: 663.8 | D137: 756.8 | E137: 912.2 | F137: 1023.4 | G137: 1109.4
A138: EBIT | B138: 451.1 | C138: 514.2 | D138: 586.2 | E138: 598.6 | F138: 638.4 | G138: 668.8
...

Sheet Results
C1: Income Statement, MLN $ | E1: Historical Results | H1: Forecast Period
C2: Revenue | E2: 2005 | F2: 2006 | G2: 2007 | H2: 2008 | I2: 2009 | J2: 2010 | K2: 2011 | L2: 2012
D3: Service revenue | E3: =Inputs!E5 -> 2827 | F3: =Inputs!F5 -> 3214.4 | G3: =Inputs!G5 -> 3679.2 | H3: =Сalculations!B37 -> 4194.288 | I3: =Сalculations!C37 -> 4781.4883 | J3: =Сalculations!D37 -> 5379.1744 | K3: =Сalculations!E37 -> 5917.0918 | L3: =Сalculations!F37 -> 6331.2882
D4: Equipment sales | E4: =Inputs!E6 -> 203.7 | F4: =Inputs!F6 -> 258.7 | G4: =Inputs!G6 -> 267 | H4: =Сalculations!B38 -> 304.38 | I4: =Сalculations!C38 -> 346.9932 | J4: =Сalculations!D38 -> 390.36735 | K4: =Сalculations!E38 -> 429.40409 | L4: =Сalculations!F38 -> 459.46237
D5: Total Revenue | E5: =E3+E4 -> 3030.7 | F5: =F3+F4 -> 3473.1 | G5: =G3+G4 -> 3946.2 | H5: =Сalculations!B39 -> 4498.668 | I5: =Сalculations!C39 -> 5128.4815 | J5: =Сalculations!D39 -> 5769.5417 | K5: =Сalculations!E39 -> 6346.4959 | L5: =Сalculations!F39 -> 6790.7506
D7: System operating expenses | E7: =Inputs!E9 -> 604.1 | F7: =Inputs!F9 -> 639.7 | G7: =Inputs!G9 -> 717.1 | H7: =Сalculations!B40 -> 817.494 | I7: =Сalculations!C40 -> 931.94316 | J7: =Сalculations!D40 -> 1048.4361 | K7: =Сalculations!E40 -> 1153.2797 | L7: =Сalculations!F40 -> 1234.0092
D8: Cost of equipment sold | E8: =Inputs!E10 -> 511.9 | F8: =Inputs!F10 -> 568.9 | G8: =Inputs!G10 -> 640.2 | H8: =Сalculations!B41 -> 729.828 | I8: =Сalculations!C41 -> 832.00392 | J8: =Сalculations!D41 -> 936.00441 | K8: =Сalculations!E41 -> 1029.6049 | L8: =Сalculations!F41 -> 1101.6772
D9: Selling, general, administration costs | E9: =Inputs!E11 -> 1217.7 | F9: =Inputs!F11 -> 1399.6 | G9: =Inputs!G11 -> 1555.6 | H9: =Сalculations!B42 -> 1773.3391 | I9: =Сalculations!C42 -> 2021.6065 | J9: =Сalculations!D42 -> 2274.3073 | K9: =Сalculations!E42 -> 2501.7381 | L9: =Сalculations!F42 -> 2676.8597
D10: EBITDA | E10: =Inputs!E12 -> 697.1 | F10: =Inputs!F12 -> 865 | G10: =Inputs!G12 -> 1033.4 | H10: =Сalculations!B43 -> 1178.0069 | I10: =Сalculations!C43 -> 1342.9279 | J10: =Сalculations!D43 -> 1510.7939 | K10: =Сalculations!E43 -> 1661.8733 | L10: =Сalculations!F43 -> 1778.2044
D12: Depreciation, amortization | E12: =Inputs!E14 -> 490.1 | F12: =Inputs!F14 -> 555.5 | G12: =Inputs!G14 -> 582.3 | H12: =Сalculations!B44 -> 668.50239 | I12: =Сalculations!C44 -> 762.09273 | J12: =Сalculations!D44 -> 918.59391 | K12: =Сalculations!E44 -> 1030.6624 | L12: =Сalculations!F44 -> 1117.2245
D13: EBIT | E13: =Inputs!E15 -> 207 | F13: =Inputs!F15 -> 309.5 | G13: =Inputs!G15 -> 451.1 | H13: =Сalculations!C138 -> 514.2 | I13: =Сalculations!D138 -> 586.2 | J13: =Сalculations!E138 -> 598.6 | K13: =Сalculations!F138 -> 638.4 | L13: =Сalculations!G138 -> 668.8
D15: Interest expenditures | E15: =Inputs!E17 -> 84.9 | F15: =Inputs!F17 -> 93.7 | G15: =Inputs!G17 -> 84.7 | H15: =Сalculations!C139 -> 199 | I15: =Сalculations!D139 -> 184 | J15: =Сalculations!E139 -> 165 | K15: =Сalculations!F139 -> 148 | L15: =Сalculations!G139 -> 127
D16: Equity in Earnings of Affiliates | E16: =Inputs!E18 -> 66.7 | F16: =Inputs!F18 -> 93.1 | G16: =Inputs!G18 -> 90 | H16: =Сalculations!C140 -> 0 | I16: =Сalculations!D140 -> 0 | J16: =Сalculations!E140 -> 0 | K16: =Сalculations!F140 -> 0 | L16: =Сalculations!G140 -> 0
D17: Gain/Loss on investment | E17: =Inputs!E19 -> 18.1 | F17: =Inputs!F19 -> 50.8 | G17: =Inputs!G19 -> 83.1 | H17: =Сalculations!C141 -> 0 | I17: =Сalculations!D141 -> 0 | J17: =Сalculations!E141 -> 0 | K17: =Сalculations!F141 -> 0 | L17: =Сalculations!G141 -> 0
D18: Other Income | E18: =Inputs!E20 -> 54.5 | F18: =Inputs!F20 -> -46.6 | G18: =Inputs!G20 -> 7 | H18: =Сalculations!C142 -> 0 | I18: =Сalculations!D142 -> 0 | J18: =Сalculations!E142 -> 0 | K18: =Сalculations!F142 -> 0 | L18: =Сalculations!G142 -> 0
D19: EBT | E19: =Inputs!E21 -> 261.4 | F19: =Inputs!F21 -> 313.1 | G19: =Inputs!G21 -> 546.5 | H19: =Сalculations!C143 -> 315.2 | I19: =Сalculations!D143 -> 402.2 | J19: =Сalculations!E143 -> 433.6 | K19: =Сalculations!F143 -> 490.4 | L19: =Сalculations!G143 -> 541.8
D21: Tax | E21: =Inputs!E23 -> 52.28 | F21: =Inputs!F23 -> 62.62 | G21: =Inputs!G23 -> 109.3 | H21: =Сalculations!C144 -> 63.04 | I21: =Сalculations!D144 -> 80.44 | J21: =Сalculations!E144 -> 86.72 | K21: =Сalculations!F144 -> 98.08 | L21: =Сalculations!G144 -> 108.36
D22: Net income | E22: =Inputs!E24 -> 209.12 | F22: =Inputs!F24 -> 250.48 | G22: =Inputs!G24 -> 437.2 | H22: =Сalculations!C145 -> 252.16 | I22: =Сalculations!D145 -> 321.76 | J22: =Сalculations!E145 -> 346.88 | K22: =Сalculations!F145 -> 392.32 | L22: =Сalculations!G145 -> 433.44
D24: NOPAT | E24: =Сalculations!B8 -> 165.6 | F24: =Сalculations!C8 -> 247.6 | G24: =Сalculations!D8 -> 360.88 | H24: =Сalculations!B47 -> 407.60364 | I24: =Сalculations!C47 -> 464.66815 | J24: =Сalculations!D47 -> 473.75999 | K24: =Сalculations!E47 -> 504.96873 | L24: =Сalculations!F47 -> 528.7839
D25: CapEx | E25: =Сalculations!B3 -> - | F25: =Сalculations!C3 -> 631.3 | G25: =Сalculations!D3 -> 548.6 | H25: =Сalculations!B55 -> 629.81352 | I25: =Сalculations!C55 -> 717.98741 | J25: =Сalculations!D55 -> 865.43126 | K25: =Сalculations!E55 -> 971.01387 | L25: =Сalculations!F55 -> 1052.5663
D26: Delta NWC | E26: =Сalculations!B5 -> - | F26: =Сalculations!C5 -> 54.8 | G26: =Сalculations!D5 -> -18.9 | H26: =Сalculations!B63 -> 16.0413 | I26: =Сalculations!C63 -> 18.303782 | J26: =Сalculations!D63 -> 18.630635 | K26: =Сalculations!E63 -> 16.767572 | L26: =Сalculations!F63 -> 12.91103
D27: Unlevered FCF | E27: - | F27: =Сalculations!C9 -> 117 | G27: =Сalculations!D9 -> 413.48 | H27: =Сalculations!B51 -> 430.25121 | I27: =Сalculations!C51 -> 490.46968 | J27: =Сalculations!D51 -> 508.29201 | K27: =Сalculations!E51 -> 547.84966 | L27: =Сalculations!F51 -> 580.53107
C30: Balance Sheet, MLN$
E31: Historical Results | H31: Forecast Period
C32: Assets | E32: 2005 | F32: 2006 | G32: 2007 | H32: 2008 | I32: 2009 | J32: 2010 | K32: 2011 | L32: 2012
C33: Current Assets
D34: Cash | E34: =Inputs!E34 -> 29 | F34: =Inputs!F34 -> 32.9 | G34: =Inputs!G34 -> 204.5 | H34: =Сalculations!D152 -> 181.6 | I34: =Сalculations!E152 -> 215.8 | J34: =Сalculations!F152 -> 263.8 | K34: =Сalculations!G152 -> 347.8 | L34: =Сalculations!H152 -> -1674.8
D35: Marketable securities | E35: =Inputs!E35 -> 0 | F35: =Inputs!F35 -> 249 | G35: =Inputs!G35 -> 16.4 | H35: =Сalculations!D153 -> 16.4 | I35: =Сalculations!E153 -> 16.4 | J35: =Сalculations!F153 -> 16.4 | K35: =Сalculations!G153 -> 16.4 | L35: =Сalculations!H153 -> 16.4
D36: Accounts receivable | E36: =Inputs!E36 -> 362.4 | F36: =Inputs!F36 -> 407.4 | G36: =Inputs!G36 -> 435.5 | H36: =Сalculations!D154 -> 496.5 | I36: =Сalculations!E154 -> 566 | J36: =Сalculations!F154 -> 636.7 | K36: =Сalculations!G154 -> 700.4 | L36: =Сalculations!H154 -> 749.4
D37: Inventory | E37: =Inputs!E37 -> 92.7 | F37: =Inputs!F37 -> 117.2 | G37: =Inputs!G37 -> 101 | H37: =Сalculations!D155 -> 115.1 | I37: =Сalculations!E155 -> 131.3 | J37: =Сalculations!F155 -> 147.7 | K37: =Сalculations!G155 -> 162.4 | L37: =Сalculations!H155 -> 173.8
D38: Prepaid expenses | E38: =Inputs!E38 -> 32.1 | F38: =Inputs!F38 -> 35 | G38: =Inputs!G38 -> 41.6 | H38: =Сalculations!D156 -> 47.4 | I38: =Сalculations!E156 -> 54.1 | J38: =Сalculations!F156 -> 60.8 | K38: =Сalculations!G156 -> 66.9 | L38: =Сalculations!H156 -> 71.6
D39: Deferred taxes | E39: =Inputs!E39 -> 8.2 | F39: =Inputs!F39 -> 0 | G39: =Inputs!G39 -> 18.6 | H39: =Сalculations!D157 -> 18.6 | I39: =Сalculations!E157 -> 18.6 | J39: =Сalculations!F157 -> 18.6 | K39: =Сalculations!G157 -> 18.6 | L39: =Сalculations!H157 -> 18.6
D40: Other current assets | E40: =Inputs!E40 -> 15.5 | F40: =Inputs!F40 -> 13.4 | G40: =Inputs!G40 -> 16.2 | H40: =Сalculations!D158 -> 16.2 | I40: =Сalculations!E158 -> 16.2 | J40: =Сalculations!F158 -> 16.2 | K40: =Сalculations!G158 -> 16.2 | L40: =Сalculations!H158 -> 16.2
D41: Total current assets | E41: 539.9 | F41: 854.9 | G41: 833.8 | H41: =SUM(H34:H40) -> 891.8 | I41: =SUM(I34:I40) -> 1018.4 | J41: =SUM(J34:J40) -> 1160.2 | K41: =SUM(K34:K40) -> 1328.7 | L41: =SUM(L34:L40) -> -628.8
C43: Fixed (Long-Term) Assets
D44: Property, plant, and equipment | E44: =Inputs!E43 -> 2553 | F44: =Inputs!F43 -> 2628.8 | G44: =Inputs!G43 -> 2595.1 | H44: =Сalculations!D161 -> 2556.4111 | I44: =Сalculations!E161 -> 2512.3058 | J44: =Сalculations!F161 -> 2459.1432 | K44: =Сalculations!G161 -> 2399.4947 | L44: =Сalculations!H161 -> 2334.8365
D45: Licenses | E45: =Inputs!E44 -> 1362.3 | F45: =Inputs!F44 -> 1494.3 | G45: =Inputs!G44 -> 1482.4 | H45: =Сalculations!D162 -> 1482.4 | I45: =Сalculations!E162 -> 1482.4 | J45: =Сalculations!F162 -> 1482.4 | K45: =Сalculations!G162 -> 1482.4 | L45: =Сalculations!H162 -> 1482.4
D46: Customer lists | E46: =Inputs!E45 -> 47.6 | F46: =Inputs!F45 -> 26.2 | G46: =Inputs!G45 -> 15.4 | H46: =Сalculations!D163 -> 15.4 | I46: =Сalculations!E163 -> 15.4 | J46: =Сalculations!F163 -> 15.4 | K46: =Сalculations!G163 -> 15.4 | L46: =Сalculations!H163 -> 15.4
D47: Marketable equity securities | E47: =Inputs!E46 -> 225.4 | F47: =Inputs!F46 -> 4.9 | G47: =Inputs!G46 -> 0 | H47: =Сalculations!D164 -> 0 | I47: =Сalculations!E164 -> 0 | J47: =Сalculations!F164 -> 0 | K47: =Сalculations!G164 -> 0 | L47: =Сalculations!H164 -> 0
D48: Investment in affiliated entities | E48: =Inputs!E47 -> 172.1 | F48: =Inputs!F47 -> 150.3 | G48: =Inputs!G47 -> 157.7 | H48: =Сalculations!D165 -> 157.7 | I48: =Сalculations!E165 -> 157.7 | J48: =Сalculations!F165 -> 157.7 | K48: =Сalculations!G165 -> 157.7 | L48: =Сalculations!H165 -> 157.7
D49: Long-Term note receivable | E49: =Inputs!E48 -> 4.7 | F49: =Inputs!F48 -> 4.5 | G49: =Inputs!G48 -> 4.4 | H49: =Сalculations!D166 -> 4.4 | I49: =Сalculations!E166 -> 4.4 | J49: =Сalculations!F166 -> 4.4 | K49: =Сalculations!G166 -> 4.4 | L49: =Сalculations!H166 -> 4.4
D50: Goodwill | E50: =Inputs!E49 -> 481.2 | F50: =Inputs!F49 -> 485.5 | G50: =Inputs!G49 -> 491.3 | H50: =Сalculations!D167 -> 491.3 | I50: =Сalculations!E167 -> 491.3 | J50: =Сalculations!F167 -> 491.3 | K50: =Сalculations!G167 -> 491.3 | L50: =Сalculations!H167 -> 491.3
D51: Other Long-Term assets | E51: =Inputs!E50 -> 30 | F51: =Inputs!F50 -> 31.4 | G51: =Inputs!G50 -> 31.8 | H51: =Сalculations!D168 -> 31.8 | I51: =Сalculations!E168 -> 31.8 | J51: =Сalculations!F168 -> 31.8 | K51: =Сalculations!G168 -> 31.8 | L51: =Сalculations!H168 -> 31.8
D52: Total fixed assets | E52: =Inputs!E51 -> 4876.3 | F52: =Inputs!F51 -> 4825.9 | G52: =Inputs!G51 -> 4778.1 | H52: =Сalculations!D169 -> 4739.4111 | I52: =Сalculations!E169 -> 4695.3058 | J52: =Сalculations!F169 -> 4642.1432 | K52: =Сalculations!G169 -> 4582.4947 | L52: =Сalculations!H169 -> 4517.8365
C54: Total Assets | E54: =Inputs!E53 -> 5416.2 | F54: =Inputs!F53 -> 5680.8 | G54: =Inputs!G53 -> 5611.9 | H54: =Сalculations!D171 -> 5631.2111 | I54: =Сalculations!E171 -> 5713.7058 | J54: =Сalculations!F171 -> 5802.3432 | K54: =Сalculations!G171 -> 5911.1947 | L54: =Сalculations!H171 -> 3889.0365
C56: Liabilities and Owner's Equity | E56: Historical Results | H56: Forecast Period
C57: Current Liabilities
D58: Accounts payable | E58: =Inputs!E57 -> 254.1 | F58: =Inputs!F57 -> 254.9 | G58: =Inputs!G57 -> 260.8 | H58: =Сalculations!D175 -> 297.3 | I58: =Сalculations!E175 -> 338.9 | J58: =Сalculations!F175 -> 381.3 | K58: =Сalculations!G175 -> 419.4 | L58: =Сalculations!H175 -> 448.8
D59: Deffered revenue deposits | E59: =Inputs!E58 -> 111.4 | F59: =Inputs!F58 -> 123.3 | G59: =Inputs!G58 -> 143.4 | H59: =Сalculations!D176 -> 163.5 | I59: =Сalculations!E176 -> 186.4 | J59: =Сalculations!F176 -> 209.7 | K59: =Сalculations!G176 -> 230.6 | L59: =Сalculations!H176 -> 246.8
D60: Accrued liabilities | E60: =Inputs!E59 -> 42.9 | F60: =Inputs!F59 -> 47.8 | G60: =Inputs!G59 -> 59.2 | H60: =Сalculations!D177 -> 67.5 | I60: =Сalculations!E177 -> 76.9 | J60: =Сalculations!F177 -> 86.6 | K60: =Сalculations!G177 -> 95.2 | L60: =Сalculations!H177 -> 101.9
D61: Tax payble | E61: =Inputs!E60 -> 36.7 | F61: =Inputs!F60 -> 26.9 | G61: =Inputs!G60 -> 43.1 | H61: =Сalculations!D178 -> 43.1 | I61: =Сalculations!E178 -> 43.1 | J61: =Сalculations!F178 -> 43.1 | K61: =Сalculations!G178 -> 43.1 | L61: =Сalculations!H178 -> 43.1
D62: Deffered taxes | E62: =Inputs!E61 -> 0 | F62: =Inputs!F61 -> 26.3 | G62: =Inputs!G61 -> 0 | H62: =Сalculations!D179 -> 0 | I62: =Сalculations!E179 -> 0 | J62: =Сalculations!F179 -> 0 | K62: =Сalculations!G179 -> 0 | L62: =Сalculations!H179 -> 0
D63: Note payables | E63: =Inputs!E62 -> 135 | F63: =Inputs!F62 -> 35 | G63: =Inputs!G62 -> 0 | H63: =Сalculations!D180 -> 0 | I63: =Сalculations!E180 -> 0 | J63: =Сalculations!F180 -> 0 | K63: =Сalculations!G180 -> 0 | L63: =Сalculations!H180 -> 0
D64: Forward contract | E64: =Inputs!E63 -> 0 | F64: =Inputs!F63 -> 159.9 | G64: =Inputs!G63 -> 0 | H64: =Сalculations!D181 -> 0 | I64: =Сalculations!E181 -> 0 | J64: =Сalculations!F181 -> 0 | K64: =Сalculations!G181 -> 0 | L64: =Сalculations!H181 -> 0
D65: Derivative liability | E65: =Inputs!E64 -> 0 | F65: =Inputs!F64 -> 88.8 | G65: =Inputs!G64 -> 0 | H65: =Сalculations!D182 -> 0 | I65: =Сalculations!E182 -> 0 | J65: =Сalculations!F182 -> 0 | K65: =Сalculations!G182 -> 0 | L65: =Сalculations!H182 -> 0
D66: Other current liabilities | E66: =Inputs!E65 -> 82.6 | F66: =Inputs!F65 -> 93.7 | G66: =Inputs!G65 -> 97.7 | H66: =Сalculations!D183 -> 97.7 | I66: =Сalculations!E183 -> 97.7 | J66: =Сalculations!F183 -> 97.7 | K66: =Сalculations!G183 -> 97.7 | L66: =Сalculations!H183 -> 97.7
D67: Total current liabilities | E67: =Inputs!E66 -> 662.7 | F67: =Inputs!F66 -> 856.6 | G67: =Inputs!G66 -> 604.2 | H67: =Сalculations!D184 -> 669.1 | I67: =Сalculations!E184 -> 743 | J67: =Сalculations!F184 -> 818.4 | K67: =Сalculations!G184 -> 886 | L67: =Сalculations!H184 -> 938.3
C68: Long-Term Liabilities
D69: Long-term debt | E69: =Inputs!E68 -> 1001.4 | F69: =Inputs!F68 -> 1001.8 | G69: =Inputs!G68 -> 1002.3 | H69: =Сalculations!D186 -> 4481.3 | I69: =Сalculations!E186 -> 4173.3 | J69: =Сalculations!F186 -> 3846.3 | K69: =Сalculations!G186 -> 3502.3 | L69: =Сalculations!H186 -> 1002.3
D70: Forward contracts | E70: =Inputs!E69 -> 159.9 | F70: =Inputs!F69 -> 0 | G70: =Inputs!G69 -> 0 | H70: =Сalculations!D187 -> 0 | I70: =Сalculations!E187 -> 0 | J70: =Сalculations!F187 -> 0 | K70: =Сalculations!G187 -> 0 | L70: =Сalculations!H187 -> 0
D71: Derivative liability | E71: =Inputs!E70 -> 25.8 | F71: =Inputs!F70 -> 0 | G71: =Inputs!G70 -> 0 | H71: =Сalculations!D188 -> 0 | I71: =Сalculations!E188 -> 0 | J71: =Сalculations!F188 -> 0 | K71: =Сalculations!G188 -> 0 | L71: =Сalculations!H188 -> 0
D72: Deferred income tax | E72: =Inputs!E71 -> 647.1 | F72: =Inputs!F71 -> 601.5 | G72: =Inputs!G71 -> 554.4 | H72: =Сalculations!D189 -> 554.4 | I72: =Сalculations!E189 -> 554.4 | J72: =Сalculations!F189 -> 554.4 | K72: =Сalculations!G189 -> 554.4 | L72: =Сalculations!H189 -> 554.4
D73: Assets retirement obligation | E73: =Inputs!E72 -> 90.2 | F73: =Inputs!F72 -> 127.6 | G73: =Inputs!G72 -> 126.8 | H73: =Сalculations!D190 -> 126.8 | I73: =Сalculations!E190 -> 126.8 | J73: =Сalculations!F190 -> 126.8 | K73: =Сalculations!G190 -> 126.8 | L73: =Сalculations!H190 -> 126.8
D74: Other deffered liabilities | E74: =Inputs!E73 -> 46.2 | F74: =Inputs!F73 -> 62.9 | G74: =Inputs!G73 -> 84.5 | H74: =Сalculations!D191 -> 84.5 | I74: =Сalculations!E191 -> 84.5 | J74: =Сalculations!F191 -> 84.5 | K74: =Сalculations!G191 -> 84.5 | L74: =Сalculations!H191 -> 84.5
D75: Minority interest | E75: =Inputs!E74 -> 41.9 | F75: =Inputs!F74 -> 36.7 | G75: =Inputs!G74 -> 43.4 | H75: =Сalculations!D192 -> 43.4 | I75: =Сalculations!E192 -> 43.4 | J75: =Сalculations!F192 -> 43.4 | K75: =Сalculations!G192 -> 43.4 | L75: =Сalculations!H192 -> 43.4
D76: Common,stocks, paid in capital | E76: =Inputs!E75 -> 1375 | F76: =Inputs!F75 -> 1378.9 | G76: =Inputs!G75 -> 1404.1 | H76: =Сalculations!D193 -> 1404.1 | I76: =Сalculations!E193 -> 1404.1 | J76: =Сalculations!F193 -> 1404.1 | K76: =Сalculations!G193 -> 1404.1 | L76: =Сalculations!H193 -> 1404.1
D77: Retained earning | E77: =Inputs!E76 -> 1366 | F77: =Inputs!F76 -> 1614.4 | G77: =Inputs!G76 -> 1792.1 | H77: =Сalculations!D194 -> 2044.26 | I77: =Сalculations!E194 -> 2366.02 | J77: =Сalculations!F194 -> 2712.9 | K77: =Сalculations!G194 -> 3105.22 | L77: =Сalculations!H194 -> 3538.66
D78: Total long-term liabilities | E78: =Inputs!E77 -> 4753.5 | F78: =Inputs!F77 -> 4823.8 | G78: =Inputs!G77 -> 5007.6 | H78: =Сalculations!D195 -> 8738.76 | I78: =Сalculations!E195 -> 8752.52 | J78: =Сalculations!F195 -> 8772.4 | K78: =Сalculations!G195 -> 8820.72 | L78: =Сalculations!H195 -> 6754.16
C80: Total Liabilities and Owner's Equity | E80: =Inputs!E79 -> 5416.2 | F80: =Inputs!F79 -> 5680.4 | G80: =Inputs!G79 -> 5611.8 | H80: =Сalculations!D197 -> 9407.86 | I80: =Сalculations!E197 -> 9495.52 | J80: =Сalculations!F197 -> 9590.8 | K80: =Сalculations!G197 -> 9706.72 | L80: =Сalculations!H197 -> 7692.46
C86: Adjusted Present Value
D87: WACC (un-levered) | E87: =Сalculations!C256 -> 0.080914128
D89: PV un-FCF | E89: =Сalculations!C260 -> 2015.0646
D91: Interest rate | E91: =Сalculations!C264 -> 0.055
D93: PV tax sheild | E93: =Сalculations!C268 -> 142.21945
C95: Total Intermediate Term Value | E95: =Сalculations!B270 -> 2157.284
D97: TV Growth Rate | E97: =Сalculations!C274 -> -0.0087682389
D99: WACC (long-term) | E99: =Сalculations!C275 -> 0.062780106
D101: Terminal Value | E101: =Сalculations!C276 -> 8042.6855
C103: PV of Terminal Value | E103: =Сalculations!B278 -> 5931.7659
C105: Value of Operating Assets | E105: =Сalculations!B281 -> 8089.0499
