Workbook

Sheet BS
A1: Баланс МСФО, тыс.руб.
A2: Наименование показателя | B2: 41274 | C2: 41639 | D2: 42004 | E2: 42369 | F2: 42735 | G2: 43100 | H2: 43465 | I2: 43830 | J2: 44196
A3: АКТИВЫ
A4: Оборотные активы
A5: Денежные средства и их эквиваленты | B5: 299000000 | C5: 275000000 | D5: 216000000 | E5: 559000000 | F5: 790000000 | G5: 322000000 | H5: 832000000 | I5: 228000000 | J5: 806000000
A6: Денежные средства с ограничением к использованию | B6: 4000000 | C6: 1000000 | D6: 1000000 | E6: 2000000 | F6: 2000000 | G6: 13000000 | H6: 12000000 | I6: 10000000 | J6: 17000000
A7: Прочие оборотные финансовые активы | B7: 90000000 | C7: 232000000 | D7: 723000000 | E7: 986000000 | F7: 447000000 | G7: 336000000 | H7: 633000000 | I7: 501000000 | J7: 817000000
A8: Дебиторская задолженность | B8: 237000000 | C8: 415000000 | D8: 554000000 | E8: 367000000 | F8: 485000000 | G8: 843000000 | H8: 642000000 | I8: 620000000 | J8: 468000000
A9: Банковские кредиты выданные | B9: - | C9: - | D9: - | E9: - | F9: - | G9: - | H9: - | I9: 130000000 | J9: 131000000
A10: Товарно-материальные запасы | B10: 134000000 | C10: 202000000 | D10: 233000000 | E10: 219000000 | F10: 283000000 | G10: 324000000 | H10: 393000000 | I10: 438000000 | J10: 361000000
A11: Авансы выданные и прочие оборотные активы | B11: 185000000 | C11: 330000000 | D11: 404000000 | E11: 271000000 | F11: 293000000 | G11: 454000000 | H11: 510000000 | I11: 469000000 | J11: 322000000
A12: Итого оборотные активы | B12: 949000000 | C12: 1455000000 | D12: 2131000000 | E12: 2404000000 | F12: 2300000000 | G12: 2292000000 | H12: 3022000000 | I12: 2396000000 | J12: =SUM(J5:J11) -> 2922000000
A13: Внеоборотные активы
A14: Основные средства | B14: 2629000000 | C14: 5330000000 | D14: 5666000000 | E14: 5891000000 | F14: 7090000000 | G14: 7923000000 | H14: 8445000000 | I14: 8706000000 | J14: 10401000000
A15: Активы в форме права пользования | B15: - | C15: - | D15: - | E15: - | F15: - | G15: - | H15: - | I15: 160000000 | J15: 155000000
A16: Нематериальные активы | B16: 19000000 | C16: 37000000 | D16: 49000000 | E16: 48000000 | F16: 59000000 | G16: 75000000 | H16: 75000000 | I16: 66000000 | J16: 80000000
A17: Прочие внеоборотные активы | B17: 24000000 | C17: 40000000 | D17: 281000000 | E17: 510000000 | F17: 808000000 | G17: 606000000 | H17: 239000000 | I17: 229000000 | J17: 275000000
A18: Инвестиции в совместные и ассоциированные предприятия | B18: 186000000 | C18: 327000000 | D18: 347000000 | E18: 353000000 | F18: 411000000 | G18: 635000000 | H18: 735000000 | I18: 801000000 | J18: 846000000
A19: Банковские кредиты выданные | B19: 13000000 | C19: 12000000 | D19: 14000000 | E19: 18000000 | F19: 26000000 | G19: 121000000 | H19: 239000000 | I19: 291000000 | J19: 363000000
A20: Отложенные налоговые активы | B20: 4000000 | C20: 14000000 | D20: 24000000 | E20: 25000000 | F20: 22000000 | G20: 26000000 | H20: 28000000 | I20: 33000000 | J20: 54000000
A21: Гудвилл | B21: 144000000 | C21: 164000000 | D21: 215000000 | E21: 230000000 | F21: 230000000 | G21: 265000000 | H21: 85000000 | I21: 93000000 | J21: 82000000
A22: Прочие внеоборотные нефинансовые активы | B22: 3000000 | C22: 12000000 | D22: 9000000 | E22: 8000000 | F22: 84000000 | G22: 285000000 | H22: 295000000 | I22: 171000000 | J22: 172000000
A23: Итого внеоборотные активы | B23: 3022000000 | C23: 5936000000 | D23: 6605000000 | E23: 7083000000 | F23: 8730000000 | G23: 9936000000 | H23: 10141000000 | I23: 10550000000 | J23: =SUM(J14:J22) -> 12428000000
A24: Активы, предназначенные для продажи | B24: 0 | C24: 147000000 | D24: 0 | E24: 150000000 | F24: 0 | G24: 0 | H24: 0 | I24: 0 | J24: 0
A25: Итого активы | B25: 3971000000 | C25: 7538000000 | D25: 8736000000 | E25: 9637000000 | F25: 11030000000 | G25: 12228000000 | H25: 13163000000 | I25: 12946000000 | J25: =J23+J12 -> 15350000000
A26: ОБЯЗАТЕЛЬСТВА И КАПИТАЛ
A27: Краткосрочные обязательства
A28: Кредиторская задолженность и начисления | B28: 211000000 | C28: 488000000 | D28: 494000000 | E28: 476000000 | F28: 583000000 | G28: 971000000 | H28: 1130000000 | I28: 1162000000 | J28: 1546000000
A29: Кредиты и займы | B29: 143000000 | C29: 684000000 | D29: 1216000000 | E29: 1040000000 | F29: 1671000000 | G29: 2229000000 | H29: 978000000 | I29: 795000000 | J29: 798000000
A30: Обязательства по налогу на прибыль | B30: 7000000 | C30: 11000000 | D30: 39000000 | E30: 8000000 | F30: 6000000 | G30: 39000000 | H30: 23000000 | I30: 23000000 | J30: 14000000
A31: Обязательства по прочим налогам | B31: 83000000 | C31: 161000000 | D31: 162000000 | E31: 138000000 | F31: 222000000 | G31: 278000000 | H31: 327000000 | I31: 379000000 | J31: 301000000
A32: Резервы | B32: 5000000 | C32: 22000000 | D32: 36000000 | E32: 28000000 | F32: 29000000 | G32: 29000000 | H32: 43000000 | I32: 55000000 | J32: 68000000
A33: Предоплата по договорам поставки нефти | B33: - | C33: - | D33: - | E33: - | F33: - | G33: 264000000 | H33: 354000000 | I33: 332000000 | J33: 357000000
A34: Прочие краткосрочные обязательства | B34: 1000000 | C34: 11000000 | D34: 123000000 | E34: 127000000 | F34: 262000000 | G34: 26000000 | H34: 19000000 | I34: 9000000 | J34: 8000000
A35: Итого краткосрочные обязательства | B35: 453000000 | C35: 1387000000 | D35: 2031000000 | E35: 1817000000 | F35: 2773000000 | G35: 3836000000 | H35: 2874000000 | I35: 2755000000 | J35: =SUM(J28:J34) -> 3092000000
A36: Долгосрочные обязательства
A37: Кредиты и займы | B37: 837000000 | C37: 1676000000 | D37: 2190000000 | E37: 2283000000 | F37: 1914000000 | G37: 1783000000 | H37: 3413000000 | I37: 3033000000 | J37: 3810000000
A38: Отложенные налоговые обязательства | B38: 264000000 | C38: 660000000 | D38: 594000000 | E38: 578000000 | F38: 785000000 | G38: 814000000 | H38: 837000000 | I38: 844000000 | J38: 1072000000
A39: Резервы | B39: 71000000 | C39: 116000000 | D39: 107000000 | E39: 143000000 | F39: 203000000 | G39: 245000000 | H39: 244000000 | I39: 343000000 | J39: 437000000
A40: Предоплата по договорам поставки нефти | B40: 0 | C40: 470000000 | D40: 887000000 | E40: 1785000000 | F40: 1586000000 | G40: 1322000000 | H40: 1072000000 | I40: 750000000 | J40: 1401000000
A41: Прочие долгосрочные обязательства | B41: 16000000 | C41: 28000000 | D41: 46000000 | E41: 39000000 | F41: 43000000 | G41: 45000000 | H41: 46000000 | I41: 73000000 | J41: 51000000
A42: Итого долгосрочные обязательства | B42: 1196000000 | C42: 2958000000 | D42: 3824000000 | E42: 4828000000 | F42: 4531000000 | G42: 4209000000 | H42: 5612000000 | I42: 5042000000 | J42: =SUM(J37:J41) -> 6771000000
A43: Капитал
A44: Уставный капитал | B44: 1000000 | C44: 1000000 | D44: 1000000 | E44: 1000000 | F44: 1000000 | G44: 1000000 | H44: 1000000 | I44: 1000000 | J44: 1000000
A45: Собственные акции, выкупленные у акционеров | B45: -299000000 | C45: 0 | D45: 0 | E45: 0 | F45: 0 | G45: 0 | H45: 0 | I45: 0 | J45: -370000000
A46: Добавочный капитал | B46: 385000000 | C46: 477000000 | D46: 493000000 | E46: 507000000 | F46: 603000000 | G46: 627000000 | H46: 633000000 | I46: 635000000 | J46: 1100000000
A47: Резерв курсовых разниц от пересчета иностранных операций | B47: - | C47: - | D47: - | E47: - | F47: - | G47: - | H47: - | I47: -185000000 | J47: -66000000
A48: Прочие фонды и резервы | B48: -6000000 | C48: -14000000 | D48: -500000000 | E48: -768000000 | F48: -497000000 | G48: -322000000 | H48: -191000000 | I48: 31000000 | J48: 34000000
A49: Нераспределенная прибыль | B49: 2202000000 | C49: 2662000000 | D49: 2878000000 | E49: 3146000000 | F49: 3202000000 | G49: 3313000000 | H49: 3610000000 | I49: 4032000000 | J49: 4007000000
A50: Итого акционерный капитал «Роснефти» | B50: 2283000000 | C50: 3126000000 | D50: 2872000000 | E50: 2886000000 | F50: 3309000000 | G50: 3619000000 | H50: 4053000000 | I50: 4514000000 | J50: =SUM(J44:J49) -> 4706000000
A51: Неконтролирующие доли | B51: 39000000 | C51: 39000000 | D51: 9000000 | E51: 43000000 | F51: 417000000 | G51: 564000000 | H51: 624000000 | I51: 635000000 | J51: 781000000
A52: Итого капитал | B52: 2322000000 | C52: 3165000000 | D52: 2881000000 | E52: 2929000000 | F52: 3726000000 | G52: 4183000000 | H52: 4677000000 | I52: 5149000000 | J52: =J50+J51 -> 5487000000
A53: Итого капитал и обязательства | B53: 3971000000 | C53: 7538000000 | D53: 8736000000 | E53: 9637000000 | F53: 11030000000 | G53: 12228000000 | H53: 13163000000 | I53: 12946000000 | J53: 15350000000
A59: Баланс МСФО, тыс.руб.
A60: Наименование показателя | B60: 43100 | C60: 43465 | D60: 43830 | E60: 44196 | F60: Тпр 2018 | G60: Тпр 2019 | H60: Тпр 2020 | K60: Наименование показателя | L60: 43465 | M60: Доля в разделе | N60: Доля в активе\пассиве | O60: 43830 | P60: Доля в разделе | Q60: Доля в активе\пассиве | R60: 44196 | S60: Доля в разделе | T60: Доля в активе\пассиве
A61: =A3 -> АКТИВЫ | K61: =A61 -> АКТИВЫ
A62: =A4 -> Оборотные активы | K62: =A62 -> Оборотные активы
A63: Денежные средства и их эквиваленты | B63: 322000000 | C63: 832000000 | D63: 228000000 | E63: 806000000 | F63: =C63/B63-1 -> 1.5838509 | G63: =D63/C63-1 -> -0.72596154 | H63: =E63/D63-1 -> 2.5350877 | K63: Денежные средства и их эквиваленты | L63: 832000000 | M63: =L63/$L$70 -> 0.27531436 | N63: =L63/$L$82 -> 0.063207475 | O63: 228000000 | P63: =O63/$O$70 -> 0.095158598 | Q63: =O63/$O$82 -> 0.017611617 | R63: 806000000 | S63: =R63/$R$70 -> 0.27583847 | T63: =R63/$R$82 -> 0.052508143
A64: Денежные средства с ограничением к использованию | B64: 13000000 | C64: 12000000 | D64: 10000000 | E64: 17000000 | F64: =C64/B64-1 -> -0.076923077 | G64: =D64/C64-1 -> -0.16666667 | H64: =E64/D64-1 -> 0.7 | K64: Денежные средства с ограничением к использованию | L64: 12000000 | M64: =L64/$L$70 -> 0.0039708802 | N64: =L64/$L$82 -> 0.00091164628 | O64: 10000000 | P64: =O64/$O$70 -> 0.0041736227 | Q64: =O64/$O$82 -> 0.00077243936 | R64: 17000000 | S64: =R64/$R$70 -> 0.0058179329 | T64: =R64/$R$82 -> 0.0011074919
A65: Прочие оборотные финансовые активы | B65: 336000000 | C65: 633000000 | D65: 501000000 | E65: 817000000 | F65: =C65/B65-1 -> 0.88392857 | G65: =D65/C65-1 -> -0.20853081 | H65: =E65/D65-1 -> 0.63073852 | K65: Прочие оборотные финансовые активы | L65: 633000000 | M65: =L65/$L$70 -> 0.20946393 | N65: =L65/$L$82 -> 0.048089341 | O65: 501000000 | P65: =O65/$O$70 -> 0.2090985 | Q65: =O65/$O$82 -> 0.038699212 | R65: 817000000 | S65: =R65/$R$70 -> 0.27960301 | T65: =R65/$R$82 -> 0.053224756
A66: Дебиторская задолженность | B66: 843000000 | C66: 642000000 | D66: 620000000 | E66: 468000000 | F66: =C66/B66-1 -> -0.23843416 | G66: =D66/C66-1 -> -0.034267913 | H66: =E66/D66-1 -> -0.24516129 | K66: Дебиторская задолженность | L66: 642000000 | M66: =L66/$L$70 -> 0.21244209 | N66: =L66/$L$82 -> 0.048773076 | O66: 620000000 | P66: =O66/$O$70 -> 0.25876461 | Q66: =O66/$O$82 -> 0.047891241 | R66: 468000000 | S66: =R66/$R$70 -> 0.16016427 | T66: =R66/$R$82 -> 0.030488599
A67: Банковские кредиты выданные | B67: - | C67: - | D67: 130000000 | E67: 131000000 | F67: - | G67: - | H67: - | K67: Банковские кредиты выданные | L67: - | M67: - | N67: - | O67: 130000000 | P67: =O67/$O$70 -> 0.054257095 | Q67: =O67/$O$82 -> 0.010041712 | R67: 131000000 | S67: =R67/$R$70 -> 0.044832307 | T67: =R67/$R$82 -> 0.008534202
A68: Товарно-материальные запасы | B68: 324000000 | C68: 393000000 | D68: 438000000 | E68: 361000000 | F68: =C68/B68-1 -> 0.21296296 | G68: =D68/C68-1 -> 0.11450382 | H68: =E68/D68-1 -> -0.17579909 | K68: Товарно-материальные запасы | L68: 393000000 | M68: =L68/$L$70 -> 0.13004633 | N68: =L68/$L$82 -> 0.029856416 | O68: 438000000 | P68: =O68/$O$70 -> 0.18280467 | Q68: =O68/$O$82 -> 0.033832844 | R68: 361000000 | S68: =R68/$R$70 -> 0.12354552 | T68: =R68/$R$82 -> 0.023517915
A69: Авансы выданные и прочие оборотные активы | B69: 454000000 | C69: 510000000 | D69: 469000000 | E69: 322000000 | F69: =C69/B69-1 -> 0.12334802 | G69: =D69/C69-1 -> -0.080392157 | H69: =E69/D69-1 -> -0.31343284 | K69: Авансы выданные и прочие оборотные активы | L69: 510000000 | M69: =L69/$L$70 -> 0.16876241 | N69: =L69/$L$82 -> 0.038744967 | O69: 469000000 | P69: =O69/$O$70 -> 0.1957429 | Q69: =O69/$O$82 -> 0.036227406 | R69: 322000000 | S69: =R69/$R$70 -> 0.11019849 | T69: =R69/$R$82 -> 0.020977199
A70: Итого оборотные активы | B70: 2292000000 | C70: 3022000000 | D70: 2396000000 | E70: =SUM(E63:E69) -> 2922000000 | F70: =C70/B70-1 -> 0.31849913 | G70: =D70/C70-1 -> -0.20714758 | H70: =E70/D70-1 -> 0.21953255 | K70: Итого оборотные активы | L70: 3022000000 | N70: =L70/$L$82 -> 0.22958292 | O70: 2396000000 | Q70: =O70/$O$82 -> 0.18507647 | R70: =SUM(R63:R69) -> 2922000000 | T70: =R70/$R$82 -> 0.19035831
A71: =A13 -> Внеоборотные активы | K71: =A71 -> Внеоборотные активы
A72: Основные средства | B72: 7923000000 | C72: 8445000000 | D72: 8706000000 | E72: 10401000000 | F72: =C72/B72-1 -> 0.065884135 | G72: =D72/C72-1 -> 0.030905861 | H72: =E72/D72-1 -> 0.19469331 | K72: Основные средства | L72: 8445000000 | M72: =L72/$L$81 -> 0.83275811 | N72: =L72/$L$82 -> 0.64157107 | O72: 8706000000 | P72: =O72/$O$81 -> 0.82521327 | Q72: =O72/$O$82 -> 0.67248571 | R72: 10401000000 | S72: =R72/$R$81 -> 0.83690055 | T72: =R72/$R$82 -> 0.67758958
A73: Активы в форме права пользования | B73: - | C73: - | D73: 160000000 | E73: 155000000 | F73: - | G73: - | H73: =E73/D73-1 -> -0.03125 | K73: Активы в форме права пользования | L73: - | M73: - | N73: - | O73: 160000000 | P73: =O73/$O$81 -> 0.015165877 | Q73: =O73/$O$82 -> 0.01235903 | R73: 155000000 | S73: =R73/$R$81 -> 0.012471838 | T73: =R73/$R$82 -> 0.01009772
A74: Нематериальные активы | B74: 75000000 | C74: 75000000 | D74: 66000000 | E74: 80000000 | F74: =C74/B74-1 -> 0 | G74: =D74/C74-1 -> -0.12 | H74: =E74/D74-1 -> 0.21212121 | K74: Нематериальные активы | L74: 75000000 | M74: =L74/$L$81 -> 0.0073957203 | N74: =L74/$L$82 -> 0.0056977893 | O74: 66000000 | P74: =O74/$O$81 -> 0.0062559242 | Q74: =O74/$O$82 -> 0.0050980998 | R74: 80000000 | S74: =R74/$R$81 -> 0.0064370776 | T74: =R74/$R$82 -> 0.0052117264
A75: Прочие внеоборотные активы | B75: 606000000 | C75: 239000000 | D75: 229000000 | E75: 275000000 | F75: =C75/B75-1 -> -0.60561056 | G75: =D75/C75-1 -> -0.041841004 | H75: =E75/D75-1 -> 0.20087336 | K75: Прочие внеоборотные активы | L75: 239000000 | M75: =L75/$L$81 -> 0.023567695 | N75: =L75/$L$82 -> 0.018156955 | O75: 229000000 | P75: =O75/$O$81 -> 0.021706161 | Q75: =O75/$O$82 -> 0.017688861 | R75: 275000000 | S75: =R75/$R$81 -> 0.022127454 | T75: =R75/$R$82 -> 0.017915309
A76: Инвестиции в совместные и ассоциированные предприятия | B76: 635000000 | C76: 735000000 | D76: 801000000 | E76: 846000000 | F76: =C76/B76-1 -> 0.15748031 | G76: =D76/C76-1 -> 0.089795918 | H76: =E76/D76-1 -> 0.056179775 | K76: Инвестиции в совместные и ассоциированные предприятия | L76: 735000000 | M76: =L76/$L$81 -> 0.072478059 | N76: =L76/$L$82 -> 0.055838335 | O76: 801000000 | P76: =O76/$O$81 -> 0.075924171 | Q76: =O76/$O$82 -> 0.061872393 | R76: 846000000 | S76: =R76/$R$81 -> 0.068072095 | T76: =R76/$R$82 -> 0.055114007
A77: Банковские кредиты выданные | B77: 121000000 | C77: 239000000 | D77: 291000000 | E77: 363000000 | F77: =C77/B77-1 -> 0.97520661 | G77: =D77/C77-1 -> 0.21757322 | H77: =E77/D77-1 -> 0.24742268 | K77: Банковские кредиты выданные | L77: 239000000 | M77: =L77/$L$81 -> 0.023567695 | N77: =L77/$L$82 -> 0.018156955 | O77: 291000000 | P77: =O77/$O$81 -> 0.027582938 | Q77: =O77/$O$82 -> 0.022477985 | R77: 363000000 | S77: =R77/$R$81 -> 0.029208239 | T77: =R77/$R$82 -> 0.023648208
A78: Отложенные налоговые активы | B78: 26000000 | C78: 28000000 | D78: 33000000 | E78: 54000000 | F78: =C78/B78-1 -> 0.076923077 | G78: =D78/C78-1 -> 0.17857143 | H78: =E78/D78-1 -> 0.63636364 | K78: Отложенные налоговые активы | L78: 28000000 | M78: =L78/$L$81 -> 0.0027610689 | N78: =L78/$L$82 -> 0.0021271747 | O78: 33000000 | P78: =O78/$O$81 -> 0.0031279621 | Q78: =O78/$O$82 -> 0.0025490499 | R78: 54000000 | S78: =R78/$R$81 -> 0.0043450274 | T78: =R78/$R$82 -> 0.0035179153
A79: Гудвилл | B79: 265000000 | C79: 85000000 | D79: 93000000 | E79: 82000000 | F79: =C79/B79-1 -> -0.67924528 | G79: =D79/C79-1 -> 0.094117647 | H79: =E79/D79-1 -> -0.11827957 | K79: Гудвилл | L79: 85000000 | M79: =L79/$L$81 -> 0.0083818164 | N79: =L79/$L$82 -> 0.0064574945 | O79: 93000000 | P79: =O79/$O$81 -> 0.0088151659 | Q79: =O79/$O$82 -> 0.0071836861 | R79: 82000000 | S79: =R79/$R$81 -> 0.0065980045 | T79: =R79/$R$82 -> 0.0053420195
A80: Прочие внеоборотные нефинансовые активы | B80: 285000000 | C80: 295000000 | D80: 171000000 | E80: 172000000 | F80: =C80/B80-1 -> 0.035087719 | G80: =D80/C80-1 -> -0.42033898 | H80: =E80/D80-1 -> 0.0058479532 | K80: Прочие внеоборотные нефинансовые активы | L80: 295000000 | M80: =L80/$L$81 -> 0.029089833 | N80: =L80/$L$82 -> 0.022411304 | O80: 171000000 | P80: =O80/$O$81 -> 0.016208531 | Q80: =O80/$O$82 -> 0.013208713 | R80: 172000000 | S80: =R80/$R$81 -> 0.013839717 | T80: =R80/$R$82 -> 0.011205212
A81: Итого внеоборотные активы | B81: 9936000000 | C81: 10141000000 | D81: 10550000000 | E81: =SUM(E72:E80) -> 12428000000 | F81: =C81/B81-1 -> 0.020632045 | G81: =D81/C81-1 -> 0.040331328 | H81: =E81/D81-1 -> 0.17800948 | K81: Итого внеоборотные активы | L81: 10141000000 | N81: =L81/$L$82 -> 0.77041708 | O81: 10550000000 | Q81: =O81/$O$82 -> 0.81492353 | R81: =SUM(R72:R80) -> 12428000000 | T81: =R81/$R$82 -> 0.80964169
A82: Итого активы | B82: 12228000000 | C82: 13163000000 | D82: 12946000000 | E82: =E81+E70 -> 15350000000 | F82: =C82/B82-1 -> 0.076463853 | G82: =D82/C82-1 -> -0.016485604 | H82: =E82/D82-1 -> 0.18569442 | K82: Итого активы | L82: 13163000000 | O82: 12946000000 | R82: =R81+R70 -> 15350000000 | T82: =O82/L82-1 -> -0.016485604
A83: =A26 -> ОБЯЗАТЕЛЬСТВА И КАПИТАЛ | K83: =A83 -> ОБЯЗАТЕЛЬСТВА И КАПИТАЛ
A84: =A27 -> Краткосрочные обязательства | K84: =A84 -> Краткосрочные обязательства
A85: Кредиторская задолженность и начисления | B85: 971000000 | C85: 1130000000 | D85: 1162000000 | E85: 1546000000 | F85: =C85/B85-1 -> 0.16374871 | G85: =D85/C85-1 -> 0.028318584 | H85: =E85/D85-1 -> 0.33046472 | K85: Кредиторская задолженность и начисления | L85: 1130000000 | M85: =L85/$L$92 -> 0.39318024 | N85: =L85/$L$110 -> 0.085846691 | O85: 1162000000 | P85: =O85/$O$92 -> 0.42177858 | Q85: =O85/$O$110 -> 0.089757454 | R85: 1546000000 | S85: =R85/$R$92 -> 0.5 | T85: =R85/$R$110 -> 0.10071661
A86: Кредиты и займы | B86: 2229000000 | C86: 978000000 | D86: 795000000 | E86: 798000000 | F86: =C86/B86-1 -> -0.56123822 | G86: =D86/C86-1 -> -0.18711656 | H86: =E86/D86-1 -> 0.0037735849 | K86: Кредиты и займы | L86: 978000000 | M86: =L86/$L$92 -> 0.34029228 | N86: =L86/$L$110 -> 0.074299172 | O86: 795000000 | P86: =O86/$O$92 -> 0.28856624 | Q86: =O86/$O$110 -> 0.061408929 | R86: 798000000 | S86: =R86/$R$92 -> 0.25808538 | T86: =R86/$R$110 -> 0.051986971
A87: Обязательства по налогу на прибыль | B87: 39000000 | C87: 23000000 | D87: 23000000 | E87: 14000000 | F87: =C87/B87-1 -> -0.41025641 | G87: =D87/C87-1 -> 0 | H87: =E87/D87-1 -> -0.39130435 | K87: Обязательства по налогу на прибыль | L87: 23000000 | M87: =L87/$L$92 -> 0.0080027836 | N87: =L87/$L$110 -> 0.001747322 | O87: 23000000 | P87: =O87/$O$92 -> 0.0083484574 | Q87: =O87/$O$110 -> 0.0017766105 | R87: 14000000 | S87: =R87/$R$92 -> 0.0045278137 | T87: =R87/$R$110 -> 0.00091205212
A88: Обязательства по прочим налогам | B88: 278000000 | C88: 327000000 | D88: 379000000 | E88: 301000000 | F88: =C88/B88-1 -> 0.17625899 | G88: =D88/C88-1 -> 0.15902141 | H88: =E88/D88-1 -> -0.20580475 | K88: Обязательства по прочим налогам | L88: 327000000 | M88: =L88/$L$92 -> 0.11377871 | N88: =L88/$L$110 -> 0.024842361 | O88: 379000000 | P88: =O88/$O$92 -> 0.13756806 | Q88: =O88/$O$110 -> 0.029275452 | R88: 301000000 | S88: =R88/$R$92 -> 0.097347995 | T88: =R88/$R$110 -> 0.019609121
A89: Резервы | B89: 29000000 | C89: 43000000 | D89: 55000000 | E89: 68000000 | F89: =C89/B89-1 -> 0.48275862 | G89: =D89/C89-1 -> 0.27906977 | H89: =E89/D89-1 -> 0.23636364 | K89: Резервы | L89: 43000000 | M89: =L89/$L$92 -> 0.014961726 | N89: =L89/$L$110 -> 0.0032667325 | O89: 55000000 | P89: =O89/$O$92 -> 0.019963702 | Q89: =O89/$O$110 -> 0.0042484165 | R89: 68000000 | S89: =R89/$R$92 -> 0.021992238 | T89: =R89/$R$110 -> 0.0044299674
A90: Предоплата по договорам поставки нефти | B90: 264000000 | C90: 354000000 | D90: 332000000 | E90: 357000000 | F90: =C90/B90-1 -> 0.34090909 | G90: =D90/C90-1 -> -0.062146893 | H90: =E90/D90-1 -> 0.075301205 | K90: Предоплата по договорам поставки нефти | L90: 354000000 | M90: =L90/$L$92 -> 0.12317328 | N90: =L90/$L$110 -> 0.026893565 | O90: 332000000 | P90: =O90/$O$92 -> 0.12050817 | Q90: =O90/$O$110 -> 0.025644987 | R90: 357000000 | S90: =R90/$R$92 -> 0.11545925 | T90: =R90/$R$110 -> 0.023257329
A91: Прочие краткосрочные обязательства | B91: 26000000 | C91: 19000000 | D91: 9000000 | E91: 8000000 | F91: =C91/B91-1 -> -0.26923077 | G91: =D91/C91-1 -> -0.52631579 | H91: =E91/D91-1 -> -0.11111111 | K91: Прочие краткосрочные обязательства | L91: 19000000 | M91: =L91/$L$92 -> 0.0066109951 | N91: =L91/$L$110 -> 0.0014434399 | O91: 9000000 | P91: =O91/$O$92 -> 0.0032667877 | Q91: =O91/$O$110 -> 0.00069519543 | R91: 8000000 | S91: =R91/$R$92 -> 0.0025873221 | T91: =R91/$R$110 -> 0.00052117264
A92: Итого краткосрочные обязательства | B92: 3836000000 | C92: 2874000000 | D92: 2755000000 | E92: =SUM(E85:E91) -> 3092000000 | F92: =C92/B92-1 -> -0.25078206 | G92: =D92/C92-1 -> -0.041405706 | H92: =E92/D92-1 -> 0.12232305 | K92: Итого краткосрочные обязательства | L92: 2874000000 | N92: =L92/$L$110 -> 0.21833928 | O92: 2755000000 | Q92: =O92/$O$110 -> 0.21280704 | R92: =SUM(R85:R91) -> 3092000000 | T92: =R92/$R$110 -> 0.20143322
A93: =A36 -> Долгосрочные обязательства | K93: =A93 -> Долгосрочные обязательства
A94: Кредиты и займы | B94: 1783000000 | C94: 3413000000 | D94: 3033000000 | E94: 3810000000 | F94: =C94/B94-1 -> 0.91418957 | G94: =D94/C94-1 -> -0.111339 | H94: =E94/D94-1 -> 0.256182 | K94: Кредиты и займы | L94: 3413000000 | M94: =L94/$L$99 -> 0.60816108 | N94: =L94/$L$110 -> 0.2592874 | O94: 3033000000 | P94: =O94/$O$99 -> 0.60154701 | Q94: =O94/$O$110 -> 0.23428086 | R94: 3810000000 | S94: =R94/$R$99 -> 0.56269384 | T94: =R94/$R$110 -> 0.24820847
A95: Отложенные налоговые обязательства | B95: 814000000 | C95: 837000000 | D95: 844000000 | E95: 1072000000 | F95: =C95/B95-1 -> 0.028255528 | G95: =D95/C95-1 -> 0.0083632019 | H95: =E95/D95-1 -> 0.27014218 | K95: Отложенные налоговые обязательства | L95: 837000000 | M95: =L95/$L$99 -> 0.14914469 | N95: =L95/$L$110 -> 0.063587328 | O95: 844000000 | P95: =O95/$O$99 -> 0.16739389 | Q95: =O95/$O$110 -> 0.065193882 | R95: 1072000000 | S95: =R95/$R$99 -> 0.15832226 | T95: =R95/$R$110 -> 0.069837134
A96: Резервы | B96: 245000000 | C96: 244000000 | D96: 343000000 | E96: 437000000 | F96: =C96/B96-1 -> -0.0040816327 | G96: =D96/C96-1 -> 0.4057377 | H96: =E96/D96-1 -> 0.27405248 | K96: Резервы | L96: 244000000 | M96: =L96/$L$99 -> 0.043478261 | N96: =L96/$L$110 -> 0.018536808 | O96: 343000000 | P96: =O96/$O$99 -> 0.06802856 | Q96: =O96/$O$110 -> 0.02649467 | R96: 437000000 | S96: =R96/$R$99 -> 0.06453995 | T96: =R96/$R$110 -> 0.028469055
A97: Предоплата по договорам поставки нефти | B97: 1322000000 | C97: 1072000000 | D97: 750000000 | E97: 1401000000 | F97: =C97/B97-1 -> -0.18910741 | G97: =D97/C97-1 -> -0.30037313 | H97: =E97/D97-1 -> 0.868 | K97: Предоплата по договорам поставки нефти | L97: 1072000000 | M97: =L97/$L$99 -> 0.19101924 | N97: =L97/$L$110 -> 0.081440401 | O97: 750000000 | P97: =O97/$O$99 -> 0.1487505 | Q97: =O97/$O$110 -> 0.057932952 | R97: 1401000000 | S97: =R97/$R$99 -> 0.20691183 | T97: =R97/$R$110 -> 0.091270358
A98: Прочие долгосрочные обязательства | B98: 45000000 | C98: 46000000 | D98: 73000000 | E98: 51000000 | F98: =C98/B98-1 -> 0.022222222 | G98: =D98/C98-1 -> 0.58695652 | H98: =E98/D98-1 -> -0.30136986 | K98: Прочие долгосрочные обязательства | L98: 46000000 | M98: =L98/$L$99 -> 0.0081967213 | N98: =L98/$L$110 -> 0.0034946441 | O98: 73000000 | P98: =O98/$O$99 -> 0.014478382 | Q98: =O98/$O$110 -> 0.0056388074 | R98: 51000000 | S98: =R98/$R$99 -> 0.0075321223 | T98: =R98/$R$110 -> 0.0033224756
A99: Итого долгосрочные обязательства | B99: 4209000000 | C99: 5612000000 | D99: 5042000000 | E99: =SUM(E94:E98) -> 6771000000 | F99: =C99/B99-1 -> 0.33333333 | G99: =D99/C99-1 -> -0.10156807 | H99: =E99/D99-1 -> 0.34291948 | K99: Итого долгосрочные обязательства | L99: 5612000000 | N99: =L99/$L$110 -> 0.42634658 | O99: 5042000000 | Q99: =O99/$O$110 -> 0.38946393 | R99: =SUM(R94:R98) -> 6771000000 | T99: =R99/$R$110 -> 0.44110749
A100: =A43 -> Капитал | K100: =A100 -> Капитал
A101: Уставный капитал | B101: 1000000 | C101: 1000000 | D101: 1000000 | E101: 1000000 | F101: =C101/B101-1 -> 0 | G101: =D101/C101-1 -> 0 | H101: =E101/D101-1 -> 0 | K101: Уставный капитал | L101: 1000000 | M101: =L101/$L$109 -> 0.00021381227 | N101: =L101/$L$110 -> 7.5970523e-05 | O101: 1000000 | P101: =O101/$O$109 -> 0.00019421247 | Q101: =O101/$O$110 -> 7.7243936e-05 | R101: 1000000 | S101: =R101/$R$109 -> 0.00018224895 | T101: =R101/$R$110 -> 6.514658e-05
A102: Собственные акции, выкупленные у акционеров | B102: 0 | C102: 0 | D102: 0 | E102: -370000000 | F102: - | G102: - | H102: -1 | K102: Собственные акции, выкупленные у акционеров | L102: 0 | M102: =L102/$L$109 -> 0 | N102: =L102/$L$110 -> 0 | O102: 0 | P102: =O102/$O$109 -> 0 | Q102: =O102/$O$110 -> 0 | R102: -370000000 | S102: =R102/$R$109 -> -0.067432112 | T102: =R102/$R$110 -> -0.024104235
A103: Добавочный капитал | B103: 627000000 | C103: 633000000 | D103: 635000000 | E103: 1100000000 | F103: =C103/B103-1 -> 0.009569378 | G103: =D103/C103-1 -> 0.0031595577 | H103: =E103/D103-1 -> 0.73228346 | K103: Добавочный капитал | L103: 633000000 | M103: =L103/$L$109 -> 0.13534317 | N103: =L103/$L$110 -> 0.048089341 | O103: 635000000 | P103: =O103/$O$109 -> 0.12332492 | Q103: =O103/$O$110 -> 0.0490499 | R103: 1100000000 | S103: =R103/$R$109 -> 0.20047385 | T103: =R103/$R$110 -> 0.071661238
A104: Резерв курсовых разниц от пересчета иностранных операций | B104: - | C104: - | D104: -185000000 | E104: -66000000 | F104: - | G104: - | H104: =E104/D104-1 -> -0.64324324 | K104: Резерв курсовых разниц от пересчета иностранных операций | L104: - | M104: - | N104: - | O104: -185000000 | P104: =O104/$O$109 -> -0.035929307 | Q104: =O104/$O$110 -> -0.014290128 | R104: -66000000 | S104: =R104/$R$109 -> -0.012028431 | T104: =R104/$R$110 -> -0.0042996743
A105: Прочие фонды и резервы | B105: -322000000 | C105: -191000000 | D105: 31000000 | E105: 34000000 | F105: =C105/B105-1 -> -0.4068323 | G105: =D105/C105-1 -> -1.1623037 | H105: =E105/D105-1 -> 0.096774194 | K105: Прочие фонды и резервы | L105: -191000000 | M105: =L105/$L$109 -> -0.040838144 | N105: =L105/$L$110 -> -0.01451037 | O105: 31000000 | P105: =O105/$O$109 -> 0.0060205865 | Q105: =O105/$O$110 -> 0.002394562 | R105: 34000000 | S105: =R105/$R$109 -> 0.0061964644 | T105: =R105/$R$110 -> 0.0022149837
...

Sheet IS
A1: Отчет о прибылях и убытках МСФО, тыс.руб.
A2: Наименование показателя | B2: 2012 | C2: 2013 | D2: 2014 | E2: 2015 | F2: 2016 | G2: 2017 | H2: 2018 | I2: 2019 | J2: 2020 | L2: 2012 | M2: 2013 | N2: 2014 | O2: 2015 | P2: 2016 | Q2: 2017 | R2: 2018 | S2: 2019 | T2: 2020 | Z2: 1526000000 | AA2: 2428000000 | AB2: 2992000000
A3: Реализация нефти и газа, нефтепродуктов и нефтехимии | B3: =Z2+Z3 -> 3024000000 | C3: =AA2+AA3 -> 4624000000 | D3: =AB2+AB3 -> 5440000000 | E3: 5071000000 | F3: 4887000000 | G3: 5877000000 | H3: 8076000000 | I3: 8490000000 | J3: 5628000000 | L3: - | M3: =C3/B3-1 -> 0.52910053 | N3: =D3/C3-1 -> 0.17647059 | O3: =E3/D3-1 -> -0.067830882 | P3: =F3/E3-1 -> -0.036284756 | Q3: =G3/F3-1 -> 0.20257827 | R3: =H3/G3-1 -> 0.3741705 | S3: =I3/H3-1 -> 0.051263001 | T3: =J3/I3-1 -> -0.33710247 | W3: срарифм | X3: =AVERAGE(M6:S6) -> 0.17499941 | Z3: 1498000000 | AA3: 2196000000 | AB3: 2448000000
A4: Вспомогательные услуги и прочая реализация | B4: 42000000 | C4: 58000000 | D4: 75000000 | E4: 70000000 | F4: 75000000 | G4: 77000000 | H4: 80000000 | I4: 86000000 | J4: 77000000 | L4: - | M4: =C4/B4-1 -> 0.38095238 | N4: =D4/C4-1 -> 0.29310345 | O4: =E4/D4-1 -> -0.066666667 | P4: =F4/E4-1 -> 0.071428571 | Q4: =G4/F4-1 -> 0.026666667 | R4: =H4/G4-1 -> 0.038961039 | S4: =I4/H4-1 -> 0.075 | T4: =J4/I4-1 -> -0.10465116 | W4: cagr | X4: =(I6/B6)^(1/8)-1 -> 0.13779155
A5: Доход от совместных и ассоциированных предприятий | B5: 23000000 | C5: 12000000 | D5: -12000000 | E5: 9000000 | F5: 26000000 | G5: 60000000 | H5: 82000000 | I5: 100000000 | J5: 52000000 | L5: - | M5: =C5/B5-1 -> -0.47826087 | N5: =D5/C5-1 -> -2 | O5: =E5/D5-1 -> -1.75 | P5: =F5/E5-1 -> 1.8888889 | Q5: =G5/F5-1 -> 1.3076923 | R5: =H5/G5-1 -> 0.36666667 | S5: =I5/H5-1 -> 0.2195122 | T5: =J5/I5-1 -> -0.48
A6: Итого выручка от реализации и доход от совместных и ассоциированных предприятий | B6: 3089000000 | C6: 4694000000 | D6: 5503000000 | E6: 5150000000 | F6: 4988000000 | G6: 6014000000 | H6: 8238000000 | I6: 8676000000 | J6: 5757000000 | L6: - | M6: =C6/B6-1 -> 0.51958563 | N6: =D6/C6-1 -> 0.17234768 | O6: =E6/D6-1 -> -0.064146829 | P6: =F6/E6-1 -> -0.031456311 | Q6: =G6/F6-1 -> 0.20569366 | R6: =H6/G6-1 -> 0.36980379 | S6: =I6/H6-1 -> 0.053168245 | T6: =J6/I6-1 -> -0.33644537
A7: Затраты и расходы
A8: Производственные и операционные расходы | B8: -247000000 | C8: -389000000 | D8: -469000000 | E8: -575000000 | F8: -559000000 | G8: -607000000 | H8: -642000000 | I8: -715000000 | J8: -767000000 | L8: - | M8: =C8/B8-1 -> 0.57489879 | N8: =D8/C8-1 -> 0.20565553 | O8: =E8/D8-1 -> 0.22601279 | P8: =F8/E8-1 -> -0.027826087 | Q8: =G8/F8-1 -> 0.085867621 | R8: =H8/G8-1 -> 0.057660626 | S8: =I8/H8-1 -> 0.11370717 | T8: =J8/I8-1 -> 0.072727273
A9: Стоимость приобретенной нефти, газа, нефтепродуктов и услуг по переработке нефти | B9: -319000000 | C9: -432000000 | D9: -495000000 | E9: -530000000 | F9: -614000000 | G9: -837000000 | H9: -1099000000 | I9: -1566000000 | J9: -691000000 | L9: - | M9: =C9/B9-1 -> 0.35423197 | N9: =D9/C9-1 -> 0.14583333 | O9: =E9/D9-1 -> 0.070707071 | P9: =F9/E9-1 -> 0.15849057 | Q9: =G9/F9-1 -> 0.36319218 | R9: =H9/G9-1 -> 0.3130227 | S9: =I9/H9-1 -> 0.42493176 | T9: =J9/I9-1 -> -0.5587484
A10: Общехозяйственные и административные расходы | B10: -68000000 | C10: -111000000 | D10: -114000000 | E10: -130000000 | F10: -129000000 | G10: -172000000 | H10: -167000000 | I10: -200000000 | J10: -127000000 | L10: - | M10: =C10/B10-1 -> 0.63235294 | N10: =D10/C10-1 -> 0.027027027 | O10: =E10/D10-1 -> 0.14035088 | P10: =F10/E10-1 -> -0.0076923077 | Q10: =G10/F10-1 -> 0.33333333 | R10: =H10/G10-1 -> -0.029069767 | S10: =I10/H10-1 -> 0.19760479 | T10: =J10/I10-1 -> -0.365
A11: Тарифы за пользование нефтепроводом и расходы на транспортировку | B11: -241000000 | C11: -392000000 | D11: -471000000 | E11: -542000000 | F11: -575000000 | G11: -596000000 | H11: -638000000 | I11: -733000000 | J11: -661000000 | L11: - | M11: =C11/B11-1 -> 0.62655602 | N11: =D11/C11-1 -> 0.20153061 | O11: =E11/D11-1 -> 0.1507431 | P11: =F11/E11-1 -> 0.060885609 | Q11: =G11/F11-1 -> 0.036521739 | R11: =H11/G11-1 -> 0.070469799 | S11: =I11/H11-1 -> 0.14890282 | T11: =J11/I11-1 -> -0.098226467
A12: Затраты, связанные с разведкой запасов нефти и газа | B12: -23000000 | C12: -17000000 | D12: -19000000 | E12: -13000000 | F12: -14000000 | G12: -15000000 | H12: -11000000 | I12: -11000000 | J12: -15000000 | L12: - | M12: =C12/B12-1 -> -0.26086957 | N12: =D12/C12-1 -> 0.11764706 | O12: =E12/D12-1 -> -0.31578947 | P12: =F12/E12-1 -> 0.076923077 | Q12: =G12/F12-1 -> 0.071428571 | R12: =H12/G12-1 -> -0.26666667 | S12: =I12/H12-1 -> 0 | T12: =J12/I12-1 -> 0.36363636
A13: Износ, истощение и амортизация | B13: -206000000 | C13: -392000000 | D13: -464000000 | E13: -450000000 | F13: -482000000 | G13: -586000000 | H13: -635000000 | I13: -687000000 | J13: -663000000 | L13: - | M13: =C13/B13-1 -> 0.90291262 | N13: =D13/C13-1 -> 0.18367347 | O13: =E13/D13-1 -> -0.030172414 | P13: =F13/E13-1 -> 0.071111111 | Q13: =G13/F13-1 -> 0.21576763 | R13: =H13/G13-1 -> 0.083617747 | S13: =I13/H13-1 -> 0.081889764 | T13: =J13/I13-1 -> -0.034934498
A14: Налоги, кроме налога на прибыль | B14: -672000000 | C14: -1024000000 | D14: -1195000000 | E14: -1277000000 | F14: -1296000000 | G14: -1919000000 | H14: -2701000000 | I14: -2666000000 | J14: -2121000000 | L14: - | M14: =C14/B14-1 -> 0.52380952 | N14: =D14/C14-1 -> 0.16699219 | O14: =E14/D14-1 -> 0.068619247 | P14: =F14/E14-1 -> 0.014878622 | Q14: =G14/F14-1 -> 0.48070988 | R14: =H14/G14-1 -> 0.40750391 | S14: =I14/H14-1 -> -0.012958164 | T14: =J14/I14-1 -> -0.20442611
A15: Экспортная пошлина | B15: -901000000 | C15: -1382000000 | D15: -1683000000 | E15: -925000000 | F15: -657000000 | G15: -658000000 | H15: -1061000000 | I15: -793000000 | J15: -334000000 | L15: - | M15: =C15/B15-1 -> 0.53385128 | N15: =D15/C15-1 -> 0.21780029 | O15: =E15/D15-1 -> -0.45038622 | P15: =F15/E15-1 -> -0.28972973 | Q15: =G15/F15-1 -> 0.00152207 | R15: =H15/G15-1 -> 0.61246201 | S15: =I15/H15-1 -> -0.25259189 | T15: =J15/I15-1 -> -0.57881463
A16: Итого затраты и расходы | B16: -2677000000 | C16: -4139000000 | D16: -4910000000 | E16: -4442000000 | F16: -4326000000 | G16: -5390000000 | H16: -6954000000 | I16: -7371000000 | J16: -5379000000 | L16: - | M16: =C16/B16-1 -> 0.54613373 | N16: =D16/C16-1 -> 0.18627688 | O16: =E16/D16-1 -> -0.095315682 | P16: =F16/E16-1 -> -0.026114363 | Q16: =G16/F16-1 -> 0.24595469 | R16: =H16/G16-1 -> 0.29016698 | S16: =I16/H16-1 -> 0.059965487 | T16: =J16/I16-1 -> -0.27024827
A17: Операционная прибыль | B17: 412000000 | C17: 555000000 | D17: 593000000 | E17: 708000000 | F17: 662000000 | G17: 624000000 | H17: 1284000000 | I17: 1305000000 | J17: 378000000 | L17: - | M17: =C17/B17-1 -> 0.34708738 | N17: =D17/C17-1 -> 0.068468468 | O17: =E17/D17-1 -> 0.19392917 | P17: =F17/E17-1 -> -0.064971751 | Q17: =G17/F17-1 -> -0.057401813 | R17: =H17/G17-1 -> 1.0576923 | S17: =I17/H17-1 -> 0.01635514 | T17: =J17/I17-1 -> -0.71034483
A18: Финансовые доходы | B18: 24000000 | C18: 21000000 | D18: 30000000 | E18: 55000000 | F18: 91000000 | G18: 107000000 | H18: 122000000 | I18: 143000000 | J18: 95000000 | L18: - | M18: =C18/B18-1 -> -0.125 | N18: =D18/C18-1 -> 0.42857143 | O18: =E18/D18-1 -> 0.83333333 | P18: =F18/E18-1 -> 0.65454545 | Q18: =G18/F18-1 -> 0.17582418 | R18: =H18/G18-1 -> 0.14018692 | S18: =I18/H18-1 -> 0.17213115 | T18: =J18/I18-1 -> -0.33566434
A19: Финансовые расходы | B19: -15000000 | C19: -56000000 | D19: -219000000 | E19: -269000000 | F19: -193000000 | G19: -225000000 | H19: -290000000 | I19: -227000000 | J19: -220000000 | L19: - | M19: =C19/B19-1 -> 2.7333333 | N19: =D19/C19-1 -> 2.9107143 | O19: =E19/D19-1 -> 0.2283105 | P19: =F19/E19-1 -> -0.28252788 | Q19: =G19/F19-1 -> 0.16580311 | R19: =H19/G19-1 -> 0.28888889 | S19: =I19/H19-1 -> -0.21724138 | T19: =J19/I19-1 -> -0.030837004
... A22: Курсовые разницы | B22: 11000000 | C22: -71000000 | D22: 64000000 | E22: 86000000 | F22: -70000000 | G22: 3000000 | H22: 107000000 | I22: 64000000 | J22: -163000000 | L22: - | M22: =C22/B22-1 -> -7.4545455 | N22: =D22/C22-1 -> -1.9014085 | O22: =E22/D22-1 -> 0.34375 | P22: =F22/E22-1 -> -1.8139535 | Q22: =G22/F22-1 -> -1.0428571 | R22: =H22/G22-1 -> 34.666667 | S22: =I22/H22-1 -> -0.40186916 | T22: =J22/I22-1 -> -3.546875
A23: Реализованные курсовые разницы по инструментам управления курсовым риском | B23: - | C23: - | D23: - | E23: -123000000 | F23: -147000000 | G23: -146000000 | H23: -146000000 | I23: -146000000 | J23: 2000000 | L23: - | M23: - | N23: - | O23: - | P23: =F23/E23-1 -> 0.19512195 | Q23: =G23/F23-1 -> -0.0068027211 | R23: =H23/G23-1 -> 0 | S23: =I23/H23-1 -> 0 | T23: =J23/I23-1 -> -1.0136986
A24: Прибыль до налогообложения | B24: 469000000 | C24: 632000000 | D24: 478000000 | E24: 460000000 | F24: 317000000 | G24: 395000000 | H24: 832000000 | I24: 994000000 | J24: 162000000 | L24: - | M24: =C24/B24-1 -> 0.34754797 | N24: =D24/C24-1 -> -0.24367089 | O24: =E24/D24-1 -> -0.037656904 | P24: =F24/E24-1 -> -0.31086957 | Q24: =G24/F24-1 -> 0.24605678 | R24: =H24/G24-1 -> 1.1063291 | S24: =I24/H24-1 -> 0.19471154 | T24: =J24/I24-1 -> -0.83702213
A25: Налог на прибыль | B25: -104000000 | C25: -81000000 | D25: -128000000 | E25: -104000000 | F25: -116000000 | G25: -98000000 | H25: -183000000 | I25: -192000000 | J25: 19000000 | L25: - | M25: =C25/B25-1 -> -0.22115385 | N25: =D25/C25-1 -> 0.58024691 | O25: =E25/D25-1 -> -0.1875 | P25: =F25/E25-1 -> 0.11538462 | Q25: =G25/F25-1 -> -0.15517241 | R25: =H25/G25-1 -> 0.86734694 | S25: =I25/H25-1 -> 0.049180328 | T25: =J25/I25-1 -> -1.0989583
A26: Чистая прибыль | B26: 365000000 | C26: 551000000 | D26: 350000000 | E26: 356000000 | F26: 201000000 | G26: 297000000 | H26: 649000000 | I26: 802000000 | J26: 181000000 | L26: - | M26: =C26/B26-1 -> 0.50958904 | N26: =D26/C26-1 -> -0.36479129 | O26: =E26/D26-1 -> 0.017142857 | P26: =F26/E26-1 -> -0.43539326 | Q26: =G26/F26-1 -> 0.47761194 | R26: =H26/G26-1 -> 1.1851852 | S26: =I26/H26-1 -> 0.2357473 | T26: =J26/I26-1 -> -0.77431421
I27: =I26/H26-1 -> 0.2357473
A29: Наименование показателя | B29: 2012 | C29: 2013 | D29: 2014 | E29: 2015 | F29: 2016 | G29: 2017 | H29: 2018 | I29: 2019 | J29: 2020
A30: Реализация нефти и газа, нефтепродуктов и нефтехимии | B30: =B3/$B$6 -> 0.97895759 | C30: =C3/$C$6 -> 0.98508735 | D30: =D3/$D$6 -> 0.9885517 | E30: =E3/$E$6 -> 0.98466019 | F30: =F3/$F$6 -> 0.9797514 | G30: =G3/$G$6 -> 0.97721982 | H30: =H3/$H$6 -> 0.98033503 | I30: =I3/$I$6 -> 0.97856155 | J30: =J3/$J$6 -> 0.9775925
A31: Вспомогательные услуги и прочая реализация | B31: =B4/$B$6 -> 0.013596633 | C31: =C4/$C$6 -> 0.012356199 | D31: =D4/$D$6 -> 0.01362893 | E31: =E4/$E$6 -> 0.013592233 | F31: =F4/$F$6 -> 0.015036087 | G31: =G4/$G$6 -> 0.012803459 | H31: =H4/$H$6 -> 0.0097110949 | I31: =I4/$I$6 -> 0.009912402 | J31: =J4/$J$6 -> 0.013375022
A32: Доход от совместных и ассоциированных предприятий | B32: =B5/$B$6 -> 0.0074457753 | C32: =C5/$C$6 -> 0.002556455 | D32: =D5/$D$6 -> -0.0021806287 | E32: =E5/$E$6 -> 0.0017475728 | F32: =F5/$F$6 -> 0.00521251 | G32: =G5/$G$6 -> 0.009976721 | H32: =H5/$H$6 -> 0.0099538723 | I32: =I5/$I$6 -> 0.011526049 | J32: =J5/$J$6 -> 0.0090324822
A33: Итого выручка от реализации и доход от совместных и ассоциированных предприятий | B33: =B6/$B$6 -> 1 | C33: =C6/$C$6 -> 1 | D33: =D6/$D$6 -> 1 | E33: =E6/$E$6 -> 1 | F33: =F6/$F$6 -> 1 | G33: =G6/$G$6 -> 1 | H33: =H6/$H$6 -> 1 | I33: =I6/$I$6 -> 1 | J33: =J6/$J$6 -> 1
A34: Затраты и расходы
A35: Производственные и операционные расходы | B35: =ABS(B8/$B$6) -> 0.079961152 | C35: =ABS(C8/$C$6) -> 0.082871751 | D35: =ABS(D8/$D$6) -> 0.08522624 | E35: =ABS(E8/$E$6) -> 0.11165049 | F35: =ABS(F8/$F$6) -> 0.11206897 | G35: =ABS(G8/$G$6) -> 0.10093116 | H35: =ABS(H8/$H$6) -> 0.077931537 | I35: =ABS(I8/$I$6) -> 0.082411249 | J35: =ABS(J8/$J$6) -> 0.13322911
A36: Стоимость приобретенной нефти, газа, нефтепродуктов и услуг по переработке нефти | B36: =ABS(B9/$B$6) -> 0.10326967 | C36: =ABS(C9/$C$6) -> 0.092032382 | D36: =ABS(D9/$D$6) -> 0.089950936 | E36: =ABS(E9/$E$6) -> 0.10291262 | F36: =ABS(F9/$F$6) -> 0.12309543 | G36: =ABS(G9/$G$6) -> 0.13917526 | H36: =ABS(H9/$H$6) -> 0.13340617 | I36: =ABS(I9/$I$6) -> 0.18049793 | J36: =ABS(J9/$J$6) -> 0.12002779
A37: Общехозяйственные и административные расходы | B37: =ABS(B10/$B$6) -> 0.022013597 | C37: =ABS(C10/$C$6) -> 0.023647209 | D37: =ABS(D10/$D$6) -> 0.020715973 | E37: =ABS(E10/$E$6) -> 0.025242718 | F37: =ABS(F10/$F$6) -> 0.025862069 | G37: =ABS(G10/$G$6) -> 0.028599933 | H37: =ABS(H10/$H$6) -> 0.020271911 | I37: =ABS(I10/$I$6) -> 0.023052098 | J37: =ABS(J10/$J$6) -> 0.022060101
A38: Тарифы за пользование нефтепроводом и расходы на транспортировку | B38: =ABS(B11/$B$6) -> 0.078018776 | C38: =ABS(C11/$C$6) -> 0.083510865 | D38: =ABS(D11/$D$6) -> 0.085589678 | E38: =ABS(E11/$E$6) -> 0.10524272 | F38: =ABS(F11/$F$6) -> 0.11527666 | G38: =ABS(G11/$G$6) -> 0.099102095 | H38: =ABS(H11/$H$6) -> 0.077445982 | I38: =ABS(I11/$I$6) -> 0.084485938 | J38: =ABS(J11/$J$6) -> 0.11481674
A39: Затраты, связанные с разведкой запасов нефти и газа | B39: =ABS(B12/$B$6) -> 0.0074457753 | C39: =ABS(C12/$C$6) -> 0.0036216447 | D39: =ABS(D12/$D$6) -> 0.0034526622 | E39: =ABS(E12/$E$6) -> 0.0025242718 | F39: =ABS(F12/$F$6) -> 0.0028067362 | G39: =ABS(G12/$G$6) -> 0.0024941802 | H39: =ABS(H12/$H$6) -> 0.0013352756 | I39: =ABS(I12/$I$6) -> 0.0012678654 | J39: =ABS(J12/$J$6) -> 0.0026055237
A40: Износ, истощение и амортизация | B40: =ABS(B13/$B$6) -> 0.066688249 | C40: =ABS(C13/$C$6) -> 0.083510865 | D40: =ABS(D13/$D$6) -> 0.084317645 | E40: =ABS(E13/$E$6) -> 0.087378641 | F40: =ABS(F13/$F$6) -> 0.096631917 | G40: =ABS(G13/$G$6) -> 0.097439308 | H40: =ABS(H13/$H$6) -> 0.077081816 | I40: =ABS(I13/$I$6) -> 0.079183956 | J40: =ABS(J13/$J$6) -> 0.11516415
A41: Налоги, кроме налога на прибыль | B41: =ABS(B14/$B$6) -> 0.21754613 | C41: =ABS(C14/$C$6) -> 0.21815083 | D41: =ABS(D14/$D$6) -> 0.21715428 | E41: =ABS(E14/$E$6) -> 0.24796117 | F41: =ABS(F14/$F$6) -> 0.25982358 | G41: =ABS(G14/$G$6) -> 0.31908879 | H41: =ABS(H14/$H$6) -> 0.32787084 | I41: =ABS(I14/$I$6) -> 0.30728446 | J41: =ABS(J14/$J$6) -> 0.36842105
A42: Экспортная пошлина | B42: =ABS(B15/$B$6) -> 0.29168016 | C42: =ABS(C15/$C$6) -> 0.29441841 | D42: =ABS(D15/$D$6) -> 0.30583318 | E42: =ABS(E15/$E$6) -> 0.17961165 | F42: =ABS(F15/$F$6) -> 0.13171612 | G42: =ABS(G15/$G$6) -> 0.10941137 | H42: =ABS(H15/$H$6) -> 0.1287934 | I42: =ABS(I15/$I$6) -> 0.091401568 | J42: =ABS(J15/$J$6) -> 0.058016328
A43: Итого затраты и расходы | B43: =ABS(B16/$B$6) -> 0.8666235 | C43: =ABS(C16/$C$6) -> 0.88176395 | D43: =ABS(D16/$D$6) -> 0.8922406 | E43: =ABS(E16/$E$6) -> 0.86252427 | F43: =ABS(F16/$F$6) -> 0.86728148 | G43: =ABS(G16/$G$6) -> 0.8962421 | H43: =ABS(H16/$H$6) -> 0.84413693 | I43: =ABS(I16/$I$6) -> 0.84958506 | J43: =ABS(J16/$J$6) -> 0.9343408
A44: Операционная прибыль | B44: =ABS(B17/$B$6) -> 0.1333765 | C44: =ABS(C17/$C$6) -> 0.11823605 | D44: =ABS(D17/$D$6) -> 0.1077594 | E44: =ABS(E17/$E$6) -> 0.13747573 | F44: =ABS(F17/$F$6) -> 0.13271852 | G44: =ABS(G17/$G$6) -> 0.1037579 | H44: =ABS(H17/$H$6) -> 0.15586307 | I44: =ABS(I17/$I$6) -> 0.15041494 | J44: =ABS(J17/$J$6) -> 0.065659197
A45: Финансовые доходы | B45: =ABS(B18/$B$6) -> 0.0077695047 | C45: =ABS(C18/$C$6) -> 0.0044737963 | D45: =ABS(D18/$D$6) -> 0.0054515719 | E45: =ABS(E18/$E$6) -> 0.010679612 | F45: =ABS(F18/$F$6) -> 0.018243785 | G45: =ABS(G18/$G$6) -> 0.017791819 | H45: =ABS(H18/$H$6) -> 0.01480942 | I45: =ABS(I18/$I$6) -> 0.01648225 | J45: =ABS(J18/$J$6) -> 0.01650165
A46: Финансовые расходы | B46: =ABS(B19/$B$6) -> 0.0048559404 | C46: =ABS(C19/$C$6) -> 0.011930124 | D46: =ABS(D19/$D$6) -> 0.039796475 | E46: =ABS(E19/$E$6) -> 0.05223301 | F46: =ABS(F19/$F$6) -> 0.038692863 | G46: =ABS(G19/$G$6) -> 0.037412704 | H46: =ABS(H19/$H$6) -> 0.035202719 | I46: =ABS(I19/$I$6) -> 0.026164131 | J46: =ABS(J19/$J$6) -> 0.038214348
... A49: Курсовые разницы | B49: =ABS(B22/$B$6) -> 0.003561023 | C49: =ABS(C22/$C$6) -> 0.015125692 | D49: =ABS(D22/$D$6) -> 0.01163002 | E49: =ABS(E22/$E$6) -> 0.016699029 | F49: =ABS(F22/$F$6) -> 0.014033681 | G49: =ABS(G22/$G$6) -> 0.00049883605 | H49: =ABS(H22/$H$6) -> 0.012988589 | I49: =ABS(I22/$I$6) -> 0.0073766713 | J49: =ABS(J22/$J$6) -> 0.028313358
A50: Реализованные курсовые разницы по инструментам управления курсовым риском | B50: - | C50: - | D50: - | E50: =ABS(E23/$E$6) -> 0.023883495 | F50: =ABS(F23/$F$6) -> 0.02947073 | G50: =ABS(G23/$G$6) -> 0.024276688 | H50: =ABS(H23/$H$6) -> 0.017722748 | I50: =ABS(I23/$I$6) -> 0.016828031 | J50: =ABS(J23/$J$6) -> 0.00034740316
A51: Прибыль до налогообложения | B51: =ABS(B24/$B$6) -> 0.15182907 | C51: =ABS(C24/$C$6) -> 0.13463997 | D51: =ABS(D24/$D$6) -> 0.086861712 | E51: =ABS(E24/$E$6) -> 0.089320388 | F51: =ABS(F24/$F$6) -> 0.063552526 | G51: =ABS(G24/$G$6) -> 0.06568008 | H51: =ABS(H24/$H$6) -> 0.10099539 | I51: =ABS(I24/$I$6) -> 0.11456893 | J51: =ABS(J24/$J$6) -> 0.028139656
A52: Налог на прибыль | B52: =ABS(B25/$B$6) -> 0.033667854 | C52: =ABS(C25/$C$6) -> 0.017256072 | D52: =ABS(D25/$D$6) -> 0.02326004 | E52: =ABS(E25/$E$6) -> 0.020194175 | F52: =ABS(F25/$F$6) -> 0.023255814 | G52: =ABS(G25/$G$6) -> 0.016295311 | H52: =ABS(H25/$H$6) -> 0.02221413 | I52: =ABS(I25/$I$6) -> 0.022130014 | J52: =ABS(J25/$J$6) -> 0.00330033
A53: Чистая прибыль | B53: =ABS(B26/$B$6) -> 0.11816122 | C53: =ABS(C26/$C$6) -> 0.11738389 | D53: =ABS(D26/$D$6) -> 0.063601672 | E53: =ABS(E26/$E$6) -> 0.069126214 | F53: =ABS(F26/$F$6) -> 0.040296712 | G53: =ABS(G26/$G$6) -> 0.049384769 | H53: =ABS(H26/$H$6) -> 0.078781258 | I53: =ABS(I26/$I$6) -> 0.092438912 | J53: =ABS(J26/$J$6) -> 0.031439986
A65: Наименование показателя | B65: 2017 | C65: 2018 | D65: 2019 | E65: 2020 | F65: 2018 | G65: 2019 | H65: 2020
A66: Реализация нефти и газа, нефтепродуктов и нефтехимии | B66: 5877000000 | C66: 8076000000 | D66: 8490000000 | E66: 5628000000 | F66: 0.3741705 | G66: 0.051263001 | H66: -0.33710247
A67: Вспомогательные услуги и прочая реализация | B67: 77000000 | C67: 80000000 | D67: 86000000 | E67: 77000000 | F67: 0.038961039 | G67: 0.075 | H67: -0.10465116
A68: Доход от совместных и ассоциированных предприятий | B68: 60000000 | C68: 82000000 | D68: 100000000 | E68: 52000000 | F68: 0.36666667 | G68: 0.2195122 | H68: -0.48
A69: Итого выручка от реализации и доход от совместных и ассоциированных предприятий | B69: 6014000000 | C69: 8238000000 | D69: 8676000000 | E69: 5757000000 | F69: 0.36980379 | G69: 0.053168245 | H69: -0.33644537
A70: Затраты и расходы
A71: Производственные и операционные расходы | B71: -607000000 | C71: -642000000 | D71: -715000000 | E71: -767000000 | F71: 0.057660626 | G71: 0.11370717 | H71: 0.072727273
A72: Стоимость приобретенной нефти, газа, нефтепродуктов и услуг по переработке нефти | B72: -837000000 | C72: -1099000000 | D72: -1566000000 | E72: -691000000 | F72: 0.3130227 | G72: 0.42493176 | H72: -0.5587484
A73: Общехозяйственные и административные расходы | B73: -172000000 | C73: -167000000 | D73: -200000000 | E73: -127000000 | F73: -0.029069767 | G73: 0.19760479 | H73: -0.365
A74: Тарифы за пользование нефтепроводом и расходы на транспортировку | B74: -596000000 | C74: -638000000 | D74: -733000000 | E74: -661000000 | F74: 0.070469799 | G74: 0.14890282 | H74: -0.098226467
A75: Затраты, связанные с разведкой запасов нефти и газа | B75: -15000000 | C75: -11000000 | D75: -11000000 | E75: -15000000 | F75: -0.26666667 | G75: 0 | H75: 0.36363636
A76: Износ, истощение и амортизация | B76: -586000000 | C76: -635000000 | D76: -687000000 | E76: -663000000 | F76: 0.083617747 | G76: 0.081889764 | H76: -0.034934498
A77: Налоги, кроме налога на прибыль | B77: -1919000000 | C77: -2701000000 | D77: -2666000000 | E77: -2121000000 | F77: 0.40750391 | G77: -0.012958164 | H77: -0.20442611
A78: Экспортная пошлина | B78: -658000000 | C78: -1061000000 | D78: -793000000 | E78: -334000000 | F78: 0.61246201 | G78: -0.25259189 | H78: -0.57881463
A79: Итого затраты и расходы | B79: -5390000000 | C79: -6954000000 | D79: -7371000000 | E79: -5379000000 | F79: 0.29016698 | G79: 0.059965487 | H79: -0.27024827
A80: Операционная прибыль | B80: 624000000 | C80: 1284000000 | D80: 1305000000 | E80: 378000000 | F80: 1.0576923 | G80: 0.01635514 | H80: -0.71034483
A81: Финансовые доходы | B81: 107000000 | C81: 122000000 | D81: 143000000 | E81: 95000000 | F81: 0.14018692 | G81: 0.17213115 | H81: -0.33566434
A82: Финансовые расходы | B82: -225000000 | C82: -290000000 | D82: -227000000 | E82: -220000000 | F82: 0.28888889 | G82: -0.21724138 | H82: -0.030837004
... A89: Чистая прибыль | B89: 297000000 | C89: 649000000 | D89: 802000000 | E89: 181000000 | F89: 1.1851852 | G89: 0.2357473 | H89: -0.77431421
B102: 2018 | D102: 2019 | F102: 2020
A103: Наименование показателя | B103: Удельный вес | C103: Тпр | D103: Удельный вес | E103: Тпр | F103: Удельный вес | G103: Тпр
A104: Реализация нефти и газа, нефтепродуктов и нефтехимии | B104: =H30 -> 0.98033503 | C104: =R3 -> 0.3741705 | D104: =I30 -> 0.97856155 | E104: =S3 -> 0.051263001 | F104: =J30 -> 0.9775925 | G104: =T3 -> -0.33710247
A105: Вспомогательные услуги и прочая реализация | B105: =H31 -> 0.0097110949 | C105: =R4 -> 0.038961039 | D105: =I31 -> 0.009912402 | E105: =S4 -> 0.075 | F105: =J31 -> 0.013375022 | G105: =T4 -> -0.10465116
A106: Доход от совместных и ассоциированных предприятий | B106: =H32 -> 0.0099538723 | C106: =R5 -> 0.36666667 | D106: =I32 -> 0.011526049 | E106: =S5 -> 0.2195122 | F106: =J32 -> 0.0090324822 | G106: =T5 -> -0.48
A107: Итого выручка от реализации и доход от совместных и ассоциированных предприятий | B107: =H33 -> 1 | C107: =R6 -> 0.36980379 | D107: =I33 -> 1 | E107: =S6 -> 0.053168245 | F107: =J33 -> 1 | G107: =T6 -> -0.33644537
A108: Затраты и расходы
A109: Производственные и операционные расходы | B109: =H35 -> 0.077931537 | C109: =R8 -> 0.057660626 | D109: =I35 -> 0.082411249 | E109: =S8 -> 0.11370717 | F109: =J35 -> 0.13322911 | G109: =T8 -> 0.072727273
A110: Стоимость приобретенной нефти, газа, нефтепродуктов и услуг по переработке нефти | B110: =H36 -> 0.13340617 | C110: =R9 -> 0.3130227 | D110: =I36 -> 0.18049793 | E110: =S9 -> 0.42493176 | F110: =J36 -> 0.12002779 | G110: =T9 -> -0.5587484
A111: Общехозяйственные и административные расходы | B111: =H37 -> 0.020271911 | C111: =R10 -> -0.029069767 | D111: =I37 -> 0.023052098 | E111: =S10 -> 0.19760479 | F111: =J37 -> 0.022060101 | G111: =T10 -> -0.365
A112: Тарифы за пользование нефтепроводом и расходы на транспортировку | B112: =H38 -> 0.077445982 | C112: =R11 -> 0.070469799 | D112: =I38 -> 0.084485938 | E112: =S11 -> 0.14890282 | F112: =J38 -> 0.11481674 | G112: =T11 -> -0.098226467
A113: Затраты, связанные с разведкой запасов нефти и газа | B113: =H39 -> 0.0013352756 | C113: =R12 -> -0.26666667 | D113: =I39 -> 0.0012678654 | E113: =S12 -> 0 | F113: =J39 -> 0.0026055237 | G113: =T12 -> 0.36363636
A114: Износ, истощение и амортизация | B114: =H40 -> 0.077081816 | C114: =R13 -> 0.083617747 | D114: =I40 -> 0.079183956 | E114: =S13 -> 0.081889764 | F114: =J40 -> 0.11516415 | G114: =T13 -> -0.034934498
A115: Налоги, кроме налога на прибыль | B115: =H41 -> 0.32787084 | C115: =R14 -> 0.40750391 | D115: =I41 -> 0.30728446 | E115: =S14 -> -0.012958164 | F115: =J41 -> 0.36842105 | G115: =T14 -> -0.20442611
A116: Экспортная пошлина | B116: =H42 -> 0.1287934 | C116: =R15 -> 0.61246201 | D116: =I42 -> 0.091401568 | E116: =S15 -> -0.25259189 | F116: =J42 -> 0.058016328 | G116: =T15 -> -0.57881463
A117: Итого затраты и расходы | B117: =H43 -> 0.84413693 | C117: =R16 -> 0.29016698 | D117: =I43 -> 0.84958506 | E117: =S16 -> 0.059965487 | F117: =J43 -> 0.9343408 | G117: =T16 -> -0.27024827
A118: Операционная прибыль | B118: =H44 -> 0.15586307 | C118: =R17 -> 1.0576923 | D118: =I44 -> 0.15041494 | E118: =S17 -> 0.01635514 | F118: =J44 -> 0.065659197 | G118: =T17 -> -0.71034483
A119: Финансовые доходы | B119: =H45 -> 0.01480942 | C119: =R18 -> 0.14018692 | D119: =I45 -> 0.01648225 | E119: =S18 -> 0.17213115 | F119: =J45 -> 0.01650165 | G119: =T18 -> -0.33566434
A120: Финансовые расходы | B120: =H46 -> 0.035202719 | C120: =R19 -> 0.28888889 | D120: =I46 -> 0.026164131 | E120: =S19 -> -0.21724138 | F120: =J46 -> 0.038214348 | G120: =T19 -> -0.030837004
... A127: Чистая прибыль | B127: =H53 -> 0.078781258 | C127: =R26 -> 1.1851852 | D127: =I53 -> 0.092438912 | E127: =S26 -> 0.2357473 | F127: =J53 -> 0.031439986 | G127: =T26 -> -0.77431421

Sheet сок+фин.устойчивость
A1: Показатель | B1: 2018 | C1: 2019 | D1: 2020
A2: Собственный оборотный капитал (СОК)=оборотные активы-текущие пассивы
A3: Оборотные активы | B3: =BS!H12 -> 3022000000 | C3: =BS!I12 -> 2396000000 | D3: =BS!J12 -> 2922000000
A4: Текущие пассивы | B4: =BS!H35 -> 2874000000 | C4: =BS!I35 -> 2755000000 | D4: =BS!J35 -> 3092000000
A5: СОК | B5: =B3-B4 -> 148000000 | C5: =C3-C4 -> -359000000 | D5: =D3-D4 -> -170000000
A6: Перманентный капитал (ПК) = Собственный оборотный капитал (СОК) + Долгосрочные обязательства (ДО)
A7: Долгосрочные обязательства | B7: =BS!H42 -> 5612000000 | C7: =BS!I42 -> 5042000000 | D7: =BS!J42 -> 6771000000
A8: ПК | B8: =B5+B7 -> 5760000000 | C8: =C5+C7 -> 4683000000 | D8: =D5+D7 -> 6601000000
A9: Общая величина основных источников формирования запасов (ОИФ) = Собственный оборотный капитал (СОК) + Долгосрочные обязательства (ДО) + Краткосрочные обязательства (КО)
A10: Текущие пассивы | B10: =B4 -> 2874000000 | C10: =C4 -> 2755000000 | D10: =D4 -> 3092000000
A11: ОИФ | B11: =B8+B10 -> 8634000000 | C11: =C5+C7+C10 -> 7438000000 | D11: =D5+D7+D10 -> 9693000000
A14: Показатель | B14: 2018 | C14: 2019 | D14: 2020
A15: Δ СОС = СОК – ПЗ
A16: Запасы | B16: =BS!H10 -> 393000000 | C16: =BS!I10 -> 438000000 | D16: =BS!J10 -> 361000000
A17: Δ СОК | B17: =B5-B16 -> -245000000 | C17: =C5-C16 -> -797000000 | D17: =D5-D16 -> -531000000
A18: Δ ПК = ПК – ПЗ
A19: Δ ПК | B19: =B8-B16 -> 5367000000 | C19: =C8-C16 -> 4245000000 | D19: =D8-D16 -> 6240000000
A20: Δ ОИФ = ОИ – ПЗ
A21: Δ ОИФ | B21: =B11-B16 -> 8241000000 | C21: =C11-C16 -> 7000000000 | D21: =D11-D16 -> 9332000000
A23: Δ СОК ≥ 0 (т.е. ПЗ ≤ СОК) – абсолютная финансовая устойчивость Δ СОК <0, Δ ПК ≥ 0 (т.е. СОК ≤ ПЗ ≤ ДИФ) – нормальная финансовая устойчивость Δ СОК <0, Δ ПК < 0, Δ ОИ ≥ 0 (т.е. ДИФ ≤ ПЗ ≤ ОИФ) – неустойчивое финансовое состояние Δ СОК <0, Δ ПК < 0, Δ ОИ < 0 (т.е. ОИФ ≤ ПЗ) – кризисное финансовое состояние
A26: Финансовая устойчивость | B26: Нормальная | C26: Нормальная | D26: Нормальная

Sheet фин.коэффициенты
A1: Показатель | B1: Рекомендуемое значение | C1: 2018 | D1: 2019 | E1: 2020
A2: К. фининансовой независимости (автономии)=СК/А
A3: Капитал | B3: - | C3: =BS!H52 -> 4677000000 | D3: =BS!I52 -> 5149000000 | E3: =BS!J52 -> 5487000000
A4: Активы | B4: - | C4: =BS!H25 -> 13163000000 | D4: =BS!I25 -> 12946000000 | E4: =BS!J25 -> 15350000000
A5: Кфн | B5: >0,5 | C5: =C3/C4 -> 0.35531414 | D5: =D3/D4 -> 0.39772903 | E5: =E3/E4 -> 0.35745928
A6: Значение показателя ниже 0,5, что говорит о высокой финансовой зависимости и возможном наличии проблем с платежеспособностью
A7: К. зависимости=О/А
A8: Долгосрочные обязательства | B8: - | C8: =BS!C99 -> 5612000000 | D8: =BS!D99 -> 5042000000 | E8: =BS!E99 -> 6771000000
A9: Краткочрочные обязательства | B9: - | C9: =BS!C92 -> 2874000000 | D9: =BS!D92 -> 2755000000 | E9: =BS!E92 -> 3092000000
A10: Активы | B10: - | C10: =C4 -> 13163000000 | D10: =D4 -> 12946000000 | E10: =E4 -> 15350000000
A11: Кз | B11: <0,8 | C11: =(C8+C9)/C10 -> 0.64468586 | D11: =(D8+D9)/D10 -> 0.60227097 | E11: =(E8+E9)/E10 -> 0.64254072
A12: Заемные средства составляют примерно 60-65% в структуре капитала, что является на 10-15% выше оптимального значения, но находится в пределах нормы
A13: К. соотношения заемного и собственного капитала=ЗК/СК
A14: =A8 -> Долгосрочные обязательства | B14: - | C14: =C8 -> 5612000000 | D14: =D8 -> 5042000000 | E14: =E8 -> 6771000000
A15: =A9 -> Краткочрочные обязательства | B15: - | C15: =C9 -> 2874000000 | D15: =D9 -> 2755000000 | E15: =E9 -> 3092000000
A16: Капитал | B16: - | C16: =BS!C109 -> 4677000000 | D16: =BS!D109 -> 5149000000 | E16: =BS!E109 -> 5487000000
A17: Ксф | B17: <0,7 | C17: =(C14+C15)/C16 -> 1.8144109 | D17: =(D14+D15)/D16 -> 1.5142746 | E17: =(E14+E15)/E16 -> 1.7975214
A18: Значение показателя значительно превышает рекомендуемое, что свидетельствует об усилении зависимости предприятия от внешних инвесторов и кредиторов, сигнализирует о том, что финансовая устойчивость предприятия вызывает сомнение, о росте риска инвесторов
A19: К. обеспеченности собственным оборотным капиталом=СОК/ОА
A20: СОК | B20: - | C20: ='сок+фин.устойчивость'!B5 -> 148000000 | D20: ='сок+фин.устойчивость'!C5 -> -359000000 | E20: ='сок+фин.устойчивость'!D5 -> -170000000
A21: Оборотные активы | B21: - | C21: =BS!H12 -> 3022000000 | D21: =BS!I12 -> 2396000000 | E21: =BS!J12 -> 2922000000
A22: Ко | B22: >0,1 | C22: =C20/C21 -> 0.048974189 | D22: =D20/D21 -> -0.14983306 | E22: =E20/E21 -> -0.058179329
A23: Отрицательные значения говорят о том, что все оборотные, а также часть внеоборотных активов созданы за счет кредитов и различных займов, это свидетельствует о низкой финансовой устойчивости
A24: К. маневренности=СОК/СК
A25: СОК | B25: - | C25: =C20 -> 148000000 | D25: =D20 -> -359000000 | E25: =E20 -> -170000000
A26: =A3 -> Капитал | B26: - | C26: =C16 -> 4677000000 | D26: =D16 -> 5149000000 | E26: =E16 -> 5487000000
A27: Км | B27: 0,2-0,5 | C27: =C25/C26 -> 0.031644216 | D27: =D25/D26 -> -0.069722276 | E27: =E25/E26 -> -0.030982322
A28: Отрицательный коэффициент маневренности означает низкую финансовую устойчивость в сочетании с тем, что средства вложены в медленно реализуемые активы (основные средства), а оборотный капитал формировался за счет заемных средств.
A29: К. соотношения мобильных и иммобилизованных активов=ОА/ВОА
A30: Оборотные активы | B30: - | C30: =C21 -> 3022000000 | D30: =D21 -> 2396000000 | E30: =E21 -> 2922000000
A31: Внеоборотные активы | B31: - | C31: =BS!H23 -> 10141000000 | D31: =BS!I23 -> 10550000000 | E31: =BS!J23 -> 12428000000
A32: Кс | B32: - | C32: =C30/C31 -> 0.29799823 | D32: =D30/D31 -> 0.227109 | E32: =E30/E31 -> 0.23511426
A33: Значение показателя индивидуально для каждого предприятия, чем выше значение, тем больше средств авансируется в оборотные (мобильные) активы
A34: К. имущества производственного назначения=(ВОА+З)/А
A35: =A31 -> Внеоборотные активы | B35: - | C35: =C31 -> 10141000000 | D35: =D31 -> 10550000000 | E35: =E31 -> 12428000000
A36: Запасы | B36: - | C36: ='сок+фин.устойчивость'!B16 -> 393000000 | D36: ='сок+фин.устойчивость'!C16 -> 438000000 | E36: ='сок+фин.устойчивость'!D16 -> 361000000
A37: =A4 -> Активы | B37: - | C37: =C4 -> 13163000000 | D37: =D4 -> 12946000000 | E37: =E4 -> 15350000000
A38: Кипн | B38: >0,6 | C38: =(C35+C36)/C37 -> 0.80027349 | D38: =(D35+D36)/D37 -> 0.84875637 | E38: =(E35+E36)/E37 -> 0.83315961
A39: Значение показателя выше нормативного, что говорит об отсутствии необходимости привлечения заемных средств для пополнения имущества производственного назначения
A40: К. обеспеченности запасов=СОК/З
A41: СОК | B41: - | C41: =C25 -> 148000000 | D41: =D25 -> -359000000 | E41: =E25 -> -170000000
A42: Запасы | B42: - | C42: ='сок+фин.устойчивость'!B16 -> 393000000 | D42: ='сок+фин.устойчивость'!C16 -> 438000000 | E42: ='сок+фин.устойчивость'!D16 -> 361000000
A43: Коз | B43: >0,5 | C43: =C41/C42 -> 0.37659033 | D43: =D41/D42 -> -0.8196347 | E43: =E41/E42 -> -0.47091413
A44: Отрицательное значение говорит о том, что собственные средства организации вложены во внеоборотные активы и на запасы ничего не приходится, это говорит о крайне неустойчивом финансовом положении организации
A45: К. покрытия процентов=EBIT/проценты к уплате
A46: EBIT | B46: - | C46: =IS!H17 -> 1284000000 | D46: =IS!I17 -> 1305000000 | E46: =IS!J17 -> 378000000
A47: Проценты к уплате | B47: - | C47: =ABS(IS!H19) -> 290000000 | D47: =ABS(IS!I19) -> 227000000 | E47: =ABS(IS!J19) -> 220000000
A48: Кпп | B48: >1,5 | C48: =C46/C47 -> 4.4275862 | D48: =D46/D47 -> 5.7488987 | E48: =E46/E47 -> 1.7181818
A49: Чем выше коэффициент покрытия процентов, тем более устойчивое финансовое положении организации, в данном случае прибыль до налогооблажения и вычета амортизации значительно превышает проценты к уплате; данный показатель значительно ухудшился в 2020 году, однако остался на границе нормы

Sheet ликвидность баланса
A1: Активы | F1: Пассивы
A2: Название группы | F2: Название группы
B3: Расчет | C3: 2018 | D3: 2019 | E3: 2020 | G3: Расчет | H3: 2018 | I3: 2019 | J3: 2020
A4: Наиболее ликвидные активы (А1) | B4: ДС+КФВ | C4: =BS!H5+BS!H6+BS!H7 -> 1477000000 | D4: =BS!I5+BS!I6+BS!I7 -> 739000000 | E4: =BS!J5+BS!J6+BS!J7 -> 1640000000 | F4: Наиболее срочные обязательства (П1) | G4: КЗ | H4: =BS!H28 -> 1130000000 | I4: =BS!I28 -> 1162000000 | J4: =BS!J28 -> 1546000000
A5: Быстро реализуемые активы (А2) | B5: ДЗ | C5: =BS!H8 -> 642000000 | D5: =BS!I8 -> 620000000 | E5: =BS!J8 -> 468000000 | F5: Краткосрочные пассивы (П2) | G5: КО-КЗ | H5: =BS!H35-BS!H28 -> 1744000000 | I5: =BS!I35-BS!I28 -> 1593000000 | J5: =BS!J35-BS!J28 -> 1546000000
A6: Медленно реализуемые активы (А3) | B6: Запасы + Прочие ВНА+ДФВ | C6: =BS!H10+BS!H17+BS!H18+BS!H19 -> 1606000000 | D6: =BS!I10+BS!I17+BS!I18+BS!I19 -> 1759000000 | E6: =BS!J10+BS!J17+BS!J18+BS!J19 -> 1845000000 | F6: Долгосрочные пассивы (П3) | G6: Долгосрочные обязательства | H6: =BS!H42 -> 5612000000 | I6: =BS!I42 -> 5042000000 | J6: =BS!J42 -> 6771000000
A7: Трудно реализуемые активы (А4) | B7: ВНА | C7: =BS!H23 -> 10141000000 | D7: =BS!I23 -> 10550000000 | E7: =BS!J23 -> 12428000000 | F7: Постоянные пассивы (П4) | G7: Капитал | H7: =BS!H52 -> 4677000000 | I7: =BS!I52 -> 5149000000 | J7: =BS!J52 -> 5487000000
C8: А1>П1 | D8: А1<П1 | E8: А1>П1
C9: A2<П2 | D9: A2<П2 | E9: A2<П2
C10: A3<П3 | D10: A3<П3 | E10: A3<П3
C11: А4>П4 | D11: А4>П4 | E11: А4>П4

Sheet коэффициенты ликвидности
A1: Показатель | B1: Рекомендуемое значение | C1: 2018 | D1: 2019 | E1: 2020
A2: общий показатель ликвидности=(ДС+КВФ+ДЗ+З)/(КО)
A3: ДС | C3: =BS!H5 -> 832000000 | D3: =BS!I5 -> 228000000 | E3: =BS!J5 -> 806000000
A4: Прочие оборотные фин активы | C4: =BS!H7 -> 633000000 | D4: =BS!I7 -> 501000000 | E4: =BS!J7 -> 817000000
A5: ДЗ | C5: =BS!H8 -> 642000000 | D5: =BS!I8 -> 620000000 | E5: =BS!J8 -> 468000000
A6: ЗП | C6: =BS!H10 -> 393000000 | D6: =BS!I10 -> 438000000 | E6: =BS!J10 -> 361000000
A7: Краткосрочные обязательства | C7: =BS!H35 -> 2874000000 | D7: =BS!I35 -> 2755000000 | E7: =BS!J35 -> 3092000000
A8: Общая ликвидность | C8: =(C3+C4+C5+C6)/C7 -> 0.86986778 | D8: =(D3+D4+D5+D6)/D7 -> 0.64863884 | E8: =(E3+E4+E5+E6)/E7 -> 0.79301423
A9: Значение показателя ниже 1-2, что говорит о недостаточности оборотных средств для покрытия краткосрочных обязательств
A12: Показатель | B12: Рекомендуемое значение | C12: 2018 | D12: 2019 | E12: 2020
A13: К. абсолютной ликвидности=(ДС+КФВ)/(КО)
A14: =A3 -> ДС | B14: - | C14: =C3 -> 832000000 | D14: =D3 -> 228000000 | E14: =E3 -> 806000000
A15: =A4 -> Прочие оборотные фин активы | B15: - | C15: =C4 -> 633000000 | D15: =D4 -> 501000000 | E15: =E4 -> 817000000
A16: =A7 -> Краткосрочные обязательства | B16: - | C16: =C7 -> 2874000000 | D16: =D7 -> 2755000000 | E16: =E7 -> 3092000000
A17: Кабслик | B17: >0,2 | C17: =(C14+C15)/C16 -> 0.50974252 | D17: =(D14+D15)/D16 -> 0.2646098 | E17: =(E14+E15)/E16 -> 0.52490298
A18: Значение показателя выше рекомендуемого, что говорит о полном покрытии краткосрочных обязательств за счет денежных средств и краткосрочных финансовых вложений
A19: K. срочной (быстрой) ликвидности=(ДС+КФВ+ДЗ)/(КО)
A20: =A3 -> ДС | B20: - | C20: =C14 -> 832000000 | D20: =D14 -> 228000000 | E20: =E14 -> 806000000
A21: =A4 -> Прочие оборотные фин активы | B21: - | C21: =C15 -> 633000000 | D21: =D15 -> 501000000 | E21: =E15 -> 817000000
A22: =A5 -> ДЗ | B22: - | C22: =C5 -> 642000000 | D22: =D5 -> 620000000 | E22: =E5 -> 468000000
A23: =A7 -> Краткосрочные обязательства | B23: - | C23: =C16 -> 2874000000 | D23: =D16 -> 2755000000 | E23: =E16 -> 3092000000
A24: Ксрлик | B24: >1 | C24: =(C20+C21+C22)/C23 -> 0.73312457 | D24: =(D20+D21+D22)/D23 -> 0.48965517 | E24: =(E20+E21+E22)/E23 -> 0.67626132
A25: Значение показателя ниже 1, что говорит о неполном покрытии краткосрочных обязательств за счет денежных средств, краткосрочных финансовых вложений и дебиторской задолженности, о неспособность компании погашать свои текущие обязательства в случае возникновения сложностей с реализацией продукции
A26: К. текущей (общей) ликвидности=(ОА)/(КО)
A27: ОА | B27: - | C27: =BS!H12 -> 3022000000 | D27: =BS!I12 -> 2396000000 | E27: =BS!J12 -> 2922000000
A28: =A7 -> Краткосрочные обязательства | B28: - | C28: =C7 -> 2874000000 | D28: =D7 -> 2755000000 | E28: =E7 -> 3092000000
A29: Ктеклик | B29: >2 | C29: =C27/C28 -> 1.0514962 | D29: =D27/D28 -> 0.86969147 | E29: =E27/E28 -> 0.9450194
A30: Значение ниже 1 говорит о высоком финансовом риске, связанном с тем, что предприятие не в состоянии стабильно оплачивать текущие счета

Sheet коэффициенты оборачиваемости
A1: Показатель | B1: 2018 | C1: 2019 | D1: 2020
A2: К. оборачиваемости активов (ресурсоотдача)=В/А
A3: Выручка | B3: =IS!H6 -> 8238000000 | C3: =IS!I6 -> 8676000000 | D3: =IS!J6 -> 5757000000
A4: Валюта баланса | B4: =BS!H25 -> 13163000000 | C4: =BS!I25 -> 12946000000 | D4: =BS!J25 -> 15350000000
A5: Коа | B5: =B3/B4 -> 0.62584517 | C5: =C3/C4 -> 0.67016839 | D5: =D3/D4 -> 0.37504886
A6: Па | B6: =365/B5 -> 583.21134 | C6: =365/C5 -> 544.63923 | D6: =365/D5 -> 973.20653
A7: К. оборачиваемости собственного капитала=В/СК
A8: Выручка | B8: =B3 -> 8238000000 | C8: =C3 -> 8676000000 | D8: =D3 -> 5757000000
A9: СК | B9: =BS!H52 -> 4677000000 | C9: =BS!I52 -> 5149000000 | D9: =BS!J52 -> 5487000000
A10: Коск | B10: =B8/B9 -> 1.7613855 | C10: =C8/C9 -> 1.6849874 | D10: =D8/D9 -> 1.0492072
A11: Пск | B11: =365/B10 -> 207.22323 | C11: =365/C10 -> 216.61883 | D11: =365/D10 -> 347.88171
A12: К. отдачи внеоборотных активов=В/ВНА
A13: Выручка | B13: =B3 -> 8238000000 | C13: =C3 -> 8676000000 | D13: =D3 -> 5757000000
A14: ВНА | B14: =BS!H23 -> 10141000000 | C14: =BS!I23 -> 10550000000 | D14: =BS!J23 -> 12428000000
A15: Ковна | B15: =B13/B14 -> 0.81234592 | C15: =C13/C14 -> 0.82236967 | D15: =D13/D14 -> 0.46322819
A16: Пвна | B16: =365/B15 -> 449.31597 | C16: =365/C15 -> 443.83933 | D16: =365/D15 -> 787.94858
A17: К. оборачиваемости оборотных активов=В/ОА
A18: Выручка | B18: =B3 -> 8238000000 | C18: =C3 -> 8676000000 | D18: =D3 -> 5757000000
A19: ОА | B19: =BS!H12 -> 3022000000 | C19: =BS!I12 -> 2396000000 | D19: =BS!J12 -> 2922000000
A20: Кооа | B20: =B18/B19 -> 2.7260093 | C20: =C18/C19 -> 3.6210351 | D20: =D18/D19 -> 1.9702259
A21: Поа | B21: =365/B20 -> 133.89536 | C21: =365/C20 -> 100.79991 | D21: =365/D20 -> 185.25795
A22: К. оборачиваемости основных средств (фондоотдача)=В/ОС
A23: Выручка | B23: =B18 -> 8238000000 | C23: =C18 -> 8676000000 | D23: =D18 -> 5757000000
A24: Основные средства | B24: =BS!H14 -> 8445000000 | C24: =BS!I14 -> 8706000000 | D24: =BS!J14 -> 10401000000
A25: Коос | B25: =B23/B24 -> 0.97548845 | C25: =C23/C24 -> 0.9965541 | D25: =D23/D24 -> 0.55350447
A26: Пос | B26: =365/B25 -> 374.17152 | C26: =365/C25 -> 366.2621 | D26: =365/D25 -> 659.4346
A27: К. оборачиваемости перманентного капитала=В/ПК
A28: Выручка | B28: =B23 -> 8238000000 | C28: =C23 -> 8676000000 | D28: =D23 -> 5757000000
A29: ПК | B29: ='сок+фин.устойчивость'!B8 -> 5760000000 | C29: ='сок+фин.устойчивость'!C8 -> 4683000000 | D29: ='сок+фин.устойчивость'!D8 -> 6601000000
A30: Копк | B30: =B28/B29 -> 1.4302083 | C30: =C28/C29 -> 1.8526586 | D30: =D28/D29 -> 0.87214058
A31: Ппк | B31: =365/B30 -> 255.20757 | C31: =365/C30 -> 197.01418 | D31: =365/D30 -> 418.51051
A32: К. оборачиваемости запасов=В/Запасы
A33: =A28 -> Выручка | B33: =B28 -> 8238000000 | C33: =C28 -> 8676000000 | D33: =D28 -> 5757000000
A34: Запасы | B34: =BS!H10 -> 393000000 | C34: =BS!I10 -> 438000000 | D34: =BS!J10 -> 361000000
A35: Коз | B35: =B33/B34 -> 20.961832 | C35: =C33/C34 -> 19.808219 | D35: =D33/D34 -> 15.947368
A36: Пз | B36: =365/B35 -> 17.4126 | C36: =365/C35 -> 18.426694 | D36: =365/D35 -> 22.887789
A37: среднее значение | B37: =AVERAGE(B36:D36) -> 19.575694
A38: К. оборачиваемости дебиторской задолженности=В/ДЗ
A39: Выручка | B39: =B28 -> 8238000000 | C39: =C28 -> 8676000000 | D39: =D28 -> 5757000000
A40: Дебиторская задолженность | B40: =BS!H8 -> 642000000 | C40: =BS!I8 -> 620000000 | D40: =BS!J8 -> 468000000
A41: Кодз | B41: =B39/B40 -> 12.831776 | C41: =C39/C40 -> 13.993548 | D41: =D39/D40 -> 12.301282
A42: Пдз | B42: =365/B41 -> 28.445011 | C42: =365/C41 -> 26.083449 | D42: =365/D41 -> 29.671704
A43: среднее значение | B43: =AVERAGE(B42:D42) -> 28.066721
A44: К. оборачиваемости кредиторской задолженности=В/КЗ
A45: Выручка | B45: =B39 -> 8238000000 | C45: =C39 -> 8676000000 | D45: =D39 -> 5757000000
A46: Кредиторская задолженность | B46: =BS!H28 -> 1130000000 | C46: =BS!I28 -> 1162000000 | D46: =BS!J28 -> 1546000000
A47: Кодз | B47: =B45/B46 -> 7.2902655 | C47: =C45/C46 -> 7.4664372 | D47: =D45/D46 -> 3.7238034
A48: Пдз | B48: =365/B47 -> 50.066764 | C48: =365/C47 -> 48.885431 | D48: =365/D47 -> 98.018065
A49: среднее значение | B49: =AVERAGE(B48:D48) -> 65.656753

Sheet коэффициенты рентабельности
A1: Показатель | B1: 2018 | C1: 2019 | D1: 2020
A2: Рентабельность продаж=Прибыль от продаж/Выручка | E2: Коэффициент рентабельности продаж (англ. Return On Sales, ROS) – показатель отражающий эффективность продаж. Рассчитывается как отношение прибыли от продаж к выручке.
A3: EBIT | B3: =IS!H17 -> 1284000000 | C3: =IS!I17 -> 1305000000 | D3: =IS!J17 -> 378000000
A4: Выручка | B4: =IS!H6 -> 8238000000 | C4: =IS!I6 -> 8676000000 | D4: =IS!J6 -> 5757000000
A5: =A13 -> Чистая прибыль | B5: =B13 -> 649000000 | C5: =C13 -> 802000000 | D5: =D13 -> 181000000
A6: ROS (по EBIT) | B6: =B3/B4 -> 0.15586307 | C6: =C3/C4 -> 0.15041494 | D6: =D3/D4 -> 0.065659197
A7: ROS (по чистой прибыли) | B7: =B5/B4 -> 0.078781258 | C7: =C5/C4 -> 0.092438912 | D7: =D5/D4 -> 0.031439986
A8: Рентабельность собственного капитала=Чистая прибыль/Собственный капитал | E8: Коэффициент рентабельности собственного капитала (англ. Return On Equity, ROE) – показатель отражающий эффективность и доходность использования собственного капитала. Данный коэффициент часто используется инвесторами для оценки капиталоемких предприятий и отражает качество управления собственным капиталом.
A9: Чистая прибыль | B9: =IS!H26 -> 649000000 | C9: =IS!I26 -> 802000000 | D9: =IS!J26 -> 181000000
A10: Капитал | B10: =BS!H52 -> 4677000000 | C10: =BS!I52 -> 5149000000 | D10: =BS!J52 -> 5487000000
A11: ROЕ | B11: =B9/B10 -> 0.13876417 | C11: =C9/C10 -> 0.1557584 | D11: =D9/D10 -> 0.03298706
A12: Рентабельность активов=Чистая прибыль/Активы | E12: Коэффициент рентабельности активов (англ. Return On Asset, ROA) – показатель эффективности использования предприятием активов и рассчитывается как отношение чистой прибыли предприятия (после налогообложения) к величине активов. Другими словами рентабельность активов (ROA) отражает доходность, полученную как с помощью собственного, так и заемного капитала.
A13: Чистая прибыль | B13: =IS!H26 -> 649000000 | C13: =IS!I26 -> 802000000 | D13: =IS!J26 -> 181000000
A14: Валюта баланса | B14: =BS!H25 -> 13163000000 | C14: =BS!I25 -> 12946000000 | D14: =BS!J25 -> 15350000000
A15: ROА | B15: =B13/B14 -> 0.04930487 | C15: =C13/C14 -> 0.061949637 | D15: =D13/D14 -> 0.011791531
A16: Рентабельность инвестированного капитала=Чистая прибыль/(Капитал+ДО) | E16: Коэффициент рентабельности на инвестиционный капитал (англ. Return On Invested Capital, ROIC, ROI) – показатель отражающий прибыльность предприятия на инвестиционный капитал. Коэффициент рентабельности инвестиционного капитала используется инвесторами для оценки эффективности предприятия создавать добавленную стоимости на вложенный капитал. Если данный показатель высок, то предприятие инвестиционно привлекательно для инвесторов.
A17: Чистая прибыль | B17: =B9 -> 649000000 | C17: =C9 -> 802000000 | D17: =D9 -> 181000000
A18: Капитал | B18: =B10 -> 4677000000 | C18: =C10 -> 5149000000 | D18: =D10 -> 5487000000
A19: ДО | B19: =BS!H42 -> 5612000000 | C19: =BS!I42 -> 5042000000 | D19: =BS!J42 -> 6771000000
A20: ROIC | B20: =B17/(B18+B19) -> 0.063077073 | C20: =C17/(C18+C19) -> 0.078696889 | D20: =D17/(D18+D19) -> 0.014765867
A21: Рентабельность на капитал=Операционная прибыль после налога (NOPAT)/(СК+ЗК)
A22: =IS!A17 -> Операционная прибыль | B22: =IS!H17 -> 1284000000 | C22: =IS!I17 -> 1305000000 | D22: =IS!J17 -> 378000000
A23: NOPAT=EBIT*(1-t) | B23: =B22*(1-0.2) -> 1027200000 | C23: =C22*(1-0.2) -> 1044000000 | D23: =D22*(1-0.2) -> 302400000
A24: D+E | B24: =BS!H29+BS!H29+BS!H52 -> 6633000000 | C24: =BS!I29+BS!I29+BS!I52 -> 6739000000 | D24: =BS!J29+BS!J29+BS!J52 -> 7083000000
A25: ROC | B25: =B23/B24 -> 0.15486205 | C25: =C23/C24 -> 0.15491913 | D25: =D23/D24 -> 0.042693774

Sheet вероятность банкротства
A1: Пятифакторная модель Альтмана (1968)
D2: Z-счет = 1,2*X1 + 1,4*X2 + 3,3*X3 + 0,6*X4 + X5
A3: Коэффициент | B3: Формула расчета | C3: Расчет по МСФО | D3: 2018 | E3: 2019 | F3: 2020
A4: X1 | B4: Х1 = Оборотный капитал/Активы | C4: (Working Capital) / Total Assets | D4: =BS!H12/BS!H25 -> 0.22958292 | E4: =BS!I12/BS!I25 -> 0.18507647 | F4: =BS!J12/BS!J25 -> 0.19035831
A5: Х2 | B5: Х2= Нераспределенная прибыль/Активы | C5: Retained Earnings / Total Assets | D5: =BS!H49/BS!H25 -> 0.27425359 | E5: =BS!I49/BS!I25 -> 0.31144755 | F5: =BS!J49/BS!J25 -> 0.26104235
A6: Х3 | B6: Х3 = Операционная прибыль/Активы | C6: EBIT / Total Assets | D6: =IS!H17/BS!H25 -> 0.097546152 | E6: =IS!I17/BS!I25 -> 0.10080334 | F6: =IS!J17/BS!J25 -> 0.024625407
A7: Х4 | B7: Х4 = Рыночная стоимость акций/ Обязательства | C7: Market value of Equity/ Book value of Total Liabilities | D7: =H7/(BS!H35+BS!H42) -> 0.36401131 | E7: =I7/(BS!I35+BS!I42) -> 0.61126074 | F7: =J7/(BS!J35+BS!J42) -> 0.43769644 | H7: 3089000000 | I7: 4766000000 | J7: 4317000000
A8: Х5 | B8: Х5 = Выручка/Активы | C8: Sales/Total Assets | D8: =IS!H6/BS!H25 -> 0.62584517 | E8: =IS!I6/BS!I25 -> 0.67016839 | F8: =IS!J6/BS!J25 -> 0.37504886
A9: Z-счет | B9: - | C9: - | D9: =1.2*D4+1.4*D5+3.3*D6+0.6*D7+D8 -> 1.8256088 | E9: =1.2*E4+1.4*E5+3.3*E6+0.6*E7+E8 -> 2.0276942 | F9: =1.2*F4+1.4*F5+3.3*F6+0.6*F7+F8 -> 1.3128198
D11: Z < 1,81 - вероятность банкротства велика
D12: 1,81 < Z < 2,675 - вероятность банкротства средняя
D13: Z =< 2,675 - вероятность банкротства 50%
D14: 2,675 < Z < 2,99 - вероятность банкротства невелика
D15: Z > 2,99 - вероятность банкротства ничтожна
A18: Модель прогнозирования банкротства предприятия Р. Лиса (Великобритания, 1972)
D19: Z=0.063*K1 + 0.092*K2 + 0.057*K3 + 0.001*K4
A20: Коэффициент | B20: Формула расчета | C20: Расчет по МСФО | D20: 2018 | E20: 2019 | F20: 2020
A21: К1 | B21: K1 = Оборотный капитал / Активы | C21: (Working Capital) / Total Assets | D21: =D4 -> 0.22958292 | E21: =E4 -> 0.18507647 | F21: =F4 -> 0.19035831
A22: К2 | B22: K2 = Прибыль до налогообложения / Активы | C22: EBIT / Total Assets | D22: =D6 -> 0.097546152 | E22: =E6 -> 0.10080334 | F22: =F6 -> 0.024625407
A23: К3 | B23: К3 = Нераспределенная прибыль / Активы | C23: Retained Earnings / Total Assets | D23: =D5 -> 0.27425359 | E23: =E5 -> 0.31144755 | F23: =F5 -> 0.26104235
A24: К4 | B24: К4 = Собственный капитал / (Краткосрочные + Долгосрочные обязательства) | C24: Value of Equity/ Book value of Total Liabilities | D24: =D7 -> 0.36401131 | E24: =E7 -> 0.61126074 | F24: =F7 -> 0.43769644
A25: Z-счет | B25: - | C25: - | D25: =0.063*D21+0.092*D22+0.057*D23+0.001*D24 -> 0.039434436 | E25: =0.063*E21+0.092*E22+0.057*E23+0.001*E24 -> 0.039297496 | F25: =0.063*F21+0.092*F22+0.057*F23+0.001*F24 -> 0.029575221
D27: Z<0.037-банкротство компании очень вероятно
D28: Z>0.037-предприятие финансово устойчивое
A32: Модель Беликова-Давыдовой (Иркутская государственная экономическая академия, 1998 г.)
C33: Z= 8.38*K1 + 1*K2 + 0.054*K3 + 0.63*K4
A34: Коэффициент | B34: Формула расчета | C34: 2018 | D34: 2019 | E34: 2020
A35: К1 | B35: K1 = Оборотный капитал / Активы | C35: =D21 -> 0.22958292 | D35: =E21 -> 0.18507647 | E35: =F21 -> 0.19035831
A36: К2 | B36: K2 = Прибыль до налогообложения / Активы | C36: =D22 -> 0.097546152 | D36: =E22 -> 0.10080334 | E36: =F22 -> 0.024625407
A37: К3 | B37: К3 = Нераспределенная прибыль / Активы | C37: =D23 -> 0.27425359 | D37: =E23 -> 0.31144755 | E37: =F23 -> 0.26104235
A38: К4 | B38: К4 = Собственный капитал / (Краткосрочные + Долгосрочные обязательства) | C38: =BS!H52/(BS!H42+BS!H35) -> 0.55114306 | D38: =BS!I52/(BS!I42+BS!I35) -> 0.6603822 | E38: =BS!J52/(BS!J42+BS!J35) -> 0.55632161
A39: Z-счет | B39: - | C39: =8.38*C35+1*C36+0.054*C37+0.63*C38 -> 2.3834809 | D39: =8.38*D35+1*D36+0.054*D37+0.63*D38 -> 2.0846031 | E39: =8.38*E35+1*E36+0.054*E37+0.63*E38 -> 1.9844069
C43: Z<0 - риск банкротства максимальный (90-100%)
C44: 0<Z<0.18 - риск банкротства высокий (60-80%)
C45: 0.18<Z<0.32 - риск банкротства средний (35-50%)
C46: 0.32<Z<0.42 - риск банкротства низкий (15-20%)
C47: Z>0.42 - риск банкротства минимальный (до 10%)
A51: Модель Савицкой прогнозирования вероятности банкротства (Белорусский государственный экономический университет)
B52: Z= 0.111*К1 + 13.23*К2 + 1.67*К3 + 0.515*К4 + 3.8*К5
A53: Коэффициент | B53: Формула расчета | C53: 2018 | D53: 2019 | E53: 2020
A54: К1 | B54: К1 = Собственный капитал / Оборотные активы | C54: =BS!H52/BS!H12 -> 1.5476506 | D54: =BS!I52/BS!I12 -> 2.1489983 | E54: =BS!J52/BS!J12 -> 1.8778234
A55: К2 | B55: К2= Оборотный капитал / Капитал | C55: ='сок+фин.устойчивость'!B5/BS!H52 -> 0.031644216 | D55: ='сок+фин.устойчивость'!C5/BS!I52 -> -0.069722276 | E55: ='сок+фин.устойчивость'!D5/BS!J52 -> -0.030982322
A56: К3 | B56: К3 = Выручка / Среднегодовая величина активов | C56: =IS!H6/BS!H25 -> 0.62584517 | D56: =IS!I6/BS!I25 -> 0.67016839 | E56: =IS!J6/BS!J25 -> 0.37504886
A57: К4 | B57: К4 = Чистая прибыль / Активы | C57: =IS!H26/BS!H25 -> 0.04930487 | D57: =IS!I26/BS!I25 -> 0.061949637 | E57: =IS!J26/BS!J25 -> 0.011791531
A58: К5 | B58: К5 = Собственный капитал / Активы | C58: =BS!H52/BS!H25 -> 0.35531414 | D58: =BS!I52/BS!I25 -> 0.39772903 | E58: =BS!J52/BS!J25 -> 0.35745928
A59: Z-счет | B59: - | C59: =0.111*C54+13.23*C55+1.67*C56+0.515*C57+3.8*C58 -> 3.0111894 | D59: =0.111*D54+13.23*D55+1.67*D56+0.515*D57+3.8*D58 -> 1.9785687 | E59: =0.111*E54+13.23*E55+1.67*E56+0.515*E57+3.8*E58 -> 1.7892918
C63: Z>8 - риск банкротства отсутствует
C64: 5<Z<8 - риск банкротства небольшой
C65: 3<Z<5 - риск банкротства средний
C66: 1<Z<3 - риск банкротства большой
C67: Z<1 - риск банкротства предприятия максимальный

Sheet WACC
A1: <TICKER> | B1: <DATE> | C1: <CLOSE> | D1: Доходность | F1: <TICKER> | G1: <DATE> | H1: <CLOSE> | I1: Доходность
A2: ROSN | B2: 42370 | C2: 272.45 | F2: IMOEX | G2: 42370 | H2: 1784.92
A3: ROSN | B3: 42401 | C3: 287.6 | D3: =C3/C2-1 -> 0.055606533 | F3: IMOEX | G3: 42401 | H3: 1840.17 | I3: =H3/H2-1 -> 0.030953768
A4: ROSN | B4: 42430 | C4: 305.2 | D4: =C4/C3-1 -> 0.061196106 | F4: IMOEX | G4: 42430 | H4: 1871.15 | I4: =H4/H3-1 -> 0.016835401 | Q4: ВЫВОД ИТОГОВ
A5: ROSN | B5: 42461 | C5: 351 | D5: =C5/C4-1 -> 0.15006553 | F5: IMOEX | G5: 42461 | H5: 1953.05 | I5: =H5/H4-1 -> 0.043769874
A6: ROSN | B6: 42491 | C6: 316 | D6: =C6/C5-1 -> -0.0997151 | F6: IMOEX | G6: 42491 | H6: 1899.01 | I6: =H6/H5-1 -> -0.027669543 | Q6: Регрессионная статистика
A7: ROSN | B7: 42522 | C7: 330 | D7: =C7/C6-1 -> 0.044303797 | F7: IMOEX | G7: 42522 | H7: 1891.09 | I7: =H7/H6-1 -> -0.0041705942 | Q7: Множественный R | R7: 0.682141
A8: ROSN | B8: 42552 | C8: 325.5 | D8: =C8/C7-1 -> -0.013636364 | F8: IMOEX | G8: 42552 | H8: 1944.62 | I8: =H8/H7-1 -> 0.028306426 | Q8: R-квадрат | R8: 0.46531634
A9: ROSN | B9: 42583 | C9: 344.7 | D9: =C9/C8-1 -> 0.058986175 | F9: IMOEX | G9: 42583 | H9: 1971.59 | I9: =H9/H8-1 -> 0.013869034 | Q9: Нормированный R-квадрат | R9: 0.45669241
A10: ROSN | B10: 42614 | C10: 342.8 | D10: =C10/C9-1 -> -0.0055120395 | F10: IMOEX | G10: 42614 | H10: 1978 | I10: =H10/H9-1 -> 0.0032511831 | Q10: Стандартная ошибка | R10: 0.063923329
A11: ROSN | B11: 42644 | C11: 347.65 | D11: =C11/C10-1 -> 0.014148191 | F11: IMOEX | G11: 42644 | H11: 1989.64 | I11: =H11/H10-1 -> 0.0058847321 | Q11: Наблюдения | R11: 64
A12: ROSN | B12: 42675 | C12: 340.2 | D12: =C12/C11-1 -> -0.021429599 | F12: IMOEX | G12: 42675 | H12: 2104.91 | I12: =H12/H11-1 -> 0.057935104
A13: ROSN | B13: 42705 | C13: 402.8 | D13: =C13/C12-1 -> 0.18400941 | F13: IMOEX | G13: 42705 | H13: 2232.72 | I13: =H13/H12-1 -> 0.060719936 | Q13: Дисперсионный анализ
A14: ROSN | B14: 42736 | C14: 400.6 | D14: =C14/C13-1 -> -0.0054617676 | F14: IMOEX | G14: 42736 | H14: 2217.39 | I14: =H14/H13-1 -> -0.0068660647 | R14: df | S14: SS | T14: MS | U14: F | V14: Значимость F
A15: ROSN | B15: 42767 | C15: 331.1 | D15: =C15/C14-1 -> -0.17348977 | F15: IMOEX | G15: 42767 | H15: 2035.77 | I15: =H15/H14-1 -> -0.081907107 | Q15: Регрессия | R15: 1 | S15: 0.22047627 | T15: 0.22047627 | U15: 53.956415 | V15: 5.4154922e-10
A16: ROSN | B16: 42795 | C16: 323.5 | D16: =C16/C15-1 -> -0.02295379 | F16: IMOEX | G16: 42795 | H16: 1995.9 | I16: =H16/H15-1 -> -0.019584727 | Q16: Остаток | R16: 62 | S16: 0.2533439 | T16: 0.004086192
A17: ROSN | B17: 42826 | C17: 317.25 | D17: =C17/C16-1 -> -0.019319938 | F17: IMOEX | G17: 42826 | H17: 2016.71 | I17: =H17/H16-1 -> 0.010426374 | Q17: Итого | R17: 63 | S17: 0.47382017
A18: ROSN | B18: 42856 | C18: 301.55 | D18: =C18/C17-1 -> -0.049487786 | F18: IMOEX | G18: 42856 | H18: 1900.38 | I18: =H18/H17-1 -> -0.057683058
A19: ROSN | B19: 42887 | C19: 323 | D19: =C19/C18-1 -> 0.071132482 | F19: IMOEX | G19: 42887 | H19: 1879.5 | I19: =H19/H18-1 -> -0.010987276 | R19: Коэффициенты | S19: Стандартная ошибка | T19: t-статистика | U19: P-Значение | V19: Нижние 95% | W19: Верхние 95% | X19: Нижние 95,0% | Y19: Верхние 95,0%
A20: ROSN | B20: 42917 | C20: 311.3 | D20: =C20/C19-1 -> -0.03622291 | F20: IMOEX | G20: 42917 | H20: 1919.53 | I20: =H20/H19-1 -> 0.021298218 | Q20: Y-пересечение | R20: -0.0030037384 | S20: 0.0083212758 | T20: -0.3609709 | U20: 0.71934828 | V20: -0.019637732 | W20: 0.013630255 | X20: -0.019637732 | Y20: 0.013630255
A21: ROSN | B21: 42948 | C21: 304 | D21: =C21/C20-1 -> -0.023450048 | F21: IMOEX | G21: 42948 | H21: 2022.22 | I21: =H21/H20-1 -> 0.053497471 | Q21: Переменная X 1 | R21: 1.4191373 | S21: 0.19319811 | T21: 7.345503 | U21: 5.4154922e-10 | V21: 1.0329398 | W21: 1.8053348 | X21: 1.0329398 | Y21: 1.8053348
A22: ROSN | B22: 42979 | C22: 318.95 | D22: =C22/C21-1 -> 0.049177632 | F22: IMOEX | G22: 42979 | H22: 2077.19 | I22: =H22/H21-1 -> 0.027182997
A23: ROSN | B23: 43009 | C23: 318.7 | D23: =C23/C22-1 -> -0.00078382192 | F23: IMOEX | G23: 43009 | H23: 2064.31 | I23: =H23/H22-1 -> -0.0062006846
A24: ROSN | B24: 43040 | C24: 293.6 | D24: =C24/C23-1 -> -0.078757452 | F24: IMOEX | G24: 43040 | H24: 2100.62 | I24: =H24/H23-1 -> 0.017589412
A25: ROSN | B25: 43070 | C25: 291.5 | D25: =C25/C24-1 -> -0.0071525886 | F25: IMOEX | G25: 43070 | H25: 2109.74 | I25: =H25/H24-1 -> 0.0043415753 | Q25: Rf | R25: 0.0675 | S25: Кривая бескупонной доходности государственных облигаций | Банк России (cbr.ru)
A26: ROSN | B26: 43101 | C26: 343.2 | D26: =C26/C25-1 -> 0.17735849 | F26: IMOEX | G26: 43101 | H26: 2289.99 | I26: =H26/H25-1 -> 0.085437068 | Q26: b | R26: =R21 -> 1.4191373
A27: ROSN | B27: 43132 | C27: 330.5 | D27: =C27/C26-1 -> -0.037004662 | F27: IMOEX | G27: 43132 | H27: 2296.8 | I27: =H27/H26-1 -> 0.0029738121 | Q27: Rm | R27: =AVERAGE(I3:I66)*12 -> 0.14429452
A28: ROSN | B28: 43160 | C28: 313.9 | D28: =C28/C27-1 -> -0.050226929 | F28: IMOEX | G28: 43160 | H28: 2270.98 | I28: =H28/H27-1 -> -0.011241728 | Q28: Re(CAPM) | R28: =R25+R26*(R27-R25) -> 0.17648197
A29: ROSN | B29: 43191 | C29: 383 | D29: =C29/C28-1 -> 0.2201338 | F29: IMOEX | G29: 43191 | H29: 2307.02 | I29: =H29/H28-1 -> 0.015869801
A30: ROSN | B30: 43221 | C30: 385.3 | D30: =C30/C29-1 -> 0.0060052219 | F30: IMOEX | G30: 43221 | H30: 2302.88 | I30: =H30/H29-1 -> -0.0017945228
A31: ROSN | B31: 43252 | C31: 396.15 | D31: =C31/C30-1 -> 0.028159875 | F31: IMOEX | G31: 43252 | H31: 2295.95 | I31: =H31/H30-1 -> -0.0030092753 | U31: Расчет средневзвешенной процентоной ставки заемного капитала | Z31: либор usd 31.12.2020 (12 мес), % | AA31: 0.0034
A32: ROSN | B32: 43282 | C32: 419 | D32: =C32/C31-1 -> 0.057680172 | F32: IMOEX | G32: 43282 | H32: 2321.11 | I32: =H32/H31-1 -> 0.010958427 | Q32: D | R32: =BS!J29+BS!J37 -> 4608000000
A33: ROSN | B33: 43313 | C33: 435.7 | D33: =C33/C32-1 -> 0.039856802 | F33: IMOEX | G33: 43313 | H33: 2345.85 | I33: =H33/H32-1 -> 0.010658693 | Q33: Доля D | R33: =R32/R38 -> 0.4564636 | U33: Кредиты стр 83 | AA33: 0.026 | AB33: =AVERAGE(AA33:AA34) -> 0.035
A34: ROSN | B34: 43344 | C34: 493 | D34: =C34/C33-1 -> 0.13151251 | F34: IMOEX | G34: 43344 | H34: 2475.36 | I34: =H34/H33-1 -> 0.055208134 | Q34: rd | R34: =W70 -> 0.063521093 | U34: 801 | V34: =AB33+AA31 -> 0.0384 | W34: =U34/$U$70 -> 0.32680539 | X34: =W34*V34 -> 0.012549327 | AA34: 0.044
A35: ROSN | B35: 43374 | C35: 460.45 | D35: =C35/C34-1 -> -0.066024341 | F35: IMOEX | G35: 43374 | H35: 2352.71 | I35: =H35/H34-1 -> -0.049548349 | Q35: E | R35: =BS!J52 -> 5487000000 | T35: =U34+U35+U36 -> 1720 | U35: 112 | V35: =AB37 -> 0.02275 | W35: =U35/$U$70 -> 0.045695634 | X35: =W35*V35 -> 0.0010395757
A36: ROSN | B36: 43405 | C36: 423.1 | D36: =C36/C35-1 -> -0.081116299 | F36: IMOEX | G36: 43405 | H36: 2392.5 | I36: =H36/H35-1 -> 0.016912412 | Q36: Доля E | R36: =R35/R38 -> 0.5435364 | U36: 807 | V36: 0.085 | W36: =U36/$U$70 -> 0.32925337 | X36: =W36*V36 -> 0.027986536
A37: ROSN | B37: 43435 | C37: 432.5 | D37: =C37/C36-1 -> 0.02221697 | F37: IMOEX | G37: 43435 | H37: 2369.17 | I37: =H37/H36-1 -> -0.0097513062 | Q37: re | R37: =R28 -> 0.17648197 | T37: =SUM(U37:U67) -> 581 | U37: 20 | V37: 0.079 | W37: =U37/$U$70 -> 0.0081599347 | X37: =W37*V37 -> 0.00064463484 | AA37: 0.02 | AB37: =AVERAGE(AA37:AA38) -> 0.02275
A38: ROSN | B38: 43466 | C38: 411.25 | D38: =C38/C37-1 -> -0.049132948 | F38: IMOEX | G38: 43466 | H38: 2521.1 | I38: =H38/H37-1 -> 0.064127944 | Q38: D+E | R38: =R32+R35 -> 10095000000 | U38: 31 | V38: 0.073 | W38: =U38/$U$70 -> 0.012647899 | X38: =W38*V38 -> 0.00092329661 | AA38: 0.0255
A39: ROSN | B39: 43497 | C39: 398.8 | D39: =C39/C38-1 -> -0.030273556 | F39: IMOEX | G39: 43497 | H39: 2485.27 | I39: =H39/H38-1 -> -0.01421205 | Q39: WACC | R39: =R36*R37+R33*R34*0.8 -> 0.11912043 | U39: 5 | V39: 0.07 | W39: =U39/$U$70 -> 0.0020399837 | X39: =W39*V39 -> 0.00014279886
A40: ROSN | B40: 43525 | C40: 412 | D40: =C40/C39-1 -> 0.033099298 | F40: IMOEX | G40: 43525 | H40: 2497.1 | I40: =H40/H39-1 -> 0.0047600462 | U40: 26 | V40: 0.0665 | W40: =U40/$U$70 -> 0.010607915 | X40: =W40*V40 -> 0.00070542636
A41: ROSN | B41: 43556 | C41: 428.8 | D41: =C41/C40-1 -> 0.040776699 | F41: IMOEX | G41: 43556 | H41: 2559.32 | I41: =H41/H40-1 -> 0.024916904 | U41: 36 | V41: 0.089 | W41: =U41/$U$70 -> 0.014687882 | X41: =W41*V41 -> 0.0013072215
A42: ROSN | B42: 43586 | C42: 433 | D42: =C42/C41-1 -> 0.0097947761 | F42: IMOEX | G42: 43586 | H42: 2665.33 | I42: =H42/H41-1 -> 0.041421159 | U42: 55 | V42: 0.094 | W42: =U42/$U$70 -> 0.02243982 | X42: =W42*V42 -> 0.0021093431
A43: ROSN | B43: 43617 | C43: 414.5 | D43: =C43/C42-1 -> -0.042725173 | F43: IMOEX | G43: 43617 | H43: 2765.85 | I43: =H43/H42-1 -> 0.037713904 | U43: 30 | V43: 0.0939 | W43: =U43/$U$70 -> 0.012239902 | X43: =W43*V43 -> 0.0011493268
A44: ROSN | B44: 43647 | C44: 421.95 | D44: =C44/C43-1 -> 0.017973462 | F44: IMOEX | G44: 43647 | H44: 2739.5 | I44: =H44/H43-1 -> -0.0095269085 | U44: 20 | V44: 0.095 | W44: =U44/$U$70 -> 0.0081599347 | X44: =W44*V44 -> 0.0007751938
A45: ROSN | B45: 43678 | C45: 406.95 | D45: =C45/C44-1 -> -0.035549236 | F45: IMOEX | G45: 43678 | H45: 2740.04 | I45: =H45/H44-1 -> 0.00019711626 | U45: 41 | V45: 0.0865 | W45: =U45/$U$70 -> 0.016727866 | X45: =W45*V45 -> 0.0014469604
A46: ROSN | B46: 43709 | C46: 419.3 | D46: =C46/C45-1 -> 0.030347709 | F46: IMOEX | G46: 43709 | H46: 2747.18 | I46: =H46/H45-1 -> 0.0026058014 | U46: 15 | V46: 0.086 | W46: =U46/$U$70 -> 0.006119951 | X46: =W46*V46 -> 0.00052631579
A47: ROSN | B47: 43739 | C47: 426 | D47: =C47/C46-1 -> 0.015979013 | F47: IMOEX | G47: 43739 | H47: 2893.98 | I47: =H47/H46-1 -> 0.053436615 | U47: 30 | V47: 0.0775 | W47: =U47/$U$70 -> 0.012239902 | X47: =W47*V47 -> 0.00094859241
A48: ROSN | B48: 43770 | C48: 441 | D48: =C48/C47-1 -> 0.035211268 | F48: IMOEX | G48: 43770 | H48: 2935.37 | I48: =H48/H47-1 -> 0.014302103 | U48: 51 | V48: 0.075 | W48: =U48/$U$70 -> 0.020807834 | X48: =W48*V48 -> 0.0015605875
A49: ROSN | B49: 43800 | C49: 449.7 | D49: =C49/C48-1 -> 0.019727891 | F49: IMOEX | G49: 43800 | H49: 3045.87 | I49: =H49/H48-1 -> 0.037644317 | U49: 20 | V49: 0.073 | W49: =U49/$U$70 -> 0.0081599347 | X49: =W49*V49 -> 0.00059567523
A50: ROSN | B50: 43831 | C50: 480.5 | D50: =C50/C49-1 -> 0.068490105 | F50: IMOEX | G50: 43831 | H50: 3076.65 | I50: =H50/H49-1 -> 0.010105487 | U50: 31 | V50: 0.087 | W50: =U50/$U$70 -> 0.012647899 | X50: =W50*V50 -> 0.0011003672
A51: ROSN | B51: 43862 | C51: 403.4 | D51: =C51/C50-1 -> -0.16045786 | F51: IMOEX | G51: 43862 | H51: 2785.08 | I51: =H51/H50-1 -> -0.094768661 | U51: 26 | V51: 0.0795 | W51: =U51/$U$70 -> 0.010607915 | X51: =W51*V51 -> 0.00084332925
... A66: ROSN | B66: 44317 | C66: 529.25 | D66: =C66/C65-1 -> 0.0077113481 | F66: IMOEX | G66: 44317 | H66: 3634.76 | I66: =H66/H65-1 -> 0.025609481 | U66: 10 | V66: 0.095 | W66: =U66/$U$70 -> 0.0040799674 | X66: =W66*V66 -> 0.0003875969
U67: 5 | V67: 0.094 | W67: =U67/$U$70 -> 0.0020399837 | X67: =W67*V67 -> 0.00019175847
S68: =T35+T37+T68 -> 2451 | T68: 150 | U68: 150 | V68: 0.04199 | W68: =U68/$U$70 -> 0.06119951 | X68: =W68*V68 -> 0.0025697674
S69: 744
S70: 750 | U70: =SUM(U34:U68) -> 2451 | W70: =SUMPRODUCT(V34:V68,W34:W68) -> 0.063521093 | X70: =SUM(X34:X68) -> 0.063521093
S71: =S68+S69+S70 -> 3945

Sheet Доходный подход
A1: Отчет о прибылях и убытках МСФО, тыс.руб. | B1: ,
A2: Наименование показателя | B2: 2017 | C2: 2018 | D2: 2019 | E2: 2020
A3: Итого выручка от реализации и доход от совместных и ассоциированных предприятий, тыс.руб | B3: 6014000000 | C3: 8238000000 | D3: 8676000000 | E3: 5757000000
A4: Добыча жуд, млн.т | B4: 225.5 | C4: 230.2 | D4: 230.2 | E4: 204.5
A5: Переработка нефти, млн.т | B5: 112.8 | C5: 115 | D5: 110.2 | E5: 104
A6: Производство нефтепродуктов и нефтехимии, млн.т | B6: 109.1 | C6: 111.7 | D6: 107.5 | E6: 101.4
A7: Реализация нефти за рубежом, млн.т | B7: 121.8 | C7: 123.7 | D7: 149.4 | E7: 115.4
A8: Реализация нефти на внутреннем рынке | B8: 6.9 | C8: 5.4 | D8: 5.6 | E8: 5.2
A9: Реализация нефтепродуктов и нефтехимии за рубежом, млн.т. | B9: 71.9 | C9: 73.7 | D9: 71.1 | E9: 64.2
A10: Реализация нефтепродуктов и нефтехимии на внутреннем рынке, млн.т. | B10: 11.7 | C10: 13.7 | D10: 42 | E10: 37.9
A11: Добыча газа | B11: 68.41 | C11: 67.3 | D11: 67 | E11: 62.8
A12: Реализация газа в России | B12: 63.2
A13: Реализация газа за рубежом | B13: 0.7
A17: Общий объем реализации нефти, млн.т. | B17: =B7+B8 -> 128.7 | C17: =C7+C8 -> 129.1 | D17: 155 | E17: 120.6
A18: За рубеж | B18: 121.8 | C18: 123.7 | D18: 149.4 | E18: 115.4
A19: На внутреннем рынке | B19: 6.9 | C19: 5.4 | D19: 5.6 | E19: 5.2
A21: Общий объем реализации газа, млрд. м3 | B21: 63.9 | C21: 62 | D21: 61.77 | E21: 56.43
A22: За рубеж | B22: 0.7 | C22: 2.9 | D22: 4.85 | E22: 4.45
A23: На внутреннем рынке | B23: 63.2 | C23: 59.13 | D23: 56.92 | E23: 51.98
A24: Выручка от реализации газа, тыс.руб. | B24: 210000000 | C24: 234000000 | D24: 258800000 | E24: 239800000
B25: =B24/B3 -> 0.034918523 | C25: =C24/C3 -> 0.028404953 | D25: =D24/D3 -> 0.029829414 | E25: =E24/E3 -> 0.041653639
A27: Общий объем реализации нефтепродуктов, млн.т. | B27: =B28+B29 -> 83.4 | C27: =C28+C29 -> 87.4 | D27: =D28+D29 -> 85.6 | E27: =E28+E29 -> 77.25 | L27: MDA_RUS_4Q2020.pdf (rosneft.ru)
A28: За рубеж | B28: 71.9 | C28: 73.7 | D28: 71.1 | E28: 64.2 | L28: Анализ руководством финансового состояния и результатов деятельности Компании «Роснефть» за четвертый квартал 2018 года и 12 месяцев 2018 года (rosneft.ru)
A29: На внутреннем рынке | B29: 11.5 | C29: 13.7 | D29: 14.5 | E29: =D29*0.9 -> 13.05
C33: =C38/B38-1 -> 0.016645327 | D33: =D38/C38-1 -> 0.0080964376 | E33: =E38/D38-1 -> -0.086025344 | F33: =F38/E38-1 -> 0.0004881859 | G33: =G38/F38-1 -> 0.073172636 | H33: =H38/G38-1 -> 0.018478103 | I33: =I38/H38-1 -> 0.0089285714 | J33: =J38/I38-1 -> 0.03852064 | K33: =_xlfn.FORECAST.ETS(J37,C33:I33,C37:I37) -> 0.03852064
A34: ПРОГНОЗ ОБЪЕМА
A35: НЕФТЬ | L35: Сценарные условия, основные параметры прогноза социально-экономического развития Российской Федерации и прогнозируемые изменения цен (тарифов) на товары, услуги хозяйствующих субъектов, осуществляющих регулируемые виды деятельности в инфраструктурном секторе, на 2022 год и на плановый период 2023 и 2024 годов | Министерство экономического развития Российской Федерации (economy.gov.ru)
A37: Прогноз добычи нефти | B37: 2017 | C37: 2018 | D37: 2019 | E37: 2020 | F37: 2021 | G37: 2022 | H37: 2023 | I37: 2024 | J37: 2025 | L37: Сценарные условия, основные параметры прогноза социально-экономического развития Российской Федерации и прогнозируемые изменения цен (тарифов) на товары, услуги хозяйствующих субъектов, осуществляющих регулируемые виды деятельности в инфраструктурном секторе, на 2022 год и на плановый период 2023 и 2024 годов
A38: Добыча нефти РФ, млн.т (базовый сценарий) | B38: 546.7 | C38: 555.8 | D38: 560.3 | E38: 512.1 | F38: 512.35 | G38: 549.84 | H38: 560 | I38: 565 | J38: =I38*(1+K33) -> 586.76416 | L38: CAGR (2021-2024) | M38: =(I38/F38)^(1/4)-1 -> 0.024755899
A39: Добыча нефти Роснефть, млн.т | B39: =B4 -> 225.5 | C39: =C4 -> 230.2 | D39: =D4 -> 230.2 | E39: =E4 -> 204.5 | F39: =F38*F40 -> 209.65874 | G39: =G38*G40 -> 225.00003 | H39: =H38*H40 -> 229.1576 | I39: =I38*I40 -> 231.20365 | J39: =J38*J40 -> 240.10976
A40: Доля добычи Роснефти от добычи РФ | B40: =B39/B38 -> 0.41247485 | C40: =C39/C38 -> 0.41417776 | D40: =D39/D38 -> 0.41085133 | E40: =E39/E38 -> 0.39933607 | F40: =$B$41 -> 0.40921 | G40: =$B$41 -> 0.40921 | H40: =$B$41 -> 0.40921 | I40: =$B$41 -> 0.40921 | J40: =$B$41 -> 0.40921
A41: Средняя доля компании | B41: =AVERAGE(B40:E40) -> 0.40921
A43: Прогноз переработки нефти | B43: 2017 | C43: 2018 | D43: 2019 | E43: 2020 | F43: 2021 | G43: 2022 | H43: 2023 | I43: 2024 | J43: 2025
A44: Добыча нефти Роснефть, млн.т | B44: =B39 -> 225.5 | C44: =C39 -> 230.2 | D44: =D39 -> 230.2 | E44: =E39 -> 204.5 | F44: =F39 -> 209.65874 | G44: =G39 -> 225.00003 | H44: =H39 -> 229.1576 | I44: =I39 -> 231.20365 | J44: =J39 -> 240.10976
A45: Переработка нефти Роснефть, млн.т | B45: =B5 -> 112.8 | C45: =C5 -> 115 | D45: =D5 -> 110.2 | E45: 103.98 | F45: =F44*F46 -> 104.14594 | G45: =G44*G46 -> 111.76658 | H45: =H44*H46 -> 113.83181 | I45: =I44*I46 -> 114.84817 | J45: =J44*J46 -> 119.27219
A46: Доля переработки от добычи | B46: =B45/B44 -> 0.50022173 | C46: =C45/C44 -> 0.4995656 | D46: =D45/D44 -> 0.47871416 | E46: =E45/E44 -> 0.50845966 | F46: =$B$47 -> 0.49674029 | G46: =$B$47 -> 0.49674029 | H46: =$B$47 -> 0.49674029 | I46: =$B$47 -> 0.49674029 | J46: =$B$47 -> 0.49674029 | O46: Прогноз реализации нефтепродуктов за рубежом по видам подукции | P46: 2017 | Q46: 2018 | R46: 2019 | S46: 2020 | T46: 2021 | U46: 2022 | V46: 2023 | W46: 2024 | X46: 2025
A47: Средняя доля переработки | B47: =AVERAGE(B46:E46) -> 0.49674029 | O47: Реализация за рубеж, млн.т | P47: =B77 -> 68.1 | Q47: =C77 -> 70.1 | R47: =D77 -> 67.8 | S47: =E77 -> 62.2 | T47: =F77 -> 63.183764 | U47: =G77 -> 67.807087 | V47: =H77 -> 69.060033 | W47: =I77 -> 69.676641 | X47: 70.612584
O48: Дальнее зарубежье (Европа и Азия) | P48: =B80+B83 -> 63.7 | Q48: =C80+C83 -> 66 | R48: =D80+D83 -> 64.1 | S48: =E80+E83 -> 58.7 | T48: =F80+F83 -> 59.488444 | U48: =G80+G83 -> 63.841371 | V48: =H80+H83 -> 65.021038 | W48: =I80+I83 -> 65.601583 | X48: 70.612584
A49: Прогноз реализации нефти | B49: 2017 | C49: 2018 | D49: 2019 | E49: 2020 | F49: 2021 | G49: 2022 | H49: 2023 | I49: 2024 | J49: 2025 | O49: Автомобильный бензин | P49: 0.6 | Q49: 0.7 | R49: 1.1 | S49: 0.5 | T49: =T48*$P$50 -> 0.6797118 | U49: =U48*$P$50 -> 0.7294481 | V49: =V48*$P$50 -> 0.74292692 | W49: =W48*$P$50 -> 0.74956019 | X49: =X48*$P$50 -> 0.80681562
A50: Добыча нефти, млн.т | B50: =B44 -> 225.5 | C50: =C44 -> 230.2 | D50: =D44 -> 230.2 | E50: =E44 -> 204.5 | F50: =F44 -> 209.65874 | G50: =G44 -> 225.00003 | H50: =H44 -> 229.1576 | I50: =I44 -> 231.20365 | J50: =J44 -> 240.10976 | O50: Средняя величина реализации | P50: =AVERAGE(P49/P48,Q49/Q48,R49/R48,S49/S48) -> 0.011425947
A51: Реализация нефти, млн.т | B51: =B17 -> 128.7 | C51: =C17 -> 129.1 | D51: =D17 -> 155 | E51: =E17 -> 120.6 | F51: =F50*F52 -> 125.51257 | G51: =G50*G52 -> 134.69666 | H51: =H50*H52 -> 137.1856 | I51: =I50*I52 -> 138.41047 | J51: =J50*J52 -> 143.74213 | O51: Нафта | P51: 6.1 | Q51: 6.2 | R51: 5.3 | S51: 5.3 | T51: =$P$52*T47 -> 5.7287723 | U51: =$P$52*U47 -> 6.1479616 | V51: =$P$52*V47 -> 6.2615643 | W51: =$P$52*W47 -> 6.3174711 | X51: =$P$52*X47 -> 6.4023316
A52: Доля реализации от добычи | B52: =B51/B50 -> 0.57073171 | C52: =C51/C50 -> 0.56081668 | D52: =D51/D50 -> 0.67332754 | E52: =E51/E50 -> 0.58973105 | F52: =$B$53 -> 0.59865175 | G52: =$B$53 -> 0.59865175 | H52: =$B$53 -> 0.59865175 | I52: =$B$53 -> 0.59865175 | J52: =$B$53 -> 0.59865175 | O52: Средняя величина реализации | P52: =AVERAGE(P51/P48,Q51/Q48,R51/R48,S51/S48) -> 0.090668423
A53: Средняя доля реализации от добычи | B53: =AVERAGE(B52:E52) -> 0.59865175 | O53: Дизильное топливо | P53: 15.8 | Q53: 15.8 | R53: 13.6 | S53: 13.3 | T53: =$P$54*T48 -> 13.774191 | U53: =$P$54*U48 -> 14.782085 | V53: =$P$54*V48 -> 15.05523 | W53: =$P$54*W48 -> 15.189652 | X53: =$P$54*X48 -> 16.349919 | AC53: Прогноз добычи нефти | AD53: 2017 | AE53: 2018 | AF53: 2019 | AG53: 2020 | AH53: 2021 | AI53: 2022 | AJ53: 2023 | AK53: 2024 | AL53: 2025
A54: Реализация за рубеж, млн.т | B54: =B18 -> 121.8 | C54: =C18 -> 123.7 | D54: =D18 -> 149.4 | E54: =E18 -> 115.4 | F54: =F51*F55 -> 120.03119 | G54: =G51*G55 -> 128.81419 | H54: =H51*H55 -> 131.19443 | I54: =I51*I55 -> 132.36581 | J54: =J51*J55 -> 137.46463 | O54: Средняя величина реализации | P54: =AVERAGE(P53/P48,Q53/Q48,R53/R48,S53/S48) -> 0.23154398 | AC54: Добыча нефти РФ, млн.т | AD54: 546.7 | AE54: 555.8 | AF54: 560.3 | AG54: 512.1 | AH54: 512.35 | AI54: 549.84 | AJ54: 560 | AK54: 565 | AL54: 586.76416
A55: Доля реализации за рубеж | B55: =B54/B51 -> 0.94638695 | C55: =C54/C51 -> 0.95817196 | D55: =D54/D51 -> 0.96387097 | E55: =E54/E51 -> 0.95688226 | F55: =$B$56 -> 0.95632803 | G55: =$B$56 -> 0.95632803 | H55: =$B$56 -> 0.95632803 | I55: =$B$56 -> 0.95632803 | J55: =$B$56 -> 0.95632803 | O55: Мазут | P55: 25 | Q55: 25.4 | R55: 26.2 | S55: 25.8 | T55: =$P$56*T48 -> 24.175695 | U55: =$P$56*U48 -> 25.944694 | V55: =$P$56*V48 -> 26.424103 | W55: =$P$56*W48 -> 26.660033 | X55: =$P$56*X48 -> 28.696469 | AC55: Добыча нефти Роснефть, млн.т | AD55: 225.5 | AE55: 230.2 | AF55: 230.2 | AG55: 204.5 | AH55: 209.65874 | AI55: 225.00003 | AJ55: 229.1576 | AK55: 231.20365 | AL55: 240.10976
A56: Средняя доля реализации за рубеж | B56: =AVERAGE(B55:E55) -> 0.95632803 | O56: Средняя величина реализации | P56: =AVERAGE(P55/P48,Q55/Q48,R55/R48,S55/S48) -> 0.40639313 | AC56: Доля добычи Роснефти от добычи РФ
A57: Реализация в Европе, млн.т | B57: 65.7 | C57: 55.8 | D57: 61 | E57: 47.2 | F57: =F58*F54 -> 54.248464 | G57: =G58*G54 -> 58.217967 | H57: =H58*H54 -> 59.293725 | I57: =I58*I54 -> 59.823133 | J57: =J58*J54 -> 62.127558 | O57: Прочее | P57: 1 | Q57: 0.8 | R57: 0.7 | S57: 1.1 | T57: =$P$58*T48 -> 3.6963519 | U57: =$P$58*U48 -> 3.9668237 | V57: =$P$58*V48 -> 4.0401231 | W57: =$P$58*W48 -> 4.0761956 | X57: =$P$58*X48 -> 4.3875574 | AC57: Средняя доля компании | AD57: 0.40921
A58: Доля реализации в Европе от реализации за рубеж | B58: =B57/B54 -> 0.53940887 | C58: =C57/C54 -> 0.45109135 | D58: =D57/D54 -> 0.40829987 | E58: =E57/E54 -> 0.40901213 | F58: =$B$59 -> 0.45195305 | G58: =$B$59 -> 0.45195305 | H58: =$B$59 -> 0.45195305 | I58: =$B$59 -> 0.45195305 | J58: =$B$59 -> 0.45195305 | O58: Средняя величина реализации | P58: =AVERAGE(P59/P48,Q59/Q48,R59/R48,S59/S48) -> 0.062135629 | AC58: Прогноз добычи газа | AD58: 2017 | AE58: 2018 | AF58: 2019 | AG58: 2020 | AH58: 2021 | AI58: 2022 | AJ58: 2023 | AK58: 2024 | AL58: 2025
A59: Средняя доля реализации в Европе | B59: =AVERAGE(B58:E58) -> 0.45195305 | O59: СНГ | P59: =B86 -> 4.4 | Q59: =C86 -> 4.1 | R59: =D86 -> 3.7 | S59: =E86 -> 3.5 | T59: =F86 -> 3.69532 | U59: =G86 -> 3.9657163 | V59: =H86 -> 4.0389952 | W59: =I86 -> 4.0750576 | X59: =J86 -> 4.2320315 | AC59: Добыча газа РФ, млрд.м3 | AD59: 689.63667 | AE59: 725.17 | AF59: 737.59 | AG59: 694.3 | AH59: 698.3 | AI59: 770.1 | AJ59: 801.7 | AK59: 826.2 | AL59: 870.53897
A60: Реализация в Азии, млн.т | B60: 47.7 | C60: 59.2 | D60: 79.7 | E60: 61.9 | F60: =F61*F54 -> 58.217084 | G60: =G61*G54 -> 62.476981 | H60: =H61*H54 -> 63.631437 | I60: =I61*I54 -> 64.199575 | J60: =J61*J54 -> 66.672584 | O60: Автомобильный бензин | P60: =$P$50*P59 -> 0.050274166 | Q60: =$P$50*Q59 -> 0.046846382 | R60: =$P$50*R59 -> 0.042276003 | S60: =$P$50*S59 -> 0.039990814 | T60: =$P$50*T59 -> 0.042222529 | U60: =$P$50*U59 -> 0.045312063 | V60: =$P$50*V59 -> 0.046149344 | W60: =$P$50*W59 -> 0.046561392 | X60: =$P$50*X59 -> 0.048354966 | AC60: Добыча газа Роснефть, млрд.м3 | AD60: 68.41 | AE60: 67.3 | AF60: 67 | AG60: 62.8 | AH60: 65.167132 | AI60: 71.86769 | AJ60: 74.816683 | AK60: 77.103085 | AL60: 81.24091
A61: Доля реализации в Азии от реализации за рубеж | B61: =B60/B54 -> 0.39162562 | C61: =C60/C54 -> 0.4785772 | D61: =D60/D54 -> 0.5334672 | E61: =E60/E54 -> 0.53639515 | F61: =$B$62 -> 0.48501629 | G61: =$B$62 -> 0.48501629 | H61: =$B$62 -> 0.48501629 | I61: =$B$62 -> 0.48501629 | J61: =$B$62 -> 0.48501629 | O61: Нафта | P61: =$P$52*P59 -> 0.39894106 | Q61: =$P$52*Q59 -> 0.37174053 | R61: =$P$52*R59 -> 0.33547316 | S61: =$P$52*S59 -> 0.31733948 | T61: =$P$52*T59 -> 0.33504883 | U61: =$P$52*U59 -> 0.35956524 | V61: =$P$52*V59 -> 0.36620932 | W61: =$P$52*W59 -> 0.36947905 | X61: =$P$52*X59 -> 0.38371162 | AC61: Доля добычи Роснефти
A62: Средняя доля реализации в Азии | B62: =AVERAGE(B61:E61) -> 0.48501629 | O62: Дизильное топливо | P62: =$P$54*P59 -> 1.0187935 | Q62: =$P$54*Q59 -> 0.94933031 | R62: =$P$54*R59 -> 0.85671272 | S62: =$P$54*S59 -> 0.81040392 | T62: =$P$54*T59 -> 0.85562909 | U62: =$P$54*U59 -> 0.91823772 | V62: =$P$54*V59 -> 0.93520501 | W62: =$P$54*W59 -> 0.94355506 | X62: =$P$54*X59 -> 0.9799014 | AC62: Средняя доля компании | AD62: 0.093322543
A63: Реализация в странах СНГ, млн.т | B63: 8.4 | C63: =8.7 -> 8.7 | D63: 8.7 | E63: =6.3 -> 6.3 | F63: =F64*F54 -> 7.5656446 | G63: =G64*G54 -> 8.1192427 | H63: =H64*H54 -> 8.2692709 | I63: =I64*I54 -> 8.3431037 | J63: =J64*J54 -> 8.6644854 | O63: Мазут | P63: =$P$56*P59 -> 1.7881298 | Q63: =$P$56*Q59 -> 1.6662118 | R63: =$P$56*R59 -> 1.5036546 | S63: =$P$56*S59 -> 1.4223759 | T63: =$P$56*T59 -> 1.5017526 | U63: =$P$56*U59 -> 1.6116398 | V63: =$P$56*V59 -> 1.6414199 | W63: =$P$56*W59 -> 1.6560754 | X63: =$P$56*X59 -> 1.7198685
A64: Доля реализации в странах СНГ от реализации за рубеж | B64: =B63/B54 -> 0.068965517 | C64: =C63/C54 -> 0.070331447 | D64: =D63/D54 -> 0.058232932 | E64: =E63/E54 -> 0.054592721 | F64: =$B$65 -> 0.063030654 | G64: =$B$65 -> 0.063030654 | H64: =$B$65 -> 0.063030654 | I64: =$B$65 -> 0.063030654 | J64: =$B$65 -> 0.063030654 | O64: Прочее | P64: =$P$58*P59 -> 0.27339677 | Q64: =$P$58*Q59 -> 0.25475608 | R64: =$P$58*R59 -> 0.22990183 | S64: =$P$58*S59 -> 0.2174747 | T64: =$P$58*T59 -> 0.22961103 | U64: =$P$58*U59 -> 0.24641228 | V64: =$P$58*V59 -> 0.25096551 | W64: =$P$58*W59 -> 0.25320627 | X64: =$P$58*X59 -> 0.26295994
A65: Средняя доля реализации в странах СНГ | B65: =AVERAGE(B64:E64) -> 0.063030654 | O65: Итого реализация по видам продукции на внешнем рынке
A66: Реализация на внутреннем рынке, млн.т | B66: =B19 -> 6.9 | C66: =C19 -> 5.4 | D66: =D19 -> 5.6 | E66: =E19 -> 5.2 | F66: =F51*F67 -> 5.481381 | G66: =G51*G67 -> 5.8824681 | H66: =H51*H67 -> 5.991165 | I66: =I51*I67 -> 6.0446575 | J66: =J51*J67 -> 6.2775016 | O66: Автомобильный бензин | P66: =P49+P60 -> 0.65027417 | Q66: =Q49+Q60 -> 0.74684638 | R66: =R49+R60 -> 1.142276 | S66: =S49+S60 -> 0.53999081 | T66: =T49+T60 -> 0.72193433 | U66: =U49+U60 -> 0.77476016 | V66: =V49+V60 -> 0.78907626 | W66: =W49+W60 -> 0.79612158 | X66: =X49+X60 -> 0.85517059
A67: Доля реализации на внутреннем рынке | B67: =B66/B51 -> 0.053613054 | C67: =C66/C51 -> 0.04182804 | D67: =D66/D51 -> 0.036129032 | E67: =E66/E51 -> 0.043117745 | F67: =$B$68 -> 0.043671968 | G67: =$B$68 -> 0.043671968 | H67: =$B$68 -> 0.043671968 | I67: =$B$68 -> 0.043671968 | J67: =$B$68 -> 0.043671968 | O67: Нафта | P67: =P51+P61 -> 6.4989411 | Q67: =Q51+Q61 -> 6.5717405 | R67: =R51+R61 -> 5.6354732 | S67: =S51+S61 -> 5.6173395 | T67: =T51+T61 -> 6.0638211 | U67: =U51+U61 -> 6.5075269 | V67: =V51+V61 -> 6.6277736 | W67: =W51+W61 -> 6.6869502 | X67: =X51+X61 -> 6.7860432
A68: Средняя доля реализации на внутреннем рынке | B68: =AVERAGE(B67:E67) -> 0.043671968 | O68: Дизильное топливо | P68: =P53+P62 -> 16.818794 | Q68: =Q53+Q62 -> 16.74933 | R68: =R53+R62 -> 14.456713 | S68: =S53+S62 -> 14.110404 | T68: =T53+T62 -> 14.62982 | U68: =U53+U62 -> 15.700323 | V68: =V53+V62 -> 15.990435 | W68: =W53+W62 -> 16.133207 | X68: =X53+X62 -> 17.32982
O69: Мазут | P69: =P55+P63 -> 26.78813 | Q69: =Q55+Q63 -> 27.066212 | R69: =R55+R63 -> 27.703655 | S69: =S55+S63 -> 27.222376 | T69: =T55+T63 -> 25.677448 | U69: =U55+U63 -> 27.556334 | V69: =V55+V63 -> 28.065523 | W69: =W55+W63 -> 28.316108 | X69: =X55+X63 -> 30.416337
O70: Прочее | P70: =P57+P64 -> 1.2733968 | Q70: =Q57+Q64 -> 1.0547561 | R70: =R57+R64 -> 0.92990183 | S70: =S57+S64 -> 1.3174747 | T70: =T57+T64 -> 3.925963 | U70: =U57+U64 -> 4.213236 | V70: =V57+V64 -> 4.2910886 | W70: =W57+W64 -> 4.3294019 | X70: =X57+X64 -> 4.6505173
A71: НЕФТЕПРОДУКТЫ
A72: Прогноз производства и реализации нефтепродуктов | B72: 2017 | C72: 2018 | D72: 2019 | E72: 2020 | F72: 2021 | G72: 2022 | H72: 2023 | I72: 2024 | J72: 2025
A73: Переработка нефти, млн.т | B73: =B45 -> 112.8 | C73: =C45 -> 115 | D73: =D45 -> 110.2 | E73: =E45 -> 103.98 | F73: =F45 -> 104.14594 | G73: =G45 -> 111.76658 | H73: =H45 -> 113.83181 | I73: =I45 -> 114.84817 | J73: =J45 -> 119.27219
A74: Производство нефтепродуктов, млн.т | B74: =B6 -> 109.1 | C74: =C6 -> 111.7 | D74: =D6 -> 107.5 | E74: =E6 -> 101.4 | F74: =F73*F75 -> 101.26083 | G74: =G73*G75 -> 108.67035 | H74: =H73*H75 -> 110.67837 | I74: =I73*I75 -> 111.66657 | J74: =J73*J75 -> 115.96804
A75: Доля производства нефтепродуктов от переработки нефти | B75: =B74/B73 -> 0.96719858 | C75: =C74/C73 -> 0.97130435 | D75: =D74/D73 -> 0.97549909 | E75: =E74/E73 -> 0.97518754 | F75: =$B$76 -> 0.97229739 | G75: =$B$76 -> 0.97229739 | H75: =$B$76 -> 0.97229739 | I75: =$B$76 -> 0.97229739 | J75: =$B$76 -> 0.97229739
A76: Средняя доля производства нефтепродуктов | B76: =AVERAGE(B75:E75) -> 0.97229739
A77: Реализация за рубеж, млн.т | B77: 68.1 | C77: 70.1 | D77: 67.8 | E77: 62.2 | F77: =F74*F78 -> 63.183764 | G77: =G74*G78 -> 67.807087 | H77: =H74*H78 -> 69.060033 | I77: =I74*I78 -> 69.676641 | J77: =J74*J78 -> 72.36063
A78: Доля реализации за рубеж | B78: =B77/B74 -> 0.62419798 | C78: =C77/C74 -> 0.62757386 | D78: =D77/D74 -> 0.63069767 | E78: =E77/E74 -> 0.61341223 | F78: =$B$79 -> 0.62397044 | G78: =$B$79 -> 0.62397044 | H78: =$B$79 -> 0.62397044 | I78: =$B$79 -> 0.62397044 | J78: =$B$79 -> 0.62397044
A79: Средняя доля реализации за рубеж | B79: =AVERAGE(B78:E78) -> 0.62397044
A80: Реализация в Европе, млн.т | B80: 46 | C80: 49 | D80: 47.5 | E80: 43.8 | F80: =F81*F77 -> 43.900849 | G80: =G81*G77 -> 47.11319 | H80: =H81*H77 -> 47.983752 | I80: =I81*I77 -> 48.412178 | J80: =J81*J77 -> 50.277046
A81: Доля реализации в Европе | B81: =B80/B77 -> 0.67547724 | C81: =C80/C77 -> 0.69900143 | D81: =D80/D77 -> 0.70058997 | E81: =E80/E77 -> 0.70418006 | F81: =$B$82 -> 0.69481218 | G81: =$B$82 -> 0.69481218 | H81: =$B$82 -> 0.69481218 | I81: =$B$82 -> 0.69481218 | J81: =$B$82 -> 0.69481218
A82: Средняя доля реализации в Европе | B82: =AVERAGE(B81:E81) -> 0.69481218
A83: Реализация в Азии, млн.т | B83: 17.7 | C83: 17 | D83: 16.6 | E83: 14.9 | F83: =F84*F77 -> 15.587596 | G83: =G84*G77 -> 16.728181 | H83: =H84*H77 -> 17.037286 | I83: =I84*I77 -> 17.189405 | J83: =J84*J77 -> 17.851552
A84: Доля реализации в Азии | B84: =B83/B77 -> 0.25991189 | C84: =C83/C77 -> 0.2425107 | D84: =D83/D77 -> 0.24483776 | E84: =E83/E77 -> 0.23954984 | F84: =$B$85 -> 0.24670255 | G84: =$B$85 -> 0.24670255 | H84: =$B$85 -> 0.24670255 | I84: =$B$85 -> 0.24670255 | J84: =$B$85 -> 0.24670255
A85: Средняя доля реализации в Азии | B85: =AVERAGE(B84:E84) -> 0.24670255
A86: Реализация в странах СНГ, млн.т | B86: 4.4 | C86: 4.1 | D86: 3.7 | E86: 3.5 | F86: =F87*F77 -> 3.69532 | G86: =G87*G77 -> 3.9657163 | H86: =H87*H77 -> 4.0389952 | I86: =I87*I77 -> 4.0750576 | J86: =J87*J77 -> 4.2320315
A87: Доля реализации в странах СНГ | B87: =B86/B77 -> 0.064610866 | C87: =C86/C77 -> 0.058487874 | D87: =D86/D77 -> 0.054572271 | E87: =E86/E77 -> 0.056270096 | F87: =$B$88 -> 0.058485277 | G87: =$B$88 -> 0.058485277 | H87: =$B$88 -> 0.058485277 | I87: =$B$88 -> 0.058485277 | J87: =$B$88 -> 0.058485277
A88: Средняя доля реализации в странах СНГ | B88: =AVERAGE(B87:E87) -> 0.058485277
A89: Реализация на внутреннем рынке, млн.т | B89: 38.7 | C89: 39.9 | D89: 41.4 | E89: 37.2 | F89: =F90*F74 -> 37.05912 | G89: =G90*G74 -> 39.770834 | H89: =H90*H74 -> 40.505723 | I89: =I90*I74 -> 40.867382 | J89: =J90*J74 -> 42.441619
A90: Доля реализации на внутреннем рынке | B90: =B89/B74 -> 0.35472044 | C90: =C89/C74 -> 0.3572068 | D90: =D89/D74 -> 0.38511628 | E90: =E89/E74 -> 0.36686391 | F90: =$B$91 -> 0.36597686 | G90: =$B$91 -> 0.36597686 | H90: =$B$91 -> 0.36597686 | I90: =$B$91 -> 0.36597686 | J90: =$B$91 -> 0.36597686
A91: Средняя доля реализации на внутреннем рынке | B91: =AVERAGE(B90:E90) -> 0.36597686
A92: Реализация бункерного топлива покупателям, млн.т | B92: 2.8 | C92: 3.1 | D92: 2.8 | E92: 1.9 | F92: =F93*F74 -> 2.4859944 | G92: =G93*G74 -> 2.6679012 | H92: =H93*H74 -> 2.717199 | I92: =I93*I74 -> 2.7414597 | J92: =J93*J74 -> 2.8470624
A93: Доля реализации бункерного топлива покупателям | B93: =B92/B74 -> 0.025664528 | C93: =C92/C74 -> 0.02775291 | D93: =D92/D74 -> 0.026046512 | E93: =E92/E74 -> 0.018737673 | F93: =$B$94 -> 0.024550405 | G93: =$B$94 -> 0.024550405 | H93: =$B$94 -> 0.024550405 | I93: =$B$94 -> 0.024550405 | J93: =$B$94 -> 0.024550405
A94: Средняя доля реализации бункерного топлива покупателям | B94: =AVERAGE(B93:E93) -> 0.024550405
A98: Прогноз реализации нефтепродуктов за рубежом по видам подукции | B98: 2017 | C98: 2018 | D98: 2019 | E98: 2020 | F98: 2021 | G98: 2022 | H98: 2023 | I98: 2024 | J98: 2025
A99: Реализация за рубеж, млн.т | B99: =B77 -> 68.1 | C99: =C77 -> 70.1 | D99: =D77 -> 67.8 | E99: =E77 -> 62.2 | F99: =F77 -> 63.183764 | G99: =G77 -> 67.807087 | H99: =H77 -> 69.060033 | I99: =I77 -> 69.676641 | J99: =J77 -> 72.36063
A100: Дальнее зарубежье (Европа и Азия) | B100: =B80+B83 -> 63.7 | C100: =C80+C83 -> 66 | D100: =D80+D83 -> 64.1 | E100: =E80+E83 -> 58.7 | F100: =F80+F83 -> 59.488444 | G100: =G80+G83 -> 63.841371 | H100: =H80+H83 -> 65.021038 | I100: =I80+I83 -> 65.601583 | J100: =J80+J83 -> 68.128598
A101: Автомобильный бензин | B101: 0.6 | C101: 0.7 | D101: 1.1 | E101: 0.5 | F101: =F100*F102 -> 0.6797118 | G101: =G100*G102 -> 0.7294481 | H101: =H100*H102 -> 0.74292692 | I101: =I100*I102 -> 0.74956019 | J101: =J100*J102 -> 0.77843373
A102: Доля реализации на автомобильного бензина | B102: =B101/B100 -> 0.0094191523 | C102: =C101/C100 -> 0.010606061 | D102: =D101/D100 -> 0.017160686 | E102: =E101/E100 -> 0.0085178876 | F102: =$B$103 -> 0.011425947 | G102: =$B$103 -> 0.011425947 | H102: =$B$103 -> 0.011425947 | I102: =$B$103 -> 0.011425947 | J102: =$B$103 -> 0.011425947
A103: Средняя величина реализации автомобильного бензина | B103: =AVERAGE(B102:E102) -> 0.011425947 | F103: Х | G103: Х | H103: Х | I103: Х | J103: Х
A104: Нафта | B104: 6.1 | C104: 6.2 | D104: 5.3 | E104: 5.3 | F104: =F100*F105 -> 5.3937234 | G104: =G100*G105 -> 5.7883964 | H104: =H100*H105 -> 5.895355 | I104: =I100*I105 -> 5.9479921 | J104: =J100*J105 -> 6.1771125
A105: Доля реализации нафты | B105: =B104/B100 -> 0.095761381 | C105: =C104/C100 -> 0.093939394 | D105: =D104/D100 -> 0.082683307 | E105: =E104/E100 -> 0.090289608 | F105: =$B$106 -> 0.090668423 | G105: =$B$106 -> 0.090668423 | H105: =$B$106 -> 0.090668423 | I105: =$B$106 -> 0.090668423 | J105: =$B$106 -> 0.090668423
A106: Средняя величина реализации нафты | B106: =AVERAGE(B105:E105) -> 0.090668423 | F106: Х | G106: Х | H106: Х | I106: Х | J106: Х
A107: Дизильное топливо | B107: 15.8 | C107: 15.8 | D107: 13.6 | E107: 13.3 | F107: =F100*F108 -> 13.774191 | G107: =G100*G108 -> 14.782085 | H107: =H100*H108 -> 15.05523 | I107: =I100*I108 -> 15.189652 | J107: =J100*J108 -> 15.774767
A108: Доля реализации дизельного топлива | B108: =B107/B100 -> 0.24803768 | C108: =C107/C100 -> 0.23939394 | D108: =D107/D100 -> 0.21216849 | E108: =E107/E100 -> 0.22657581 | F108: =$B$109 -> 0.23154398 | G108: =$B$109 -> 0.23154398 | H108: =$B$109 -> 0.23154398 | I108: =$B$109 -> 0.23154398 | J108: =$B$109 -> 0.23154398
A109: Средняя величина реализации дизельного топлива | B109: =AVERAGE(B108:E108) -> 0.23154398 | F109: Х | G109: Х | H109: Х | I109: Х | J109: Х
A110: Мазут | B110: 25 | C110: 25.4 | D110: 26.2 | E110: 25.8 | F110: =F100*F111 -> 24.175695 | G110: =G100*G111 -> 25.944694 | H110: =H100*H111 -> 26.424103 | I110: =I100*I111 -> 26.660033 | J110: =J100*J111 -> 27.686994
A111: Доля реализации мазута | B111: =B110/B100 -> 0.39246468 | C111: =C110/C100 -> 0.38484848 | D111: =D110/D100 -> 0.40873635 | E111: =E110/E100 -> 0.439523 | F111: =$B$112 -> 0.40639313 | G111: =$B$112 -> 0.40639313 | H111: =$B$112 -> 0.40639313 | I111: =$B$112 -> 0.40639313 | J111: =$B$112 -> 0.40639313
A112: Средняя величина реализации мазута | B112: =AVERAGE(B111:E111) -> 0.40639313 | F112: Х | G112: Х | H112: Х | I112: Х | J112: Х | AC112: Прогноз переработки нефти | AD112: 2017 | AE112: 2018 | AF112: 2019 | AG112: 2020 | AH112: 2021 | AI112: 2022 | AJ112: 2023 | AK112: 2024 | AL112: 2025
A113: Прочее | B113: 1 | C113: 0.8 | D113: 0.7 | E113: 1.1 | F113: =F100*F114 -> 0.85484283 | G113: =G100*G114 -> 0.91739393 | H113: =H100*H114 -> 0.93434563 | I113: =I100*I114 -> 0.942688 | J113: =J100*J114 -> 0.97900095 | AC113: Добыча нефти Роснефть, млн.т | AD113: 225.5 | AE113: 230.2 | AF113: 230.2 | AG113: 204.5 | AH113: 209.65874 | AI113: 225.00003 | AJ113: 229.1576 | AK113: 231.20365 | AL113: 240.10976
...

Sheet Сравнительный подход
C1: https://finance.yahoo.com
C2: КУРС ДОЛЛАРА НА 31.12.2020 | D2: 73.87
A3: Общие сведения
A4: Эмитент | B4: Страна | C4: Тикер | D4: Запасы углеводородов, млрд. барр. нефтяного эквивалента на 31.12.2019 | E4: Выручка, млрд.руб. | F4: Чистая прибыль, млрд.руб | G4: Активы, млрд.руб | H4: Собственнный капитал, млрд.руб | I4: ROE | J4: ROS | K4: ROA
A7: Российские компании
A8: ПАО «НК «Роснефть» | B8: РФ | C8: ROSN | D8: 42.018 | E8: =[1]IS!J6/1000000 -> 5757 | F8: =[1]IS!J26/1000000 -> 181 | G8: =[1]BS!J25/1000000 -> 15350 | H8: =[1]BS!J52/1000000 -> 5487 | I8: =F8/H8 -> 0.03298706 | J8: =F8/E8 -> 0.031439986 | K8: =F8/G8 -> 0.011791531
A9: ПАО «Газпром» | B9: РФ | C9: GAZP | D9: 177.1 | E9: 6321 | F9: 162.407 | G9: 23352 | H9: 14804 | I9: =F9/H9 -> 0.010970481 | J9: =F9/E9 -> 0.025693245 | K9: =F9/G9 -> 0.0069547362
A10: ПАО «ЛУКОЙЛ» | B10: РФ | C10: LKOH | D10: 15.8 | E10: 5639 | F10: 16.63 | G10: 5992 | H10: 4130.76 | I10: =F10/H10 -> 0.0040258935 | J10: =F10/E10 -> 0.0029491045 | K10: =F10/G10 -> 0.0027753672
A11: ПАО «НОВАТЭК» | B11: РФ | C11: NVTK | D11: 16.265 | E11: 711.8 | F11: 169 | G11: 2059 | H11: 1638.42 | I11: =F11/H11 -> 0.10314815 | J11: =F11/E11 -> 0.23742624 | K11: =F11/G11 -> 0.082078679
A12: ПАО «Сургутнефтегаз» | B12: РФ | C12: SNGS | D12: =0.76*7.3 -> 5.548 | E12: 1075.2 | F12: 743 | G12: 5876 | H12: 5160.4 | I12: =F12/H12 -> 0.14398109 | J12: =F12/E12 -> 0.69103423 | K12: =F12/G12 -> 0.12644656
A13: ПАО «Татнефть» им. В.Д. Шашина | B13: РФ | C13: TATN | D13: 6.679 | E13: 720.7 | F13: 103.6 | G13: 1264 | H13: 831.59 | I13: =F13/H13 -> 0.12458062 | J13: =F13/E13 -> 0.14374913 | K13: =F13/G13 -> 0.081962025
A14: Стандартное отклонение | D14: =_xlfn.STDEV.S(D8:D13) -> 66.566304 | E14: =_xlfn.STDEV.S(E8:E13) -> 2789.4606 | F14: =_xlfn.STDEV.S(F8:F13) -> 258.98276 | G14: =_xlfn.STDEV.S(G8:G13) -> 8638.647 | H14: =_xlfn.STDEV.S(H8:H13) -> 5002.2166 | I14: =_xlfn.STDEV.S(I8:I13) -> 0.061250395 | J14: =_xlfn.STDEV.S(J8:J13) -> 0.26174026 | K14: =_xlfn.STDEV.S(K8:K13) -> 0.051794984 | P14: ev/ebitda
A15: Среднее значение | D15: =AVERAGE(D8:D13) -> 43.901667 | E15: =AVERAGE(E8:E13) -> 3370.7833 | F15: =AVERAGE(F8:F13) -> 229.27283 | G15: =AVERAGE(G8:G13) -> 8982.1667 | H15: =AVERAGE(H8:H13) -> 5342.0283 | I15: =AVERAGE(I8:I13) -> 0.069948883 | J15: =AVERAGE(J8:J13) -> 0.18871532 | K15: =AVERAGE(K8:K13) -> 0.052001483
A16: Коэффициент вариации | D16: =D14/D15 -> 1.5162591 | E16: =E14/E15 -> 0.82754076 | F16: =F14/F15 -> 1.1295833 | G16: =G14/G15 -> 0.96175537 | H16: =H14/H15 -> 0.936389 | I16: =I14/I15 -> 0.87564508 | J16: =J14/J15 -> 1.3869582 | K16: =K14/K15 -> 0.99602897 | P16: 8.9644573 | Q16: =MAX(P16:P21) -> 28.111842 | S16: убираем новатэк | U16: =MAX(S17:S21) -> 8.9644573
A17: Зарубежные компании | P17: 5.9195471 | Q17: =MIN(P16:P21) -> 5.5502008 | S17: 8.9644573 | U17: =MIN(S17:S21) -> 5.5502008
A18: ExxonMobil | B18: США | C18: XOM | D18: 22.45 | E18: 13191 | F18: -1657.6428 | G18: 24580 | H18: 12124 | I18: =F18/H18 -> -0.13672408 | J18: =F18/E18 -> -0.12566468 | K18: =F18/G18 -> -0.067438682 | P18: 6.2532751 | Q18: =AVERAGE(P16:P21) -> 10.171395 | S18: 5.9195471 | U18: =AVERAGE(S17:S21) -> 6.5833061
A19: Chevron Corporation | B19: США | C19: CVX | D19: 13 | E19: 6979 | F19: -409 | G19: 17713 | H19: 9804 | I19: =F19/H19 -> -0.041717666 | J19: =F19/E19 -> -0.058604385 | K19: =F19/G19 -> -0.023090386 | P19: 28.111842 | Q19: =_xlfn.STDEV.S(P16:P21) -> 8.8729221 | S19: 6.2532751 | U19: =_xlfn.STDEV.S(S17:S21) -> 1.3612661
A20: Royal Dutch Shell | B20: Нидерланды | C20: RDS | D20: 9.8 | E20: =180543000*$D$2/1000000 -> 13336.711 | F20: =-21680000*$D$2/1000000 -> -1601.5016 | G20: =379267000*$D$2/1000000 -> 28016.453 | H20: =158537000*$D$2/1000000 -> 11711.128 | I20: =F20/H20 -> -0.13675041 | J20: =F20/E20 -> -0.1200822 | K20: =F20/G20 -> -0.057162896 | P20: 5.5502008 | S20: 5.5502008
A21: Total | B21: Франция | C21: TOT | D21: 12.681 | E21: =119704000*$D$2/1000000 -> 8842.5345 | F21: =-7242000*$D$2/1000000 -> -534.96654 | G21: =266132000*$D$2/1000000 -> 19659.171 | H21: =180543000*$D$2/1000000 -> 13336.711 | I21: =F21/H21 -> -0.040112328 | J21: =F21/E21 -> -0.060499231 | K21: =F21/G21 -> -0.02721206 | P21: 6.2290503 | Q21: =(Q16-Q18)/Q19 -> 2.0219322 | S21: 6.2290503 | U21: =(U16-U18)/U19 -> 1.7492181
A22: BP | B22: Великобритания | C22: BP | D22: 19.341 | E22: =180366000*$D$2/1000000 -> 13323.636 | F22: =-20306000*$D$2/1000000 -> -1500.0042 | G22: =267654000*$D$2/1000000 -> 19771.601 | H22: =85568000*$D$2/1000000 -> 6320.9082 | I22: =F22/H22 -> -0.23730834 | J22: =F22/E22 -> -0.11258219 | K22: =F22/G22 -> -0.075866604 | Q22: =ABS(Q17-Q18)/Q19 -> 0.52081993 | U22: =ABS(U17-U18)/U19 -> 0.75892975
A23: Стандартное отклонение | D23: =_xlfn.STDEV.S(D18:D22) -> 5.2376556 | E23: =_xlfn.STDEV.S(E18:E22) -> 3016.3111 | F23: =_xlfn.STDEV.S(F18:F22) -> 614.60666 | G23: =_xlfn.STDEV.S(G18:G22) -> 4232.7363 | H23: =_xlfn.STDEV.S(H18:H22) -> 2737.3985 | I23: =_xlfn.STDEV.S(I18:I22) -> 0.081885236 | J23: =_xlfn.STDEV.S(J18:J22) -> 0.033137339 | K23: =_xlfn.STDEV.S(K18:K22) -> 0.023810684 | Q23: 1.89 | U23: 1.79
A24: Среднее значение | D24: =AVERAGE(D18:D22) -> 15.4544 | E24: =AVERAGE(E18:E22) -> 11134.576 | F24: =AVERAGE(F18:F22) -> -1140.623 | G24: =AVERAGE(G18:G22) -> 21948.045 | H24: =AVERAGE(H18:H22) -> 10659.35 | I24: =AVERAGE(I18:I22) -> -0.11852257 | J24: =AVERAGE(J18:J22) -> -0.095486537 | K24: =AVERAGE(K18:K22) -> -0.050154125 | S24: =AVERAGE(S17:S21) -> 6.5833061
A25: Коэффициент вариации | D25: =D23/D24 -> 0.33891032 | E25: =E23/E24 -> 0.2708959 | F25: =F23/F24 -> -0.53883416 | G25: =G23/G24 -> 0.19285254 | H25: =H23/H24 -> 0.25680727 | I25: =I23/I24 -> -0.69088309 | J25: =J23/J24 -> -0.34703677 | K25: =K23/K24 -> -0.47475026
A26: В целом по выборке
A27: Стандартное отклонение | D27: =_xlfn.STDEV.S(D8:D13,D18:D22) -> 49.469317 | E27: =_xlfn.STDEV.S(E8:E13,E18:E22) -> 4895.7981 | F27: =_xlfn.STDEV.S(F8:F13,F18:F22) -> 834.52776 | G27: =_xlfn.STDEV.S(G8:G13,G18:G22) -> 9504.1468 | H27: =_xlfn.STDEV.S(H8:H13,H18:H22) -> 4818.6607 | I27: =_xlfn.STDEV.S(I8:I13,I18:I22) -> 0.11935477 | J27: =_xlfn.STDEV.S(J8:J13,J18:J22) -> 0.23816294 | K27: =_xlfn.STDEV.S(K8:K13,K18:K22) -> 0.066439885
A28: Среднее значение | D28: =AVERAGE(D8:D13,D18:D22) -> 30.971091 | E28: =AVERAGE(E8:E13,E18:E22) -> 6899.7802 | F28: =AVERAGE(F8:F13,F18:F22) -> -393.40711 | G28: =AVERAGE(G8:G13,G18:G22) -> 14875.748 | H28: =AVERAGE(H8:H13,H18:H22) -> 7758.9925 | I28: =AVERAGE(I8:I13,I18:I22) -> -0.015719957 | J28: =AVERAGE(J8:J13,J18:J22) -> 0.059532659 | K28: =AVERAGE(K8:K13,K18:K22) -> 0.0055671158
A29: Коэффициент вариации | D29: =D27/D28 -> 1.597274 | E29: =E27/E28 -> 0.70955856 | F29: =F27/F28 -> -2.1212829 | G29: =G27/G28 -> 0.63890212 | H29: =H27/H28 -> 0.62104205 | I29: =I27/I28 -> -7.5925631 | J29: =J27/J28 -> 4.0005426 | K29: =K27/K28 -> 11.934346
A32: ПРИБЫЛИ
A33: КУРС ДОЛЛАРА НА 21.05.2021 | B33: 73.58 | T33: 17.053651 | V33: =MAX(T34:T38) -> 18.733273
A34: Эмитент | B34: Капитализация, млрд.руб. на 21.05.2021 | C34: ЧП, млрд.руб | D34: Долг, млрд.руб. | E34: Денежные средства, млрд.руб. | F34: EV, млрд.руб. | G34: Операционная прибыль, млрд.руб. | H34: Амортизация, млрд.руб | I34: EBITDA, млрд.руб | J34: P/E | K34: EV/EBITDA | P34: Среднее значение Р/Е по российским компаниям | Q34: =J65 -> 28.214597 | T34: 18.733273 | V34: =MIN(T34:T38) -> 3.4733246
P35: Чистая прибыль «Роснефть», тыс.руб. | Q35: =F8*1000000 -> 181000000 | T35: 9.810425 | V35: =AVERAGE(T34:T38) -> 10.672341
P36: Количество акций, шт. | Q36: 10598177817 | T36: 3.4733246 | V36: =_xlfn.STDEV.S(T34:T38) -> 7.6663992
A37: Российские компании | P37: Текущая стоимость, руб. (на 21.05.2021) | Q37: 525.55
A38: ПАО «НК «Роснефть» | B38: 5530 | C38: =F8 -> 181 | D38: 4608 | E38: =[1]BS!J5/1000000 -> 806 | F38: =B38+D38-E38 -> 9332 | G38: =[1]IS!J17/1000000 -> 378 | H38: =-[1]IS!J13/1000000 -> 663 | I38: =G38+H38 -> 1041 | J38: =B38/C38 -> 30.552486 | K38: =F38/I38 -> 8.9644573 | P38: Справедливая стоимость по Р/Е российсхих компаний, руб. | Q38: =Q34*Q35/Q36*1000 -> 481.86039 | V38: =(V33-V35)/V36 -> 1.0514626
A39: ПАО «Газпром» | B39: 6060 | C39: 135 | D39: 4908 | E39: 1035 | F39: =B39+D39-E39 -> 9933 | G39: 615 | H39: 1063 | I39: =G39+H39 -> 1678 | J39: =B39/C39 -> 44.888889 | K39: =F39/I39 -> 5.9195471 | P39: Различие внутренней стоимости и текущей по Р/Е российских компаний | Q39: =Q38/Q37-1 -> -0.083131218 | V39: =ABS(V34-V35)/V36 -> 0.93903486
A40: ПАО «ЛУКОЙЛ» | B40: 3980 | C40: =F10 -> 16.63 | D40: 660 | E40: 344 | F40: =B40+D40-E40 -> 4296 | G40: 282 | H40: 405 | I40: =G40+H40 -> 687 | J40: =B40/C40 -> 239.32652 | K40: =F40/I40 -> 6.2532751 | P40: Среднее значение Р/Е по зарубежным компаниям | Q40: нд | V40: 1.65
A41: ПАО «НОВАТЭК» | B41: 4160 | C41: 79 | D41: 233 | E41: 120 | F41: =B41+D41-E41 -> 4273 | G41: 113 | H41: 39 | I41: =G41+H41 -> 152 | J41: =B41/C41 -> 52.658228 | K41: =F41/I41 -> 28.111842 | P41: Чистая прибыль «Роснефть», тыс.руб. | Q41: нд
A42: ПАО «Сургутнефтегаз» | B42: 1560 | C42: =F12 -> 743 | D42: 0 | E42: 178 | F42: =B42+D42-E42 -> 1382 | G42: 165 | H42: 84 | I42: =G42+H42 -> 249 | J42: =B42/C42 -> 2.0995962 | K42: =F42/I42 -> 5.5502008 | P42: Количество акций, шт. | Q42: нд
A43: ПАО «Татнефть» им. В.Д. Шашина | B43: 1120 | C43: 103 | D43: 35 | E43: 40 | F43: =B43+D43-E43 -> 1115 | G43: 138 | H43: 41 | I43: =G43+H43 -> 179 | J43: =B43/C43 -> 10.873786 | K43: =F43/I43 -> 6.2290503 | P43: Текущая стоимость, руб. (на 21.05.2021) | Q43: 525.55
A44: Стандартное отклонение | J44: =_xlfn.STDEV.S(J38:J43) -> 88.322011 | K44: =_xlfn.STDEV.S(K38:K43) -> 8.8729221 | P44: Справедливая стоимость по Р/Е зарубежных компаний, руб. | Q44: нд
A45: Среднее значение | J45: =AVERAGE(J38:J43) -> 63.399917 | K45: =AVERAGE(K38:K43) -> 10.171395 | P45: Различие внутренней стоимости и текущей по Р/Е зарубежных компаний | Q45: нд
A46: Зарубежные компании | P46: Среднее значение Р/Е по выборке | Q46: =Q34 -> 28.214597
A47: ExxonMobil | B47: =249.44*$B$33 -> 18353.795 | C47: =F18 -> -1657.6428 | D47: =67.64*$D$2 -> 4996.5668 | E47: =4.36*$D$2 -> 322.0732 | F47: =B47+D47-E47 -> 23028.289 | G47: =-27.72*$D$2 -> -2047.6764 | H47: =46*$D$2 -> 3398.02 | I47: =G47+H47 -> 1350.3436 | J47: - | K47: =F47/I47 -> 17.053651 | P47: Чистая прибыль «Роснефть», тыс.руб. | Q47: =Q35 -> 181000000 | T47: 8.9644573 | V47: =MAX(T47:T56) -> 28.111842
A48: Chevron Corporation | B48: =200.75*$B$33 -> 14771.185 | C48: =F19 -> -409 | D48: =44.32*$D$2 -> 3273.9184 | E48: =5.62*$D$2 -> 415.1494 | F48: =B48+D48-E48 -> 17629.954 | G48: =-6.76*$D$2 -> -499.3612 | H48: =19.5*$D$2 -> 1440.465 | I48: =G48+H48 -> 941.1038 | J48: - | K48: =F48/I48 -> 18.733273 | P48: Количество акций, шт. | Q48: 10598177817 | T48: 5.9195471 | V48: =MIN(T47:T56) -> 3.4733246
A49: Royal Dutch Shell | B49: =(150.87)*$B$33 -> 11101.015 | C49: =F20 -> -1601.5016 | D49: =108.01*$D$2 -> 7978.6987 | E49: =31.765*$D$2 -> 2346.4806 | F49: =B49+D49-E49 -> 16733.233 | G49: =-22.91*$D$2 -> -1692.3617 | H49: =46*$D$2 -> 3398.02 | I49: =G49+H49 -> 1705.6583 | J49: - | K49: =F49/I49 -> 9.810425 | P49: Текущая стоимость, руб. (на 21.05.2021) | Q49: 525.55 | T49: 6.2532751 | V49: =AVERAGE(T47:T56) -> 11.009905
A50: Total | B50: =123.8*$B$33 -> 9109.204 | C50: =F21 -> -534.96654 | D50: =77.3*$D$2 -> 5710.151 | E50: =35.77*$D$2 -> 2642.3299 | F50: =B50+D50-E50 -> 12177.025 | G50: =-4.98*$D$2 -> -367.8726 | H50: =52.44*$D$2 -> 3873.7428 | I50: =G50+H50 -> 3505.8702 | J50: - | K50: =F50/I50 -> 3.4733246 | P50: Справедливая стоимость по Р/Е выборки, руб. | Q50: =Q46*Q47/Q48*1000 -> 481.86039 | T50: 28.111842 | V50: =_xlfn.STDEV.S(T47:T56) -> 7.8335347
A51: BP | B51: =88.76*$B$33 -> 6530.9608 | C51: =F22 -> -1500.0042 | D51: =43.47*$D$2 -> 3211.1289 | E51: =29.53*$D$2 -> 2181.3811 | F51: =B51+D51-E51 -> 7560.7086 | G51: =-21.73*$D$2 -> -1605.1951 | H51: =14.89*$D$2 -> 1099.9243 | I51: =G51+H51 -> -505.2708 | J51: - | K51: - | P51: Различие внутренней стоимости и текущей по Р/Е выборки | Q51: =Q50/Q49-1 -> -0.083131218 | T51: 5.5502008
A52: Стандартное отклонение | J52: нд | K52: =_xlfn.STDEV.S(K47:K51) -> 7.0258617 | T52: 6.2290503 | V52: =(V47-V49)/V50 -> 2.1831699
A53: Среднее значение | J53: нд | K53: =AVERAGE(K47:K51) -> 12.267668 | T53: 17.053651 | V53: =ABS(V48-V49)/V50 -> 0.96209187
A54: В целом по выборке | P54: Среднее значение EV/EBITDA по российским компаниям | Q54: =S24 -> 6.5833061 | T54: 18.733273 | V54: 2.15
A55: Стандартное отклонение | J55: =_xlfn.STDEV.S(J38:J43) -> 88.322011 | K55: =_xlfn.STDEV.S(K38:K43,K47:K51) -> 7.8335347 | P55: EBITDA «Роснефть», тыс.руб. | Q55: =[1]IS!J17-[1]IS!J13 -> 1041000000 | T55: 9.810425
A56: Среднее значение | J56: =AVERAGE(J38:J43) -> 63.399917 | K56: =AVERAGE(K38:K43,K47:K51) -> 11.009905 | P56: Количество акций, шт. | Q56: 10598177817 | T56: 3.4733246
P57: Текущая стоимость, руб. (на 21.05.2021) | Q57: 525.55
A58: Мультипликатор Р/Е российских компаний | G58: Р/Е | P58: Справедливая стоимость по EV/EBITDA российсхих компаний, руб. | Q58: =Q54*Q55/Q56*1000 -> 646.64151 | T58: убираем новотэк
A59: Компания | B59: Р/Е | D59: max | E59: =G59 -> 239.32652 | F59: 30.552486 | G59: =MAX(F59:F64) -> 239.32652 | P59: Различие внутренней стоимости и текущей по EV/EBITDA российских компаний | Q59: =Q58/Q57-1 -> 0.2304091
A60: ПАО «НК «Роснефть» | B60: =J38 -> 30.552486 | D60: min | E60: =G60 -> 2.0995962 | F60: 44.888889 | G60: =MIN(F59:F64) -> 2.0995962 | J60: 30.552486 | L60: =MAX(J60:J64) -> 52.658228 | P60: Среднее значение EV/EBITDA по зарубежным компаниям | Q60: =K53 -> 12.267668 | T60: 8.9644573 | V60: =MAX(T60:T68) -> 18.733273
A61: ПАО «Газпром» | B61: =J39 -> 44.888889 | D61: mean | E61: =G61 -> 63.399917 | F61: 239.32652 | G61: =AVERAGE(F59:F64) -> 63.399917 | J61: 44.888889 | L61: =MIN(J60:J64) -> 2.0995962 | P61: EBITDA «Роснефть», тыс.руб. | Q61: =Q55 -> 1041000000 | T61: 5.9195471 | V61: =MIN(T60:T68) -> 3.4733246
A62: ПАО «ЛУКОЙЛ» | B62: =J40 -> 239.32652 | D62: Sd | E62: =G62 -> 88.322011 | F62: 52.658228 | G62: =_xlfn.STDEV.S(F59:F64) -> 88.322011 | J62: 52.658228 | L62: =AVERAGE(J60:J64) -> 28.214597 | P62: Количество акций, шт. | Q62: =Q56 -> 10598177817 | T62: 6.2532751 | V62: =AVERAGE(T60:T68) -> 9.1096893
A63: ПАО «НОВАТЭК» | B63: =J41 -> 52.658228 | F63: 2.0995962 | J63: 2.0995962 | L63: =_xlfn.STDEV.S(J60:J64) -> 21.585214 | P63: Текущая стоимость, руб. (на 21.05.2021) | Q63: 525.55 | T63: 5.5502008 | V63: =_xlfn.STDEV.S(T60:T68) -> 5.3303936
A64: ПАО «Сургутнефтегаз» | B64: =J42 -> 2.0995962 | D64: Tоп min | E64: =G64 -> 1.9918772 | F64: 10.873786 | G64: =(G59-G61)/G62 -> 1.9918772 | J64: 10.873786 | P64: Справедливая стоимость по EV/EBITDA зарубежных компаний, руб. | Q64: =Q60*Q61/Q62*1000 -> 1204.9848 | T64: 6.2290503
A65: ПАО «Татнефть» им. В.Д. Шашина | B65: =J43 -> 10.873786 | D65: Tоп max | E65: =G65 -> 0.69405486 | G65: =ABS(G60-G61)/G62 -> 0.69405486 | J65: =AVERAGE(J60:J64) -> 28.214597 | L65: =(L60-L62)/L63 -> 1.1324248 | P65: Различие внутренней стоимости и текущей по EV/EBITDA зарубежных компаний | Q65: =Q64/Q63-1 -> 1.2928071 | T65: 17.053651 | V65: =(V60-V62)/V63 -> 1.805417
D66: Tкрит | E66: =G66 -> 1.89 | G66: 1.89 | J66: =_xlfn.STDEV.S(J60:J65) -> 19.306402 | L66: =ABS(L61-L62)/L63 -> 1.209856 | P66: Среднее значение EV/EBITDA по выборке | Q66: =T70 -> 9.1096893 | T66: 18.733273 | V66: =ABS(V61-V62)/V63 -> 1.0574012
L67: 1.79 | P67: EBITDA «Роснефть», тыс.руб. | Q67: =Q55 -> 1041000000 | T67: 9.810425 | V67: 2.1
P68: Количество акций, шт. | Q68: 10598177817 | T68: 3.4733246
P69: Текущая стоимость, руб. (на 21.05.2021) | Q69: 525.55
P70: Справедливая стоимость по EV/EBITDA выборки, руб. | Q70: =Q66*Q67/Q68*1000 -> 894.79406 | T70: =AVERAGE(T60:T68) -> 9.1096893
P71: Различие внутренней стоимости и текущей по EV/EBITDA выборки | Q71: =Q70/Q69-1 -> 0.70258598
A73: БАЛАНСОВОЙ СТОИМОСТИ
A74: Эмитент | B74: Капитализация, млрд.руб. на 21.05.2021 | C74: Активы, млрд.руб | D74: Долговые обязательства, млрд.руб | E74: Чистые активы, млрд.руб. | F74: P/BV | J74: P/BV | P74: Среднее значение P/BV по российским компаниям | Q74: =F85 -> 1.0947945
J75: 1.0078367 | L75: =MAX(J75:J80) -> 2.5396825 | P75: BV «Роснефть», тыс.руб. | Q75: =[1]BS!J25-[1]BS!J35-[1]BS!J42 -> 5487000000
J76: 0.40932118 | L76: =MIN(J75:J80) -> 0.30232558 | P76: Количество акций, шт. | Q76: 10598177817
A77: Российские компании | J77: 0.96344711 | L77: =AVERAGE(J75:J80) -> 1.0947945 | P77: Текущая стоимость, руб. (на 21.05.2021) | Q77: 525.55
A78: ПАО «НК «Роснефть» | B78: 5530 | C78: =G8 -> 15350 | D78: =([1]BS!J35+[1]BS!J42)/1000000 -> 9863 | E78: =C78-D78 -> 5487 | F78: =B78/E78 -> 1.0078367 | J78: 2.5396825 | L78: =_xlfn.STDEV.S(J75:J80) -> 0.80914491 | P78: Справедливая стоимость по P/BV российсхих компаний, руб. | Q78: =Q74*Q75/Q76*1000 -> 566.80851
A79: ПАО «Газпром» | B79: 6060 | C79: =G9 -> 23352 | D79: 8547 | E79: =C79-D79 -> 14805 | F79: =B79/E79 -> 0.40932118 | J79: 0.30232558 | P79: Различие внутренней стоимости и текущей по P/BV российских компаний | Q79: =Q78/Q77-1 -> 0.078505395
A80: ПАО «ЛУКОЙЛ» | B80: 3980 | C80: =G10 -> 5992 | D80: 1861 | E80: =C80-D80 -> 4131 | F80: =B80/E80 -> 0.96344711 | J80: 1.3461538 | L80: =(L75-L77)/L78 -> 1.7856975 | P80: Среднее значение P/BV по зарубежным компаниям | Q80: =F93 -> 1.2328067
A81: ПАО «НОВАТЭК» | B81: 4160 | C81: =G11 -> 2059 | D81: 421 | E81: =C81-D81 -> 1638 | F81: =B81/E81 -> 2.5396825 | L81: =ABS(L76-L77)/L78 -> 0.97939059 | P81: BV «Роснефть», тыс.руб. | Q81: =Q75 -> 5487000000
A82: ПАО «Сургутнефтегаз» | B82: 1560 | C82: =G12 -> 5876 | D82: 716 | E82: =C82-D82 -> 5160 | F82: =B82/E82 -> 0.30232558 | L82: 1.89 | P82: Количество акций, шт. | Q82: =Q76 -> 10598177817
A83: ПАО «Татнефть» им. В.Д. Шашина | B83: 1120 | C83: =G13 -> 1264 | D83: 432 | E83: =C83-D83 -> 832 | F83: =B83/E83 -> 1.3461538 | P83: Текущая стоимость, руб. (на 21.05.2021) | Q83: 525.55
A84: Стандартное отклонение | F84: =_xlfn.STDEV.S(F78:F83) -> 0.80914491 | J84: 1.5138349 | L84: =MAX(J84:J89) -> 1.5138349 | P84: Справедливая стоимость по P/BV зарубежных компаний, руб. | Q84: =Q80*Q81/Q82*1000 -> 638.26162
A85: Среднее значение | F85: =AVERAGE(F78:F83) -> 1.0947945 | J85: 1.5065754 | L85: =MIN(J84:J89) -> 0.94790309 | P85: Различие внутренней стоимости и текущей по P/BV зарубежных компаний | Q85: =Q84/Q83-1 -> 0.21446412
A86: Зарубежные компании | J86: 0.94790309 | L86: =AVERAGE(J84:J88) -> 1.2328067 | P86: Среднее значение P/BV по выборке | Q86: 1.02
A87: ExxonMobil | B87: =249.44*$B$33 -> 18353.795 | C87: =G18 -> 24580 | D87: =168.62*$D$2 -> 12455.959 | E87: =C87-D87 -> 12124.041 | F87: =B87/E87 -> 1.5138349 | J87: 1.1624402 | L87: =_xlfn.STDEV.S(J84:J88) -> 0.26450834 | P87: BV «Роснефть», тыс.руб. | Q87: =Q75 -> 5487000000
A88: Chevron Corporation | B88: =200.75*$B$33 -> 14771.185 | C88: =G19 -> 17713 | D88: =107.06*$D$2 -> 7908.5222 | E88: =C88-D88 -> 9804.4778 | F88: =B88/E88 -> 1.5065754 | J88: 1.0332797 | P88: Количество акций, шт. | Q88: 10598177817
A89: Royal Dutch Shell | B89: =(150.87)*$B$33 -> 11101.015 | C89: =G20 -> 28016.453 | D89: =220.73*$D$2 -> 16305.325 | E89: =C89-D89 -> 11711.128 | F89: =B89/E89 -> 0.94790309 | L89: =(L84-L86)/L87 -> 1.062455 | P89: Текущая стоимость, руб. (на 21.05.2021) | Q89: 525.55
A90: Total | B90: =123.8*$B$33 -> 9109.204 | C90: =G21 -> 19659.171 | D90: =160.05*$D$2 -> 11822.894 | E90: =C90-D90 -> 7836.2773 | F90: =B90/E90 -> 1.1624402 | L90: =ABS(L85-L86)/L87 -> 1.0771062 | P90: Справедливая стоимость по P/BV выборки, руб. | Q90: =Q86*Q87/Q88*1000 -> 528.08512
A91: BP | B91: =88.76*$B$33 -> 6530.9608 | C91: =G22 -> 19771.601 | D91: =182.09*$D$2 -> 13450.988 | E91: =C91-D91 -> 6320.6127 | F91: =B91/E91 -> 1.0332797 | L91: 1.79 | P91: Различие внутренней стоимости и текущей по P/BV выборки | Q91: =Q90/Q89-1 -> 0.0048237458
A92: Стандартное отклонение | F92: =_xlfn.STDEV.S(F87:F91) -> 0.26450834
A93: Среднее значение | F93: =AVERAGE(F87:F91) -> 1.2328067
A94: В целом по выборке | J94: 1.0078367 | L94: =MAX(J94:J104) -> 2.5396825
A95: Стандартное отклонение | F95: =_xlfn.STDEV.S(F78:F83,F87:F91) -> 0.60044845 | J95: 0.40932118 | L95: =MIN(J94:J104) -> 0.30232558
A96: Среднее значение | F96: =AVERAGE(F78:F83,F87:F91) -> 1.1575273 | J96: 0.96344711 | L96: =AVERAGE(J94:J104) -> 1.1575273
J97: 2.5396825 | L97: =_xlfn.STDEV.S(J94:J104) -> 0.60044845
J98: 0.30232558
J99: 1.3461538 | L99: =(L94-L96)/L97 -> 2.3018716
A100: БАЛАНСОВОЙ СТОИМОСТИ | J100: 1.5138349 | L100: =ABS(L95-L96)/L97 -> 1.4242717 | P100: Среднее значение P/S по российским компаниям | Q100: =P143 -> 1.126003
A101: Эмитент | B101: Капитализация, млрд.руб. на 21.05.2021 | C101: Выручка, млрд.руб | D101: P/S | J101: 1.5065754 | L101: 2.19 | P101: S «Роснефть», тыс.руб. | Q101: =[1]IS!J6 -> 5757000000
J102: 0.94790309 | P102: Количество акций, шт. | Q102: 10598177817
J103: 1.1624402 | P103: Текущая стоимость, руб. (на 21.05.2021) | Q103: 525.55
A104: Российские компании | J104: 1.0332797 | P104: Справедливая стоимость по P/S российсхих компаний, руб. | Q104: =Q100*Q101/Q102*1000 -> 611.65227
A105: ПАО «НК «Роснефть» | B105: =B78 -> 5530 | C105: =E8 -> 5757 | D105: =B105/C105 -> 0.96056974 | P105: Различие внутренней стоимости и текущей по P/S российских компаний | Q105: =Q104/Q103-1 -> 0.1638327
...

Sheet Затратный подход
A1: Показатель, тыс.руб. | B1: 2020
A2: Итого оборотные активы | B2: =BS!J12 -> 2922000000
A3: Итого внеоборотные активы | B3: =BS!J23 -> 12428000000
A4: Итого активы | B4: =BS!J25 -> 15350000000
A5: Итого краткосрочные обязательства | B5: =BS!J35 -> 3092000000
A6: Итого долгосрочные обязательства | B6: =BS!J42 -> 6771000000
A7: Стоимость чистых активов | B7: =B4-B5-B6 -> 5487000000
A8: Количество акций, шт. | B8: ='Доходный подход'!H279 -> 10598177817
A9: Справедливая стоиость, руб. | B9: =B7/B8*1000 -> 517.73051
A10: Текущая стоимость, руб. (на 21.05.2021) | B10: =Согласование!F5 -> 525.55
A11: Различие внутренней стоимости и текущей | B11: =B9/B10-1 -> -0.014878681

Sheet Согласование
A1: Параметр | B1: Подход к оценке
B2: Доходный | C2: Сравнительный
A3: Текущая стоимость, руб. (на 21.05.2021) | B3: 525.55
A4: Результат расчета, руб. | B4: ='Доходный подход'!H283 -> 559.70683 | C4: =F6 -> 617.79
A5: Диапазон стоимости по двум критериям, ± % | B5: 10 | F5: 525.55
A6: Показатель качества модели, ед. | B6: 1.2 | C6: 1 | F6: 617.79 | H6: =F6/F5-1 -> 0.17551137
A7: Диапазон стоимости, ± % | B7: =B5*B6 -> 12 | C7: =B5*C6 -> 10
A8: Нижняя граница диапазона стоимости (Сmin), руб. | B8: =B4*(1-B7/100) -> 492.54201 | C8: =C4*(1-C7/100) -> 556.011
A9: Верхняя граница диапазона стоимости (Сmax), руб. | B9: =B4*(1+B7/100) -> 626.87165 | C9: =C4*(1+C7/100) -> 679.569
A10: Существенность отличий | B10: Отличия существенны, одна имеется пересечение в диапазонах двух подходов [612,51; 724,92]
A17: Параметр | B17: Подход к оценке
B18: Доходный | C18: Сравнительный
A19: Текущая стоимость, руб. (на 21.05.2021) | B19: 525.55
A20: Результат расчета, руб. | B20: =B4 -> 559.70683 | C20: =C4 -> 617.79
A21: Показатель качества модели, ед. | B21: 1.2 | C21: 1
A22: Весовой коэффициент | B22: =(1/B21)/(1/B21+1/C21) -> 0.45454545 | C22: =(1/C21)/(1/B21+1/C21) -> 0.54545455
A23: Итоговая величина стоимости, руб. | B23: =B20*B22+C20*C22 -> 591.38856
A24: Диапазон стоимости подхода, ± % | B24: =B7 -> 12 | C24: =C7 -> 10
A25: Диапазон стоимости, ± % | B25: =B24*B22+C24*C22 -> 10.909091
A26: Нижняя граница диапазона стоимости (Сmin), руб. | B26: =B23*(1-B25/100) -> 526.87344
A27: Верхняя граница диапазона стоимости (Сmax), руб. | B27: =B23*(1+B25/100) -> 655.90367
A28: Границы интервала итоговой величины инвестиционной стоимости | B28: [522,25 - 650,15]
B31: =B23/B3-1 -> 0.12527554
B32: =B26/B3-1 -> 0.0025182043
B33: =B27/B3-1 -> 0.24803287 | C33: =AVERAGE(B32:B33) -> 0.12527554
